Workbook
Name Accrued_Physical: [2]ImpAnalysis!$I$26
Name Actual_Age: [2]Inputs!$C$159
Name Actual_Taxes: [2]Tax!$G$21
Name Adj_Pro_Assessed_Val: [2]Tax!$K$12
Name AdjCatNo: '[2]IS Grid'!$A$81
Name Ambient_Area: [2]Inputs!$C$96
Name AmtBdgt: [3]OpActuals!$I:$I
Name AMTY1: [3]OpActuals!$C:$C
Name AMTY2: [3]OpActuals!$D:$D
Name AMTY3: [3]OpActuals!$E:$E
Name AMTY4: [3]OpActuals!$F:$F
Name AMTY5: [3]OpActuals!$H:$H
Name AnalysisType: [4]Assumptions!$C$2:$C$3
Name Anchor_1_Name: [2]Inputs!$C$119
Name Anchor_1_SF: [2]Inputs!$C$120
Name Anchor_2_Name: [2]Inputs!$C$121
Name Anchor_2_SF: [2]Inputs!$C$122
Name Anchor_3_Name: [2]Inputs!$C$123
Name Anchor_3_SF: [2]Inputs!$C$124
Name Anchor_4_Name: [2]Inputs!$C$125
Name Anchor_4_SF: [2]Inputs!$C$126
Name Anchor_5_Name: [2]Inputs!$C$127
Name Anchor_5_SF: [2]Inputs!$C$128
Name Anchor_6_Name: [2]Inputs!$C$129
Name Anchor_6_SF: [2]Inputs!$C$130
Name Annual_Mkt_Rent: '[2]Mkt Rent'!$BE$85
Name Appraisal_Fee: [2]Inputs!$C$58
Name Appraiser: [2]Inputs!$C$9
Name Apt.Concessions: '[2]Dir Cap'!$H$8
Name Apt.Concessions.Percent: '[2]Dir Cap'!$E$8
Name Apt.LosstoLease: '[2]Dir Cap'!$H$7
Name Apt.LosstoLease.Percent: '[2]Dir Cap'!$E$7
Name Apt_Row_Cost: [2]Cost!#REF!
Name ARC.Homesites: '[1]ARC Financials'!$F$240
Name ARC.No: [1]Instructions!$B$3
Name ARC.PropAddress: '[1]ARC Property List'!$D$9:$D$67
Name ARC.PropCity: '[1]ARC Property List'!$E$9:$E$67
Name ARC.PropCode: '[1]ARC Property List'!$B$9:$B$67
Name ARC.PropName: '[1]ARC Property List'!$C$9:$C$67
Name ARC.PropState: '[1]ARC Property List'!$F$9:$F$67
Name ARC.PropZip: '[1]ARC Property List'!$G$9:$G$67
Name ARI: '[2]Dir Cap'!$H$9
Name ArrTot: [6]Assumptions!$F$9:$G$21
Name ArrTotal: [4]Assumptions!$F$9:$G$21
Name As_Is_Value: [2]Values!$M$21
Name bbDateOfValueEffectiveDate: '[7]Valuation Scenarios'!$D$85
Name bbDateReport: [7]Assignment!$B$44
Name bbMarketValues: '[7]Valuation Scenarios'!$D$76
Name bbPropertyOwner: [7]Assignment!$B$27
Name bbValuationType: '[7]Valuation Scenarios'!$D$79
Name bbValueConditionScen1: '[3]Valuation Scenarios'!$B$8
Name bbValueDateScen1: '[3]Valuation Scenarios'!$B$5
Name bbValueInterestScen1: '[3]Valuation Scenarios'!$B$7
Name bbValueNameScen1: '[3]Valuation Scenarios'!$B$4
Name Building_Area: [2]Inputs!$C$146
Name Building_Class_List: [2]InputsRangeNames!$J$4:$J$8
Name Building_Class_Value: [2]InputsRangeNames!$J$2
Name Building_Class_Value_List: [2]InputsRangeNames!$I$4:$I$8
Name caDeferredMaint: [3]Cost!$F$44
Name caLandValueRND: [3]LSaleAdj!$E$48

Sheet Property Info
A1: Building Labels | B1: =IF($B$4>=2,"Building 1","") | C1: =IF($B$4=1,"Bldg 1",IF($B$4>=2,"Bldg 2","")) | D1: =IF($B$4>=3,"Bldg 3","") | E1: =IF($B$4>=4,"Bldg 4","") | F1: =IF($B$4>=5,"Bldg 5","") | G1: =IF($B$4>=6,"Bldg 6","") | H1: =IF($B$4>=7,"Bldg 7","") | I1: =IF($B$4>=8,"Bldg 8","") | J1: =IF($B$4>=9,"Bldg 9","") | K1: =IF($B$4>=10,"Bldg 10","") | L1: =IF($B$4>=11,"Bldg 11","") | M1: =IF($B$4>=12,"Bldg 12","")
A2: Account
A3: Occ. Code
A4: Number of Buildings
A5: GBA
A6: Footprint
A7: NRA
A8: SF Basis | B8: GBA
A9: Year Built
A10: Condition
A11: Year/Condition | B11: 1999/Average
A12: Site Size
A13: Acres | B13: =B12/43560
A14: Coverage Ratio | B14: =B5/B12
A15: Office %
A16: Type
A17: Address
A18: City
A19: County | B19: Adams County
A20: Assumed Occupancy
A21: Assessor's Assigned Value
A22: Petitioner's Value
A23: Recent Sale Date
A24: Recent Sale Price
A25: Sale Type
A26: Value Premise | B26: Fee Simple
A27: Date of Value
A28: Report Date
A29: Hearing Date
A30: Zoning
A31: Zoning Authority | B31: Adams County

Sheet FE
A1: Note: | B1: FILL ONLY HIGHLIGHTED CELLS
B3: EXECUTIVE SUMMARY
B4: Account Number | C4: ='Property Info'!B2
B5: Address | C5: ='Property Info'!B17
B6: County | C6: ='Property Info'!B19
B7: City, State | C7: ='Property Info'!B18
B8: Effective Date | C8: ='Property Info'!B27
B9: Appraisal Date | C9: ='Property Info'!B28
B10: Hearing Date | C10: ='Property Info'!B29
B12: Property Type | C12: ='Property Info'!B16
B13: Property Size
B14: ='Property Info'!B8 | C14: =IF(B14="GBA", 'Property Info'!B5,IF(B14="NRA",'Property Info'!B7,'Property Info'!B5))
B15: Number of Buildings | C15: ='Property Info'!B4
B16: Year Built/Condition | C16: ='Property Info'!B11
B17: Condition | C17: ='Property Info'!B10
B18: Site Size (SF) | C18: ='Property Info'!B12
B19: Property Rights Appraised | C19: ='Property Info'!B26
B20: Assumed Occupancy | C20: ='Property Info'!B20
B21: Stabilized Occupancy | C21: ='Income Approach'!D22
D23: PETITION SCENARIO
E24: $ | F24: $/SF
D25: Assessor's Assigned Value | E25: ='Basic Sales Grid'!D51 | F25: =E25/C14
D26: Petitioner’s Requested Value | E26: ='Basic Sales Grid'!D52 | F26: =E26/C14
G28: APPRAISAL INFORMATION
G29: Intended User | H29: Adams County Board of Equalization, Adams County Attorney, Colorado Board of Assessment Appeals
H30: =clCompanyAddressStreet1&", "&clCompanyAddressStreet2
H31: =clCompanyAddressCity&", "&clCompanyAddressState&" "&clCompanyAddressZip
G32: Intended User(s) | H32: =H29
G33: Intended Use | H33: Aid in tax appeal decision
G34: Values Concluded | H34: Retrospective Market Value
G35: Property Rights Appraised / Premise
G36: Premise Summary
G37: Date of Inspection
G38: Report Date | H38: ='Property Info'!B28
G39: Marketing Time | H39: 12 months
G40: Exposure Time | H40: 12 months
G41: Owner of Record
G42: Property Contact(s)
G43: Most Probable Purchaser | H43: =pdMostProbablePurchaser
G44: Highest and Best Use
G45: If Vacant | H45: Light Industrial Development
G46: As Improved | H46: =pdHBUAsImproved
M49: SCOPE OF THE INVESTIGATION
M50: General and Market Data Analyzed | N50: § Regional economic data and trends
N51: § Market analysis data specific to the subject property type
N52: § Published survey data
N53: § Neighborhood demographic data
N54: § Comparable cost, sale, rental, expense, and capitalization rate data
N55: § Floodplain status
N56: § Zoning information
N57: § Assessor’s information
N58: § Interviewed professionals knowledgeable about the subject’s property type and market
M59: Inspection Details | N59: The interior and exterior of the subject was inspected.
M60: Data Sources
M61: Site Size | N61: Adams County Assessor Records, Appraiser Measurement
M62: Building Size | N62: Adams County Assessor Records, Appraiser Measurement
M63: Zoning information | N63: Adams County Planning Department
M64: Flood Status | N64: FEMA Flood Map Service Center
M65: Demographics | N65: CoStar Market Reports
M66: Land Sales | N66: CoStar, MLS, Adams County Sales Data, Local Brokers
M67: Cost Estimate Data | N67: Marshall & Swift Cost Estimator
M68: Comparable Improved Sales | N68: CoStar, MLS, Adams County Sales Data, Local Brokers
M69: Comparable Improved Rents | N69: CoStar, MLS, Adams County Lease Data, Local Brokers
M70: Property Specific Data Requested and Received
N71: Lease, Lease Addendum
N72: Estimated financial analysis
N73: Property Expenses (2019, 2020)
M75: Data Requested, but not Provided
N76: Rent Roll
N77: Building Plans
N78: Environmental survey
N79: ALTA Survey
R81: EXTRAORDINARY ASSUMPTION(S) AND HYPOTHETICAL CONDITION(S)
R82: The values presented within this appraisal report are subject to the extraordinary assumptions and hypothetical conditions listed below. Pursuant to the requirement within Uniform Standards of Professional Appraisal Practice Standards, it is stated here that the use of any extraordinary assumptions might have affected the assignment results.
R83: Extraordinary Assumption(s)
A84: =IF(R84="","X","") | Q84: 1 | R84: This appraisal employs no extroidinary assumptions.
A85: =IF(R85="","X","") | Q85: 2 | R85: =IFERROR(IF(INDEX([14]!TableCondLang[#Data],MATCH($E85,[14]!TableCondLang[Row_Num],0),COLUMN([14]!TableCondLang[Discriminator])-1)="Extraordinary",INDEX([14]!TableCondLang[#Data],MATCH($E85,[14]!TableCondLang[Row_Num],0),COLUMN([14]!TableCondLang[Description])-1),""),"")
A86: =IF(R86="","X","") | Q86: 3 | R86: =IFERROR(IF(INDEX([14]!TableCondLang[#Data],MATCH($E86,[14]!TableCondLang[Row_Num],0),COLUMN([14]!TableCondLang[Discriminator])-1)="Extraordinary",INDEX([14]!TableCondLang[#Data],MATCH($E86,[14]!TableCondLang[Row_Num],0),COLUMN([14]!TableCondLang[Description])-1),""),"")
A87: =IF(R87="","X","") | Q87: 4 | R87: =IFERROR(IF(INDEX([14]!TableCondLang[#Data],MATCH($E87,[14]!TableCondLang[Row_Num],0),COLUMN([14]!TableCondLang[Discriminator])-1)="Extraordinary",INDEX([14]!TableCondLang[#Data],MATCH($E87,[14]!TableCondLang[Row_Num],0),COLUMN([14]!TableCondLang[Description])-1),""),"")
A88: =IF(S88="","X","") | S88: =IFERROR(IF(INDEX([14]!TableCondLang[#Data],MATCH($E88,[14]!TableCondLang[Row_Num],0),COLUMN([14]!TableCondLang[Discriminator])-1)="Extraordinary",INDEX([14]!TableCondLang[#Data],MATCH($E88,[14]!TableCondLang[Row_Num],0),COLUMN([14]!TableCondLang[Description])-1),""),"")
A89: =IF(S89="","X","") | R89: Hypothetical Condition(s) | S89: =IFERROR(IF(INDEX([14]!TableCondLang[#Data],MATCH($E89,[14]!TableCondLang[Row_Num],0),COLUMN([14]!TableCondLang[Discriminator])-1)="Extraordinary",INDEX([14]!TableCondLang[#Data],MATCH($E89,[14]!TableCondLang[Row_Num],0),COLUMN([14]!TableCondLang[Description])-1),""),"")
A90: =IF(R90="","X","") | Q90: 1 | R90: This appraisal employs no hypothetical conditions.
A91: =IF(R91="","X","") | Q91: 2 | R91: =IFERROR(IF(INDEX([14]!TableCondLang[#Data],MATCH($E91,[14]!TableCondLang[Row_Num],0),COLUMN([14]!TableCondLang[Discriminator])-1)="Extraordinary",INDEX([14]!TableCondLang[#Data],MATCH($E91,[14]!TableCondLang[Row_Num],0),COLUMN([14]!TableCondLang[Description])-1),""),"")
A92: =IF(R92="","X","") | Q92: 3 | R92: =IFERROR(IF(INDEX([14]!TableCondLang[#Data],MATCH($E92,[14]!TableCondLang[Row_Num],0),COLUMN([14]!TableCondLang[Discriminator])-1)="Extraordinary",INDEX([14]!TableCondLang[#Data],MATCH($E92,[14]!TableCondLang[Row_Num],0),COLUMN([14]!TableCondLang[Description])-1),""),"")
A93: =IF(R93="","X","") | Q93: 4 | R93: =IFERROR(IF(INDEX([14]!TableCondLang[#Data],MATCH($E93,[14]!TableCondLang[Row_Num],0),COLUMN([14]!TableCondLang[Discriminator])-1)="Extraordinary",INDEX([14]!TableCondLang[#Data],MATCH($E93,[14]!TableCondLang[Row_Num],0),COLUMN([14]!TableCondLang[Description])-1),""),"")
A94: =IF(R94="","X","") | R94: =IFERROR(IF(INDEX([14]!TableCondLang[#Data],MATCH($E94,[14]!TableCondLang[Row_Num],0),COLUMN([14]!TableCondLang[Discriminator])-1)="Extraordinary",INDEX([14]!TableCondLang[#Data],MATCH($E94,[14]!TableCondLang[Row_Num],0),COLUMN([14]!TableCondLang[Description])-1),""),"")
T95: PROPERTY OVERVIEW
T96: Property Name
T97: Address | U97: ='Property Info'!B17
U98: ='Property Info'!B18
T99: Location
T100: Property Description | U100: =U96
T101: and | U101: ='[7]Improvement Description_2'!C31&" ("&'[7]Improvement Description_2'!C32&") "&'[7]Improvement Description_2'!C33
T102: County | U102: ='Property Info'!B19
T103: Account Number(s) | U103: ='Property Info'!B2
T104: Note:
T105: Census Tract No. | U105: =pdCensusTract
T106: Legal Description
T107: Site Area
T108: Primary Site | U108: ='Property Info'!B12 | V108: =U108/43560
...

Sheet Market Neighborhood
B2: MARKET DATA
B3: Surrounding Area | C3: Industrial | D3: Market Trend | E3: Growth
B4: Overall Real Estate Values | C4: Increasing | D4: Neighborhood Vacancy
B5: Predominant Property Use(s) | C5: Industrial Neighborhood Retail Lodging | D5: Estimated Marketing | E5: 12 months
D6: Estimated Exposure | E6: 12 months
B7: Market Subsector(s) | F7: ←Change this
B8: Vacancy - CoStar - Industrial 20,000 SF-50,000 SF | F8: ←From Income
D9: =D7 | F9: ←Change This
B10: Vacancy - CoStar - Industrial 20,000 SF-50,000 SF | F10: ←From Income
F11: NEIGHBORHOOD DATA
F12: Market Area Comments
F13: Surrounding Uses | H13: Industrial Lots
H14: Light Industrial
H15: Industrial Storage Lot
H16: Light Industrial
F17: Property Contact Interview | G17: =clInspectionContactName
I18: CHANGE → | J18: Average Sale Price - Denver Market Industrial - 10,000 SF-50,000 SF | N18: Average Sale Price - Adams County Industrial - 10,000 SF-50,000 SF
J19: Period | K19: Avg. Price ($/SF) | L19: % Change - Q2 2020 | M19: ←CHANGE → | N19: Period | O19: Avg. Price ($/SF) | P19: % Change - Q2 2020

Sheet Site Information
B2: SITE DESCRIPTION OVERVIEW
B4: Location | C4: =FE!U99
B5: Account Number | C5: =FE!U103
B6: Legal Description | C6: =FE!U106
B7: Site Area
B8: Primary Site | C8: =FE!U108 | D8: =FE!V108
B9: Excess Land | C9: =FE!U109 | D9: =FE!V109
B10: Surplus Land | C10: =FE!U110 | D10: =FE!V110
B11: Total | C11: =FE!U111 | D11: =FE!V111
B12: Configuration
B13: Topography | C13: Generally Level
B14: Drainage | C14: Appears adequate
B15: Utilities/Municipal Services | C15: Typical utilities and municipal services available to site.
B16: Floodplain | C16: Zone | D16: Map | E16: Date
C17: Zone X (Unshaded) | I17: Zone A | J17: Zone X (Shaded)
C18: Zone X (unshaded) is a Non-Special Flood Hazard Area (NSFHA) of minimal flood hazard, usually depicted on Flood Insurance Rate Maps (FIRM) as above the 500-year flood level. This is an area in a low to moderate risk flood zone that is not in any immediate danger from flooding caused by overflowing rivers or hard rains. In communities that participate in the National Flood Insurance Program (NFIP), flood insurance is available to all property owners and renters in this zone.
B19: Census Tract No. | C19: =pdCensusTract
B21: SITE DESCRIPTION OVERVIEW - CONTINUED
B22: Soil/Subsoil Conditions | C22: We did not receive nor review a soil report. However, we assume that the soil's load-bearing capacity is sufficient to support existing structure(s). We did not observe any evidence to the contrary during our physical inspection of the property.
B23: Environmental Concerns | C23: No unusual conditions observed. No studies provided. Site is assumed to be free of any environmental concerns.
B24: Land Use Restrictions
B25: Hazards Nuisances | C25: None noted
B26: Frontage
B27: Access
B28: Visibility
B29: Surrounding Land Uses | C29: Light to medium-intensity industrial
B30: Enterprise Zone | C30: None noted
B31: Traffic Counts
B32: Transportation Facilities
B33: Comments
H35: ZONING
H36: Designation
H37: Description | I37: Industrial-1 (Light Industrial)
H38: Zoning Intent | I38: The purpose of the Industrial‐1 District is to provide a general commercial and limited industrial district designed to provide for a variety of compatible business, warehouse, wholesale, offices and very limited industrial uses. Special uses are permitted in an Industrial‐1 District, subject to the issuance of a Special Use Permit from the Board of Adjustment. Temporary uses are permitted in the Industrial‐1 District, subject to the issuance of a Temporary Use Permit from the Director of Community and Economic Development.
H39: Compliance | I39: The subject is a legal confirming use in the I-1 zoning designation.
H40: ZONING REQUIREMENTS
H41: Min. Lot Size: | I41: 1 Acre
H42: Min. Lot Width: | I42: 100 Feet
H43: Setbacks:
H44: Front | I44: 25 Feet
H45: Side | I45: 15 feet on one side and five 5 feet on the other side; 0 foot setbacks may be approved for fireproof structures.
H46: Rear | I46: 15 Feet
H47: Maximum Height: | I47: 60 Feet

Sheet Improvements
B2: =IF(OR(pdGenPropUse2="",pdGenPropUse2=0),"GENERAL DESCRIPTION OVERVIEW", "GENERAL DESCRIPTION OVERVIEW - "&UPPER(pdGenPropUse))
B3: Address | C3: ='Property Info'!B17
C4: ='Property Info'!B18
B5: Property Description | C5: =FE!U100
B6: Year Built | C6: ='Property Info'!B9
B7: Year Renovated | C7: =FE!U116
B8: Number of Buildings | C8: =FE!U120
B9: Number of Stories
B10: Total Number of Units | C10: =FE!U126
B11: Building Construction Class
B12: Net Rentable Area | C12: =FE!U124
B13: Gross Leasable Area | C13: =FE!U122
B14: + Clubhouse | C14: =pdBldgAreaClubhouse
B15: + Others(s) | C15: =pdBldgAreaOther
B16: Mezzanine Area
B17: Building Footprint | C17: ='Property Info'!B6
B18: Bay Depth | C18: =pdBayDepth
B19: LEED Ratio | C19: =pdLEEDRating
B20: Floor-Area Ratio | C20: =pdFAR
B21: Elevator(s) | C21: None
B22: Ceiling Heights
B23: Utility Metering | C23: Master metered
B24: Density (Units/Acre) | C24: =C10/'Site Information'!C11
B25: Coverage Ratio | C25: =C17/'Site Information'!C11
B26: Land-to-Building Ratio | C26: ='Site Information'!C11/Improvements!C13
B27: Ingress/Egress
B28: Percentage Office Build-Out | C28: ='Property Info'!B15
B29: Clear Height
B30: Power | C30: Assumed adequate for industrial use.
B31: Loading Doors
B32: Dock High
B33: Roll-Up
B34: Rail Access | C34: None
B35: Storage Yard
B36: Truck Court
B37: Parking
B38: Surface Parking Spaces
B39: Other | C39: 0
B40: Garages | C40: 0
B41: Total Parking Spaces | C41: =SUM(C38:C40)
B42: Parking Ratio (Spaces/1,000 SF GBA) | C42: =(C41/C13)*1000
B43: ADA Compliance | C43: =pdADA
B45: CONSTRUCTION DETAIL
B47: General Layout
B48: Foundation
B49: Construction
B50: Floor Structure
B51: Exterior Walls
B52: Roof Type
B53: Roof Cover
B54: Windows
B55: Balcony/Patios: | C55: None
B57: INTERIOR DETAIL
B59: Interior Walls
B60: Ceilings
B61: Floor Coverings
B62: Doors
B63: Lighting
B64: Ceiling Heights
B65: Restrooms
B66: Kitchen Finish
B67: Bathroom Finish
B68: Amenities (Unit) | C68: Small structural mezzanine above temporary structure in warehouse (not part of GBA)
B70: MECHANICAL DETAIL
B71: Heating
B72: Cooling
B73: Plumbing
B74: Electrical
B75: Fire Protection
B77: SITE IMPROVEMENTS
B78: Parking Type
B79: Landscaping
B80: Signage
B81: Fencing
B82: Other
... B87: Deferred Maintenance
B88: Cost to Cure | C88: =pdCosttoCure
B91: SUMMARY
B92: Building Condition | C92: =FE!U129
C93: We did not inspect the roof of the building(s) nor make a detailed inspection of the mechanical systems. We are not qualified to render an opinion as to the adequacy or condition of these components. Interested parties are urged to retain an expert in this field if detailed information is needed about the adequacy and condition of mechanical systems.
B94: Building Quality | C94: =FE!U130
B95: Design and Functionality | C95: =FE!U131
B96: Actual Age | C96: =YEAR('Cost Approach'!C17)-'Property Info'!B9
B97: Expected Economic Life | C97: ='Cost Approach'!C59
B98: Effective Age | C98: ='Cost Approach'!C58
B99: Remaining Economic Life | C99: =C97-C98

Sheet H&BU
C1: NOTE: Most of the below text is standard boilerplate and should remain the same. Read through and change only the descriptions as they pertain to your property.
B3: AS IF VACANT
B4: Legally | C4: Legal restrictions include deed restrictions, CC&R’s, lease encumbrances, zoning requirements, building codes, historic district controls and environmental regulations, and were previously analyzed to determine legally permitted uses. Legally, the subject is zoned I-1 (Light Industrial). The purpose of the Industrial‐1 District is to provide a general commercial and limited industrial district designed to provide for a variety of compatible business, warehouse, wholesale, offices and very limited industrial uses. Special uses are permitted in an Industrial‐1 District, subject to the issuance of a Special Use Permit from the Board of Adjustment. Temporary uses are permitted in the Industrial‐1 District, subject to the issuance of a Temporary Use Permit from the Director of Community and Economic Development. Allowable uses include but are not limited to storage, distribution, wholesale, office/flex, warehousing, maintenance, and light manufacturing.
B5: Physically | C5: Size, shape, topography, soil condition, availability of utilities, transportation access, surrounding uses, and locational characteristics were previously analyzed to determine which legal land uses are physically possible and which are best to conform to the physical and locational aspects of the site and its setting with respect to the neighborhood and community. Overall, the physical site attributes result in adequate utility, and the property could be developed with a variety of legally-conforming uses. Given the surrounding uses and location, the site is best suited for light industrial use.
B6: Financially | C6: Financial feasibility is determined by the relationship of supply and demand for the legally probable land uses versus the cost to create them. The market analysis section reveals that retail uses in the subject's market are generally stabilized. Ongoing industrial development during the period in question throughout the market area serve as direct evidence that new industrial development was financially feasible at this time. Comparisons of rental rates, operating expenses and construction costs indicate the subject property would have been capable of providing an adequate return on investment to warrant new industrial development in the market. This assertion is supported by the fact that the property has the potential to generate rental income as shown in the income approach. Therefore, retail use is considered financially feasible.
B7: Maximally | C7: The final test of highest and best use of the site as vacant is that the use be maximally productive, yielding the highest return to the land. In order to determine the maximally productive use, a comparison of rental rates, occupancy, operating expenses, and rates of return for the financially feasible uses have been made. Based on this analysis, light industrial use renders the highest residual land value; therefore, light industrial development on the subject's site is the maximally productive use of the subject as vacant.
B11: AS IMPROVED
B12: Legally | C12: The subject is a legal conforming use in the I-1 zoning district. No other known legal encumbrances exists that limit use or function on the improved property.
B13: Physically
B14: Financially | C14: Financial feasibility as an income-producing investment is based on the amount of rental income it can generate net of the required operating expenses. If the resulting net operating income motivates continued operation, then the land is being put to a productive and financially feasible use. The subject is capable of producing positive net cash flow to an investor. The existing improvements provide contributory value to the site, and there is no alternate use that would result in a greater value. Therefore, utilization of the existing improvements is financially feasible.
B15: Maximally | C15: The maximally productive use should conform to neighborhood trends and be consistent with existing nearby land uses. The single use that produces the greatest return on investment and usually the highest price and value is typically the highest and best use. As shown in the applicable valuation sections, properties like the subject have been acquired and continue to be used for retail use. None of the comparable properties were acquired for conversion to an alternative use. This provides evidence suggesting that the current retail use is maximally productive.

Sheet Final Value
C2: VALUE INDICATIONS
C3: As Is - Land Value Only
C4: Sales Comparison Approach | D4: ='Land Sales'!#REF! | E4: =D4/'Property Info'!B12 | F4: Per Square Foot (LA)
C5: Value Conclusion - As Is | D5: =D4 | E5: =E4 | F5: =F4
C6: As Is - Retrospective Market Value - Fee Simple Estate
C7: Cost Approach | D7: Not Developed
C8: Sales Comparison Approach | D8: ='Basic Sales Grid'!D46 | E8: =D8/FE!$C$14 | F8: =FE!B14
C9: Income Capitalization Approach
C10: Direct Capitalization | D10: ='Income Approach'!C65 | E10: =D10/FE!$C$14 | F10: =F8
C11: Approach Reliance | D11: =IF(FE!B14="GBA",'Final Value'!C8,'Final Value'!C9)
C12: Value Conclusion | D12: =D10 | E12: =D12/FE!$C$14 | F12: =F8
C13: As Is
C14: Sales Comparison Approach | D14: =#REF! | E14: =#REF! | F14: Per Square Foot (GBA)
C15: Income Capitalization Approach
C16: Direct Capitalization | F16: =F14
C17: Approach Reliance | D17: Sales Comparison Approach
C18: ="Value Conclusion - "&PROPER(bbValueConditionScen1)&"" | D18: =D14 | E18: =E14 | F18: =F14
C19: Exposure Time | D19: 12 months
C20: Marketing Time | D20: 12 months
G21: MARKET VALUE CONCLUSION
G22: Appraisal Premise | H22: Interest Appraised | I22: Date of Value | J22: Value Conclusion
G23: Retrospective Market Value | H23: Fee Simple | I23: ='Property Info'!B27 | J23: =D12
G26: 6 MONTH LIQUIDATION VALUE CONCLUSION
G27: Appraisal Premise | H27: Interest Appraised | I27: Date of Value | J27: Value Conclusion
G28: =bbValueNameScen1 | H28: Fee Simple
G30: HYPOTHETICAL MARKET VALUE CONCLUSION (UNDERLYING LAND ONLY)
G31: Appraisal Premise | H31: Interest Appraised | I31: Date of Value | J31: Value Conclusion
G32: As If Vacant | H32: Fee Simple
G34: PROSPECTIVE MARKET VALUE CONCLUSION
G35: Appraisal Premise | H35: Interest Appraised | I35: Date of Value | J35: Value Conclusion
G36: Upon Completion | H36: Fee Simple | J36: =D12

Sheet Land Sales
B1: NOTES:
B2: Change Highlighted fields only
B3: Change highlighted areas to WHITE when complete
B4: Check all cells for accuracy after completing
B5: Remember to spell check every worksheet as you go.
B7: COMPARABLE SALE ADJUSTMENT GRID
C8: Subject | D8: Sale 1 | F8: Sale 2 | H8: Sale 3 | J8: Sale 4 | L8: Sale 5
B9: Address | C9: ='Property Info'!B17
B10: City, State | C10: ='Property Info'!B18
B11: Account/Parcel Number | C11: ='Property Info'!B2
B12: Property Type | C12: Industrial Land | E12: Industrial Land | G12: Industrial Land | I12: Industrial Land | K12: Industrial Land | L12: Commercial Land
B13: Sale Date | C13: N/A
B14: Sale Price | C14: N/A
B15: Listing Price | C15: N/A | E15: Not Reported | G15: 1224040 | I15: 1600000 | K15: Not Reported | L15: 500000
B16: Days On Market | C16: N/A | E16: Not Reported | G16: 1117 | I16: 259 | K16: Not Reported | L16: 725
B17: Data Source | C17: Assessor, appraiser measurements | E17: Costar, Assessor Data, Deed, Troy DeVos (Buyer Representative) | G17: CoStar, Assessor Data, Listing Broker (Phil Foster & Co.) | I17: CoStar, Assessor Data, Listing Broker (Mark Goodman/Goodman Commercial) | K17: CoStar, Denver Assessor, Deed, Loan | L17: CoStar, Assessor, Listing
B18: Grantor | C18: TBD
B19: Grantee | C19: TBD
B20: Site Size (SF) | C20: ='Property Info'!B12
B21: Zoning | C21: ='Property Info'!B30 | E21: B-3 (Business/Commercial) | G21: PUD-I (Industrial) | I21: I-2 (General Industrial) | K21: I-B (General Industrial) | L21: B-2
B22: Comments | C22: Industrial land
B23: Unadjusted Price Per SF | E23: =E14/E20 | G23: =G14/G20 | I23: =I14/I20 | K23: =K14/K20 | M23: =L15/L20
B24: Quantified Adjustments
B25: Property Rights Conveyed | C25: Fee Simple | D25: Fee Simple | E25: 0 | F25: Fee Simple | G25: 0 | H25: Fee Simple | I25: 0 | J25: Fee Simple | K25: 0 | L25: Fee Simple
B26: Property Rights Conveyed Adjusted | E26: =IF(LEFT(CELL("format",E25),1)="P",E23*(1+E25),IF(LEFT(CELL("format",E25),1)="C",E23+E25)) | G26: =IF(LEFT(CELL("format",G25),1)="P",G23*(1+G25),IF(LEFT(CELL("format",G25),1)="C",G23+G25)) | I26: =IF(LEFT(CELL("format",I25),1)="P",I23*(1+I25),IF(LEFT(CELL("format",I25),1)="C",I23+I25)) | K26: =IF(LEFT(CELL("format",K25),1)="P",K23*(1+K25),IF(LEFT(CELL("format",K25),1)="C",K23+K25)) | M26: =IF(LEFT(CELL("format",M25),1)="P",M23*(1+M25),IF(LEFT(CELL("format",M25),1)="C",M23+M25))
B27: Financing | C27: N/A | D27: Market-Based | E27: 0 | F27: Market-Based | G27: 0 | H27: Market-Based | I27: 0 | J27: Market-Based | K27: 0 | L27: Market-Based | M27: 0
B28: Financing Adjusted | E28: =IF(LEFT(CELL("format",E27),1)="P",E26*(1+E27),IF(LEFT(CELL("format",E27),1)="C",E26+E27)) | G28: =IF(LEFT(CELL("format",G27),1)="P",G26*(1+G27),IF(LEFT(CELL("format",G27),1)="C",G26+G27)) | I28: =IF(LEFT(CELL("format",I27),1)="P",I26*(1+I27),IF(LEFT(CELL("format",I27),1)="C",I26+I27)) | K28: =IF(LEFT(CELL("format",K27),1)="P",K26*(1+K27),IF(LEFT(CELL("format",K27),1)="C",K26+K27)) | M28: =IF(LEFT(CELL("format",M27),1)="P",M26*(1+M27),IF(LEFT(CELL("format",M27),1)="C",M26+M27)) | R28: =0.25*J20
B29: Terms/Conditions of Sale | C29: N/A | D29: None | E29: 0 | F29: None | G29: 0 | H29: None | I29: 0 | J29: None | K29: 0 | L29: None | M29: 0
B30: Terms/Conditions of Sale Adjusted | E30: =IF(LEFT(CELL("format",E29),1)="P",E28*(1+E29),IF(LEFT(CELL("format",E29),1)="C",E28+E29)) | G30: =IF(LEFT(CELL("format",G29),1)="P",G28*(1+G29),IF(LEFT(CELL("format",G29),1)="C",G28+G29)) | I30: =IF(LEFT(CELL("format",I29),1)="P",I28*(1+I29),IF(LEFT(CELL("format",I29),1)="C",I28+I29)) | K30: =IF(LEFT(CELL("format",K29),1)="P",K28*(1+K29),IF(LEFT(CELL("format",K29),1)="C",K28+K29)) | M30: =IF(LEFT(CELL("format",M29),1)="P",M28*(1+M29),IF(LEFT(CELL("format",M29),1)="C",M28+M29))
B31: Expenditures After Sale | C31: N/A | D31: None | E31: 0 | F31: None | G31: 0 | H31: None | I31: 0 | J31: None | K31: 0 | L31: None | M31: 0
B32: Expenditures After Sale Adjusted | E32: =IF(LEFT(CELL("format",E31),1)="P",E30*(1+E31),IF(LEFT(CELL("format",E31),1)="C",E30+E31)) | G32: =IF(LEFT(CELL("format",G31),1)="P",G30*(1+G31),IF(LEFT(CELL("format",G31),1)="C",G30+G31)) | I32: =IF(LEFT(CELL("format",I31),1)="P",I30*(1+I31),IF(LEFT(CELL("format",I31),1)="C",I30+I31)) | K32: =IF(LEFT(CELL("format",K31),1)="P",K30*(1+K31),IF(LEFT(CELL("format",K31),1)="C",K30+K31)) | M32: =IF(LEFT(CELL("format",M31),1)="P",M30*(1+M31),IF(LEFT(CELL("format",M31),1)="C",M30+M31))
B33: Market Conditions | C33: N/A | D33: =D13 | E33: 0 | F33: =F13 | G33: 0 | H33: =H13 | I33: 0 | J33: =J13 | K33: 0 | L33: TBD | M33: 0
B34: Market Conditions Adjusted | E34: =IF(LEFT(CELL("format",E33),1)="P",E32*(1+E33),IF(LEFT(CELL("format",E33),1)="C",E32+E33)) | G34: =IF(LEFT(CELL("format",G33),1)="P",G32*(1+G33),IF(LEFT(CELL("format",G33),1)="C",G32+G33)) | I34: =IF(LEFT(CELL("format",I33),1)="P",I32*(1+I33),IF(LEFT(CELL("format",I33),1)="C",I32+I33)) | K34: =IF(LEFT(CELL("format",K33),1)="P",K32*(1+K33),IF(LEFT(CELL("format",K33),1)="C",K32+K33)) | M34: =IF(LEFT(CELL("format",M33),1)="P",M32*(1+M33),IF(LEFT(CELL("format",M33),1)="C",M32+M33))
B35: Total Quantified Adjustment | E35: =IFERROR(TEXT(E34-E23,"$#,##0.00")&CHAR(10)&" or "&CHAR(10)&TEXT((E34-E23)/E23,"0.00%"),0) | G35: =IFERROR(TEXT(G34-G23,"$#,##0.00")&CHAR(10)&" or "&CHAR(10)&TEXT((G34-G23)/G23,"0.00%"),0) | I35: =IFERROR(TEXT(I34-I23,"$#,##0.00")&CHAR(10)&" or "&CHAR(10)&TEXT((I34-I23)/I23,"0.00%"),0) | K35: =IFERROR(TEXT(K34-K23,"$#,##0.00")&CHAR(10)&" or "&CHAR(10)&TEXT((K34-K23)/K23,"0.00%"),0) | M35: =IFERROR(TEXT(M34-M23,"$#,##0.00")&CHAR(10)&" or "&CHAR(10)&TEXT((M34-M23)/M23,"0.00%"),0)
B36: Quantitatively Adjusted Price | E36: =E34 | G36: =G34 | I36: =I34 | K36: =K34 | M36: =M34
B37: Location | C37: ='Basic Sales Grid'!D28 | D37: Average
B38: Distance from Subject | C38: N/A
B39: Surrounding Land Uses | C39: Retail, residential, developable land
B40: Quality/Condition of Surrounding Area | C40: Average to New
B41: Access to Commercial Services/Amenities | C41: Good
B42: Visibility/Access | C42: Average- access and visibility from two secondary thoroughfares.
B43: Description | C43: Developing residential/retail area. Commercial thoroughfare exposure. Adjacent to anchored retail center.
B44: =B20 | C44: =C20 | D44: =D20
B45: Zoning | C45: =C21 | D45: =D21
B46: Utilities / Infrastructure | C46: Average | D46: Average
B47: Water/Sewer | C47: Available - Municipal Services | D47: Available - Municipal Services
B48: Electricity/Gas | C48: Available - Xcel Energy | D48: Available - Xcel Energy
B49: Other | C49: All available | D49: Historical Design
B50: Site Utility | C50: Average | D50: Average
B51: Site Shape | C51: Rectangular | D51: Rectangular
B52: Topography | C52: Generally Level | D52: Generally Level
B53: Easement/Encroachments/Obstructions | C53: None known | D53: None known
B54: Other | C54: None | D54: None
B55: Total Non Quantified Adj.
B56: Indication for Subject: | E56: =IF(LEFT(CELL("format",E55),1)="P",E36*(1+E55),IF(LEFT(CELL("format",E55),1)="C",E36+E55)) | G56: =IF(LEFT(CELL("format",G55),1)="P",G36*(1+G55),IF(LEFT(CELL("format",G55),1)="C",G36+G55)) | I56: =IF(LEFT(CELL("format",I55),1)="P",I36*(1+I55),IF(LEFT(CELL("format",I55),1)="C",I36+I55)) | K56: =IF(LEFT(CELL("format",K55),1)="P",K36*(1+K55),IF(LEFT(CELL("format",K55),1)="C",K36+K55)) | M56: =IF(LEFT(CELL("format",M55),1)="P",M36*(1+M55),IF(LEFT(CELL("format",M55),1)="C",M36+M55))
B59: VALUE CONCLUSION - UNDERLYING LAND AREA
B60: Indicated Value per SF
B61: Land Area (SF) | C61: =C44
B62: =IF(C63=0,"HIDE THIS ROW IF NO DEFERRED MAINTENANCE", "Indicated Value") | C62: =C60*C61
B63: Contract Price
B65: =IF(SUM(C63:C63)=0,"Indicated Value","Indicated Value - Adjusted") | C65: =C60*C61
B66: 5000 | C66: =ROUND((C65/B66),0)*B66
B67: Per SF | C67: =C66/C61

Sheet M&S Inputs
B1: MARSHALL AND SWIFT (MVS) REFERENCE ENGINE -- June 2024 Ed. (Section 99/98 multiplier inserts dated Jan 2025)
B2: ALL WORKING INPUTS LIVE ON THE 'COST APPROACH' TAB -- this sheet is locked MVS reference/lookup data only. Go to Cost Approach to value a property.
B4: CURRENT RESULT (mirrors the 'Cost Approach' tab)
B5: Total Replacement Cost New (RCN) | C5: ='Cost Approach'!G51
B6: Depreciated Value of Improvements | C6: ='Cost Approach'!G64
B7: Plus: Land Value | C7: ='Cost Approach'!G67
B8: INDICATED VALUE BY COST APPROACH | C8: ='Cost Approach'!G70
B11: MVS QUICK-REFERENCE TABLES -- DO NOT EDIT (sourced &amp; verified from the licensed MVS June 2024 edition; Sec.99/98 multiplier inserts dated Jan 2025)
B13: REFERENCE 1 -- Class of Construction Indicators (MVS Section 1, pp.4-9)
B14: Class | C14: Frame | D14: Floor | E14: Roof | F14: Walls
B15: A | C15: Structural steel columns and beams, fireproofed with masonry, concrete, plaster, or other noncombustible material. | D15: Concrete or concrete on steel deck, fireproofed. | E15: Formed concrete, precast slabs, concrete or gypsum on steel deck, fireproofed. | F15: Nonbearing curtain walls, masonry, concrete, metal and glass panels, stone, steel studs and masonry, tile or stucco, etc.
B16: B | C16: Reinforced concrete columns and beams. | D16: Concrete or concrete on steel deck, fireproofed. | E16: Formed concrete, precast slabs, concrete or gypsum on steel deck, fireproofed. | F16: Nonbearing curtain walls, masonry, concrete, metal and glass panels, stone, steel studs and masonry, tile or stucco, etc.
B17: C | C17: Masonry or concrete load-bearing walls with or without pilasters. Masonry, concrete or curtain walls with full or partial open steel, wood, or concrete frame. | D17: Wood or concrete plank on wood or steel floor joists, or concrete slab on grade. | E17: Wood or steel joists with wood or steel deck. Concrete plank. | F17: Brick, concrete block, or tile masonry, tilt-up, formed concrete, nonbearing curtain walls.
B18: D | C18: Wood or steel studs in bearing wall, full or partial open wood or steel frame, primarily combustible construction. | D18: Wood or steel floor joists or concrete slab on grade. | E18: Wood or steel joists with wood or steel deck. | F18: Almost any material except bearing or curtain walls of solid masonry or concrete. Generally combustible construction.
B19: S | C19: Metal bents, columns, girders, purlins and girts without fireproofing, incombustible construction. | D19: Wood or steel deck on steel floor joists, or concrete slab on grade. | E19: Steel or wood deck on steel joists. | F19: Metal skin or sandwich panels. Generally incombustible.
B21: REFERENCE 2 -- Quality Tier Definitions (MVS Section 1, pp.10-12)
B22: Quality | C22: Description
B23: Low Cost | C23: Constructed to minimum code requirements, little regard for architectural appearance, minimum investment, little ornamentation, minimal/low-quality interior finish.
B24: Average | C24: Largest group of buildings constructed (~50% of all buildings). Designed for maximum economic potential without pride-of-ownership amenities. Good standard code construction, simple ornamentation and finishes.
B25: Good | C25: Designed for good appearance, comfort and convenience with an element of prestige. Higher-quality ornamental treatment, interiors designed for upper-class rentals, better lighting and mechanical work.
B26: Excellent | C26: Prestige buildings. Part of cost is attributable to pride of ownership. Expensive finishes and fixtures; built for established professionals/institutions or high-profile tenants.
B28: REFERENCE 3 -- Occupancy Base Cost Tables (Calculator Method, $/SF)
B29: Occupancy Name | C29: Occ. Code | D29: Section | E29: Page | F29: Class | G29: Quality | H29: $/SF | I29: Lookup Key | J29: Story Tbl | K29: Sprinkler Tbl | L29: Elevator Tbl | M29: Citation
B30: Storage Warehouses | C30: 406 | D30: 14 | E30: 26 | F30: A | G30: Good | H30: 137 | I30: =B30&"~"&F30&"~"&G30 | J30: 14 | K30: 14 | L30: 14 | M30: MVS Sec.14 p.26
B31: Storage Warehouses | C31: 406 | D31: 14 | E31: 26 | F31: A | G31: Average | H31: 101 | I31: =B31&"~"&F31&"~"&G31 | J31: 14 | K31: 14 | L31: 14 | M31: MVS Sec.14 p.26
B32: Storage Warehouses | C32: 406 | D32: 14 | E32: 26 | F32: A | G32: Low Cost | H32: 79.5 | I32: =B32&"~"&F32&"~"&G32 | J32: 14 | K32: 14 | L32: 14 | M32: MVS Sec.14 p.26
B33: Storage Warehouses | C33: 406 | D33: 14 | E33: 26 | F33: B | G33: Good | H33: 121 | I33: =B33&"~"&F33&"~"&G33 | J33: 14 | K33: 14 | L33: 14 | M33: MVS Sec.14 p.26
B34: Storage Warehouses | C34: 406 | D34: 14 | E34: 26 | F34: B | G34: Average | H34: 88 | I34: =B34&"~"&F34&"~"&G34 | J34: 14 | K34: 14 | L34: 14 | M34: MVS Sec.14 p.26
B35: Storage Warehouses | C35: 406 | D35: 14 | E35: 26 | F35: B | G35: Low Cost | H35: 69 | I35: =B35&"~"&F35&"~"&G35 | J35: 14 | K35: 14 | L35: 14 | M35: MVS Sec.14 p.26
B36: Storage Warehouses | C36: 406 | D36: 14 | E36: 26 | F36: C | G36: Excellent | H36: 134 | I36: =B36&"~"&F36&"~"&G36 | J36: 14 | K36: 14 | L36: 14 | M36: MVS Sec.14 p.26
B37: Storage Warehouses | C37: 406 | D37: 14 | E37: 26 | F37: C | G37: Good | H37: 86.5 | I37: =B37&"~"&F37&"~"&G37 | J37: 14 | K37: 14 | L37: 14 | M37: MVS Sec.14 p.26
B38: Storage Warehouses | C38: 406 | D38: 14 | E38: 26 | F38: C | G38: Average | H38: 61 | I38: =B38&"~"&F38&"~"&G38 | J38: 14 | K38: 14 | L38: 14 | M38: MVS Sec.14 p.26
B39: Storage Warehouses | C39: 406 | D39: 14 | E39: 26 | F39: C | G39: Low Cost | H39: 43 | I39: =B39&"~"&F39&"~"&G39 | J39: 14 | K39: 14 | L39: 14 | M39: MVS Sec.14 p.26
B40: Storage Warehouses | C40: 406 | D40: 14 | E40: 26 | F40: CMILL | G40: Good | H40: 119 | I40: =B40&"~"&F40&"~"&G40 | J40: 14 | K40: 14 | L40: 14 | M40: MVS Sec.14 p.26
B41: Storage Warehouses | C41: 406 | D41: 14 | E41: 26 | F41: CMILL | G41: Average | H41: 82 | I41: =B41&"~"&F41&"~"&G41 | J41: 14 | K41: 14 | L41: 14 | M41: MVS Sec.14 p.26
... B289: Hotels, Limited Service | C289: 595 | D289: 11 | E289: 22 | F289: S | G289: Average | H289: 135 | I289: =B289&"~"&F289&"~"&G289 | J289: 11 | K289: 11 | L289: 11 | M289: MVS Sec.11 p.22
B291: REFERENCE 4 -- Occupancy Master List (dropdown source)
B292: Occupancy Name | C292: Occ. Code | D292: Section | E292: Page | F292: Story Table Section
B293: Storage Warehouses | C293: 406 | D293: 14 | E293: 26 | F293: 14
B294: Distribution Warehouses | C294: 407 | D294: 14 | E294: 23 | F294: 14
B295: Mini-Warehouses / Self-Storage | C295: 386 | D295: 14 | E295: 28 | F295: 14
B296: Mini-Warehouses, High-Rise | C296: 525 | D296: 14 | E296: 28 | F296: 14
B297: Industrials, Light Manufacturing | C297: 494 | D297: 14 | E297: 14 | F297: 14
B298: Industrials, Heavy (Process) Manufacturing | C298: 495 | D298: 14 | E298: 15 | F298: 14
B299: Service Garages (Commercial/Repair) | C299: 528 | D299: 14 | E299: 32 | F299: 14
B300: Retail Stores | C300: 353 | D300: 13 | E300: 26 | F300: 13
B301: Neighborhood Shopping Centers | C301: 412 | D301: 13 | E301: 33 | F301: 13
B302: Community Shopping Centers | C302: 413 | D302: 13 | E302: 34 | F302: 13
B303: Regional Shopping Centers | C303: 414 | D303: 13 | E303: 35 | F303: 13
... B310: Hotels, Limited Service | C310: 595 | D310: 11 | E310: 22 | F310: 11
B312: REFERENCE 5 -- Story Height Multiplier Tables (per MVS section, single-column for lookup)
B313: Section 14 (base = 14 ft) | C313: Height (ft) | D313: Multiplier
C314: 8 | D314: 0.885
C315: 10 | D315: 0.921
C316: 12 | D316: 0.96
C317: 14 | D317: 1
C318: 16 | D318: 1.041
C319: 18 | D319: 1.086
C320: 20 | D320: 1.133
C321: 22 | D321: 1.181
C322: 24 | D322: 1.231
C323: 26 | D323: 1.281
C324: 28 | D324: 1.331
C325: 30 | D325: 1.382
... C337: 120 | D337: 3.977
B339: Section 13 (base = 12 ft) | C339: Height (ft) | D339: Multiplier
C340: 8 | D340: 0.915
C341: 9 | D341: 0.936
C342: 10 | D342: 0.957
C343: 11 | D343: 0.979
C344: 12 | D344: 1
C345: 13 | D345: 1.021
C346: 14 | D346: 1.042
C347: 15 | D347: 1.064
C348: 16 | D348: 1.085
C349: 18 | D349: 1.127
C350: 20 | D350: 1.17
C351: 22 | D351: 1.213
... C357: 34 | D357: 1.468
B359: Section 15 (base = 12 ft) | C359: Height (ft) | D359: Multiplier
C360: 8 | D360: 0.9
C361: 9 | D361: 0.928
C362: 10 | D362: 0.953
C363: 11 | D363: 0.977
C364: 12 | D364: 1
C365: 13 | D365: 1.023
C366: 14 | D366: 1.046
C367: 15 | D367: 1.069
C368: 16 | D368: 1.092
C369: 18 | D369: 1.138
C370: 20 | D370: 1.184
C371: 24 | D371: 1.276
... C374: 36 | D374: 1.552
B376: Section 11 (base = 10 ft) | C376: Height (ft) | D376: Multiplier
C377: 7 | D377: 0.922
C378: 8 | D378: 0.947
C379: 9 | D379: 0.973
C380: 10 | D380: 1
C381: 11 | D381: 1.027
C382: 12 | D382: 1.055
...

Sheet Cost Approach
B1: COST APPROACH -- MVS Calculator
B2: Fill in the yellow cells only (Steps 1-3 below, plus the site-improvement/depreciation line items further down). Everything else calculates automatically from the MVS reference tables on the 'M&S Inputs' tab. Your final indicated value appears at the bottom of this sheet.
B3: STEP 1 -- BUILDING IDENTIFICATION
B4: Occupancy Type | C4: Storage Warehouses | I4: Choose the occupancy that best matches the subject improvement.
B5: Occupancy Code / Section / Page (auto) | C5: =IFERROR(INDEX(OCC_CODE,MATCH($C$4,OCC_NAME,0))&" | MVS Sec. "&INDEX(OCC_SECTION,MATCH($C$4,OCC_NAME,0))&" p."&INDEX(OCC_PAGE,MATCH($C$4,OCC_NAME,0)),"")
B6: Building Class | C6: C | I6: A=Fireproofed steel. B=Reinf. concrete. C=Masonry/steel-or-wood frame. D=Wood/combustible (DPOLE=pole-frame). S=Pre-engineered metal. See Class Reference on M&S Inputs.
B7: Quality | C7: Average | I7: Low Cost | Average | Good | Excellent (some occupancies also use Cheap). See Quality Reference on M&S Inputs.
B8: City / Local Area (for Local Multiplier) | C8: Denver | I8: Adams County has no dedicated MVS line -- 'Denver' is the recommended proxy (nearest larger city, per MVS's own guidance); 'Colorado (statewide average)' is the fallback.
B10: STEP 2 -- SIZE, SHAPE & SPRINKLER
B11: Avg Eave / Wall Height (ft) | C11: 18
B12: Area/Perimeter Multiplier Factor 1 | C12: 1 | I12: Look up your building's SF vs. average perimeter in the MVS Floor Area-Perimeter grid for this occupancy's section; enter the two bracketing values here to average.
B13: Area/Perimeter Multiplier Factor 2 | C13: 1
B14: Sprinkler Quality Tier | C14: Average | I14: Independent of building quality -- set to match the actual sprinkler system grade. Section 11 (hotels) has no verified sprinkler table; price manually if needed.
B16: STEP 3 -- APPRAISAL DATE & DE-TREND
B17: Appraisal / Level-of-Value Date | C17: =DATE(2024,6,30) | I17: Colorado's biennial reassessment fixes this at the end of the statutory base period. Current cycle: 7/1/2022-6/30/2024, level of value = 6/30/2024. Update to 6/30/2025 next cycle.
B18: Bracket Quarter - Earlier | C18: Apr 2024 | I18: Pick the two MVS Sec.98 Denver index quarters that straddle the Appraisal Date above (see Denver Index table on M&S Inputs). Rolls the Jan-2025-vintage multipliers below back to your actual valuation date.
B19: Bracket Quarter - Later | C19: Jul 2024
B21: COST APPROACH SUMMARY
B22: Replacement Cost New (RCN) | C22: Area (SF) | D22: $/SF | F22: Subtotal | G22: Total Cost
B23: Building Improvements
B24: Base Cost | C24: ='Property Info'!B5 | D24: =IFERROR(INDEX(BC_VALUE,MATCH($C$4&"~"&$C$6&"~"&$C$7,BC_KEY,0)),"NOT FOUND") | F24: =C24*D24 | I24: =IFERROR("Verified MVS base cost -- "&INDEX(BC_CITE,MATCH($C$4&"~"&$C$6&"~"&$C$7,BC_KEY,0)),"")&" | Area auto-linked to Property Info!B5 (GBA)."
B25: Sprinklers | C25: =C24 | D25: =IFERROR(IF(INDEX(OCC_STORY,MATCH($C$4,OCC_NAME,0))="14",INDEX(SPR14_VALS,MATCH($C$24,SPR14_SF,1),MATCH($C$14,SPR_HDR,0)),IF(INDEX(OCC_STORY,MATCH($C$4,OCC_NAME,0))="13",INDEX(SPR13_VALS,MATCH($C$24,SPR13_SF,1),MATCH($C$14,SPR_HDR,0)),IF(INDEX(OCC_STORY,MATCH($C$4,OCC_NAME,0))="15",INDEX(SPR15_VALS,MATCH($C$24,SPR15_SF,1),MATCH($C$14,SPR_HDR,0)),0))),0) | F25: =C25*D25 | I25: Wet-system cost, by building SF (nearest coverage bracket <= actual SF). Enter 0 manually below if unsprinklered.
B31: Subtotal | F31: =SUM(F24:F30)
B32: Multipliers
B33: Current Cost (de-trended to Appraisal Date) | D33: =IFERROR(INDEX(CCM_VALUES,MATCH(IF($C$6="CMILL","C",IF($C$6="DPOLE","D",IF($C$6="A-B","B",$C$6))),CCM_CLASS,0),MATCH("Sec."&INDEX(OCC_SECTION,MATCH($C$4,OCC_NAME,0)),CCM_SECTIONHDR,0)),"")/IFERROR(INDEX(DEN_VALUES,MATCH($C$18,DEN_LABEL,0),MATCH("Class "&IF($C$6="CMILL","C",IF($C$6="DPOLE","D",IF($C$6="A-B","B",$C$6))),DEN_CLASSHDR,0))+(INDEX(DEN_VALUES,MATCH($C$19,DEN_LABEL,0),MATCH("Class "&IF($C$6="CMILL","C",IF($C$6="DPOLE","D",IF($C$6="A-B","B",$C$6))),DEN_CLASSHDR,0))-INDEX(DEN_VALUES,MATCH($C$18,DEN_LABEL,0),MATCH("Class "&IF($C$6="CMILL","C",IF($C$6="DPOLE","D",IF($C$6="A-B","B",$C$6))),DEN_CLASSHDR,0)))*($C$17-DATEVALUE("1 "&$C$18))/(DATEVALUE("1 "&$C$19)-DATEVALUE("1 "&$C$18)),1) | I33: MVS Sec.99 p.3 Current Cost Multiplier (WESTERN region assumed for Colorado) divided by the Sec.98 Denver de-trend factor for the Appraisal Date -- see Step 3.
B34: Local Area | D34: =IFERROR(INDEX(LAM_VALUES,MATCH($C$8,LAM_CITY,0),MATCH("Class "&IF($C$6="CMILL","C",IF($C$6="DPOLE","D",IF($C$6="A-B","B",$C$6))),LAM_CLASSHDR,0)),"") | I34: MVS Sec.99 p.7 Local Area Multiplier.
B35: Area/Perimeter Multiplier | D35: =AVERAGE(C12:C13)
B36: Story Height (Height entered in Step 2) | D36: =IFERROR(IF(INDEX(OCC_STORY,MATCH($C$4,OCC_NAME,0))="14",INDEX(SH14_M,MATCH($C$11,SH14_H,1)),IF(INDEX(OCC_STORY,MATCH($C$4,OCC_NAME,0))="13",INDEX(SH13_M,MATCH($C$11,SH13_H,1)),IF(INDEX(OCC_STORY,MATCH($C$4,OCC_NAME,0))="15",INDEX(SH15_M,MATCH($C$11,SH15_H,1)),IF(INDEX(OCC_STORY,MATCH($C$4,OCC_NAME,0))="11",INDEX(SH11_M,MATCH($C$11,SH11_H,1)),1)))),1)
B37: Product of Multipliers | F37: =ROUND(PRODUCT(D33:D36),3)
B38: Adjusted Base Building Cost | G38: =F37*F31
B39: Site Improvements (enter your own measured quantities in the Area column)
B40: Parking/Loading Areas (asphalt) | D40: 3.1 | F40: =D40*C40 | I40: MVS Sec.66 p.1, 4-inch asphalt (large areas >3,000 SF), average of low-high range. Enter your own measured SF in the Area column.
B41: Striping (Per Space) | D41: 20 | F41: =D41*C41 | I41: Market-derived; no dedicated MVS table. Enter number of striped spaces in the Area column.
B42: Paving (concrete) | D42: 5.51 | F42: =D42*C42 | I42: MVS Sec.66 p.1, 6-inch concrete (large areas >3,000 SF), average of low-high range.
B43: Other1 | F43: =D43*C43
B44: Other2 | F44: =D44*C44
B45: Landscaping, Lighting, Other Site Improvements | D45: 5.5 | F45: =D45*C45 | I45: MVS Sec.66 landscaping / market estimate. Enter your own measured lot SF in the Area column.
B46: Total Site Improvements | G46: =SUM(F40:F45)
B47: Total Construction Costs | G47: =SUM(G38:G46)
B48: Plus Other Indirect Costs (% of Direct Costs) | C48: 0.1 | G48: =G47*(C48) | I48: Financing, permits, professional fees, insurance during construction. Typical 8-15%.
B49: Subtotal Replacement Cost New (RCN) | G49: =SUM(G47:G48)
B50: Plus Entrepreneurial Profit (% of RCN) | C50: 0.15 | G50: =G49*C50 | I50: Developer expected return above cost. Typical 10-20%.
B51: Total Replacement Cost New (RCN) | G51: =SUM(G49:G50)
B52: per square foot of gross building area | G52: =caRCN/C24
B54: Less Accrued Depreciation
B55: Physical
B56: Curable (Deferred Maintenance) | F56: 0 | I56: Dollar cost to cure deferred items (roof, HVAC, etc). 0 = none.
B57: Incurable
B58: Effective Age (Years) | C58: 0 | I58: Per MVS Sec.97: true age adjusted for modernization/condition, not necessarily chronological age. Judgment call from inspection.
B59: Typical Life Expectancy (MVS Sec.97, auto) | C59: =IFERROR(INDEX(LIFE_VALUES,MATCH($C$4&"~"&$C$7,LIFE_KEY,0),MATCH("Class "&IF($C$6="CMILL","C",IF($C$6="DPOLE","D",IF($C$6="A-B","B",$C$6))),LIFE_CLASSHDR,0)),"n/a for this Class/Quality -- see Life Expectancy table on M&S Inputs") | I59: MVS Sec.97 pp.10-13, by occupancy/quality/class.
B60: Total Incurable Physical Depreciation (MVS Sec.97 percent-good curve) | C60: =IFERROR(INDEX(DEPR_VALUES,MATCH($C$58,DEPR_AGE,1),MATCH($C$59,DEPR_LIFEHDR,0))/100,"n/a -- age exceeds tabulated range; treat as fully depreciated per Sec.97 salvage guidance") | F60: =G51*C60 | I60: MVS Sec.97 p.24, Commercial Properties percent-good table -- replaces a naive straight-line age/life ratio.
B61: Functional Obsolescence | C61: 0 | F61: =C61*caRCN | I61: Loss from design deficiencies (excess bays, substandard ceiling height, etc). 0 = none.
B62: External Obsolescence | C62: 0 | F62: =C62*caRCN | I62: Loss from external/locational/market factors. 0 = none.
B63: Total | C63: =G63/caRCN | G63: =SUM(F56:F62)
B64: Depreciated Value of the Improvements | G64: =caRCN-G63
B65: per square foot of gross building area | G65: =caRCNDeprec/C24
B67: Plus Land Value | G67: ='Land Sales'!C65 | I67: Set to the value concluded on the Land Sales worksheet. If using a land value from another source, overwrite this cell directly.
B69: Indicated Value by Cost Approach | G69: =G64+G67
B70: 5000 | G70: =ROUND((G69/B70),0)*B70 | I70: Rounded to the nearest $5,000 (change the value in column B to round to a different increment).
B71: per square foot of gross building area | G71: =G70/C24
B73: MVS June 2024 Ed. | C73: =IFERROR(INDEX(BC_OCC,MATCH($C$4&"~"&$C$6&"~"&$C$7,BC_KEY,0)),"")&" | "&$C$4 | D73: ="Class: "&$C$6&" / "&$C$7
B74: Colorado -- WESTERN region (assumed) | C74: ="CCM/De-trend: "&TEXT(D33,"0.000")&" | LAM: "&TEXT(D34,"0.000") | D74: ="Sec.99 p.3/p.7 (Jan 2025 insert) + Sec.98 Denver de-trend"
C75: ="Story Ht Mult: "&TEXT(D36,"0.000")&" | Area Mult: "&TEXT(D35,"0.000")

Sheet Construction Costs
B2: Subject's Budgeted Construction Costs
B3: Item | C3: Cost | D3: Cost PSF
B4: Site Inspection, Architectural & Engineering | D4: =C4/'Property Info'!$B$5
B5: Government Fees & Permits | D5: =C5/'Property Info'!$B$5
B6: Site Improvements | D6: =C6/'Property Info'!$B$5
B7: Off-Site Construction | D7: =C7/'Property Info'!$B$5
B8: Vertical Improvements | D8: =C8/'Property Info'!$B$5
B9: Contractor Overhead & Profit | D9: =C9/'Property Info'!$B$5
B10: Inderect Costs | D10: =C10/'Property Info'!$B$5
B11: Total | C11: =SUM(C4:C10) | D11: =C11/'Property Info'!$B$5
F12: Comparable Constrution Cots
F13: Comparable
F14: Location
F15: YOC
F16: Property Type
F17: Total Direct Cost

Sheet Export030823
B1: Property Address | C1: Property City | D1: Account/Parcel | E1: Property Type | F1: Sale Date | G1: Sale Price | H1: Price ($/SF) | I1: Asking Price | J1: DOM | K1: Building SF | L1: Land Area SF | M1: Property Rights Conveyed | N1: Financing | O1: Terms/ Conditions of Sale | P1: Expenditures After Sale | Q1: Market Conditions | R1: Location | S1: Property Size (SF) | T1: YOC / Condition | U1: Quality | V1: Land-To-Building Ratio | W1: Tenancy / Occupancy | X1: Functional Utility | Y1: Total Net Adj. | Z1: Adjusted Price ($/SF)

Sheet Basic Sales Grid
C2: COMPARABLE SALE ADJUSTMENT GRID
D3: Subject | E3: Sale 1 | F3: Sale 2 | G3: Sale 3 | H3: Sale 4 | I3: Sale 5 | J3: Listing 1
C4: Address | D4: =Export030823!B2 | E4: =Export030823!B3 | F4: =Export030823!B4 | G4: =Export030823!B5 | H4: =Export030823!B6 | I4: =Export030823!B7
C5: City, State | D5: =Export030823!C2 | E5: =Export030823!C3 | F5: =Export030823!C4 | G5: =Export030823!C5 | H5: =Export030823!C6 | I5: =Export030823!C7
C6: Parcel Number | D6: =Export030823!D2 | E6: =Export030823!D3 | F6: =Export030823!D4 | G6: =Export030823!D5 | H6: =Export030823!D6 | I6: =Export030823!D7
C7: Property Type | D7: =Export030823!E2 | E7: =Export030823!E3 | F7: =Export030823!E4 | G7: =Export030823!E5 | H7: =Export030823!E6 | I7: =Export030823!E7
C8: Sale Date | D8: N/A | E8: =Export030823!F3 | F8: =Export030823!F4 | G8: =Export030823!F5 | H8: =Export030823!F6 | I8: =Export030823!F7
C9: Sale Price | D9: N/A | E9: =Export030823!G3 | F9: =Export030823!G4 | G9: =Export030823!G5 | H9: =Export030823!G6 | I9: =Export030823!G7
C10: Listing Price | D10: N/A | E10: =Export030823!I3 | F10: =Export030823!I4 | G10: =Export030823!I5 | H10: =Export030823!I6 | I10: =Export030823!I7 | K10: 6769231
C11: Days On Market | D11: N/A | E11: =Export030823!J3 | F11: =Export030823!J4 | G11: =Export030823!J5 | H11: =Export030823!J6 | I11: =Export030823!J7
C12: Data Source | D12: Inspection, Lease, Site Plans, Assessor | E12: CoStar, Assessor, Deed | F12: CoStar, Assessor, Deed | G12: CoStar, Assessor, Deed | H12: CoStar, Assessor, Deed | I12: CoStar, Assessor, Offering Memorandum
C13: Property Size (SF) | D13: =Export030823!K2 | E13: =Export030823!K3 | F13: =Export030823!K4 | G13: =Export030823!K5 | H13: =Export030823!K6 | I13: =Export030823!K7
C14: Site Size (SF) | D14: =Export030823!L2 | E14: =Export030823!L3 | F14: =Export030823!L4 | G14: =Export030823!L5 | H14: =Export030823!L6 | I14: =Export030823!L7
C15: Parking Spaces | D15: 41
C16: Comments
C17: Unadjusted Price Per SF | E17: =E9/E13 | F17: =F9/F13 | G17: =G9/G13 | H17: =H9/H13 | I17: =I9/I13 | K17: =K10/J13
C18: Quantified Adjustments
C19: Sale Type | D19: =Export030823!M2 | E19: =Export030823!M3 | F19: =Export030823!M4 | G19: =Export030823!M5 | H19: =Export030823!M6 | I19: =Export030823!M7 | J19: Leased Fee
C20: Financing | D20: Market Based | E20: =Export030823!N3 | F20: =Export030823!N4 | G20: =Export030823!N5 | H20: =Export030823!N6 | I20: =Export030823!N7
C21: Terms/Conditions of Sale | D21: None | E21: =Export030823!O3 | F21: =Export030823!O4 | G21: =Export030823!O5 | H21: =Export030823!O6 | I21: =Export030823!O7 | J21: Active Listing
C22: Expenditures After Sale | D22: None | E22: =Export030823!P3 | F22: =Export030823!P4 | G22: =Export030823!P5 | H22: =Export030823!P6 | I22: =Export030823!P7
C23: Market Conditions | D23: N/A | E23: =Export030823!Q3 | F23: =Export030823!Q4 | G23: =Export030823!Q5 | H23: =Export030823!Q6 | I23: =Export030823!Q7
C24: Market Conditions Adjusted | E24: =IF(LEFT(CELL("format",E23),1)="P",#REF!*(1+E23),IF(LEFT(CELL("format",E23),1)="C",#REF!+E23)) | F24: =IF(LEFT(CELL("format",F23),1)="P",#REF!*(1+F23),IF(LEFT(CELL("format",F23),1)="C",#REF!+F23)) | G24: =IF(LEFT(CELL("format",G23),1)="P",#REF!*(1+G23),IF(LEFT(CELL("format",G23),1)="C",#REF!+G23)) | H24: =IF(LEFT(CELL("format",H23),1)="P",#REF!*(1+H23),IF(LEFT(CELL("format",H23),1)="C",#REF!+H23)) | I24: =IF(LEFT(CELL("format",I23),1)="P",#REF!*(1+I23),IF(LEFT(CELL("format",I23),1)="C",#REF!+I23))
C25: Total Quantified Adjustment | E25: =SUM(E19:E23) | F25: =SUM(F19:F23) | G25: =SUM(G19:G23) | H25: =SUM(H19:H23) | I25: =SUM(I19:I23)
C26: Quantitatively Adjusted Price | E26: =E17+(E17*E25) | F26: =F17+(F17*F25) | G26: =G17+(G17*G25) | H26: =H17+(H17*H25) | I26: =I17+(I17*I25)
C27: Qualitative Adjustments
C28: =Export030823!R1 | D28: =Export030823!R2 | E28: =Export030823!R3 | F28: =Export030823!R4 | G28: =Export030823!R5 | H28: =Export030823!R6 | I28: =Export030823!R7 | J28: Good
C29: =Export030823!S1 | D29: =Export030823!S2 | E29: =Export030823!S3 | F29: =Export030823!S4 | G29: =Export030823!S5 | H29: =Export030823!S6 | I29: =Export030823!S7 | J29: =J13
C30: =Export030823!T1 | D30: =Export030823!T2 | E30: =Export030823!T3 | F30: =Export030823!T4 | G30: =Export030823!T5 | H30: =Export030823!T6 | I30: =Export030823!T7 | J30: 2019 / Very Good
C31: =Export030823!U1 | D31: =Export030823!U2 | E31: =Export030823!U3 | F31: =Export030823!U4 | G31: =Export030823!U5 | H31: =Export030823!U6 | I31: =Export030823!U7 | J31: Good
C32: =Export030823!V1 | D32: =Export030823!V2 | E32: =Export030823!V3 | F32: =Export030823!V4 | G32: =Export030823!V5 | H32: =Export030823!V6 | I32: =Export030823!V7 | J32: =ROUND((J15/J13)*1000,2)& ":1,000 SF"
C33: =Export030823!W1 | D33: =Export030823!W2 | E33: =Export030823!W3 | F33: =Export030823!W4 | G33: =Export030823!W5 | H33: =Export030823!W6 | I33: =Export030823!W7 | J33: Good
C34: =Export030823!X1 | D34: =Export030823!X2 | E34: =Export030823!X3 | F34: =Export030823!X4 | G34: =Export030823!X5 | H34: =Export030823!X6 | I34: =Export030823!X7 | J34: Good
C35: Total Non Quantified Adj. | E35: =SUM(E28,E29,E30,E31,E32,E33,E34) | F35: =SUM(F28,F29,F30,F31,F32,F33,F34) | G35: =SUM(G28,G29,G30,G31,G32,G33,G34) | H35: =SUM(H28,H29,H30,H31,H32,H33,H34) | I35: =SUM(I28,I29,I30,I31,I32,I33,I34) | K35: =SUM(K28,K29,K30,K31,K32,K33,K34)
C36: Indication for Subject: | E36: =E26+(E26*E35) | F36: =F26+(F26*F35) | G36: =G26+(G26*G35) | H36: =H26+(H26*H35) | I36: =I26+(I26*I35) | K36: =IF(LEFT(CELL("format",K35),1)="P",K26*(1+K35),IF(LEFT(CELL("format",K35),1)="C",K26+K35))
C39: SALES COMPARISON APPROACH VALUE CONCLUSION
C40: Indicated Value per SF
C41: Building Area (SF) | D41: ='Property Info'!B5
C42: =IF(D43=0,"HIDE THIS ROW IF NO DEFERRED MAINTENANCE", "Indicated Value") | D42: =D40*D41
C43: Contract Price | D43: 0
C44: =D42+D43
C45: =IF(SUM(D43:D43)=0,"Indicated Value","Indicated Value - Adjusted") | D45: =C44
C46: 5000 | D46: =ROUND((D45/C46),0)*C46
C47: Per SF | D47: =D46/D41
C51: Assessor's Assigned Value | D51: ='Property Info'!B21 | E51: =D51/D29
C52: Petition Value | D52: ='Property Info'!B22 | E52: ='Basic Sales Grid'!D52/'Basic Sales Grid'!D29 | O52: COMPARABLE SALE SEARCH
O53: SEARCH FOR COMPARABLE SALES
O54: Property Type Searched
O55: Search Radius
O56: SF Parameters
O57: Property Rights Conveyed
O58: COMPARABLES UTILIZED
O59: Sales
O60: Confirmations
R63: RANKING OF THE SUBJECT PROPERTY
R64: COMPARABLE | S64: VALUE PSF | T64: COMPARISON
R65: 4 | S65: =H36 | T65: Below
R66: 2 | S66: =F36 | T66: Below
R67: Subject
R68: 3 | S68: =G36 | T68: Above
R69: 1 | S69: =E36 | T69: Above
R70: 1 | T70: Inferior

Sheet Detailed Sales Grid
C2: COMPARABLE SALE ADJUSTMENT GRID
D3: Subject | E3: Sale 1 | G3: Sale 2 | I3: Sale 3 | K3: Sale 4 | M3: Sale 5 | O3: Listing 1
C4: Address
C5: City, State
C6: Parcel Number
C7: Property Type
C8: Sale Date
C9: Sale Price
C10: Listing Price
C11: Days On Market
C12: Data Source
C13: Property Size (SF)
C14: Site Size (SF)
C15: Parking Spaces
... C59: Indication for Subject:

Sheet LA
B2: LEASE ABSTRACT
B3: Lessor | G3: Annual Rent Calc. Table
B4: Lessee | G4: Month | H4: Monthly Rent
B5: Building Size (SF)
B6: Lease Sign Date
B7: Lease Commencement Date
B8: Lease Expiration Date
B9: Base Lease Term (Months) | C9: =+(C8-C7)/365*12
B10: 12 Months Contract Rental Income (Jan-Dec 2020) | C10: =H17
B11: 12 Months Contract Rental Income (Jan-Dec 2020) | C11: =C10/C5
B12: Base Rents | D12: Annual Rent (Lease)
B13: Year 1 (11/16-10/17) | C13: =D13/$C$5
B14: Year 2 (11/17-10/18) | C14: =D14/$C$5
B15: Year 3 (11/18-10/19) | C15: =D15/$C$5
B16: Year 4 (11/19-10/20) | C16: =D16/$C$5
B17: Year 5 (11/20-10/21) | C17: =D17/$C$5 | G17: Total | H17: =SUM(H5:H16)
B18: Frist Renewal Period | G18: PSF | H18: =H17/FE!C14
B19: Year 6 | C19: =D19/$C$5
B20: Year 7 | C20: =D20/$C$5
B21: Year 8 | C21: =D21/$C$5
B22: Year 9 | C22: =D22/$C$5
B23: Year 10 | C23: =D23/$C$5
B24: Year 11 | C24: =D24/$C$5
B29: Expense Structure | C29: NNN
B30: Landlord Expense Responsibilities
B31: Tenant Expense Responsibilities
B32: Comments
B33: Purchase Options | C33: None
B34: Termination Clause | C34: None
B35: Guarantor | C35: None
B36: Other
B37: Source | C37: Lease Agreement, owner, inspection, assessor data

Sheet LAG Percent
A2: COMPARABLE LEASE ADJUSTMENT GRID
A3: Characteristics | C3: Subject | E3: Lease 1 | G3: Lease 2 | I3: Lease 3 | K3: Lease 4 | M3: Rent 5
A4: Address | C4: ='Property Info'!B17
A5: City | C5: ='Property Info'!B18
A6: Distance from Subject | C6: N/A | E6: 1 mile | G6: 1 mile | I6: 1 mile | K6: 1/4 mile | M6: 1 mile
A7: Data Source | C7: ='Detailed Sales Grid'!D12 | E7: CoStar, Assessor, OM | G7: CoStar, Assessor, OM | I7: CoStar, Assessor, OM | K7: CoStar, Broker, Listing | M7: CoStar, Assessor
A8: Proximity to Subject | C8: N/A | E8: 1.5 miles | G8: 1.5 miles | I8: 1.5 miles | K8: 5.0 miles | M8: 3.0 miles
A9: Building Size | C9: ='Property Info'!B5
A10: Vacancy | D10: =C10/C9 | E10: 0 | F10: 0 | G10: 0 | H10: 0 | I10: 0 | J10: 0 | K10: 0 | L10: 0 | M10: 0 | N10: 0
A11: Parking Ratio | D11: =ROUND((C11/C9)*1000,2)&":1,000SF" | E11: 19 | F11: =ROUND((E11/E9)*1000,2)&":1,000SF" | G11: 19 | H11: =ROUND((G11/G9)*1000,2)&":1,000SF" | I11: 19 | J11: =ROUND((I11/I9)*1000,2)&":1,000SF" | K11: 19 | L11: =ROUND((K11/K9)*1000,2)&":1,000SF" | M11: 19 | N11: =ROUND((M11/M9)*1000,2)&":1,000SF"
A12: Representative Lease
A13: Actual or Asking Lease Rate | C13: N/A | E13: Actual | G13: Actual | I13: Actual | K13: Actual | M13: Actual
A14: Tenant | C14: =LA!C4
A15: SF Area Leased | C15: ='Property Info'!B5 | E15: =E9 | G15: 22248 | I15: 20000 | K15: 37044 | M15: =M9
A16: Commencement
A17: Term | E17: 3 Years | G17: 5 Years | I17: 3 Years | K17: 3 Years | M17: 5 Years
A18: TI Allowance | C18: N/A | E18: N/R | G18: N/R | I18: N/R | K18: N/R | M18: N/R
A19: Lease Rate Expense Structure | C19: NNN | E19: NNN | G19: NNN | I19: NNN | K19: NNN | M19: NNN
A20: Base Annual Rent | C20: =LA!C11
A21: Expense Adjustments | C21: N/A | E21: 0 | G21: 0 | I21: 0 | K21: 0 | M21: 0
A22: Adjusted Rent (NNN) | C22: =C20 | E22: =E20+E21 | G22: =G20+G21 | I22: =I20+I21 | K22: =K20+K21 | M22: =M20+M21
A23: Adjustments | C23: Description | E23: Description | F23: Adj. | G23: Description | H23: Adj. | I23: Description | J23: Adj. | K23: Description | L23: Adj. | M23: Description | N23: Adj.
A24: Market Trends | C24: N/A | E24: =E16 | F24: 0 | G24: =G16 | H24: 0 | I24: =I16 | J24: 0 | K24: =K16 | L24: 0 | M24: =M16 | N24: 0.1
A25: Economics/Tenancy | C25: Industrial, Average Credit Risk | E25: Industrial, Average Credit Risk | F25: 0 | G25: Industrial, Average Credit Risk | H25: 0 | I25: Industrial, Average Credit Risk | J25: 0 | K25: Industrial, Average Credit Risk | L25: 0 | M25: Local Tenant - Good Quality | N25: 0.1
A26: Location | C26: =Export030823!R2 | E26: Average | F26: 0 | G26: Average | H26: 0 | I26: Average | J26: 0 | K26: Average | L26: 0 | N26: 0
A27: Age/Condition | C27: =Export030823!T2 | E27: 1972/Average | F27: 0 | G27: 1971/Fair | H27: 0.1 | I27: 1922 (Ren.)/ Above-Average | J27: -0.05 | K27: 1954/Average | L27: 0 | M27: 2014 (Ren.)/Above-Average | N27: 0.1
A28: Size (SF) | C28: =C15 | E28: =E15 | F28: 0 | G28: =G15 | H28: -0.05 | I28: =I15 | J28: -0.05 | K28: =K15 | L28: 0 | M28: =M15 | N28: -0.05
A29: Quality | C29: =Export030823!U2 | E29: Average | F29: 0 | G29: Average | H29: 0 | I29: Average | J29: 0 | K29: Average | L29: 0 | M29: Good | N29: 0
A30: Land-To-Building Ratio | C30: =Export030823!V2 | E30: =75359/E9 | F30: 0 | G30: =143748/G9 | H30: 0 | I30: =87120/I9 | J30: 0 | K30: =91912/K9 | L30: 0 | M30: 5.52 | N30: -0.05
A31: Functional Utility | C31: =Export030823!X2 | E31: Good: I-3 Zoning | F31: -0.1 | G31: Average | H31: 0 | I31: Above-Average: I-B Zoning | J31: -0.05 | K31: Average | L31: 0 | M31: Average | N31: 0
A32: Subtotal Net Adjustments | F32: =SUM(F24:F31) | H32: =SUM(H24:H31) | J32: =SUM(J24:J31) | L32: =SUM(L24:L31) | N32: =SUM(N24:N31)
A33: Adjusted Lease Rate Per Square Foot | F33: =+E22*(1+F32) | H33: =+G22*(1+H32) | J33: =+I22*(1+J32) | L33: =+K22*(1+L32) | N33: =+M22*(1+N32)
F36: =F33
F37: =H33
F38: =J33
F39: =L33
E41: =(E28-$C$28)/$C$28 | G41: =(G28-$C$28)/$C$28 | I41: =(I28-$C$28)/$C$28 | K41: =(K28-$C$28)/$C$28

Sheet IS Summary
C3: SUMMARY OF IMPROVED SALES
C4: No. | D4: Type | E4: Property Type / Location | F4: Date of Sale | G4: Property Rights | H4: Year Built | I4: Bldg. Size (SF) | J4: Site Size (SF) (Acres) | K4: Building Footprint | L4: Coverage Ratio | M4: Percent Office | N4: Clear Heights (ft.) | O4: Occupancy | P4: Sale Price | Q4: Price PSF | R4: Overall Rate
C5: =ROW()-4 | D5: Sale | O5: Vacant at TOS | P5: 1800000 | Q5: =P5/I5 | R5: N/A
C9: 2 | D9: Sale | O9: Vacant at TOS | P9: 1350000 | Q9: =P9/I9 | R9: N/A
C13: 3 | D13: Sale | O13: Vacant at TOS | P13: 530000 | Q13: =P13/I13 | R13: 0.074
C17: 4 | D17: Sale | O17: Vacant at TOS | P17: 417000 | Q17: =P17/I17 | R17: 0.065
C21: 5 | D21: Sale | O21: Vacant at TOS | P21: 400000 | Q21: =P21/I21 | R21: 0.055
C25: Subj. | E25: ='Property Info'!B15 | H25: ='Property Info'!B8 | I25: ='Property Info'!B5 | J25: ='Property Info'!B11 | K25: ='Property Info'!B5 | L25: ='Property Info'!B13 | M25: ='Property Info'!B14 | N25: ='Property Info'!#REF! | O25: ='Property Info'!B19
E26: ='Property Info'!B16 | J26: ='Property Info'!B12
E27: ='Property Info'!B17

Sheet HOA
C2: HISTORICAL OPERATING ANALYSIS
AA3: =LA!C5
S4: Budget | V4: BBG Projection*
D5: Total | E5: per SF | G5: Total | H5: per SF | J5: Total | K5: per SF | M5: Total | N5: per SF | P5: Total | Q5: per SF | S5: Total | T5: per SF | V5: Total | W5: per SF
C6: Rental Income | D6: =SUMIF(Category,$B6,AMTY1) | E6: =D6/NRA | G6: =SUMIF(Category,$B6,AMTY2) | H6: =G6/NRA | J6: =SUMIF(Category,$B6,AMTY3) | K6: =J6/NRA | N6: =M6/$AA$3 | Q6: =P6/$AA$3 | S6: =SUMIF(Category,$B6,AmtBdgt) | T6: =S6/NRA | V6: =[3]ProForma!C3 | W6: =V6/NRA
C7: Operating Expense Recoveries | D7: =SUMIF(Category,$B7,AMTY1) | E7: =D7/NRA | G7: =SUMIF(Category,$B7,AMTY2) | H7: =G7/NRA | J7: =SUMIF(Category,$B7,AMTY3) | K7: =J7/NRA | N7: =M7/$AA$3 | Q7: =P7/$AA$3 | S7: =SUMIF(Category,$B7,AmtBdgt) | T7: =S7/NRA | V7: =[3]ProForma!C4 | W7: =V7/NRA
C8: Parking | D8: =SUMIF(Category,$B8,AMTY1) | E8: =D8/NRA | G8: =SUMIF(Category,$B8,AMTY2) | H8: =G8/NRA | J8: =SUMIF(Category,$B8,AMTY3) | K8: =J8/NRA | M8: =SUMIF(Category,$B8,AMTY4) | N8: =M8/$AA$3 | P8: =SUMIF(Category,$B8,AMTY5) | Q8: =P8/$AA$3 | S8: =SUMIF(Category,$B8,AmtBdgt) | T8: =S8/NRA | V8: =W8*NRA | W8: 0
C9: Late Charges | D9: =SUMIF(Category,$B9,AMTY1) | E9: =D9/NRA | G9: =SUMIF(Category,$B9,AMTY2) | H9: =G9/NRA | J9: =SUMIF(Category,$B9,AMTY3) | K9: =J9/NRA | M9: =SUMIF(Category,$B9,AMTY4) | N9: =M9/$AA$3 | P9: =SUMIF(Category,$B9,AMTY5) | Q9: =P9/$AA$3 | S9: =SUMIF(Category,$B9,AmtBdgt) | T9: =S9/NRA | V9: =W9*NRA | W9: 0
C10: NSF Fee Income | D10: =SUMIF(Category,$B10,AMTY1) | E10: =D10/NRA | G10: =SUMIF(Category,$B10,AMTY2) | H10: =G10/NRA | J10: =SUMIF(Category,$B10,AMTY3) | K10: =J10/NRA | M10: =SUMIF(Category,$B10,AMTY4) | N10: =M10/$AA$3 | P10: =SUMIF(Category,$B10,AMTY5) | Q10: =P10/$AA$3 | S10: =SUMIF(Category,$B10,AmtBdgt) | T10: =S10/NRA | V10: =W10*NRA | W10: 0
C11: Keys, Lock, Lock Charge | D11: =SUMIF(Category,$B11,AMTY1) | E11: =D11/NRA | G11: =SUMIF(Category,$B11,AMTY2) | H11: =G11/NRA | J11: =SUMIF(Category,$B11,AMTY3) | K11: =J11/NRA | M11: =SUMIF(Category,$B11,AMTY4) | N11: =M11/$AA$3 | P11: =SUMIF(Category,$B11,AMTY5) | Q11: =P11/$AA$3 | S11: =SUMIF(Category,$B11,AmtBdgt) | T11: =S11/NRA | V11: =W11*NRA | W11: 0
C12: Lease Termination Fee Income | D12: =SUMIF(Category,$B12,AMTY1) | E12: =D12/NRA | G12: =SUMIF(Category,$B12,AMTY2) | H12: =G12/NRA | J12: =SUMIF(Category,$B12,AMTY3) | K12: =J12/NRA | M12: =SUMIF(Category,$B12,AMTY4) | N12: =M12/$AA$3 | P12: =SUMIF(Category,$B12,AMTY5) | Q12: =P12/$AA$3 | S12: =SUMIF(Category,$B12,AmtBdgt) | T12: =S12/NRA | V12: =W12*NRA | W12: 0
C13: Legal and Collection Fee Income | D13: =SUMIF(Category,$B13,AMTY1) | E13: =D13/NRA | G13: =SUMIF(Category,$B13,AMTY2) | H13: =G13/NRA | J13: =SUMIF(Category,$B13,AMTY3) | K13: =J13/NRA | M13: =SUMIF(Category,$B13,AMTY4) | N13: =M13/$AA$3 | P13: =SUMIF(Category,$B13,AMTY5) | Q13: =P13/$AA$3 | S13: =SUMIF(Category,$B13,AmtBdgt) | T13: =S13/NRA | V13: =W13*NRA | W13: 0
C14: Storage Space Rental | D14: =SUMIF(Category,$B14,AMTY1) | E14: =D14/NRA | G14: =SUMIF(Category,$B14,AMTY2) | H14: =G14/NRA | J14: =SUMIF(Category,$B14,AMTY3) | K14: =J14/NRA | M14: =SUMIF(Category,$B14,AMTY4) | N14: =M14/$AA$3 | P14: =SUMIF(Category,$B14,AMTY5) | Q14: =P14/$AA$3 | S14: =SUMIF(Category,$B14,AmtBdgt) | T14: =S14/NRA | V14: =W14*NRA | W14: 0
C15: Miscellaneous | D15: =SUMIF(Category,$B15,AMTY1) | E15: =D15/NRA | G15: =SUMIF(Category,$B15,AMTY2) | H15: =G15/NRA | J15: =SUMIF(Category,$B15,AMTY3) | K15: =J15/NRA | M15: =SUMIF(Category,$B15,AMTY4) | N15: =M15/$AA$3 | P15: =SUMIF(Category,$B15,AMTY5) | Q15: =P15/$AA$3 | S15: =SUMIF(Category,$B15,AmtBdgt) | T15: =S15/NRA | V15: =[3]ProForma!C7 | W15: =V15/NRA
C16: Total Potential Gross Income | D16: =SUM(D6:D15) | E16: =D16/NRA | G16: =SUM(G6:G15) | H16: =G16/NRA | J16: =SUM(J6:J15) | K16: =J16/NRA | M16: =SUM(M6:M15) | N16: =M16/$AA$3 | P16: =SUM(P6:P15) | Q16: =P16/$AA$3 | S16: =SUM(S6:S15) | T16: =S16/NRA | V16: =SUM(V6:V15) | W16: =V16/NRA
N17: =M17/$AA$3 | Q17: =P17/$AA$3
C18: Physical Vacancy | D18: =SUMIF(Category,$B18,AMTY1) | E18: =D18/NRA | G18: =SUMIF(Category,$B18,AMTY2) | H18: =G18/NRA | J18: =SUMIF(Category,$B18,AMTY3) | K18: =J18/NRA | M18: =SUMIF(Category,$B18,AMTY4) | N18: =M18/$AA$3 | P18: =SUMIF(Category,$B18,AMTY5) | Q18: =P18/$AA$3 | S18: =SUMIF(Category,$B18,AmtBdgt) | T18: =S18/NRA
C19: Bad Debt / Collection Loss | D19: =SUMIF(Category,$B19,AMTY1) | E19: =D19/NRA | G19: =SUMIF(Category,$B19,AMTY2) | H19: =G19/NRA | J19: =SUMIF(Category,$B19,AMTY3) | K19: =J19/NRA | M19: =SUMIF(Category,$B19,AMTY4) | N19: =M19/$AA$3 | P19: =SUMIF(Category,$B19,AMTY5) | Q19: =P19/$AA$3 | S19: =SUMIF(Category,$B19,AmtBdgt) | T19: =S19/NRA
C20: Concessions | D20: =SUMIF(Category,$B20,AMTY1) | E20: =D20/NRA | G20: =SUMIF(Category,$B20,AMTY2) | H20: =G20/NRA | J20: =SUMIF(Category,$B20,AMTY3) | K20: =J20/NRA | M20: =SUMIF(Category,$B20,AMTY4) | N20: =M20/$AA$3 | P20: =SUMIF(Category,$B20,AMTY5) | Q20: =P20/$AA$3 | S20: =SUMIF(Category,$B20,AmtBdgt) | T20: =S20/NRA
C21: Vacancy & Collection Loss | D21: =-[3]OpActuals!B13 | E21: =D21/NRA | G21: =-[3]OpActuals!C13 | H21: =G21/NRA | J21: =-[3]OpActuals!D13 | K21: =J21/NRA | M21: =-[3]OpActuals!E13 | N21: =M21/$AA$3 | P21: =-[3]OpActuals!G13 | Q21: =P21/$AA$3 | S21: =-[3]OpActuals!H13 | T21: =S21/NRA
C22: EFFECTIVE GROSS INCOME | D22: =D16+D21 | E22: =D22/NRA | G22: =G16+G21 | H22: =G22/NRA | J22: =J16+J21 | K22: =J22/NRA | M22: =SUM(M6:M7) | N22: =M22/$AA$3 | P22: =SUM(P6:P7) | Q22: =P22/$AA$3 | S22: =S16+S21 | T22: =S22/NRA | V22: =[3]ProForma!C11 | W22: =V22/NRA
C23: Fixed Expenses
C24: Real Estate Taxes | D24: =SUMIF(Category,$B24,AMTY1) | E24: =D24/NRA | G24: =SUMIF(Category,$B24,AMTY2) | H24: =G24/NRA | J24: =SUMIF(Category,$B24,AMTY3) | K24: =J24/NRA | N24: =M24/$AA$3 | Q24: =P24/$AA$3 | S24: =SUMIF(Category,$B24,AmtBdgt) | T24: =S24/NRA | V24: =W24*NRA | W24: 0
C25: Property Insurance | D25: =SUMIF(Category,$B25,AMTY1) | E25: =D25/NRA | G25: =SUMIF(Category,$B25,AMTY2) | H25: =G25/NRA | J25: =SUMIF(Category,$B25,AMTY3) | K25: =J25/NRA | N25: =M25/$AA$3 | Q25: =P25/$AA$3 | S25: =SUMIF(Category,$B25,AmtBdgt) | T25: =S25/NRA | V25: =W25*NRA | W25: 0
C26: Variable Expenses
C27: Utilities | D27: =SUMIF(Category,$B27,AMTY1) | E27: =D27/NRA | G27: =SUMIF(Category,$B27,AMTY2) | H27: =G27/NRA | J27: =SUMIF(Category,$B27,AMTY3) | K27: =J27/NRA | N27: =M27/$AA$3 | Q27: =P27/$AA$3 | S27: =SUMIF(Category,$B27,AmtBdgt) | T27: =S27/NRA | V27: =W27*NRA | W27: =[3]SummaryExpenseTbl!M32
C28: CAM Repairs & Maintenance | D28: =SUMIF(Category,$B28,AMTY1) | E28: =D28/NRA | G28: =SUMIF(Category,$B28,AMTY2) | H28: =G28/NRA | J28: =SUMIF(Category,$B28,AMTY3) | K28: =J28/NRA | N28: =M28/$AA$3 | Q28: =P28/$AA$3 | S28: =SUMIF(Category,$B28,AmtBdgt) | T28: =S28/NRA | V28: =W28*NRA | W28: 0
C29: Administrative and General | D29: =SUMIF(Category,$B29,AMTY1) | E29: =D29/NRA | G29: =SUMIF(Category,$B29,AMTY2) | H29: =G29/NRA | J29: =SUMIF(Category,$B29,AMTY3) | K29: =J29/NRA | N29: =M29/$AA$3 | Q29: =P29/$AA$3 | S29: =SUMIF(Category,$B29,AmtBdgt) | T29: =S29/NRA | V29: =W29*NRA | W29: 0
C30: Management | D30: =SUMIF(Category,$B30,AMTY1) | E30: =D30/NRA | G30: =SUMIF(Category,$B30,AMTY2) | H30: =G30/NRA | J30: =SUMIF(Category,$B30,AMTY3) | K30: =J30/NRA | N30: =M30/$AA$3 | Q30: =P30/$AA$3 | S30: =SUMIF(Category,$B30,AmtBdgt) | T30: =S30/NRA | V30: =W30*NRA | W30: =[3]SummaryExpenseTbl!M38
C31: Replacement Reserves | D31: =SUMIF(Category,$B31,AMTY1) | E31: =D31/NRA | G31: =SUMIF(Category,$B31,AMTY2) | H31: =G31/NRA | J31: =SUMIF(Category,$B31,AMTY3) | K31: =J31/NRA | M31: =SUMIF(Category,$B31,AMTY4) | N31: =M31/$AA$3 | P31: =SUMIF(Category,$B31,AMTY5) | Q31: =P31/$AA$3 | S31: =SUMIF(Category,$B31,AmtBdgt) | T31: =S31/NRA | V31: =W31*NRA | W31: =[3]SummaryExpenseTbl!M41
C33: TOTAL EXPENSES | D33: =SUM(#REF!,#REF!, D27, D28,D29,D30, D31) | E33: =D33/NRA | G33: =SUM(#REF!,#REF!, G27, G28,G29,G30, G31) | H33: =G33/NRA | J33: =SUM(#REF!,#REF!, J27, J28,J29,J30, J31) | K33: =J33/NRA | M33: =SUM(M24:M25,M27:M30) | N33: =M33/$AA$3 | P33: =SUM(P24:P25,P27:P30) | Q33: =P33/$AA$3 | S33: =SUM(#REF!,#REF!, S27, S28,S29,S30, S31) | T33: =S33/NRA | V33: =SUM(#REF!,#REF!, V27,#REF!, V30, V31) | W33: =V33/NRA
C35: NET OPERATING INCOME (NOI) | D35: =D22-D33 | E35: =D35/NRA | G35: =G22-G33 | H35: =G35/NRA | J35: =J22-J33 | K35: =J35/NRA | M35: =M22-M33 | N35: =M35/$AA$3 | P35: =P22-P33 | Q35: =P35/$AA$3 | S35: =S22-S33 | T35: =S35/NRA | V35: =V22-V33 | W35: =V35/NRA

Sheet CED
D2: COMPARABLE EXPENSES DATA
D3: Comparable No. | E3: 1 | H3: 2 | K3: 3 | N3: 3
D4: City
D5: Year Built
D6: Rentable Area | T6: Cmp1 | U6: Cmp2 | V6: Cmp3 | W6: Cmp4 | X6: Min | Y6: Max | AA6: Range | AB6: Avg
D7: Year Operations | E7: 2016 | F7: 2019 | H7: 2016 | I7: 2020 | K7: 2016 | L7: 2020 | N7: 2016
D8: Occupancy | E8: 1 | F8: 1 | H8: 1 | I8: 1 | K8: 1 | L8: 1 | N8: 1
D9: Expenses
D10: Real Estate Taxes | O10: =N10/N6 | Q10: =AVERAGE(F10,I10,L10) | T10: =F10 | U10: =I10 | V10: =L10 | W10: =IF(ISERROR(Q24),"",IF(Q24=0,"",Q24)) | X10: =MIN(T10:W10) | Y10: =MAX(T10:W10) | AA10: =IF(X10=Y10,TEXT(X10,"$0.00;;-"),CONCATENATE(TEXT(X10,"$0.00;;-"),"–",TEXT(Y10,"$0.00;;-"))) | AB10: =AVERAGE(T10:W10)
D11: Insurance | O11: =N11/N6 | Q11: =AVERAGE(F11,I11,L11) | T11: =F11 | U11: =I11 | V11: =L11 | W11: =IF(ISERROR(Q25),"",IF(Q25=0,"",Q25)) | X11: =MIN(T11:W11) | Y11: =MAX(T11:W11) | AA11: =IF(X11=Y11,TEXT(X11,"$0.00;;-"),CONCATENATE(TEXT(X11,"$0.00;;-"),"–",TEXT(Y11,"$0.00;;-"))) | AB11: =AVERAGE(T11:W11)
D12: Utilities | O12: =N12/N6 | T12: =F12 | U12: =I12 | V12: =L12 | W12: =IF(ISERROR(Q26),"",IF(Q26=0,"",Q26)) | X12: =MIN(T12:W12) | Y12: =MAX(T12:W12) | AA12: =IF(X12=Y12,TEXT(X12,"$0.00;;-"),CONCATENATE(TEXT(X12,"$0.00;;-"),"–",TEXT(Y12,"$0.00;;-"))) | AB12: =AVERAGE(T12:W12)
D13: CAM Repairs and Maintenace | O13: =N13/N6 | T13: =F13 | U13: =I13 | V13: =L13 | W13: =IF(ISERROR(Q27),"",IF(Q27=0,"",Q27)) | X13: =MIN(T13:W13) | Y13: =MAX(T13:W13) | AA13: =IF(X13=Y13,TEXT(X13,"$0.00;;-"),CONCATENATE(TEXT(X13,"$0.00;;-"),"–",TEXT(Y13,"$0.00;;-"))) | AB13: =AVERAGE(T13:W13)
D14: Administrative and General | O14: =N14/N6 | T14: =F14 | U14: =I14 | V14: =L14 | W14: =IF(ISERROR(Q28),"",IF(Q28=0,"",Q28)) | X14: =MIN(T14:W14) | Y14: =MAX(T14:W14) | AA14: =IF(X14=Y14,TEXT(X14,"$0.00;;-"),CONCATENATE(TEXT(X14,"$0.00;;-"),"–",TEXT(Y14,"$0.00;;-"))) | AB14: =AVERAGE(T14:W14)
D15: Management | O15: =N15/N6 | T15: =F15 | U15: =I15 | V15: =L15 | W15: =IF(ISERROR(Q29),"",IF(Q29=0,"",Q29)) | X15: =MIN(T15:W15) | Y15: =MAX(T15:W15) | AA15: =IF(X15=Y15,TEXT(X15,"$0.00;;-"),CONCATENATE(TEXT(X15,"$0.00;;-"),"–",TEXT(Y15,"$0.00;;-"))) | AB15: =AVERAGE(T15:W15)
D16: Replacement Reserves | O16: =N16/N6 | T16: =F16 | U16: =I16 | V16: =I16 | W16: =IF(ISERROR(Q30),"",IF(Q30=0,"",Q30)) | X16: =MIN(T16:W16) | Y16: =MAX(T16:W16) | AA16: =IF(X16=Y16,TEXT(X16,"$0.00;;-"),CONCATENATE(TEXT(X16,"$0.00;;-"),"–",TEXT(Y16,"$0.00;;-"))) | AB16: =AVERAGE(T16:W16)
D17: Total Expenses | E17: =SUM(E10:E16) | F17: =SUM(F10:F15) | H17: =SUM(H10:H16) | I17: =SUM(I10:I15) | K17: =SUM(K10:K16) | L17: =SUM(L9:L15) | N17: =SUM(N10:N16) | O17: =N17/N6 | T17: =F17 | U17: =I17 | V17: =L17 | W17: =IF(ISERROR(Q31),"",IF(Q31=0,"",Q31)) | X17: =MIN(T17:W17) | Y17: =MAX(T17:W17) | AA17: =IF(X17=Y17,TEXT(X17,"$0.00;;-"),CONCATENATE(TEXT(X17,"$0.00;;-"),"–",TEXT(Y17,"$0.00;;-"))) | AB17: =AVERAGE(T17:W17)
T18: =IF(H32=0,"",H32) | U18: =IF(K32=0,"",K32) | V18: =IF(N32=0,"",N32) | W18: =IF(ISERROR(Q32),"",IF(Q32=0,"",Q32)) | X18: =MIN(T18:W18) | Y18: =MAX(T18:W18) | AA18: =IF(X18=Y18,TEXT(X18,"$0.00;;-"),CONCATENATE(TEXT(X18,"$0.00;;-"),"–",TEXT(Y18,"$0.00;;-"))) | AB18: =AVERAGE(T18:W18)
T19: =IF(H33=0,"",H33) | U19: =IF(K33=0,"",K33) | V19: =IF(N33=0,"",N33) | W19: =IF(ISERROR(Q33),"",IF(Q33=0,"",Q33)) | X19: =MIN(T19:W19) | Y19: =MAX(T19:W19) | AA19: =IF(X19=Y19,TEXT(X19,"$0.00;;-"),CONCATENATE(TEXT(X19,"$0.00;;-"),"–",TEXT(Y19,"$0.00;;-"))) | AB19: =AVERAGE(T19:W19)
T20: =IF(H34=0,"",H34) | U20: =IF(K34=0,"",K34) | V20: =IF(N34=0,"",N34) | W20: =IF(ISERROR(Q34),"",IF(Q34=0,"",Q34)) | X20: =MIN(T20:W20) | Y20: =MAX(T20:W20) | AA20: =IF(X20=Y20,TEXT(X20,"$0.00;;-"),CONCATENATE(TEXT(X20,"$0.00;;-"),"–",TEXT(Y20,"$0.00;;-"))) | AB20: =AVERAGE(T20:W20)
T21: =IF(H35=0,"",H35) | U21: =IF(K35=0,"",K35) | V21: =IF(N35=0,"",N35) | W21: =IF(ISERROR(Q35),"",IF(Q35=0,"",Q35)) | X21: =MIN(T21:W21) | Y21: =MAX(T21:W21) | AA21: =IF(X21=Y21,TEXT(X21,"$0.00;;-"),CONCATENATE(TEXT(X21,"$0.00;;-"),"–",TEXT(Y21,"$0.00;;-"))) | AB21: =AVERAGE(T21:W21)
T22: =IF(H36=0,"",H36) | U22: =IF(K36=0,"",K36) | V22: =IF(N36=0,"",N36) | W22: =IF(ISERROR(Q36),"",IF(Q36=0,"",Q36)) | X22: =MIN(T22:W22) | Y22: =MAX(T22:W22) | AA22: =IF(X22=Y22,TEXT(X22,"$0.00;;-"),CONCATENATE(TEXT(X22,"$0.00;;-"),"–",TEXT(Y22,"$0.00;;-"))) | AB22: =AVERAGE(T22:W22)
T23: =IF(H37=0,"",H37) | U23: =IF(K37=0,"",K37) | V23: =IF(N37=0,"",N37) | W23: =IF(ISERROR(Q37),"",IF(Q37=0,"",Q37)) | X23: =MIN(T23:W23) | Y23: =MAX(T23:W23) | AA23: =IF(X23=Y23,TEXT(X23,"$0.00;;-"),CONCATENATE(TEXT(X23,"$0.00;;-"),"–",TEXT(Y23,"$0.00;;-"))) | AB23: =AVERAGE(T23:W23)
T24: =IF(H38=0,"",H38) | U24: =IF(K38=0,"",K38) | V24: =IF(N38=0,"",N38) | W24: =IF(ISERROR(Q38),"",IF(Q38=0,"",Q38)) | X24: =MIN(T24:W24) | Y24: =MAX(T24:W24) | AA24: =IF(X24=Y24,TEXT(X24,"$0.00;;-"),CONCATENATE(TEXT(X24,"$0.00;;-"),"–",TEXT(Y24,"$0.00;;-"))) | AB24: =AVERAGE(T24:W24)
T25: =IF(H39=0,"",H39) | U25: =IF(K39=0,"",K39) | V25: =IF(N39=0,"",N39) | W25: =IF(Q39=0,"",Q39) | X25: =MIN(T25:W25) | Y25: =MAX(T25:W25) | AA25: =IF(X25=Y25,TEXT(X25,"$0.00;;-"),CONCATENATE(TEXT(X25,"$0.00;;-"),"–",TEXT(Y25,"$0.00;;-"))) | AB25: =AVERAGE(T25:W25)
T26: =IF(I38=0,"",I38) | U26: =IF(L38=0,"",L38) | V26: =IF(O38=0,"",O38) | W26: =IF(R38=0,"",R38) | X26: =MIN(T26:W26) | Y26: =MAX(T26:W26) | AA26: =IF(X26=Y26,TEXT(X26,"0%;-"),CONCATENATE(TEXT(X26,"0%;-"),"–",TEXT(Y26,"0%;-")))
T28: =G42 | U28: =J42 | V28: =M42 | W28: =P42 | X28: =MIN(T28:W28) | Y28: =MAX(T28:W28) | AA28: =IF(X28=Y28,TEXT(X28,"$#,##0"),CONCATENATE(TEXT(X28,"$#,##0"),"–",TEXT(Y28,"$#,##0"))) | AB28: =IF(SUM(T28:W28)=0,0,ROUND(AVERAGE(T28:W28),0))
T29: =G43 | U29: =J43 | V29: =M43 | W29: =P43 | X29: =MIN(T29:W29) | Y29: =MAX(T29:W29) | AA29: =IF(X29=Y29,TEXT(X29,"$0.00;;-"),CONCATENATE(TEXT(X29,"$0.00;;-"),"–",TEXT(Y29,"$0.00;;-"))) | AB29: =IF(SUM(T29:W29)=0,0,ROUND(AVERAGE(T29:W29),2))
T30: =G44 | U30: =J44 | V30: =M44 | W30: =P44 | X30: =MIN(T30:W30) | Y30: =MAX(T30:W30) | AA30: =IF(X30=Y30,TEXT(X30,"0%;-"),CONCATENATE(TEXT(X30,"0%;-"),"–",TEXT(Y30,"0%;-"))) | AB30: =IF(SUM(T30:W30)=0,0,ROUND(AVERAGE(T30:W30),3))

Sheet OECC
E2: OPERATING EXPENSE COMPARISON AND CONCLUSION | O2: =LA!C5
C3: =LA!C5 | F3: Expense Comps
E4: Expense Item | F4: Range | G4: Average | H4: 2016 | I4: 2017 | J4: Forecast | K4: Comments
E5: Real Estate Taxes | F5: =CED!AA10 | G5: =CED!AB10 | H5: =HOA!M24 | I5: =HOA!P24
H6: =H5/$O$2 | I6: =I5/$O$2 | J6: =J5/$O$2
E8: Insurance | F8: =CED!AA11 | G8: =CED!AB11 | H8: =HOA!M25 | I8: =HOA!P25 | J8: =J9*C3
H9: =H8/$O$2 | I9: =I8/$O$2
E11: Utilities | F11: =CED!AA12 | G11: =CED!AB12 | H11: =HOA!M27 | I11: =HOA!P27 | J11: =J12*C3
H12: =H11/$O$2 | I12: =I11/$O$2
E14: CAM Repairs and Maintenance | F14: =CED!AA13 | G14: =CED!AB13 | H14: =HOA!M28 | I14: =HOA!P28 | J14: =J15*C3
H15: =H14/$O$2 | I15: =I14/$O$2
E17: Management | F17: N/R | G17: N/R | H17: =HOA!M30 | I17: =HOA!P30 | J17: =PF!G9*0.03
H18: =H17/$O$2 | I18: =I17/$O$2 | J18: =J17/C3
E20: Replacement Reserves | H20: =H21/NRA | I20: =I21/NRA | J20: 0
F21: 0 | G21: 0 | H21: 0 | I21: 0 | J21: =J20/$O$2
E23: Total Operating Expenses | H23: =SUM(H5,H8,H11,H14,#REF!,H17,H20) | I23: =SUM(I5,I8,I11,I14,#REF!,I17,I20) | J23: =SUM(J5,J8,J11,J14,J17)
E24: Total Operating Expenses Per SF | H24: =SUM(H6,H9,H12,H15,#REF!,H18,H21) | I24: =SUM(I6,I9,I12,I15,#REF!,I18,I21) | J24: =J23/C3
H28: =H17/HOA!M22 | I28: =I17/HOA!P22
H29: =J23
H30: 0
H31: =SUM(H29:H30)
H32: =#REF!
H34: =SUM(H31:H32) | I34: =J17 | J34: =I34/H34

Sheet PF
E2: PRO FORMA OPERATIONS
E3: Income | G3: $ | H3: Per SF
E4: Gross Potential Rent | G4: =#REF! | H4: =G4/LA!C5
E5: Expense Recoveries | G5: 0 | H5: =G5/LA!C5
E6: Total Potential Gross Income | G6: =SUM(G4:G5) | H6: =G6/LA!C5
E7: Less Vacancy/Collection Loss | F7: =#REF! | G7: =-(F7*G6) | H7: =G7/LA!C5
E8: Less Collection Loss | F8: 0 | G8: =-(F8*G6) | H8: =G8/LA!C5
E9: Effective Gross Income (EGI) | G9: =SUM(G6:G8) | H9: =G9/LA!C5
E10: Expenses
E11: Real Estate Taxes | G11: 0 | H11: =G11/LA!$C$5
E12: Insurance | G12: 0 | H12: =G12/LA!$C$5
E13: Utilities | G13: 0 | H13: =G13/LA!$C$5
E14: CAM Repairs and Maintenance | G14: 0 | H14: =G14/LA!$C$5
E15: Management | G15: 0 | H15: =G15/LA!$C$5
E16: Replacement Reserves | G16: =H16*#REF! | H16: 0.25
E17: Total Expenses | F17: =G17/G9 | G17: =SUM(G11:G16) | H17: =G17/LA!C5
E18: Net Operating Income (NOI) | G18: =G9-G17 | H18: =G18/LA!C5

Sheet Cap Rate Lease-Up
B2: MARKET DERIVED CAPITALIZATION RATE SUMMARY
B3: No. | C3: Name | D3: Type | E3: Location | F3: Date of Sale | G3: Year Built | H3: Size | I3: Occupancy | J3: Sale Price PSF | K3: NOI PSF | L3: Lease Remaining | M3: Capitalization Rate
B4: 1
B5: 2
B6: 3
B7: 4
B8: 5
B9: 6
B10: 7
B11: 8
B12: 9
B14: Low | M14: =ROUND(MIN(M4:M13),4)
B15: High | M15: =ROUND(MAX(M4:M13),4)
B16: Median | M16: =ROUND(MEDIAN(M4:M13),4)
B17: Average | M17: =ROUND(AVERAGE(M4:M12),4)
B18: Appraiser's Concluded Range
O20: Third Party Surveys - Capitalization Rates
O21: Category
O22: Date of Survey
O23: Market
O24: Property Type
O25: Range Average
O26: Average
T40: SUMMARY CAPITALIZATION RATE AND CONCLUSION
T41: Method | U41: Capitalization Rate
T42: Market Extraction | U42: =M18
T43: Investor Surveys | U43: 6.00% - 6.50%
T44: Market Participants | U44: =iaOARBrokers
T45: Band of Investment | U45: 0.075
T46: DCR | U46: =iaOARDCR
T47: Primary Weight | U47: Market Extraction
T48: Secondary Weight | U48: Investor Surveys
T49: Capitalization Rate Conclusion
T53: LEASE-UP COSTS
T54: Method | U54: Capitalization Rate
T55: Preliminary Value | U55: ='IA Values'!G13
T56: Less: Lost Income
T57: Less: Tenant Finish | U57: =iaOARBrokers
T58: Less: Leasing Commissions
T59: Total | U59: =SUM(U56:U58)
T60: Entrepreneurial Profit | U60: =U59*0.1
T61: Total Deductions | U61: =SUM(U59,U60)
T62: "As Is" Value | U62: =U55-U61
T63: Rounded Value

Sheet IA Values
K2: =#REF!
E3: DIRECT CAPITALIZATION METHOD VALUE CONCLUSION - AS IS
E4: Net Operating Income (NOI) | G4: =#REF! | H4: =G4/K2
E5: 0.0025 | G5: Value | H5: $/SF
G6: =G4/('Cap Rate Lease-Up'!U49-0.0025) | H6: =G6/K2
G7: =G4/'Cap Rate Lease-Up'!U49 | H7: =G7/K2
G8: =G4/('Cap Rate Lease-Up'!U49+0.0025) | H8: =G8/K2
E10: =IF(SUM(G11:G11)=0,"HIDE THIS ROW IF NO DEFERRED MAINTENANCE", "Indicated Value") | G10: =G7
E11: =IF(G11=0,"HIDE THIS ROW IF NO DEFERRED MAINTENANCE","Less: Deferred Maintenance") | G11: =-caDeferredMaint
E12: =IF(G11=0,"Reconciled Value","Reconciled Value - Adjusted") | G12: =SUM(G10:G11) | H12: =G12/K2
E13: 5000 | G13: =ROUND((G12/E13),0)*E13 | H13: =G13/K2
A16: DEDUCTIONS TO REACH AN AS IS VALUE
A17: Indicated Value UPON COMPLETION | B17: =G13
A18: Remaining Capital Improvements
A19: Entrepreneurial Incentive (15% of Total Construction Costs)
A20: =IF(B21=0,"HIDE THIS ROW IF NO DEFERRED MAINTENANCE", "Indicated Value") | B20: 0
A21: =IF(B21=0,"HIDE THIS ROW IF NO DEFERRED MAINTENANCE","Less: Deferred Maintenance") | B21: 0
A22: Indicated Value AS IS | B22: =SUM(B17:B19)
A23: Indicated Value AS IS | B23: =MROUND(B22,5000)
A24: Per SF | B24: =B23/3112

Sheet Income Approach
A2: Subject's Total SF Area | B2: =FE!C14 | C2: ←
G3: POTENTIAL GROSS RENTAL INCOME
A4: Use only if comparing contract to market rent. Hide for owner-user buildings→ | H4: Area | J4: Contract Rent | M4: Market Rent
G5: Tenant | H5: Total (SF) | J5: $/SF | K5: Annl. Rent | M5: $/SF | N5: Annl. Rent
G6: =LA!C3 | H6: =FE!C14 | J6: =LA!C11 | K6: =LA!C10 | M6: =C11 | N6: =H6*M6
A8: PGRI – MARKET RENTS
A9: Space Type | B9: SF | C9: Rent PSF | D9: PGRI
A11: ='Property Info'!B16 | D11: =C11*B11
A13: VACANCY AND COLLECTION LOSS
A14: Source | D14: Rate
A15: CoStar - Denver CBSA - Industrial 20,000 SF - 50,000 SF- Q1 2019-Q2 2020
A16: CoStar - Adams County - Industrial - Q1 2019-Q2 2020
A21: Range | D21: =TEXT(MIN(D15:D20),"0.00%")&" to "&TEXT(MAX(D15:D20),"0.00%")
A22: Concluded Overall Vacancy Rate | F22: ←Change
A24: EXPENSES IN TIME OF VACANCY
A25: Expense | C25: PSF | D25: Total
A26: Real Estate Taxes | C26: =D26/$B$11 | F26: ← | G26: Actual
A27: Insurance | D27: =C27*$B$2 | F27: ← | G27: Estimated
A28: Utilities | D28: =C28*$B$2 | F28: ← | G28: Estimated
A29: CAM Repairs and Maintenance | D29: =C29*$B$2 | F29: ← | G29: Estimated
A30: Management | C30: =D30/$B$11 | D30: =D42*0.03 | F30: ← | G30: 3% EGI
A31: Total | C31: =D31/B2 | D31: =SUM(D26:E30)
A32: Multiplied by Vacancy Factor of | B32: =D22 | C32: =$B$41*C31 | D32: =$B$41*D31
A33: Divided by EGI | D33: =D32/D42
A35: PRO FORMA OPERATING STATEMENT
A36: Category | C36: Projected Expenses | D36: Projected Income | E36: PSF
A37: Potential Gross Rental Income (PGRI) | D37: =+D11 | E37: =+D37/$B$2
A38: Plus: Other Income | D38: 0 | E38: =+D38/$B$2
A39: Plus: Pass-Through Income | D39: 0 | E39: =+D39/$B$2
A40: Total Potential Gross Rental Income | D40: =SUM(D37:D39) | E40: =+D40/$B$2
A41: Less: Market Vacancy | B41: =D22 | C41: =+B41*D40*-1 | E41: =+C41/$B$2
A42: Effective Gross Income (EGI) | D42: =+D40+C41 | E42: =+D42/$B$2
A43: Fixed Expenses
A44: Owner's Expenses | C44: =+B44*D42*-1 | E44: =+C44/$B$2
A45: Operating Expense Recovery Loss During Vacancy | B45: =D33 | C45: =-D32 | E45: =+C45/$B$2
A46: Total Expenses | C46: =SUM(C44:C45) | E46: =+C46/$B$2
A47: Net Operating Income | D47: =+D42+C46 | E47: =+D47/$B$2 | S47: Reconciled OAR | U47: ←
S48: Sensitivity | T48: 0.0025 | U48: ←
A49: Third Party Surveys - Capitalization Rates
A50: Category | C50: CoStar | D50: CoStar | S50: Value Indications
A51: Date of Survey | C51: 01/01/2019-06/30/2020 | D51: 01/01/2019-06/30/2020 | S51: Category | T51: Value Range
A52: Market | C52: Denver CBSA | D52: Adams County | S52: Net Operating Income | T52: =+$D$47 | U52: =+$D$47 | V52: =+$D$47
A53: Property Type | C53: Industrial/Flex | D53: Industrial/Flex | S53: Capitalization Rate | T53: =U53-T48 | U53: =T47 | V53: =U53+T48
A54: Range Average | F54: ←Change | S54: Value Indication | T54: =+T52/T53 | U54: =+U52/U53 | V54: =+V52/V53
A55: Average | F55: ←Change | S55: Rounded | T55: =MROUND(T54,5000) | U55: =MROUND(U54,5000) | V55: =MROUND(V54,5000)
A56: Capitalization Rate Conclusion | F56: =D56*100
A58: DIRECT CAPITALIZATION METHOD VALUE CONCLUSION | T58: psf | U58: =U55/B2
A59: Net Operating Income (NOI) | C59: =D47 | D59: =C59/B2
A60: 0.0025 | C60: Value | D60: $/SF
A61: =A72 | C61: =C59/(D56-0.0025) | D61: =C61/B2
A62: =A70 | C62: =C59/D56 | D62: =C62/B2
A63: =A71 | C63: =C59/(D56+0.0025) | D63: =C63/B2
A64: Reconciled Value | C64: =C62 | D64: =C64/B2
A65: 5000 | C65: =ROUND((C64/A65),0)*A65 | D65: =C65/B2
A69: Do not overwright
A70: =CONCATENATE("Based on Most Probable Range of ", FIXED(F56, 2), "%")
A71: =CONCATENATE("Based on High-Range of ", FIXED(F56+0.25, 2), "%")
A72: =CONCATENATE("Based on Low-Range of ", FIXED(F56-0.25, 2), "%")

Sheet Property Registry
A1: COMMERCIAL PROPERTY EXPENSE DATABASE ? PROPERTY REGISTRY
A2: Adams County Assessor | Add one row per property | Used to track all expense comp submissions
A3: Prop ID | B3: Occ Code | C3: Account # | D3: Address | E3: City | F3: State | G3: Property Type | H3: Subtype | I3: Year Built | J3: Bldg SF | K3: Land SF | L3: Parcel / Schedule # | M3: Owner | N3: Data Source | O3: Date Added | P3: Notes
A4: P001 | B4: 407 | C4: R0157664 | D4: 6045 E. 76th Avenue | E4: Commerce City | F4: CO | G4: Light Industrial | H4: Distribution Warehouse | I4: 1988 | J4: 21000 | K4: 66700 | L4: R0157664 / 0172132216014 | M4: 4711 West Tennessee Avenue LLC | N4: Owner P&L + RH Jacobson Analysis | O4: 2026-06-01 | P4: 28.5% vacancy; inferior access through 2 adjoining parcels; appeal tax year 2025-26
A5: P002 | B5: 344 | C5: Unknown | D5: 13659 E. 104th Ave | E5: Adams County | F5: CO | G5: Office/Commercial | H5: Multi-tenant | L5: Unknown | M5: PMC-managed HOA structure | N5: Owner Operating Statements (BAA CASES root) | O5: 2026-06-01 | P5: SF unknown; 2023-2024 actuals from operating statement submitted in BAA appeal
A6: P003 | B6: 344 | C6: R0024063 | D6: Park Centre - Wells Fargo Bldg (12000 N Pecos area) | E6: Westminster | F6: CO | G6: Office | H6: Class B Multi-tenant | J6: 49479 | L6: R0024063 | M6: Westfield Managed | N6: FINANCIALS.pdf + PROFORMA REVISED.xlsx | O6: 2026-06-01 | P6: 49,479 SF leasable; complex multi-tenant office; Westfield managed; BAA appeal case
A7: P004 | B7: 412 | C7: R0050221 | D7: 8860 Federal Blvd | E7: Adams County | F7: CO | G7: Retail | H7: Strip/Multi-tenant | J7: 65850 | L7: R0050221 | M7: Enger Family Partnership LLLP | N7: ACTUALS.pdf (BAA CASES) | O7: 2026-06-01 | P7: 65,850 SF retail strip; triple-net structure with CAM recoveries; 2023-2024 actuals
A8: P005 | B8: 344 | C8: R0050977 | D8: 9351 Grant St (Horizon Terrace) | E8: Thornton | F8: CO | G8: Office | H8: Class B Multi-story Multi-tenant | J8: 91646 | L8: R0050977 | M8: Horizon Terrace | N8: Income Statements 2023 & 2024 PDFs | O8: 2026-06-01 | P8: 91,646 SF; full-service multi-tenant office with janitorial, security, elevator; Westfield managed
A9: P006 | B9: 210 | C9: R0062937 | D9: 8670 Wolff Ct (Sheridan Park 8) | E9: Westminster | F9: CO | G9: Office/Flex | H9: Multi-tenant | J9: 37078 | L9: R0062937 | M9: Unknown | N9: Operating Expense History DYCO.pdf | O9: 2026-06-01 | P9: ~37,078 SF (derived from PSF); CAM reimbursable expense structure; 2020-2024 expense history
A10: P007 | B10: 341 | C10: R0062944 | D10: 8787 (medical office complex) | E10: Adams County | F10: CO | G10: Medical Office | H10: Multi-tenant | J10: 19430 | L10: R0062944 | M10: MENDI-CO II LLC | N10: 2023 OPS.xlsx + 2024 OPS.xlsx | O10: 2026-06-01 | P10: ~19,430 SF (derived); tenants: Denver Springs, Access VP, Colorado Net, Westminster Eye; 2023-2024 actuals
A11: P008 | B11: 210 | C11: R0070622 | D11: 460-550 E. 76th Ave (WPC Corporate) | E11: Adams County | F11: CO | G11: Industrial | H11: Distribution/Flex Multi-tenant | J11: 330935 | L11: R0070622 | M11: WPC Corporate LLC | N11: ACTUALS.pdf (BAA CASES) | O11: 2026-06-01 | P11: 330,935 SF industrial; 2024 actuals only; large multi-tenant distribution complex
A12: P009 | B12: 407 | C12: R0075212 | D12: 10500 Havana Court | E12: Adams County | F12: CO | G12: Industrial | H12: NNN Single-tenant | L12: R0075212 | M12: Jellison Street LLP | N12: PLEA USING ACTUALS AND TAX LOAD.pdf | O12: 2026-06-01 | P12: SF unknown; NNN lease structure; P&L includes depreciation/mortgage (excluded from NOI calc); 2023-2024
A13: P010 | B13: 210 | C13: R0098225 | D13: Broadway Business Center (7040B Broadway) | E13: Denver | F13: CO | G13: Flex/Industrial | H13: Multi-tenant CAM | J13: 105000 | L13: R0098225 | M13: Broadway Business Center | N13: 2023 OPS.xlsx + 2024 OPS.xlsx | O13: 2026-06-01 | P13: ~105,000 SF estimated; CAM-recoverable structure; 2024 RE Tax inflated by $111,314 prior-yr catchup; 2023-2024 actuals
A14: P011 | B14: 210 | C14: R0103767 | D14: 5650 Washington St (Washington Business Park) | E14: Adams County | F14: CO | G14: Industrial/Flex | H14: Multi-tenant | L14: R0103767 | M14: Unknown | N14: Operating Statement (sans rent roll).pdf | O14: 2026-06-01 | P14: SF unknown; 2022-2024 actuals; management fee $54,025 in 2022 not shown in later years
A15: P012 | B15: 344 | C15: R0124385 | D15: Unknown (Tax District 555) | E15: Adams County | F15: CO | G15: Office | H15: Multi-tenant | J15: 20170 | L15: R0124385 | M15: Unknown | N15: PROFORMA BASIS FOR OFFER.xlsx (actuals section) | O15: 2026-06-01 | P15: 20,170 SF; 2023-2024 actuals extracted from proforma submission; limited line-item detail
A16: P013 | B16: 353 | C16: R0169176 | D16: Unknown (new construction, opened Oct 2023) | E16: Adams County | F16: CO | G16: Retail/Office | H16: Multi-tenant | I16: 2023 | L16: R0169176 | M16: Unknown | N16: Income Statement 2023.xlsx + 2024.xlsx | O16: 2026-06-01 | P16: SF unknown; 2023 partial year (opened Oct 2023); 2024 full year; large RE tax load typical of new construction
A17: P014 | B17: 407 | C17: R0198530 | D17: Amazon DEN7 Distribution Center | E17: Aurora | F17: CO | G17: Industrial/Distribution | H17: Single-tenant NNN | J17: 555840 | L17: R0198530 | M17: Amazon (tenant) | N17: CAM Reconciliation 2023 & 2024 OPS.pdf | O17: 2026-06-01 | P17: 555,840 SF Amazon fulfillment center; NNN ? expenses = LL CAM billed to tenant; RE Tax dominant expense; 2023-2024
A18: P015 | B18: 407 | C18: R0180894 | D18: 1910 N Gun Club Rd | E18: Aurora | F18: CO | G18: Industrial | H18: Distribution Warehouse Multi-Tenant NNN | I18: 2019 | J18: 163386 | L18: R0180894 | N18: MHE 2025 BAA – Owner submitted P&L | O18: 2026-06-01 | P18: Actual accrual income; 2023–2024
A19: P016 | B19: 584 | C19: R0212546/R0212547 | D19: 2780 N Tower Rd | E19: Aurora | F19: CO | G19: Industrial | H19: Mega Warehouse NNN | I19: 1983 | J19: 384953 | L19: R0212546/R0212547 | N19: MHE 2025 BAA – County proforma | O19: 2026-06-01 | P19: County proforma; 2024 only
A20: P017 | B20: 210 | C20: R0098098 | D20: 1445 E 68th Ave | E20: Denver | F20: CO | G20: Industrial | H20: Industrial Office Mix | I20: 1972 | J20: 63348 | L20: R0098098 | N20: MHE 2025 BAA – County proforma | O20: 2026-06-01 | P20: YOC 1972/2006/2023; county proforma 2024
A21: P018 | B21: 406 | C21: R0103783 | D21: 2031 E 58th Ave | E21: Denver | F21: CO | G21: Industrial | H21: Storage Warehouse / Mod Office NNN | I21: 2004 | J21: 18720 | L21: R0103783 | N21: MHE 2025 BAA – NNN billed charges | O21: 2026-06-01 | P21: NNN actual billed charges 2019–2024
A22: P019 | B22: 407 | C22: R0210402/R0210403 | D22: 17190 E 85th Ave | E22: Commerce City | F22: CO | G22: Industrial | H22: Industrial Warehouse NNN | I22: 2021 | J22: 329940 | L22: R0210402/R0210403 | N22: MHE 2025 BAA – Petitioner proforma | O22: 2026-06-01 | P22: Petitioner proforma 2024/25
A23: P020 | B23: 584 | C23: R0209679 | D23: 17501 E 84th Ave | E23: Commerce City | F23: CO | G23: Industrial | H23: Mega Warehouse / Distribution Center NNN (Lowe's) | I23: 2021 | J23: 999780 | L23: R0209679 | N23: MHE 2025 BAA – Owner submitted P&L | O23: 2026-06-01 | P23: Actual accrual; 2023 NOI inflated by ~$2.8M prior-yr tax adj
A24: P021 | B24: 210 | C24: R0091931 | D24: 6300 E. 58th Ave | E24: Commerce City | F24: CO | G24: Industrial | H24: Multi-Tenant Industrial/Flex | I24: 1999 | J24: 90000 | L24: R0091931 | N24: MHE 2025 BOE – Owner actual P&L | O24: 2026-06-02 | P24: Actual accrual 2023+2024; YOC 1999–2001
A25: P022 | B25: 210 | C25: R0111559 | D25: 3590 N. Himalaya Rd (Bldg 6) | E25: Aurora | F25: CO | G25: Industrial | H25: Multi-Tenant Industrial/Flex NNN | L25: R0111559 | N25: MHE 2025 BOE – Sterling actual P&L | O25: 2026-06-02 | P25: 2023 transitional (vacancy); 2024 new tenant in place; SF not confirmed
A26: P023 | B26: 407 | C26: R0191098 | D26: 19754 E. 35th Dr (Bldg 4) | E26: Aurora | F26: CO | G26: Industrial | H26: Single-Tenant Industrial NNN | J26: 155033 | L26: R0191098 | N26: MHE 2025 BOE – Sterling actual P&L | O26: 2026-06-02 | P26: Single-tenant NNN (Quality Custom Distribution); lease thru 12/31/2029
A27: P024 | B27: 407 | C27: R0111560 | D27: 20320 E. 36th Dr (Bldg 7) | E27: Aurora | F27: CO | G27: Industrial | H27: Single-Tenant Industrial NNN | J27: 200000 | L27: R0111560 | N27: MHE 2025 BOE – Sterling actual P&L | O27: 2026-06-02 | P27: FedEx NNN; lease expired 4/30/2024 – 2023 only usable
A28: P025 | B28: 210 | C28: R0191099 | D28: 3559 N. Himalaya Rd (Bldg 5) | E28: Aurora | F28: CO | G28: Industrial | H28: Multi-Tenant Industrial NNN | J28: 159047 | L28: R0191099 | N28: MHE 2025 BOE – Sterling actual P&L | O28: 2026-06-02 | P28: Multi-tenant NNN; 3 tenants; 2023+2024
A29: P026 | B29: 406 | C29: R0092667 | D29: 4901 Locust St | E29: Commerce City | F29: CO | G29: Industrial | H29: Industrial Warehouse | J29: 29512 | L29: R0092667 | N29: MHE 2025 BOE – Newmark appraisal proforma | O29: 2026-06-02 | P29: Stabilized proforma; Newmark V&A appraisal 6/30/2024
A30: P027 | B30: 407 | C30: R0132030 | D30: Majestic Commercenter (R0132030) | E30: Commerce City | F30: CO | G30: Industrial | H30: Warehouse NNN | I30: 2001 | J30: 200094 | L30: R0132030 | N30: AXG – Whse Expenses PSF.xlsx | O30: 2026-06-02 | P30: NNN landlord expenses only; 2021–2022
A31: P028 | B31: 407 | C31: R0084040 | D31: Majestic Commercenter (R0084040) | E31: Commerce City | F31: CO | G31: Industrial | H31: Warehouse NNN | I31: 1997 | J31: 177736 | L31: R0084040 | N31: AXG – Whse Expenses PSF.xlsx | O31: 2026-06-02 | P31: NNN landlord expenses only; 2021–2022
A32: P029 | B32: 407 | C32: R0084041 | D32: Majestic Commercenter (R0084041) | E32: Commerce City | F32: CO | G32: Industrial | H32: Warehouse NNN | I32: 1997 | J32: 200371 | L32: R0084041 | N32: AXG – Whse Expenses PSF.xlsx | O32: 2026-06-02 | P32: NNN landlord expenses only; 2021–2022
A33: P030 | B33: 584 | C33: R0217015 | D33: Majestic Commercenter (R0217015) | E33: Commerce City | F33: CO | G33: Industrial | H33: Mega Warehouse NNN | I33: 2021 | J33: 548510 | L33: R0217015 | N33: AXG – Whse Expenses PSF.xlsx | O33: 2026-06-02 | P33: NNN landlord expenses only; 2022 only
A34: P031 | B34: 407 | C34: R0111562 | D34: Majestic Commercenter (R0111562) | E34: Commerce City | F34: CO | G34: Industrial | H34: Warehouse NNN | I34: 2000 | J34: 149175 | L34: R0111562 | N34: AXG – Whse Expenses PSF.xlsx | O34: 2026-06-02 | P34: NNN landlord expenses only; 2019–2020
A35: P032 | B35: 407 | C35: R0118875 | D35: Majestic Commercenter (R0118875) | E35: Commerce City | F35: CO | G35: Industrial | H35: Warehouse NNN | I35: 1999 | J35: 279640 | L35: R0118875 | N35: AXG – Whse Expenses PSF.xlsx | O35: 2026-06-02 | P35: NNN landlord expenses only; 2021–2022
A36: P033 | B36: 407 | C36: R0132031 | D36: Majestic Commercenter (R0132031) | E36: Commerce City | F36: CO | G36: Industrial | H36: Warehouse NNN | I36: 2002 | J36: 280098 | L36: R0132031 | N36: AXG – Whse Expenses PSF.xlsx | O36: 2026-06-02 | P36: NNN landlord expenses only; 2021–2022
A37: P034 | B37: 407 | C37: R0172865 | D37: Majestic Commercenter (R0172865) | E37: Commerce City | F37: CO | G37: Industrial | H37: Warehouse NNN | I37: 2008 | J37: 215461 | L37: R0172865 | N37: AXG – Whse Expenses PSF.xlsx | O37: 2026-06-02 | P37: NNN landlord expenses only; 2021–2022
A38: P035 | B38: 407 | C38: R0172867 | D38: Majestic Commercenter (R0172867) | E38: Commerce City | F38: CO | G38: Industrial | H38: Warehouse NNN | I38: 2007 | J38: 215560 | L38: R0172867 | N38: AXG – Whse Expenses PSF.xlsx | O38: 2026-06-02 | P38: NNN landlord expenses only; 2021–2022
A39: P036 | B39: 407 | C39: R0172868 | D39: Majestic Commercenter (R0172868) | E39: Commerce City | F39: CO | G39: Industrial | H39: Warehouse NNN | I39: 2007 | J39: 202091 | L39: R0172868 | N39: AXG – Whse Expenses PSF.xlsx | O39: 2026-06-02 | P39: NNN landlord expenses only; 2021–2022
A40: P037 | B40: 407 | C40: R0145680 | D40: Majestic Commercenter (R0145680) | E40: Commerce City | F40: CO | G40: Industrial | H40: Warehouse NNN | I40: 2001 | J40: 150027 | L40: R0145680 | N40: AXG – Whse Expenses PSF.xlsx | O40: 2026-06-02 | P40: NNN landlord expenses only; 2021–2022
A41: P038 | B41: 584 | C41: R0181787 | D41: Majestic Commercenter (R0181787) | E41: Commerce City | F41: CO | G41: Industrial | H41: Mega Warehouse NNN | I41: 2013 | J41: 500358 | L41: R0181787 | N41: AXG – Whse Expenses PSF.xlsx | O41: 2026-06-02 | P41: NNN landlord expenses only; 2021–2022
A42: P039 | B42: 584 | C42: R0191101 | D42: Majestic Commercenter (R0191101) | E42: Commerce City | F42: CO | G42: Industrial | H42: Mega Warehouse NNN | I42: 2017 | J42: 522120 | L42: R0191101 | N42: AXG – Whse Expenses PSF.xlsx | O42: 2026-06-02 | P42: NNN landlord expenses only; 2021–2022
A43: P040 | B43: 407 | C43: R0202874 | D43: 900 E 128th Ave | E43: Henderson | F43: CO | G43: Industrial | H43: Last-Mile Distribution NNN | L43: R0202874 | M43: Amazon | N43: AXG – Owner Income Statement 2021–2022 | O43: 2026-06-02 | P43: Amazon AMZL Last Mile Site 51812; SF not extracted
A44: P041 | B44: 386 | C44: R0189384 | D44: 1101 Colorado Blvd | E44: Thornton | F44: CO | G44: Self-Storage | H44: Climate-Controlled | J44: 65766 | L44: R0189384 | N44: AXG – Carlson SS Portfolio P&L | O44: 2026-06-02 | P44: Actual FY2021–2023; 101.5% occ Q4 2023
A45: P042 | B45: 386 | C45: R0126235 | D45: 15024 Laroy Drive | E45: Northglenn | F45: CO | G45: Self-Storage | H45: Climate-Controlled | J45: 79950 | L45: R0126235 | N45: AXG – Carlson SS Portfolio P&L | O45: 2026-06-02 | P45: Actual FY2021–2023; 91.4% occ Dec 2023
A46: P043 | B46: 386 | C46: R0126234 | D46: 715 W 112th Ave | E46: Northglenn | F46: CO | G46: Self-Storage | H46: Drive-Up/Drop-Off | J46: 83756 | L46: R0126234 | N46: AXG – Carlson SS Portfolio P&L | O46: 2026-06-02 | P46: Actual FY2021–2023
A47: P044 | B47: 386 | C47: R0027089/R0178319 | D47: 2290 E 120th Ave | E47: Thornton | F47: CO | G47: Self-Storage | H47: Drive-Up/Drop-Off | J47: 71909 | L47: R0027089/R0178319 | N47: AXG – Carlson SS Portfolio P&L | O47: 2026-06-02 | P47: Combined parcel FY2021–2023; 88.2% occ Dec 2023
A48: P045 | B48: 386 | C48: R0043569 | D48: 40131 Quivas St (104th & Quivas) | E48: Thornton | F48: CO | G48: Self-Storage | H48: Drive-Up/Drop-Off | J48: 41900 | L48: R0043569 | N48: AXG – SS Expense Matrix + FY2024 P&L | O48: 2026-06-02 | P48: Actual FY2024 monthly P&L + expense matrix
A49: P046 | B49: 386 | C49: R0193009 | D49: Address unknown – see R0193009 | E49: Adams County | F49: CO | G49: Self-Storage | H49: Climate-Controlled | J49: 94736 | L49: R0193009 | N49: AXG – SS Expense Matrix | O49: 2026-06-02 | P49: Expense matrix data; EGI $1,582,087
A50: P047 | B50: 386 | C50: R0099616 | D50: Address unknown – see R0099616 | E50: Adams County | F50: CO | G50: Self-Storage | H50: Drive-Up/Drop-Off | J50: 73500 | L50: R0099616 | N50: AXG – SS Expense Matrix | O50: 2026-06-02 | P50: Expense matrix data; EGI $834,358
A51: P048 | B51: 386 | C51: R0098019 | D51: Address unknown – see R0098019 | E51: Adams County | F51: CO | G51: Self-Storage | H51: Drive-Up/Drop-Off | J51: 44975 | L51: R0098019 | N51: AXG – SS Expense Matrix | O51: 2026-06-02 | P51: Expense matrix data; EGI $588,827
A52: P049 | B52: 386 | C52: R0102989 | D52: Fitzsimons area – see R0102989 | E52: Aurora | F52: CO | G52: Self-Storage | H52: Climate-Controlled | J52: 94797 | L52: R0102989 | N52: AXG – SS Expense Matrix | O52: 2026-06-02 | P52: Expense matrix data; EGI $1,184,503
A53: P050 | B53: 386 | C53: R0085523 | D53: Address unknown – see R0085523 | E53: Adams County | F53: CO | G53: Self-Storage | H53: Drive-Up/Drop-Off | J53: 39525 | L53: R0085523 | N53: AXG – SS Expense Matrix | O53: 2026-06-02 | P53: Expense matrix data; EGI $541,974
A54: P051 | B54: 386 | C54: R0174860 | D54: Address unknown – see R0174860 | E54: Adams County | F54: CO | G54: Self-Storage | H54: Drive-Up/Drop-Off (containers) | J54: 45980 | L54: R0174860 | N54: AXG – SS Expense Matrix | O54: 2026-06-02 | P54: Expense matrix data; EGI $646,496
A55: P052 | B55: 386 | C55: R0161412 | D55: Address unknown – see R0161412 | E55: Adams County | F55: CO | G55: Self-Storage | H55: Drive-Up/Drop-Off | J55: 88043 | L55: R0161412 | N55: AXG – SS Expense Matrix | O55: 2026-06-02 | P55: Expense matrix data; EGI $1,206,603
A56: P053 | B56: 386 | C56: R0169115 | D56: Address unknown – see R0169115 | E56: Adams County | F56: CO | G56: Self-Storage | H56: Drive-Up/Drop-Off | J56: 41764 | L56: R0169115 | N56: AXG – SS Expense Matrix | O56: 2026-06-02 | P56: Expense matrix data; EGI $787,364
A57: P054 | B57: 210 | C57: R0180551 | D57: 1953 N Gun Club Rd | E57: Aurora | F57: CO | G57: Industrial | H57: Multi-Tenant Industrial/Office NNN | L57: R0180551 | M57: Cherry Owner III LLC / AIP KKR | N57: 08_2025 Review – owner actual P&L | O57: 2026-06-02 | P57: Actual 2023+2024; base rent + full recovery; adj for prior-yr tax
A58: P055 | B58: 407 | C58: R0211072/R0211073/R0211074 | D58: Park 76 Distribution Center | E58: Aurora | F58: CO | G58: Industrial | H58: Industrial Warehouse (3-bldg campus) NNN | L58: R0211072/R0211073/R0211074 | M58: Park 76 Owner LLC / Alpha Industrial | N58: 08_2025 Review – owner actual P&L | O58: 2026-06-02 | P58: 3-building campus; actual 2023+2024; lease-up completed ~2023
A59: P056 | B59: 407 | C59: R0210485 | D59: 1101 E 126th Ave (Bldg A) | E59: Thornton | F59: CO | G59: Industrial | H59: Industrial Warehouse NNN | I59: 2022 | L59: R0210485 | M59: Thornton Owner LLC / Alpha Industrial | N59: 08_2025 Review – owner actual P&L | O59: 2026-06-02 | P59: New (YOC ~2022); 2023 lease-up; 2024 near-stabilized; 2024 only added
A60: P057 | B60: 407 | C60: R0210486 | D60: 12625 Lafayette St (Bldg B) | E60: Thornton | F60: CO | G60: Industrial | H60: Industrial Warehouse NNN | I60: 2022 | L60: R0210486 | M60: Thornton Owner LLC / Alpha Industrial | N60: 08_2025 Review – owner actual P&L | O60: 2026-06-02 | P60: New (YOC ~2022); 2023 lease-up; 2024 near-stabilized; 2024 only added
A61: P058 | B61: 407 | C61: R0091934 | D61: 350 Park Industrial (5759) | E61: Aurora | F61: CO | G61: Industrial | H61: Multi-Tenant Industrial 407 | I61: 1995 | J61: 32600 | L61: R0091934 | N61: 08_2025 Review – owner actual P&L | O61: 2026-06-02 | P61: Actual accrual 2023+2024; multi-tenant; 3 tenants
A62: P059 | B62: 407 | C62: R0093111 | D62: Industrial Property (yden0702) | E62: Aurora | F62: CO | G62: Industrial | H62: Multi-Tenant Industrial 407 | L62: R0093111 | N62: 08_2025 Review – owner actual P&L | O62: 2026-06-02 | P62: Actual 2023+2024; SF not confirmed; multi-tenant 3 tenants
A63: P060 | B63: 407 | C63: R0100104 | D63: 312 Kew West | E63: Aurora | F63: CO | G63: Industrial | H63: Multi-Tenant Industrial 407 | L63: R0100104 | N63: 08_2025 Review – owner actual P&L | O63: 2026-06-02 | P63: Actual 2023+2024; SF not confirmed
A64: P061 | B64: 584 | C64: R0083935 | D64: 20101 E 36th Ave (RK Industries) | E64: Aurora | F64: CO | G64: Industrial | H64: Mega Warehouse NNN | J64: 278538 | L64: R0083935 | M64: RK Industries | N64: 08_2025 Review – CBRE income statement | O64: 2026-06-02 | P64: Single-tenant NNN; 2024 partial data; rent $4.47/SF NNN
A65: P062 | B65: 407 | C65: R0200721 | D65: 3420 N Lisbon St | E65: Aurora | F65: CO | G65: Industrial | H65: Single-Tenant Industrial NNN | I65: 2019 | J65: 36212 | L65: R0200721 | M65: Cameron Ashley Bldg Products | N65: 08_2025 Review – rent roll | O65: 2026-06-02 | P65: NNN lease thru 12/31/2028; rent only; tenant pays all opex
A66: P063 | B66: 344 | C66: R0040581 | D66: 2090 E 104th Ave | E66: Thornton | F66: CO | G66: Office | H66: Multi-Tenant Office | J66: 19764 | L66: R0040581 | N66: 08_2025 Review – owner P&L | O66: 2026-06-02 | P66: Actual 2023+2024; 11 suites
A67: P064 | B67: 344 | C67: R0050977 | D67: 9351 Grant St | E67: Thornton | F67: CO | G67: Office | H67: Multi-Tenant Office | L67: R0050977 | M67: Crown Real Estate Group | N67: 08_2025 Review – owner P&L | O67: 2026-06-02 | P67: Actual 2023; SF not stated; large property
A68: P065 | B68: 344 | C68: R0069041 | D68: 7475 Dakin St (Turnpike Tower) | E68: Denver | F68: CO | G68: Office | H68: Multi-Tenant Office | J68: 114843 | L68: R0069041 | N68: 08_2025 Review – owner P&L | O68: 2026-06-02 | P68: Actual 2023+2024; 87.7% occ; NNN/Modified leases
A69: P066 | B69: 344 | C69: R0079409 | D69: 6401 E 72nd Ave | E69: Commerce City | F69: CO | G69: Office | H69: Multi-Tenant Office | J69: 8218 | L69: R0079409 | N69: 08_2025 Review – owner P&L | O69: 2026-06-02 | P69: Actual 2023; 9 tenants; small multi-tenant office
A70: P067 | B70: 344 | C70: R0189338 | D70: 203 Telluride St | E70: Aurora | F70: CO | G70: Office | H70: Multi-Tenant Office | L70: R0189338 | N70: 08_2025 Review – owner P&L | O70: 2026-06-02 | P70: Actual 2023+2024; SF not stated
A71: P068 | B71: 344 | C71: R0193830 | D71: Justice Center Office Plaza | E71: Denver | F71: CO | G71: Office | H71: Multi-Tenant Office NNN | J71: 41979 | L71: R0193830 | N71: 08_2025 Review – owner P&L | O71: 2026-06-02 | P71: Actual 2023+2024; govt tenants; 100% occ; NNN leases
A72: P069 | B72: 210 | C72: R0098223 | D72: Washington Commerce Center | E72: Commerce City | F72: CO | G72: Office/Industrial | H72: Multi-Tenant Office/Industrial | J72: 278538 | L72: R0098223 | N72: 08_2025 Review – owner P&L | O72: 2026-06-02 | P72: Actual 2023+2024; SF est; opex very low – likely tenant-pay NNN
A73: P070 | B73: 210 | C73: R0084242 | D73: Upland Dist Ctr I (Bldg 1 bt46274) | E73: Aurora | F73: CO | G73: Industrial | H73: Multi-Tenant Industrial NNN | L73: R0084242 | M73: Link Logistics | N73: 08_2025 Review – Link Logistics actual P&L | O73: 2026-06-02 | P73: Actual accrual 2023+2024; NNN reimbursable structure
A74: P071 | B74: 210 | C74: R0084243 | D74: Upland Dist Ctr I (Bldg 2 bt46275) | E74: Aurora | F74: CO | G74: Industrial | H74: Multi-Tenant Industrial NNN | L74: R0084243 | M74: Link Logistics | N74: 08_2025 Review – Link Logistics actual P&L | O74: 2026-06-02 | P74: Actual accrual 2023+2024
A75: P072 | B75: 210 | C75: R0084244 | D75: Upland Dist Ctr I (Bldg 3 bt46276) | E75: Aurora | F75: CO | G75: Industrial | H75: Multi-Tenant Industrial NNN | L75: R0084244 | M75: Link Logistics | N75: 08_2025 Review – Link Logistics actual P&L | O75: 2026-06-02 | P75: 2023 only; large warehouse; notable vacancy/free rent period
A76: P073 | B76: 210 | C76: R0084247 | D76: 13802 E 33rd Place | E76: Aurora | F76: CO | G76: Industrial | H76: Multi-Tenant Industrial NNN | L76: R0084247 | M76: Link Logistics | N76: 08_2025 Review – Link Logistics actual P&L | O76: 2026-06-02 | P76: Actual accrual 2023+2024
A77: P074 | B77: 210 | C77: R0084248 | D77: 14002 E 33rd Place | E77: Aurora | F77: CO | G77: Industrial | H77: Multi-Tenant Industrial NNN | L77: R0084248 | M77: Link Logistics | N77: 08_2025 Review – Link Logistics actual P&L | O77: 2026-06-02 | P77: Actual accrual 2023+2024; 2023 RE tax net of $53k refund
A78: P075 | B78: 210 | C78: R0084250 | D78: 3250 Abilene Street | E78: Aurora | F78: CO | G78: Industrial | H78: Multi-Tenant Industrial NNN | L78: R0084250 | M78: Link Logistics | N78: 08_2025 Review – Link Logistics actual P&L | O78: 2026-06-02 | P78: 2024 tenant turnover; base rent dropped $787k→$407k; 2023 more stable
A79: P076 | B79: 210 | C79: R0084253 | D79: 14509 E 33rd Place (bt46265) | E79: Aurora | F79: CO | G79: Industrial | H79: Multi-Tenant Industrial NNN | L79: R0084253 | M79: Link Logistics | N79: 08_2025 Review – Link Logistics actual P&L | O79: 2026-06-02 | P79: Actual 2023+2024; 3-bldg campus R0084253
A80: P077 | B80: 210 | C80: R0084253 | D80: 14704 E 33rd Place (bt46266) | E80: Aurora | F80: CO | G80: Industrial | H80: Multi-Tenant Industrial NNN | L80: R0084253 | M80: Link Logistics | N80: 08_2025 Review – Link Logistics actual P&L | O80: 2026-06-02 | P80: Actual 2024; partial vacancy (electric/gas vacancy costs); same parcel R0084253
A81: P078 | B81: 210 | C81: R0084253 | D81: 14705 E 33rd Place (bt46267) | E81: Aurora | F81: CO | G81: Industrial | H81: Multi-Tenant Industrial NNN | L81: R0084253 | M81: Link Logistics | N81: 08_2025 Review – Link Logistics actual P&L | O81: 2026-06-02 | P81: Actual 2024; partial lease-up/free rent; same parcel R0084253
A82: P079 | B82: 584 | C82: R0086214 | D82: Aurora Warehouse (Polar br40666) | E82: Aurora | F82: CO | G82: Industrial | H82: Mega Warehouse NNN | L82: R0086214 | M82: Link Logistics | N82: 08_2025 Review – Link Logistics actual P&L | O82: 2026-06-02 | P82: Actual 2023+2024; very large — RE tax $2.2-2.4M; revenue $6.5-7M
A83: P080 | B83: 407 | C83: R0194277 | D83: 8251 Quintero St | E83: Commerce City | F83: CO | G83: Industrial | H83: Industrial Warehouse NNN | L83: R0194277 | M83: Becknell Industrial | N83: 08_2025 Review – Becknell Industrial actual P&L | O83: 2026-06-02 | P83: Actual accrual 2023+2024; large RE taxes ~$2M; snow $151-188k
A84: P081 | B84: 407 | C84: R0198176 | D84: 21800 E 19th Ave | E84: Aurora | F84: CO | G84: Industrial | H84: Industrial Warehouse NNN | L84: R0198176 | M84: Becknell Industrial | N84: 08_2025 Review – Becknell Industrial actual P&L | O84: 2026-06-02 | P84: Actual accrual 2023+2024; absolute NNN – tenant pays RE taxes directly
... A87: P084 | B87: 407 | C87: R0201311 | D87: Ascent Commerce Center Bldg III | E87: Aurora | F87: CO | G87: Industrial | H87: Industrial Warehouse NNN | L87: R0201311 | M87: Ambrose Property Group | N87: 08_2025 Review – Ambrose Property Group actual P&L | O87: 2026-06-02 | P87: Q4 2024 only (Oct–Dec); lease-up/negative NOI; same campus R0201311
A88: P085 | B88: 210 | C88: R0093018 | D88: 3350 Peoria St | E88: Denver | F88: CO | G88: Industrial | H88: Office/Industrial Flex | J88: 33057 | L88: R0093018 | N88: Lease, Rent or Op Income info – owner P&L 2024 | O88: 2026-06-03 | P88: Office/Industrial flex; owner-submitted 2024 P&L
A89: P086 | B89: 406 | C89: R0210684 | D89: 14200 E Moncrieff Place | E89: Aurora | F89: CO | G89: Industrial | H89: Industrial Warehouse | I89: 1980 | J89: 233808 | L89: R0210684 | N89: Lease, Rent or Op Income info – owner P&L 2023+2024 | O89: 2026-06-03 | P89: Large industrial; 1980 YOC; 233,808 SF
A90: P087 | B90: 407 | C90: R0102985 | D90: 5861 Tennyson St | E90: Arvada | F90: CO | G90: Industrial | H90: Industrial NNN | I90: 2000 | J90: 80640 | L90: R0102985 | N90: Lease, Rent or Op Income info – owner P&L 2023+2024 | O90: 2026-06-03 | P90: NNN; landlord expenses only (tenant pays RE tax); 2000 YOC
A91: P088 | B91: 210 | C91: R0090973 | D91: 3975 E 56th Ave | E91: Commerce City | F91: CO | G91: Industrial | H91: Multi-Tenant Industrial | J91: 42299 | L91: R0090973 | N91: Lease, Rent or Op Income info – owner P&L 2024 | O91: 2026-06-03 | P91: Sand Creek Business Park; 2024 only
A92: P089 | B92: 407 | C92: R0180951 | D92: (Address TBD – R0180951) | E92: Adams County | F92: CO | G92: Industrial | H92: Industrial NNN | I92: 2016 | J92: 122106 | L92: R0180951 | N92: WH Expenses 2026-Working File – NNN landlord expenses 2023+2024 | O92: 2026-06-03 | P92: NNN; landlord RE Tax, Ins, Utils, CAM only; 2023+2024
A93: P090 | B93: 407 | C93: R0110351 | D93: (Address TBD – R0110351) | E93: Adams County | F93: CO | G93: Industrial | H93: Industrial NNN | I93: 2000 | J93: 85200 | L93: R0110351 | N93: WH Expenses 2026-Working File – NNN landlord expenses 2023+2024 | O93: 2026-06-03 | P93: NNN; landlord RE Tax, Ins, CAM only; 2023+2024
A94: P091 | B94: 584 | C94: R0198530 | D94: (Address TBD – R0198530) | E94: Adams County | F94: CO | G94: Industrial | H94: Industrial Mega-Warehouse NNN | I94: 2019 | J94: 555867 | L94: R0198530 | N94: WH Expenses 2026-Working File – NNN landlord expenses 2024 | O94: 2026-06-03 | P94: Mega-warehouse; NNN; landlord RE Tax, Ins, Mgmt only; 2024
A95: P092 | B95: 447 | C95: R0180834 | D95: (Address TBD – R0180834) | E95: Adams County | F95: CO | G95: Industrial | H95: Cold Storage/Mega-Warehouse NNN | I95: 2012 | J95: 550031 | L95: R0180834 | N95: WH Expenses 2026-Working File – NNN landlord expenses 2024 | O95: 2026-06-03 | P95: Cold storage/mega-WH; NNN; 2012 YOC; landlord RE Tax, Ins, Mgmt only
A96: P093 | B96: 407 | C96: R0114792 | D96: (Address TBD – R0114792) | E96: Adams County | F96: CO | G96: Industrial | H96: Industrial NNN | I96: 1998 | J96: 64501 | L96: R0114792 | N96: WH Expenses 2026-Working File – NNN landlord expenses 2023+2024 | O96: 2026-06-03 | P96: NNN; landlord RE Tax, Ins, Mgmt only; 1998 YOC
A97: P094 | B97: 407 | C97: R0104122 | D97: 550 W 53rd Pl | E97: Denver | F97: CO | G97: Industrial | H97: Distribution Warehouse | I97: 1971 | J97: 127900 | L97: R0104122 | N97: Brad-CBOE 2024 – appraiser income approach pro forma | O97: 2026-06-03 | P97: YOC 1971 (remod 1999/eff 1985); 127,900 SF; 2024 CBOE abatement income approach
A98: P095 | B98: 386 | C98: R0086010 | D98: 15413 E 18th Ave | E98: Aurora | F98: CO | G98: Self-Storage | H98: Self-Storage | I98: 1984 | J98: 63989 | L98: R0086010 | N98: AXG CBOE 2024 – appraiser income approach pro forma | O98: 2026-06-03 | P98: 8 buildings; NRA 57,754 SF; GBA 63,989 SF; 1984 YOC
A99: P096 | B99: 407 | C99: R0083917 | D99: 14701 E 38th Ave | E99: Aurora | F99: CO | G99: Industrial | H99: Industrial Owner-User | J99: 117280 | L99: R0083917 | N99: MT.xlsx I&E Survey 2024 | O99: 2026-06-03 | P99: Owner-user; expenses may include non-RE items (flag); 117,280 SF
A100: P097 | B100: 210 | C100: R0137586 | D100: 7273-7285 E 96th Ave | E100: Commerce City | F100: CO | G100: Industrial | H100: Multi-Tenant Industrial | J100: 57200 | L100: R0137586 | N100: MT.xlsx I&E Survey 2023 | O100: 2026-06-03 | P100: Modified lease; 57,200 SF; 2023 survey data
A101: P098 | B101: 210 | C101: R0187010 | D101: 8020 Steele St | E101: Denver | F101: CO | G101: Industrial | H101: Industrial Modified Gross | J101: 70000 | L101: R0187010 | N101: MT.xlsx I&E Survey 2024 | O101: 2026-06-03 | P101: Modified gross; owner pays ins/R&M/mgmt; tenant pays utils/trash; 70,000 SF
A102: P099 | B102: 210 | C102: R0111914 | D102: 1963 Jasper St | E102: Aurora | F102: CO | G102: Industrial | H102: Multi-Tenant Industrial Gross | J102: 33574 | L102: R0111914 | N102: MT.xlsx I&E Survey 2024 | O102: 2026-06-03 | P102: Gross lease; owner pays all expenses except gas/elec; 33,574 SF
...

Sheet Expense Database
A1: COMMERCIAL PROPERTY EXPENSE DATABASE ? ANNUAL DETAIL
A2: One row per property per year | All dollar figures from owner P&L unless noted | $/SF = $ / Building SF
A3: Prop ID | B3: Occ Code | C3: Account # | D3: Address | E3: City | F3: State | G3: Prop Type | H3: Subtype | I3: Year Built | J3: Bldg SF | K3: Year | L3: Gross Rental Income | M3: Other Income | N3: EGI | O3: Insurance | P3: Mgmt/Admin | Q3: Plumbing R&M | R3: Electrical R&M | S3: Exterior R&M | T3: Fire/Life Safety R&M | U3: HVAC R&M | V3: Interior Unit R&M | W3: Interior Common R&M | X3: General Maint & Repairs | Y3: Total R&M | Z3: Trash | AA3: Landscape | AB3: Snow Removal | AC3: Total Contract Svcs | AD3: Water & Sewer | AE3: Electric | AF3: Total Utilities | AG3: Other/Admin (Misc) | AH3: Total OPX excl RE Taxes | AI3: Real Estate Taxes | AJ3: Total OPX incl RE Taxes | AK3: NOI | AL3: CapEx (non-op) | AM3: Notes
A4: P001 | B4: 407 | C4: R0157664 | D4: 6045 E. 76th Avenue | E4: Commerce City | F4: CO | G4: Light Industrial | H4: Distribution Warehouse | I4: 1988 | J4: 21000 | K4: 2021 | L4: 282764.52 | M4: 6372 | N4: 289136.52 | O4: 4893 | P4: 0 | Q4: 1144 | R4: 0 | S4: 198.75 | T4: 0 | U4: 280 | V4: 846 | W4: 2923 | X4: 0 | Y4: 5391.75 | Z4: 6710.19 | AA4: 3875 | AB4: 870 | AC4: 11455.19 | AD4: 3344.39 | AE4: 648.33 | AF4: 3992.72 | AG4: 762.49 | AH4: 26515.15 | AI4: 48263.72 | AJ4: 74778.87 | AK4: 214357.65 | AL4: 2642.04 | AM4: 2021: other income = damages $2,392 + misc $3,863 + interest $117
A5: P001 | B5: 407 | C5: R0157664 | D5: 6045 E. 76th Avenue | E5: Commerce City | F5: CO | G5: Light Industrial | H5: Distribution Warehouse | I5: 1988 | J5: 21000 | K5: 2022 | L5: 255992.67 | M5: 3000 | N5: 258992.67 | O5: 5276 | P5: 0 | Q5: 4115 | R5: 611 | S5: 2333.33 | T5: 0 | U5: 0 | V5: 0 | W5: 780 | X5: 0 | Y5: 7839.33 | Z5: 8303.97 | AA5: 4280 | AB5: 0 | AC5: 12583.97 | AD5: 3043.11 | AE5: 887.54 | AF5: 3930.65 | AG5: 658.98 | AH5: 30288.93 | AI5: 66104.78 | AJ5: 96393.71 | AK5: 162598.96 | AL5: 5791.72 | AM5: 2022: other income = damages $500 + misc $2,500; CapEx unit interior
A6: P001 | B6: 407 | C6: R0157664 | D6: 6045 E. 76th Avenue | E6: Commerce City | F6: CO | G6: Light Industrial | H6: Distribution Warehouse | I6: 1988 | J6: 21000 | K6: 2023 | L6: 256200 | M6: 0 | N6: 256200 | O6: 5867.85 | P6: 800 | Q6: 1094.49 | R6: 990 | S6: 0 | T6: 3870.75 | U6: 480 | V6: 618 | W6: 0 | X6: 480 | Y6: 7533.24 | Z6: 9561.9 | AA6: 2200 | AB6: 2800 | AC6: 14561.9 | AD6: 7111.97 | AE6: 760.15 | AF6: 7872.12 | AG6: 597.59 | AH6: 31952.7 | AI6: 59985.48 | AJ6: 91938.18 | AK6: 164261.82 | AL6: 0
A7: P001 | B7: 407 | C7: R0157664 | D7: 6045 E. 76th Avenue | E7: Commerce City | F7: CO | G7: Light Industrial | H7: Distribution Warehouse | I7: 1988 | J7: 21000 | K7: 2024 | L7: 229531 | M7: 0 | N7: 229531 | O7: 1834.57 | P7: 1570 | Q7: 0 | R7: 0 | S7: 8000 | T7: 8299.8 | U7: 0 | V7: 175 | W7: 0 | X7: 819.88 | Y7: 17294.68 | Z7: 8500.75 | AA7: 3350 | AB7: 1050 | AC7: 12900.75 | AD7: 3438.85 | AE7: 712.77 | AF7: 4151.62 | AG7: 600.11 | AH7: 38151.7 | AI7: 69401.6 | AJ7: 107553.3 | AK7: 121977.7 | AL7: 0
A8: P002 | B8: 344 | C8: Unknown | D8: 13659 E. 104th Ave | E8: Adams County | F8: CO | G8: Office/Commercial | H8: Multi-tenant | K8: 2023 | N8: 258808 | O8: 3292 | P8: 18539 | X8: 24750 | Y8: 24750 | AA8: 13331 | AC8: 13331 | AF8: 3990 | AG8: 11264 | AH8: 75327 | AI8: 51707 | AJ8: 127034 | AK8: 131774 | AM8: Insurance: $3,292; Mgmt fee $13,242 + asset mgmt $5,297; Professional svcs $11,264; actuals from BAA operating statement
A9: P002 | B9: 344 | C9: Unknown | D9: 13659 E. 104th Ave | E9: Adams County | F9: CO | G9: Office/Commercial | H9: Multi-tenant | K9: 2024 | N9: 264959 | O9: 7442 | P9: 18228 | X9: 37394 | Y9: 37394 | AA9: 11888 | AC9: 11888 | AF9: 5290 | AG9: 13341 | AH9: 93583 | AI9: 44649 | AJ9: 138232 | AK9: 126727 | AM9: Insurance $7,442; Mgmt fee $13,020 + asset mgmt $5,208; Prof svcs $13,341; Utilities: gas/elec $1,091 + water/sewer $4,199
A10: P003 | B10: 344 | C10: R0024063 | D10: Park Centre - Wells Fargo Bldg | E10: Westminster | F10: CO | G10: Office | H10: Class B Multi-tenant | J10: 49479 | K10: 2023 | L10: 1017928 | M10: 93575 | N10: 1111503 | AH10: 453480 | AI10: 184874 | AJ10: 638354 | AK10: 473149 | AM10: Westfield managed; recoveries $49,658 + other $43,917 = $93,575; OpEx BT per PROFORMA REVISED.xlsx
A11: P003 | B11: 344 | C11: R0024063 | D11: Park Centre - Wells Fargo Bldg | E11: Westminster | F11: CO | G11: Office | H11: Class B Multi-tenant | J11: 49479 | K11: 2024 | L11: 944040 | M11: 77962 | N11: 1022002 | AH11: 488239 | AI11: 179568 | AJ11: 667807 | AK11: 354195 | AM11: Recoveries $21,696 + other $56,266; OpEx BT per PROFORMA REVISED.xlsx; NOI decline reflects higher vacancy
A12: P004 | B12: 412 | C12: R0050221 | D12: 8860 Federal Blvd | E12: Adams County | F12: CO | G12: Retail | H12: Strip/Multi-tenant | J12: 65850 | K12: 2023 | N12: 570777 | AI12: 74000 | AJ12: 269935 | AK12: 300842 | AM12: RE Tax estimated ~$74k (2023 not detailed); Total OpEx per actuals submission; NOI confirmed
A13: P004 | B13: 412 | C13: R0050221 | D13: 8860 Federal Blvd | E13: Adams County | F13: CO | G13: Retail | H13: Strip/Multi-tenant | J13: 65850 | K13: 2024 | N13: 587819 | O13: 51223 | X13: 28919 | Y13: 28919 | Z13: 17561 | AA13: 2002 | AB13: 3485 | AC13: 23048 | AD13: 12892 | AE13: 7120 | AF13: 20012 | AG13: 10978 | AH13: 159331 | AI13: 105466 | AJ13: 264797 | AK13: 323022 | AM13: Detailed 2024 actuals; R&M includes CAM component $261; insurance unusually high at $51,223; drainage/lighting included in Other
A14: P005 | B14: 344 | C14: R0050977 | D14: 9351 Grant St (Horizon Terrace) | E14: Thornton | F14: CO | G14: Office | H14: Class B Multi-story | J14: 91646 | K14: 2023 | L14: 2011958 | M14: 227276 | N14: 2239234 | O14: 24425 | P14: 132014 | X14: 144543 | Y14: 144543 | AA14: 108773 | AB14: 65183 | AC14: 273332 | AD14: 14762 | AE14: 225588 | AF14: 240350 | AG14: 32925 | AH14: 845814 | AI14: 372013 | AJ14: 1217827 | AK14: 1021407 | AM14: Full-service office: janitorial $164,559 in contract total; security/life safety $29,726 in Other; landscape incl snow $65,183; 2023 actuals confirmed
A15: P005 | B15: 344 | C15: R0050977 | D15: 9351 Grant St (Horizon Terrace) | E15: Thornton | F15: CO | G15: Office | H15: Class B Multi-story | J15: 91646 | K15: 2024 | L15: 2052556 | M15: 269597 | N15: 2322153 | O15: 24269 | P15: 149428 | X15: 150462 | Y15: 150462 | AA15: 109178 | AC15: 262640 | AF15: 232174 | AG15: 37416 | AH15: 856390 | AI15: 413583 | AJ15: 1269973 | AK15: 1052180 | AM15: 2024 actuals; janitorial $153,462 in contract total; security $32,603 in Other; sales/use tax $4,813 in Other
A16: P006 | B16: 210 | C16: R0062937 | D16: 8670 Wolff Ct (Sheridan Park 8) | E16: Westminster | F16: CO | G16: Office/Flex | H16: Multi-tenant | J16: 37078 | K16: 2020 | O16: 5777 | P16: 19499 | AC16: 133689 | AF16: 116321 | AH16: 275286 | AI16: 88705 | AJ16: 363991 | AM16: Income not available; expense-only from DYCO CAM history; CAM in contract total
A17: P006 | B17: 210 | C17: R0062937 | D17: 8670 Wolff Ct (Sheridan Park 8) | E17: Westminster | F17: CO | G17: Office/Flex | H17: Multi-tenant | J17: 37078 | K17: 2021 | O17: 6826 | P17: 18000 | AC17: 104519 | AF17: 108857 | AH17: 238202 | AI17: 84200 | AJ17: 322402 | AM17: Income not available; expense-only from DYCO CAM history
A18: P006 | B18: 210 | C18: R0062937 | D18: 8670 Wolff Ct (Sheridan Park 8) | E18: Westminster | F18: CO | G18: Office/Flex | H18: Multi-tenant | J18: 37078 | K18: 2022 | O18: 7867 | P18: 20952 | AC18: 112201 | AF18: 111968 | AH18: 252988 | AI18: 137142 | AJ18: 390130 | AM18: Income not available; expense-only from DYCO CAM history; RE Tax jumped from $84k to $137k (reval year)
A19: P006 | B19: 210 | C19: R0062937 | D19: 8670 Wolff Ct (Sheridan Park 8) | E19: Westminster | F19: CO | G19: Office/Flex | H19: Multi-tenant | J19: 37078 | K19: 2023 | O19: 8654 | P19: 18000 | AC19: 116495 | AF19: 111903 | AH19: 255052 | AI19: 131777 | AJ19: 386829 | AM19: Income not available; 2023 YTD annualized per DYCO
A20: P006 | B20: 210 | C20: R0062937 | D20: 8670 Wolff Ct (Sheridan Park 8) | E20: Westminster | F20: CO | G20: Office/Flex | H20: Multi-tenant | J20: 37078 | K20: 2024 | O20: 8654 | P20: 21600 | AC20: 139794 | AF20: 134284 | AH20: 304332 | AI20: 131777 | AJ20: 436109 | AM20: Income not available; 2024 actuals per DYCO CAM history
A21: P007 | B21: 341 | C21: R0062944 | D21: 8787 (medical office complex) | E21: Adams County | F21: CO | G21: Medical Office | H21: Multi-tenant | J21: 19430 | K21: 2023 | N21: 393809 | O21: 9485 | P21: 10200 | U21: 21615 | X21: 26521 | Y21: 26521 | Z21: 2032 | AA21: 11685 | AB21: 6338 | AC21: 20055 | AD21: 7660 | AE21: 37676 | AF21: 45336 | AG21: 18144 | AH21: 151355 | AI21: 53397 | AJ21: 204752 | AK21: 189057 | AM21: HVAC maint $21,615 included in R&M; janitorial $16,418 in Other; professional svcs $1,726 in Other; 2023 actuals
A22: P007 | B22: 341 | C22: R0062944 | D22: 8787 (medical office complex) | E22: Adams County | F22: CO | G22: Medical Office | H22: Multi-tenant | J22: 19430 | K22: 2024 | N22: 390497 | O22: 13960 | P22: 38622 | U22: 13067 | X22: 25835 | Y22: 25835 | Z22: 1958 | AA22: 15696 | AB22: 5885 | AC22: 23539 | AD22: 6421 | AE22: 33074 | AF22: 39495 | AG22: 16022 | AH22: 170540 | AI22: 63200 | AJ22: 233740 | AK22: 156757 | AM22: Mgmt = CAM portion $10,600 + non-CAM $28,022; janitorial $16,022 in Other; HVAC $13,067 in R&M; 2024 actuals
A23: P008 | B23: 210 | C23: R0070622 | D23: 460-550 E. 76th Ave (WPC Corporate) | E23: Adams County | F23: CO | G23: Industrial | H23: Distribution/Flex Multi-tenant | J23: 330935 | K23: 2024 | N23: 2750538 | AJ23: 1338440 | AK23: 1412098 | AM23: 2024 only; total OPX derived (EGI - NOI); limited line-item detail from scanned actuals; large multi-tenant industrial complex
A24: P009 | B24: 407 | C24: R0075212 | D24: 10500 Havana Court | E24: Adams County | F24: CO | G24: Industrial | H24: NNN Single-tenant | K24: 2023 | N24: 332759 | O24: 22784 | P24: 4000 | X24: 12804 | Y24: 12804 | AA24: 6910 | AB24: 1800 | AC24: 8710 | AD24: 2209 | AE24: 1956 | AF24: 4165 | AG24: 8397 | AH24: 127005 | AI24: 60552 | AJ24: 187557 | AK24: 265550 | AM24: NNN; P&L excludes depreciation ($68,209) and mortgage interest ($60,714) from NOI calc; acctg/legal/bank/dues in Other; 2023 actuals
A25: P009 | B25: 407 | C25: R0075212 | D25: 10500 Havana Court | E25: Adams County | F25: CO | G25: Industrial | H25: NNN Single-tenant | K25: 2024 | N25: 359583 | O25: 27489 | P25: 6000 | X25: 9601 | Y25: 9601 | AA25: 3045 | AB25: 1960 | AC25: 5005 | AD25: 3555 | AE25: 1567 | AF25: 5122 | AG25: 10035 | AH25: 69350 | AI25: 101114 | AJ25: 170464 | AK25: 290993 | AM25: NNN; depreciation ($52,109) and mortgage interest ($58,574) excluded from NOI; Other includes acctg, dues, inspections; 2024 actuals
A26: P010 | B26: 210 | C26: R0098225 | D26: Broadway Business Center (7040B Broadway) | E26: Denver | F26: CO | G26: Flex/Industrial | H26: Multi-tenant CAM | J26: 105000 | K26: 2023 | L26: 737984 | M26: 508740 | N26: 1246724 | O26: 48903 | P26: 104311 | X26: 66445 | Y26: 66445 | Z26: 49021 | AA26: 22802 | AB26: 58641 | AC26: 130464 | AD26: 53517 | AF26: 75845 | AH26: 484485 | AI26: 229515 | AJ26: 714000 | AK26: 533000 | AM26: CAM recovery structure; mgmt = prop mgmt fee $50,590 + recoverable mgmt $53,721; snow in contract; 2023 actuals; NOI estimated
A27: P010 | B27: 210 | C27: R0098225 | D27: Broadway Business Center (7040B Broadway) | E27: Denver | F27: CO | G27: Flex/Industrial | H27: Multi-tenant CAM | J27: 105000 | K27: 2024 | L27: 902782 | M27: 784277 | N27: 1687059 | O27: 50508 | P27: 123399 | X27: 75128 | Y27: 75128 | Z27: 58998 | AA27: 18144 | AB27: 52328 | AC27: 129470 | AD27: 87196 | AF27: 100191 | AH27: 502686 | AI27: 544314 | AJ27: 1047000 | AK27: 640000 | AM27: 2024 RE Tax inflated by $111,314 prior-yr catchup; normalized tax ~$425k; parking lot $52,328 in snow/contract; NOI estimated
A28: P011 | B28: 210 | C28: R0103767 | D28: 5650 Washington St (Washington Business Park) | E28: Adams County | F28: CO | G28: Industrial/Flex | H28: Multi-tenant | K28: 2022 | N28: 502006 | O28: 16872 | P28: 54025 | X28: 71762 | Y28: 71762 | AA28: 6528 | AC28: 6528 | AD28: 4858 | AE28: 525 | AF28: 5383 | AH28: 209625 | AI28: 64792 | AJ28: 274417 | AK28: 227649 | AM28: Mgmt fee $54,025 (2022 only ? not in later years); R&M = bldg maint + repairs + HVAC + plumbing; water/gas from operating stmt
A29: P011 | B29: 210 | C29: R0103767 | D29: 5650 Washington St (Washington Business Park) | E29: Adams County | F29: CO | G29: Industrial/Flex | H29: Multi-tenant | K29: 2023 | N29: 532468 | O29: 15442 | X29: 83293 | Y29: 83293 | AA29: 6029 | AC29: 6029 | AD29: 6487 | AF29: 6487 | AH29: 141304 | AI29: 63133 | AJ29: 204437 | AK29: 328030 | AM29: No mgmt fee in 2023; R&M higher due to building repairs; gas negligible per statement; 2023 actuals
A30: P011 | B30: 210 | C30: R0103767 | D30: 5650 Washington St (Washington Business Park) | E30: Adams County | F30: CO | G30: Industrial/Flex | H30: Multi-tenant | K30: 2024 | N30: 517234 | O30: 20795 | X30: 32385 | Y30: 32385 | AA30: 4814 | AC30: 4814 | AD30: 5690 | AF30: 5690 | AJ30: 331645 | AK30: 185389 | AM30: RE Tax not separately identified in 2024 column of operating stmt; total OPX from actuals; NOI confirmed
A31: P012 | B31: 344 | C31: R0124385 | D31: Unknown (Tax District 555) | E31: Adams County | F31: CO | G31: Office | H31: Multi-tenant | J31: 20170 | K31: 2023 | N31: 275740 | AH31: 108096 | AI31: 45179 | AJ31: 153275 | AK31: 167644 | AM31: Limited line-item detail; totals from PROFORMA BASIS FOR OFFER.xlsx actuals section
A32: P012 | B32: 344 | C32: R0124385 | D32: Unknown (Tax District 555) | E32: Adams County | F32: CO | G32: Office | H32: Multi-tenant | J32: 20170 | K32: 2024 | N32: 298556 | AH32: 127491 | AI32: 43698 | AJ32: 185189 | AK32: 171065 | AM32: CapEx $14,000 non-recurring excluded from OPX; limited line-item detail
A33: P013 | B33: 353 | C33: R0169176 | D33: Unknown (new const., opened Oct 2023) | E33: Adams County | F33: CO | G33: Retail/Office | H33: Multi-tenant | I33: 2023 | K33: 2023 | L33: 270793 | M33: 258323 | N33: 524533 | O33: 16865 | P33: 26496 | X33: 50972 | Y33: 50972 | AA33: 7543 | AC33: 7543 | AD33: 4602 | AE33: 51467 | AF33: 56069 | AH33: 157946 | AI33: 125577 | AJ33: 283523 | AK33: 241009 | AM33: 2023 partial year (opened Oct 2023); RE Tax high for new construction; gas $3,877 + elec $47,590 in utilities
A34: P013 | B34: 353 | C34: R0169176 | D34: Unknown (new const., opened Oct 2023) | E34: Adams County | F34: CO | G34: Retail/Office | H34: Multi-tenant | I34: 2023 | K34: 2024 | L34: 260040 | M34: 337015 | N34: 597056 | O34: 12437 | P34: 26717 | X34: 36931 | Y34: 36931 | AA34: 27159 | AC34: 27159 | AD34: 5043 | AE34: 54230 | AF34: 59273 | AH34: 162518 | AI34: 156074 | AJ34: 318592 | AK34: 278464 | AM34: Tax consultant $11,515 added to RE Tax line; HOA/exterior maint $27,159 in landscape; recoveries $336,319 + other $696
A35: P014 | B35: 407 | C35: R0198530 | D35: Amazon DEN7 Distribution Center | E35: Aurora | F35: CO | G35: Industrial/Distribution | H35: Single-tenant NNN | J35: 555840 | K35: 2023 | L35: 3123377 | N35: 3123377 | O35: 86084 | P35: 62468 | AC35: 22360 | AF35: 1107 | AH35: 197351 | AI35: 1617282 | AJ35: 1814633 | AM35: NNN ? expenses = LL CAM billed to Amazon tenant; RE Tax $1.617M dominates; base rent $3.12M; 2023 CAM reconciliation
A36: P014 | B36: 407 | C36: R0198530 | D36: Amazon DEN7 Distribution Center | E36: Aurora | F36: CO | G36: Industrial/Distribution | H36: Single-tenant NNN | J36: 555840 | K36: 2024 | L36: 3201462 | N36: 3201462 | O36: 89809 | P36: 64029 | AB36: 2110 | AC36: 17455 | AF36: 2024 | AH36: 154693 | AI36: 2161856 | AJ36: 2316549 | AM36: NNN; RE Tax $2.162M = $3.89/SF reflecting Adams County assessment increase (+34% YOY); 2024 CAM reconciliation
A37: P015 | B37: 407 | C37: R0180894 | D37: 1910 N Gun Club Rd | E37: Aurora | F37: CO | G37: Industrial | H37: Distribution Warehouse Multi-Tenant NNN | I37: 2019 | J37: 163386 | K37: 2023 | L37: 2096086 | N37: 2096086 | O37: 40706 | P37: 55071 | Y37: 6447 | AA37: 14502 | AB37: 55450 | AF37: 43911 | AG37: 159500 | AH37: 379886 | AI37: 923586 | AJ37: 1303472 | AK37: 792614 | AM37: Actual accrual; security $159,500 in Other
A38: P015 | B38: 407 | C38: R0180894 | D38: 1910 N Gun Club Rd | E38: Aurora | F38: CO | G38: Industrial | H38: Distribution Warehouse Multi-Tenant NNN | I38: 2019 | J38: 163386 | K38: 2024 | L38: 2154019 | N38: 2154019 | O38: 48091 | P38: 74844 | Y38: 5257 | AA38: 13438 | AB38: 46667 | AF38: 53895 | AG38: 132552 | AH38: 394495 | AI38: 912402 | AJ38: 1306897 | AK38: 847122 | AM38: Actual accrual; security $132,552 in Other
A39: P016 | B39: 584 | C39: R0212546/R0212547 | D39: 2780 N Tower Rd | E39: Aurora | F39: CO | G39: Industrial | H39: Mega Warehouse NNN | I39: 1983 | J39: 384953 | K39: 2024 | AM39: County proforma only; limited line-item detail available
A40: P017 | B40: 210 | C40: R0098098 | D40: 1445 E 68th Ave | E40: Denver | F40: CO | G40: Industrial | H40: Industrial Office Mix | I40: 1972 | J40: 63348 | K40: 2024 | AM40: County proforma 2024; YOC 1972/2006/2023 additions
A41: P018 | B41: 406 | C41: R0103783 | D41: 2031 E 58th Ave | E41: Denver | F41: CO | G41: Industrial | H41: Storage Warehouse / Mod Office NNN | I41: 2004 | J41: 18720 | K41: 2024 | L41: 248796 | N41: 299942 | O41: 3858 | AC41: 2427 | AH41: 6285 | AI41: 44860 | AJ41: 51145 | AK41: 248797 | AM41: NNN billed charges; EGI = base rent + NNN pass-throughs
A42: P018 | B42: 406 | C42: R0103783 | D42: 2031 E 58th Ave | E42: Denver | F42: CO | G42: Industrial | H42: Storage Warehouse / Mod Office NNN | I42: 2004 | J42: 18720 | K42: 2023 | L42: 243918 | N42: 295063 | O42: 3858 | AC42: 2427 | AH42: 6285 | AI42: 44860 | AJ42: 51145 | AK42: 243918 | AM42: NNN billed charges; EGI = base rent + NNN pass-throughs
A43: P019 | B43: 407 | C43: R0210402/R0210403 | D43: 17190 E 85th Ave | E43: Commerce City | F43: CO | G43: Industrial | H43: Industrial Warehouse NNN | I43: 2021 | J43: 329940 | K43: 2024 | AM43: Petitioner proforma 2024/25; limited line-item detail
A44: P020 | B44: 584 | C44: R0209679 | D44: 17501 E 84th Ave | E44: Commerce City | F44: CO | G44: Industrial | H44: Mega Warehouse / Distribution Center NNN (Lowe's) | I44: 2021 | J44: 999780 | K44: 2023 | L44: 12396458 | N44: 12396458 | O44: 150453 | P44: 100437 | Y44: 53276 | AA44: 50764 | AB44: 117765 | AG44: 8384 | AH44: 1354674 | AI44: 4922300 | AJ44: 8277752 | AK44: 4118706 | AM44: Actual accrual; 2023 NOI inflated ~$2.8M by prior-yr RE tax adj; security in Other
A45: P020 | B45: 584 | C45: R0209679 | D45: 17501 E 84th Ave | E45: Commerce City | F45: CO | G45: Industrial | H45: Mega Warehouse / Distribution Center NNN (Lowe's) | I45: 2021 | J45: 999780 | K45: 2024 | L45: 10000751 | N45: 10000751 | O45: 171963 | P45: 101559 | Y45: 120481 | AA45: 37766 | AB45: 131877 | AG45: 30799 | AH45: 797409 | AI45: 4996600 | AJ45: 5794009 | AK45: 4206742 | AM45: Actual accrual; security $30,799 in Other
A46: P021 | B46: 210 | C46: R0091931 | D46: 6300 E. 58th Ave | E46: Commerce City | F46: CO | G46: Industrial | H46: Multi-Tenant Industrial/Flex | I46: 1999 | J46: 90000 | K46: 2023 | L46: 949132 | N46: 1238350 | O46: 15839 | P46: 46438 | Q46: 3968 | S46: 27292 | T46: 6577 | X46: 23213 | Y46: 61050 | Z46: 930 | AA46: 4777 | AB46: 11271 | AC46: 16978 | AD46: 14167 | AE46: 5593 | AF46: 19760 | AH46: 162482 | AI46: 283603 | AJ46: 446085 | AK46: 792265 | AM46: Actual accrual; parking sweep in Trash; admin fees in Mgmt
A47: P021 | B47: 210 | C47: R0091931 | D47: 6300 E. 58th Ave | E47: Commerce City | F47: CO | G47: Industrial | H47: Multi-Tenant Industrial/Flex | I47: 1999 | J47: 90000 | K47: 2024 | L47: 911911 | N47: 1307178 | O47: 15815 | P47: 65253 | Q47: 620 | S47: 35961 | T47: 7833 | X47: 22008 | Y47: 66422 | Z47: 1176 | AA47: 4463 | AB47: 14953 | AC47: 20592 | AD47: 15736 | AE47: 5731 | AF47: 21467 | AH47: 158481 | AI47: 290988 | AJ47: 449469 | AK47: 842728 | AM47: Actual accrual; snow $14,953 also listed under ext R&M; security/admin in ext maint
A48: P022 | B48: 210 | C48: R0111559 | D48: 3590 N. Himalaya Rd (Bldg 6) | E48: Aurora | F48: CO | G48: Industrial | H48: Multi-Tenant Industrial/Flex NNN | K48: 2024 | L48: 548918 | N48: 766859 | O48: 23025 | AD48: 7986 | AE48: 33669 | AF48: 41655 | AI48: 129107 | AJ48: 250157 | AK48: 374789 | AM48: 2024 only – 2023 was transitional vacancy year; SF not confirmed; approx figures
A49: P023 | B49: 407 | C49: R0191098 | D49: 19754 E. 35th Dr (Bldg 4) | E49: Aurora | F49: CO | G49: Industrial | H49: Single-Tenant Industrial NNN | J49: 155033 | K49: 2023 | L49: 969912 | N49: 968340 | O49: 20444 | P49: 29946 | AA49: 3990 | AD49: 37966 | AE49: 13715 | AF49: 51681 | AH49: 295391 | AI49: 92518 | AJ49: 387909 | AK49: 580431 | AM49: NNN; tenant pays most R&M directly; Quality Custom Distribution lease thru 12/31/2029
A50: P023 | B50: 407 | C50: R0191098 | D50: 19754 E. 35th Dr (Bldg 4) | E50: Aurora | F50: CO | G50: Industrial | H50: Single-Tenant Industrial NNN | J50: 155033 | K50: 2024 | L50: 1011167 | N50: 1011168 | O50: 28366 | P50: 29365 | AD50: 36662 | AE50: 27344 | AF50: 64006 | AH50: 264833 | AI50: 120903 | AJ50: 385736 | AK50: 625432 | AM50: NNN; tenant pays most R&M directly
A51: P024 | B51: 407 | C51: R0111560 | D51: 20320 E. 36th Dr (Bldg 7) | E51: Aurora | F51: CO | G51: Industrial | H51: Single-Tenant Industrial NNN | J51: 200000 | K51: 2023 | L51: 1391167 | N51: 1357167 | O51: 4008 | AE51: 2419 | AF51: 2419 | AH51: 235792 | AI51: 3481 | AJ51: 239273 | AK51: 1117893 | AM51: FedEx NNN thru 4/30/2024; tenant pays nearly all expenses; 2024 excluded (lease expiry vacancy)
A52: P025 | B52: 210 | C52: R0191099 | D52: 3559 N. Himalaya Rd (Bldg 5) | E52: Aurora | F52: CO | G52: Industrial | H52: Multi-Tenant Industrial NNN | J52: 159047 | K52: 2023 | N52: 2146251 | P52: 5837 | AB52: 2813 | AJ52: 1015103 | AK52: 1131148 | AM52: Multi-tenant NNN; limited expense detail available; approx figures
A53: P025 | B53: 210 | C53: R0191099 | D53: 3559 N. Himalaya Rd (Bldg 5) | E53: Aurora | F53: CO | G53: Industrial | H53: Multi-Tenant Industrial NNN | J53: 159047 | K53: 2024 | N53: 2148251 | AB53: 2813 | AJ53: 1176766 | AK53: 971485 | AM53: Multi-tenant NNN; limited expense detail available; approx figures
A54: P026 | B54: 406 | C54: R0092667 | D54: 4901 Locust St | E54: Commerce City | F54: CO | G54: Industrial | H54: Industrial Warehouse | J54: 29512 | K54: 2024 | N54: 419456 | O54: 4427 | P54: 10486 | X54: 16232 | Y54: 16232 | AF54: 7378 | AG54: 14756 | AH54: 59181 | AI54: 97831 | AJ54: 157012 | AK54: 262444 | AL54: 5902 | AM54: Newmark stabilized proforma 6/30/2024; cap rate 7.00%; not actual historical
A55: P022 | B55: 210 | C55: R0111559 | D55: 3590 N. Himalaya Rd (Bldg 6) | E55: Aurora | F55: CO | G55: Industrial | H55: Multi-Tenant Industrial/Flex NNN | I55: 1998 | J55: 123603 | K55: 2021 | O55: 10376 | P55: 43384 | AC55: 88626 | AF55: 37062 | AH55: 179448 | AI55: 289126 | AJ55: 468574 | AM55: NNN landlord expenses only; from AXG Whse Expenses PSF.xlsx
A56: P022 | B56: 210 | C56: R0111559 | D56: 3590 N. Himalaya Rd (Bldg 6) | E56: Aurora | F56: CO | G56: Industrial | H56: Multi-Tenant Industrial/Flex NNN | I56: 1998 | J56: 123603 | K56: 2022 | O56: 11039 | P56: 39811 | AC56: 91945 | AF56: 38461 | AH56: 181256 | AI56: 318845 | AJ56: 500101 | AM56: NNN landlord expenses only; from AXG Whse Expenses PSF.xlsx
A57: P024 | B57: 407 | C57: R0111560 | D57: 20320 E. 36th Dr (Bldg 7) | E57: Aurora | F57: CO | G57: Industrial | H57: Single-Tenant Industrial NNN | I57: 1998 | J57: 199962 | K57: 2019 | O57: 8457 | P57: 26194 | AC57: 261694 | AH57: 296345 | AI57: 494719 | AJ57: 791064 | AM57: NNN landlord expenses only; from AXG Whse Expenses PSF.xlsx
A58: P024 | B58: 407 | C58: R0111560 | D58: 20320 E. 36th Dr (Bldg 7) | E58: Aurora | F58: CO | G58: Industrial | H58: Single-Tenant Industrial NNN | I58: 1998 | J58: 199962 | K58: 2020 | O58: 9678 | P58: 26625 | AC58: 144817 | AH58: 181120 | AI58: 415592 | AJ58: 596712 | AM58: NNN landlord expenses only; from AXG Whse Expenses PSF.xlsx
A59: P025 | B59: 210 | C59: R0191099 | D59: 3559 N. Himalaya Rd (Bldg 5) | E59: Aurora | F59: CO | G59: Industrial | H59: Multi-Tenant Industrial NNN | I59: 2017 | J59: 159047 | K59: 2021 | O59: 15209 | P59: 53747 | AC59: 59915 | AF59: 46324 | AH59: 175195 | AI59: 554960 | AJ59: 730155 | AM59: NNN landlord expenses only; from AXG Whse Expenses PSF.xlsx
A60: P025 | B60: 210 | C60: R0191099 | D60: 3559 N. Himalaya Rd (Bldg 5) | E60: Aurora | F60: CO | G60: Industrial | H60: Multi-Tenant Industrial NNN | I60: 2017 | J60: 159047 | K60: 2022 | O60: 16181 | P60: 49338 | AC60: 53323 | AF60: 51404 | AH60: 170246 | AI60: 468848 | AJ60: 639094 | AM60: NNN landlord expenses only; from AXG Whse Expenses PSF.xlsx
A61: P027 | B61: 407 | C61: R0132030 | D61: Majestic Commercenter (R0132030) | E61: Commerce City | F61: CO | G61: Industrial | H61: Warehouse NNN | I61: 2001 | J61: 200094 | K61: 2021 | O61: 14313 | P61: 53036 | AC61: 98037 | AF61: 70815 | AH61: 236201 | AI61: 570651 | AJ61: 806852 | AM61: NNN landlord expenses only; from AXG Whse Expenses PSF.xlsx (R0132030)
A62: P027 | B62: 407 | C62: R0132030 | D62: Majestic Commercenter (R0132030) | E62: Commerce City | F62: CO | G62: Industrial | H62: Warehouse NNN | I62: 2001 | J62: 200094 | K62: 2022 | O62: 15228 | P62: 49506 | AC62: 98037 | AF62: 70815 | AH62: 233586 | AI62: 451706 | AJ62: 685292 | AM62: NNN landlord expenses only; from AXG Whse Expenses PSF.xlsx (R0132030)
A63: P028 | B63: 407 | C63: R0084040 | D63: Majestic Commercenter (R0084040) | E63: Commerce City | F63: CO | G63: Industrial | H63: Warehouse NNN | I63: 1997 | J63: 177736 | K63: 2021 | O63: 13073 | P63: 55346 | AC63: 98118 | AF63: 51405 | AH63: 217942 | AI63: 483220 | AJ63: 701162 | AM63: NNN landlord expenses only; from AXG Whse Expenses PSF.xlsx (R0084040)
A64: P028 | B64: 407 | C64: R0084040 | D64: Majestic Commercenter (R0084040) | E64: Commerce City | F64: CO | G64: Industrial | H64: Warehouse NNN | I64: 1997 | J64: 177736 | K64: 2022 | O64: 13909 | P64: 55347 | AC64: 117141 | AF64: 63264 | AH64: 249661 | AI64: 506747 | AJ64: 756408 | AM64: NNN landlord expenses only; from AXG Whse Expenses PSF.xlsx (R0084040)
A65: P029 | B65: 407 | C65: R0084041 | D65: Majestic Commercenter (R0084041) | E65: Commerce City | F65: CO | G65: Industrial | H65: Warehouse NNN | I65: 1997 | J65: 200371 | K65: 2021 | O65: 13750 | P65: 32155 | AC65: 117597 | AH65: 163502 | AI65: 499309 | AJ65: 662811 | AM65: NNN landlord expenses only; from AXG Whse Expenses PSF.xlsx (R0084041)
A66: P029 | B66: 407 | C66: R0084041 | D66: Majestic Commercenter (R0084041) | E66: Commerce City | F66: CO | G66: Industrial | H66: Warehouse NNN | I66: 1997 | J66: 200371 | K66: 2022 | O66: 14629 | P66: 29974 | AC66: 103927 | AH66: 148530 | AI66: 518816 | AJ66: 667346 | AM66: NNN landlord expenses only; from AXG Whse Expenses PSF.xlsx (R0084041)
A67: P030 | B67: 584 | C67: R0217015 | D67: Majestic Commercenter (R0217015) | E67: Commerce City | F67: CO | G67: Industrial | H67: Warehouse NNN | I67: 2021 | J67: 548510 | K67: 2022 | O67: 64009 | P67: 58266 | AC67: 96936 | AF67: 20844 | AH67: 240055 | AI67: 1245681 | AJ67: 1485736 | AM67: NNN landlord expenses only; from AXG Whse Expenses PSF.xlsx (R0217015)
A68: P031 | B68: 407 | C68: R0111562 | D68: Majestic Commercenter (R0111562) | E68: Commerce City | F68: CO | G68: Industrial | H68: Warehouse NNN | I68: 2000 | J68: 149175 | K68: 2019 | O68: 6519 | P68: 22700 | AC68: 101769 | AH68: 130988 | AI68: 281972 | AJ68: 412960 | AM68: NNN landlord expenses only; from AXG Whse Expenses PSF.xlsx (R0111562)
A69: P031 | B69: 407 | C69: R0111562 | D69: Majestic Commercenter (R0111562) | E69: Commerce City | F69: CO | G69: Industrial | H69: Warehouse NNN | I69: 2000 | J69: 149175 | K69: 2020 | O69: 7450 | P69: 3942 | AC69: 23921 | AF69: 165141 | AH69: 200454 | AI69: 282989 | AJ69: 483443 | AM69: NNN landlord expenses only; from AXG Whse Expenses PSF.xlsx (R0111562)
A70: P032 | B70: 407 | C70: R0118875 | D70: Majestic Commercenter (R0118875) | E70: Commerce City | F70: CO | G70: Industrial | H70: Warehouse NNN | I70: 1999 | J70: 279640 | K70: 2021 | O70: 24629 | P70: 62870 | AC70: 100363 | AH70: 187862 | AI70: 640886 | AJ70: 828748 | AM70: NNN landlord expenses only; from AXG Whse Expenses PSF.xlsx (R0118875)
A71: P032 | B71: 407 | C71: R0118875 | D71: Majestic Commercenter (R0118875) | E71: Commerce City | F71: CO | G71: Industrial | H71: Warehouse NNN | I71: 1999 | J71: 279640 | K71: 2022 | O71: 26204 | P71: 63433 | AC71: 18197 | AH71: 107834 | AI71: 657060 | AJ71: 764894 | AM71: NNN landlord expenses only; from AXG Whse Expenses PSF.xlsx (R0118875)
A72: P033 | B72: 407 | C72: R0132031 | D72: Majestic Commercenter (R0132031) | E72: Commerce City | F72: CO | G72: Industrial | H72: Warehouse NNN | I72: 2002 | J72: 280098 | K72: 2021 | O72: 19984 | P72: 64701 | AC72: 73763 | AF72: 85895 | AH72: 244343 | AI72: 639063 | AJ72: 883406 | AM72: NNN landlord expenses only; from AXG Whse Expenses PSF.xlsx (R0132031)
A73: P033 | B73: 407 | C73: R0132031 | D73: Majestic Commercenter (R0132031) | E73: Commerce City | F73: CO | G73: Industrial | H73: Warehouse NNN | I73: 2002 | J73: 280098 | K73: 2022 | O73: 21261 | P73: 59067 | AC73: 120936 | AF73: 94786 | AH73: 296050 | AI73: 669090 | AJ73: 965140 | AM73: NNN landlord expenses only; from AXG Whse Expenses PSF.xlsx (R0132031)
A74: P034 | B74: 407 | C74: R0172865 | D74: Majestic Commercenter (R0172865) | E74: Commerce City | F74: CO | G74: Industrial | H74: Warehouse NNN | I74: 2008 | J74: 215461 | K74: 2021 | O74: 17428 | P74: 65798 | AC74: 100975 | AF74: 73139 | AH74: 257340 | AI74: 614041 | AJ74: 871381 | AM74: NNN landlord expenses only; from AXG Whse Expenses PSF.xlsx (R0172865)
A75: P034 | B75: 407 | C75: R0172865 | D75: Majestic Commercenter (R0172865) | E75: Commerce City | F75: CO | G75: Industrial | H75: Warehouse NNN | I75: 2008 | J75: 215461 | K75: 2022 | O75: 18350 | P75: 62443 | AC75: 73459 | AF75: 74975 | AH75: 229227 | AI75: 590782 | AJ75: 820009 | AM75: NNN landlord expenses only; from AXG Whse Expenses PSF.xlsx (R0172865)
A76: P035 | B76: 407 | C76: R0172867 | D76: Majestic Commercenter (R0172867) | E76: Commerce City | F76: CO | G76: Industrial | H76: Warehouse NNN | I76: 2007 | J76: 215560 | K76: 2021 | O76: 21017 | P76: 52362 | AC76: 64218 | AF76: 67129 | AH76: 204726 | AI76: 537207 | AJ76: 741933 | AM76: NNN landlord expenses only; from AXG Whse Expenses PSF.xlsx (R0172867)
A77: P035 | B77: 407 | C77: R0172867 | D77: Majestic Commercenter (R0172867) | E77: Commerce City | F77: CO | G77: Industrial | H77: Warehouse NNN | I77: 2007 | J77: 215560 | K77: 2022 | O77: 22360 | P77: 55092 | AC77: 67277 | AF77: 72040 | AH77: 216769 | AI77: 558214 | AJ77: 774983 | AM77: NNN landlord expenses only; from AXG Whse Expenses PSF.xlsx (R0172867)
A78: P036 | B78: 407 | C78: R0172868 | D78: Majestic Commercenter (R0172868) | E78: Commerce City | F78: CO | G78: Industrial | H78: Warehouse NNN | I78: 2007 | J78: 202091 | K78: 2021 | O78: 17434 | P78: 31149 | AC78: 83142 | AH78: 131725 | AI78: 499000 | AJ78: 630725 | AM78: NNN landlord expenses only; from AXG Whse Expenses PSF.xlsx (R0172868)
A79: P036 | B79: 407 | C79: R0172868 | D79: Majestic Commercenter (R0172868) | E79: Commerce City | F79: CO | G79: Industrial | H79: Warehouse NNN | I79: 2007 | J79: 202091 | K79: 2022 | O79: 18548 | P79: 27554 | AC79: 66184 | AH79: 112286 | AI79: 509649 | AJ79: 621935 | AM79: NNN landlord expenses only; from AXG Whse Expenses PSF.xlsx (R0172868)
A80: P037 | B80: 407 | C80: R0145680 | D80: Majestic Commercenter (R0145680) | E80: Commerce City | F80: CO | G80: Industrial | H80: Warehouse NNN | I80: 2001 | J80: 150027 | K80: 2021 | O80: 11682 | P80: 41521 | AC80: 49834 | AH80: 103037 | AI80: 427951 | AJ80: 530988 | AM80: NNN landlord expenses only; from AXG Whse Expenses PSF.xlsx (R0145680)
A81: P037 | B81: 407 | C81: R0145680 | D81: Majestic Commercenter (R0145680) | E81: Commerce City | F81: CO | G81: Industrial | H81: Warehouse NNN | I81: 2001 | J81: 150027 | K81: 2022 | O81: 12428 | P81: 34409 | AC81: 54262 | AH81: 101099 | AI81: 410892 | AJ81: 511991 | AM81: NNN landlord expenses only; from AXG Whse Expenses PSF.xlsx (R0145680)
A82: P038 | B82: 584 | C82: R0181787 | D82: Majestic Commercenter (R0181787) | E82: Commerce City | F82: CO | G82: Industrial | H82: Warehouse NNN | I82: 2013 | J82: 500358 | K82: 2021 | O82: 37172 | P82: 117764 | AC82: 156518 | AF82: 117148 | AH82: 428602 | AI82: 1142695 | AJ82: 1571297 | AM82: NNN landlord expenses only; from AXG Whse Expenses PSF.xlsx (R0181787)
A83: P038 | B83: 584 | C83: R0181787 | D83: Majestic Commercenter (R0181787) | E83: Commerce City | F83: CO | G83: Industrial | H83: Warehouse NNN | I83: 2013 | J83: 500358 | K83: 2022 | O83: 39548 | P83: 100791 | AC83: 116474 | AF83: 113231 | AH83: 370044 | AI83: 1270807 | AJ83: 1640851 | AM83: NNN landlord expenses only; from AXG Whse Expenses PSF.xlsx (R0181787)
A84: P039 | B84: 584 | C84: R0191101 | D84: Majestic Commercenter (R0191101) | E84: Commerce City | F84: CO | G84: Industrial | H84: Warehouse NNN | I84: 2017 | J84: 522120 | K84: 2021 | O84: 42908 | P84: 134812 | AC84: 147507 | AF84: 93640 | AH84: 418867 | AI84: 1137439 | AJ84: 1556306 | AM84: NNN landlord expenses only; from AXG Whse Expenses PSF.xlsx (R0191101)
A85: P039 | B85: 584 | C85: R0191101 | D85: Majestic Commercenter (R0191101) | E85: Commerce City | F85: CO | G85: Industrial | H85: Warehouse NNN | I85: 2017 | J85: 522120 | K85: 2022 | O85: 45651 | P85: 115853 | AC85: 89739 | AF85: 90763 | AH85: 342006 | AI85: 1169645 | AJ85: 1511651 | AM85: NNN landlord expenses only; from AXG Whse Expenses PSF.xlsx (R0191101)
A86: P040 | B86: 407 | C86: R0202874 | D86: 900 E 128th Ave | E86: Henderson | F86: CO | G86: Industrial | H86: Last-Mile Distribution NNN | K86: 2021 | L86: 2633716 | N86: 3256403 | O86: 56624 | Q86: 300 | X86: 29535 | Y86: 30138 | AA86: 54136 | AB86: 127274 | AF86: 18748 | AH86: 731951 | AK86: 2524452 | AM86: Amazon AMZL Site 51812; SF not extracted; RE Tax not broken out in 2021
A87: P040 | B87: 407 | C87: R0202874 | D87: 900 E 128th Ave | E87: Henderson | F87: CO | G87: Industrial | H87: Last-Mile Distribution NNN | K87: 2022 | P87: 69999 | AI87: 1080500 | AJ87: 1527913 | AK87: 2475461 | AM87: Amazon AMZL Site 51812; 2022 dominated by RE Tax $1.08M; asset mgmt fee $70k
A88: P041 | B88: 386 | C88: R0189384 | D88: 1101 Colorado Blvd | E88: Thornton | F88: CO | G88: Self-Storage | H88: Climate-Controlled | J88: 65766 | K88: 2021 | N88: 879992 | AJ88: 418098 | AK88: 461894 | AM88: Actual SS P&L; mgmt=off-site+on-site combined; admin+adv in Other
A89: P041 | B89: 386 | C89: R0189384 | D89: 1101 Colorado Blvd | E89: Thornton | F89: CO | G89: Self-Storage | H89: Climate-Controlled | J89: 65766 | K89: 2022 | N89: 924824 | AJ89: 455769 | AK89: 469055 | AM89: Actual SS P&L; mgmt=off-site+on-site combined; admin+adv in Other
A90: P041 | B90: 386 | C90: R0189384 | D90: 1101 Colorado Blvd | E90: Thornton | F90: CO | G90: Self-Storage | H90: Climate-Controlled | J90: 65766 | K90: 2023 | N90: 931247 | O90: 41471 | P90: 104101 | Y90: 15564 | AF90: 37120 | AH90: 294563 | AI90: 179920 | AJ90: 474483 | AK90: 469746 | AM90: Actual SS P&L; mgmt=off-site+on-site combined; admin+adv in Other
A91: P042 | B91: 386 | C91: R0126235 | D91: 15024 Laroy Drive | E91: Northglenn | F91: CO | G91: Self-Storage | H91: Climate-Controlled | J91: 79950 | K91: 2021 | N91: 956337 | AJ91: 481614 | AK91: 514723 | AM91: Actual SS P&L; mgmt=off-site+on-site combined
A92: P042 | B92: 386 | C92: R0126235 | D92: 15024 Laroy Drive | E92: Northglenn | F92: CO | G92: Self-Storage | H92: Climate-Controlled | J92: 79950 | K92: 2022 | N92: 1017929 | AJ92: 432239 | AK92: 585690 | AM92: Actual SS P&L; mgmt=off-site+on-site combined
A93: P042 | B93: 386 | C93: R0126235 | D93: 15024 Laroy Drive | E93: Northglenn | F93: CO | G93: Self-Storage | H93: Climate-Controlled | J93: 79950 | K93: 2023 | N93: 954605 | O93: 40815 | P93: 108523 | Y93: 24068 | AF93: 20683 | AH93: 274666 | AI93: 244725 | AJ93: 519391 | AK93: 435215 | AM93: Actual SS P&L; mgmt=off-site+on-site combined
A94: P043 | B94: 386 | C94: R0126234 | D94: 715 W 112th Ave | E94: Northglenn | F94: CO | G94: Self-Storage | H94: Drive-Up/Drop-Off | J94: 83756 | K94: 2021 | N94: 814763 | AJ94: 436596 | AK94: 378167 | AM94: Actual SS P&L; mgmt=off-site+on-site combined
A95: P043 | B95: 386 | C95: R0126234 | D95: 715 W 112th Ave | E95: Northglenn | F95: CO | G95: Self-Storage | H95: Drive-Up/Drop-Off | J95: 83756 | K95: 2022 | N95: 980798 | AJ95: 455854 | AK95: 524944 | AM95: Actual SS P&L; mgmt=off-site+on-site combined
A96: P043 | B96: 386 | C96: R0126234 | D96: 715 W 112th Ave | E96: Northglenn | F96: CO | G96: Self-Storage | H96: Drive-Up/Drop-Off | J96: 83756 | K96: 2023 | N96: 1011950 | O96: 47107 | P96: 111748 | Y96: 10236 | AF96: 15944 | AH96: 257858 | AI96: 202686 | AJ96: 460544 | AK96: 551606 | AM96: Actual SS P&L; mgmt=off-site+on-site combined
A97: P044 | B97: 386 | C97: R0027089/R0178319 | D97: 2290 E 120th Ave | E97: Thornton | F97: CO | G97: Self-Storage | H97: Drive-Up/Drop-Off | J97: 71909 | K97: 2021 | N97: 837430 | AJ97: 445701 | AK97: 391729 | AM97: Actual SS P&L; combined parcels R0027089+R0178319; mgmt=off-site+on-site
A98: P044 | B98: 386 | C98: R0027089/R0178319 | D98: 2290 E 120th Ave | E98: Thornton | F98: CO | G98: Self-Storage | H98: Drive-Up/Drop-Off | J98: 71909 | K98: 2022 | N98: 945562 | AJ98: 445701 | AK98: 466302 | AM98: Actual SS P&L; combined parcels R0027089+R0178319; mgmt=off-site+on-site
A99: P044 | B99: 386 | C99: R0027089/R0178319 | D99: 2290 E 120th Ave | E99: Thornton | F99: CO | G99: Self-Storage | H99: Drive-Up/Drop-Off | J99: 71909 | K99: 2023 | N99: 980778 | O99: 43407 | P99: 141702 | Y99: 17835 | AF99: 21431 | AH99: 298955 | AI99: 186365 | AJ99: 485320 | AK99: 492300 | AM99: Actual SS P&L; combined parcels R0027089+R0178319; mgmt=off-site+on-site
A100: P045 | B100: 386 | C100: R0043569 | D100: 40131 Quivas St | E100: Thornton | F100: CO | G100: Self-Storage | H100: Drive-Up/Drop-Off | J100: 41900 | K100: 2024 | N100: 718060 | O100: 19037 | P100: 93975 | Y100: 11768 | AF100: 5417 | AH100: 208790 | AI100: 176524 | AJ100: 385314 | AK100: 332746 | AM100: Actual FY2024 P&L; mgmt=off-site $42,964+on-site $51,011; RE Tax est from matrix
...

Sheet PSF Summary
A1: COMMERCIAL PROPERTY EXPENSE DATABASE - PSF SUMMARY ($/SF)
A2: Figures in $/SF of building area | Rows with no BldgSF show raw dollar amounts flagged [NO SF] | Text/ID fields copied from Expense Database
A3: Prop ID | B3: Occ Code | C3: Account # | D3: Address | E3: City | F3: State | G3: Prop Type | H3: Subtype | I3: Year Built | J3: Bldg SF | K3: Year | L3: Gross Rental Income | M3: Other Income | N3: EGI | O3: Insurance | P3: Mgmt/Admin | Q3: Plumbing R&M | R3: Electrical R&M | S3: Exterior R&M | T3: Fire/Life Safety R&M | U3: HVAC R&M | V3: Interior Unit R&M | W3: Interior Common R&M | X3: General Maint & Repairs | Y3: Total R&M | Z3: Trash | AA3: Landscape | AB3: Snow Removal | AC3: Total Contract Svcs | AD3: Water & Sewer | AE3: Electric | AF3: Total Utilities | AG3: Other/Admin (Misc) | AH3: Total OPX excl RE Taxes | AI3: Real Estate Taxes | AJ3: Total OPX incl RE Taxes | AK3: NOI | AL3: CapEx (non-op) | AM3: Notes
A4: P001 | B4: 407 | C4: R0157664 | D4: 6045 E. 76th Avenue | E4: Commerce City | F4: CO | G4: Light Industrial | H4: Distribution Warehouse | I4: 1988 | J4: 21000 | K4: 2021 | L4: 13.465 | M4: 0.3034 | N4: 13.7684 | O4: 0.233 | P4: 0 | Q4: 0.0545 | R4: 0 | S4: 0.0095 | T4: 0 | U4: 0.0133 | V4: 0.0403 | W4: 0.1392 | X4: 0 | Y4: 0.2567 | Z4: 0.3195 | AA4: 0.1845 | AB4: 0.0414 | AC4: 0.5455 | AD4: 0.1593 | AE4: 0.0309 | AF4: 0.1901 | AG4: 0.0363 | AH4: 1.2626 | AI4: 2.2983 | AJ4: 3.5609 | AK4: 10.2075 | AL4: 0.1258 | AM4: 2021: other income = damages $2,392 + misc $3,863 + interest $117
A5: P001 | B5: 407 | C5: R0157664 | D5: 6045 E. 76th Avenue | E5: Commerce City | F5: CO | G5: Light Industrial | H5: Distribution Warehouse | I5: 1988 | J5: 21000 | K5: 2022 | L5: 12.1901 | M5: 0.1429 | N5: 12.333 | O5: 0.2512 | P5: 0 | Q5: 0.196 | R5: 0.0291 | S5: 0.1111 | T5: 0 | U5: 0 | V5: 0 | W5: 0.0371 | X5: 0 | Y5: 0.3733 | Z5: 0.3954 | AA5: 0.2038 | AB5: 0 | AC5: 0.5992 | AD5: 0.1449 | AE5: 0.0423 | AF5: 0.1872 | AG5: 0.0314 | AH5: 1.4423 | AI5: 3.1478 | AJ5: 4.5902 | AK5: 7.7428 | AL5: 0.2758 | AM5: 2022: other income = damages $500 + misc $2,500; CapEx unit interior
A6: P001 | B6: 407 | C6: R0157664 | D6: 6045 E. 76th Avenue | E6: Commerce City | F6: CO | G6: Light Industrial | H6: Distribution Warehouse | I6: 1988 | J6: 21000 | K6: 2023 | L6: 12.2 | M6: 0 | N6: 12.2 | O6: 0.2794 | P6: 0.0381 | Q6: 0.0521 | R6: 0.0471 | S6: 0 | T6: 0.1843 | U6: 0.0229 | V6: 0.0294 | W6: 0 | X6: 0.0229 | Y6: 0.3587 | Z6: 0.4553 | AA6: 0.1048 | AB6: 0.1333 | AC6: 0.6934 | AD6: 0.3387 | AE6: 0.0362 | AF6: 0.3749 | AG6: 0.0285 | AH6: 1.5216 | AI6: 2.8565 | AJ6: 4.378 | AK6: 7.822 | AL6: 0
A7: P001 | B7: 407 | C7: R0157664 | D7: 6045 E. 76th Avenue | E7: Commerce City | F7: CO | G7: Light Industrial | H7: Distribution Warehouse | I7: 1988 | J7: 21000 | K7: 2024 | L7: 10.93 | M7: 0 | N7: 10.93 | O7: 0.0874 | P7: 0.0748 | Q7: 0 | R7: 0 | S7: 0.381 | T7: 0.3952 | U7: 0 | V7: 0.0083 | W7: 0 | X7: 0.039 | Y7: 0.8236 | Z7: 0.4048 | AA7: 0.1595 | AB7: 0.05 | AC7: 0.6143 | AD7: 0.1638 | AE7: 0.0339 | AF7: 0.1977 | AG7: 0.0286 | AH7: 1.8167 | AI7: 3.3048 | AJ7: 5.1216 | AK7: 5.8085 | AL7: 0
A8: P002 | B8: 344 | C8: Unknown | D8: 13659 E. 104th Ave | E8: Adams County | F8: CO | G8: Office/Commercial | H8: Multi-tenant | K8: 2023 | N8: 258808 | O8: 3292 | P8: 18539 | X8: 24750 | Y8: 24750 | AA8: 13331 | AC8: 13331 | AF8: 3990 | AG8: 11264 | AH8: 75327 | AI8: 51707 | AJ8: 127034 | AK8: 131774 | AM8: [NO SF] Insurance: $3,292; Mgmt fee $13,242 + asset mgmt $5,297; Professional svcs $11,264; actuals from BAA operating statement
A9: P002 | B9: 344 | C9: Unknown | D9: 13659 E. 104th Ave | E9: Adams County | F9: CO | G9: Office/Commercial | H9: Multi-tenant | K9: 2024 | N9: 264959 | O9: 7442 | P9: 18228 | X9: 37394 | Y9: 37394 | AA9: 11888 | AC9: 11888 | AF9: 5290 | AG9: 13341 | AH9: 93583 | AI9: 44649 | AJ9: 138232 | AK9: 126727 | AM9: [NO SF] Insurance $7,442; Mgmt fee $13,020 + asset mgmt $5,208; Prof svcs $13,341; Utilities: gas/elec $1,091 + water/sewer $4,199
A10: P003 | B10: 344 | C10: R0024063 | D10: Park Centre - Wells Fargo Bldg | E10: Westminster | F10: CO | G10: Office | H10: Class B Multi-tenant | J10: 49479 | K10: 2023 | L10: 20.5729 | M10: 1.8912 | N10: 22.4641 | AH10: 9.1651 | AI10: 3.7364 | AJ10: 12.9015 | AK10: 9.5626 | AM10: Westfield managed; recoveries $49,658 + other $43,917 = $93,575; OpEx BT per PROFORMA REVISED.xlsx
A11: P003 | B11: 344 | C11: R0024063 | D11: Park Centre - Wells Fargo Bldg | E11: Westminster | F11: CO | G11: Office | H11: Class B Multi-tenant | J11: 49479 | K11: 2024 | L11: 19.0796 | M11: 1.5757 | N11: 20.6553 | AH11: 9.8676 | AI11: 3.6292 | AJ11: 13.4968 | AK11: 7.1585 | AM11: Recoveries $21,696 + other $56,266; OpEx BT per PROFORMA REVISED.xlsx; NOI decline reflects higher vacancy
A12: P004 | B12: 412 | C12: R0050221 | D12: 8860 Federal Blvd | E12: Adams County | F12: CO | G12: Retail | H12: Strip/Multi-tenant | J12: 65850 | K12: 2023 | N12: 8.6678 | AI12: 1.1238 | AJ12: 4.0992 | AK12: 4.5686 | AM12: RE Tax estimated ~$74k (2023 not detailed); Total OpEx per actuals submission; NOI confirmed
A13: P004 | B13: 412 | C13: R0050221 | D13: 8860 Federal Blvd | E13: Adams County | F13: CO | G13: Retail | H13: Strip/Multi-tenant | J13: 65850 | K13: 2024 | N13: 8.9266 | O13: 0.7779 | X13: 0.4392 | Y13: 0.4392 | Z13: 0.2667 | AA13: 0.0304 | AB13: 0.0529 | AC13: 0.35 | AD13: 0.1958 | AE13: 0.1081 | AF13: 0.3039 | AG13: 0.1667 | AH13: 2.4196 | AI13: 1.6016 | AJ13: 4.0212 | AK13: 4.9054 | AM13: Detailed 2024 actuals; R&M includes CAM component $261; insurance unusually high at $51,223; drainage/lighting included in Other
A14: P005 | B14: 344 | C14: R0050977 | D14: 9351 Grant St (Horizon Terrace) | E14: Thornton | F14: CO | G14: Office | H14: Class B Multi-story | J14: 91646 | K14: 2023 | L14: 21.9536 | M14: 2.4799 | N14: 24.4335 | O14: 0.2665 | P14: 1.4405 | X14: 1.5772 | Y14: 1.5772 | AA14: 1.1869 | AB14: 0.7112 | AC14: 2.9825 | AD14: 0.1611 | AE14: 2.4615 | AF14: 2.6226 | AG14: 0.3593 | AH14: 9.2291 | AI14: 4.0592 | AJ14: 13.2884 | AK14: 11.1451 | AM14: Full-service office: janitorial $164,559 in contract total; security/life safety $29,726 in Other; landscape incl snow $65,183; 2023 actuals confirmed
A15: P005 | B15: 344 | C15: R0050977 | D15: 9351 Grant St (Horizon Terrace) | E15: Thornton | F15: CO | G15: Office | H15: Class B Multi-story | J15: 91646 | K15: 2024 | L15: 22.3966 | M15: 2.9417 | N15: 25.3383 | O15: 0.2648 | P15: 1.6305 | X15: 1.6418 | Y15: 1.6418 | AA15: 1.1913 | AC15: 2.8658 | AF15: 2.5334 | AG15: 0.4083 | AH15: 9.3445 | AI15: 4.5128 | AJ15: 13.8574 | AK15: 11.4809 | AM15: 2024 actuals; janitorial $153,462 in contract total; security $32,603 in Other; sales/use tax $4,813 in Other
A16: P006 | B16: 210 | C16: R0062937 | D16: 8670 Wolff Ct (Sheridan Park 8) | E16: Westminster | F16: CO | G16: Office/Flex | H16: Multi-tenant | J16: 37078 | K16: 2020 | O16: 0.1558 | P16: 0.5259 | AC16: 3.6056 | AF16: 3.1372 | AH16: 7.4245 | AI16: 2.3924 | AJ16: 9.8169 | AM16: Income not available; expense-only from DYCO CAM history; CAM in contract total
A17: P006 | B17: 210 | C17: R0062937 | D17: 8670 Wolff Ct (Sheridan Park 8) | E17: Westminster | F17: CO | G17: Office/Flex | H17: Multi-tenant | J17: 37078 | K17: 2021 | O17: 0.1841 | P17: 0.4855 | AC17: 2.8189 | AF17: 2.9359 | AH17: 6.4243 | AI17: 2.2709 | AJ17: 8.6952 | AM17: Income not available; expense-only from DYCO CAM history
A18: P006 | B18: 210 | C18: R0062937 | D18: 8670 Wolff Ct (Sheridan Park 8) | E18: Westminster | F18: CO | G18: Office/Flex | H18: Multi-tenant | J18: 37078 | K18: 2022 | O18: 0.2122 | P18: 0.5651 | AC18: 3.0261 | AF18: 3.0198 | AH18: 6.8231 | AI18: 3.6987 | AJ18: 10.5219 | AM18: Income not available; expense-only from DYCO CAM history; RE Tax jumped from $84k to $137k (reval year)
A19: P006 | B19: 210 | C19: R0062937 | D19: 8670 Wolff Ct (Sheridan Park 8) | E19: Westminster | F19: CO | G19: Office/Flex | H19: Multi-tenant | J19: 37078 | K19: 2023 | O19: 0.2334 | P19: 0.4855 | AC19: 3.1419 | AF19: 3.018 | AH19: 6.8788 | AI19: 3.554 | AJ19: 10.4328 | AM19: Income not available; 2023 YTD annualized per DYCO
A20: P006 | B20: 210 | C20: R0062937 | D20: 8670 Wolff Ct (Sheridan Park 8) | E20: Westminster | F20: CO | G20: Office/Flex | H20: Multi-tenant | J20: 37078 | K20: 2024 | O20: 0.2334 | P20: 0.5826 | AC20: 3.7703 | AF20: 3.6217 | AH20: 8.2079 | AI20: 3.554 | AJ20: 11.7619 | AM20: Income not available; 2024 actuals per DYCO CAM history
A21: P007 | B21: 341 | C21: R0062944 | D21: 8787 (medical office complex) | E21: Adams County | F21: CO | G21: Medical Office | H21: Multi-tenant | J21: 19430 | K21: 2023 | N21: 20.2681 | O21: 0.4882 | P21: 0.525 | U21: 1.1125 | X21: 1.365 | Y21: 1.365 | Z21: 0.1046 | AA21: 0.6014 | AB21: 0.3262 | AC21: 1.0322 | AD21: 0.3942 | AE21: 1.9391 | AF21: 2.3333 | AG21: 0.9338 | AH21: 7.7898 | AI21: 2.7482 | AJ21: 10.5379 | AK21: 9.7302 | AM21: HVAC maint $21,615 included in R&M; janitorial $16,418 in Other; professional svcs $1,726 in Other; 2023 actuals
A22: P007 | B22: 341 | C22: R0062944 | D22: 8787 (medical office complex) | E22: Adams County | F22: CO | G22: Medical Office | H22: Multi-tenant | J22: 19430 | K22: 2024 | N22: 20.0976 | O22: 0.7185 | P22: 1.9878 | U22: 0.6725 | X22: 1.3296 | Y22: 1.3296 | Z22: 0.1008 | AA22: 0.8078 | AB22: 0.3029 | AC22: 1.2115 | AD22: 0.3305 | AE22: 1.7022 | AF22: 2.0327 | AG22: 0.8246 | AH22: 8.7771 | AI22: 3.2527 | AJ22: 12.0299 | AK22: 8.0678 | AM22: Mgmt = CAM portion $10,600 + non-CAM $28,022; janitorial $16,022 in Other; HVAC $13,067 in R&M; 2024 actuals
A23: P008 | B23: 210 | C23: R0070622 | D23: 460-550 E. 76th Ave (WPC Corporate) | E23: Adams County | F23: CO | G23: Industrial | H23: Distribution/Flex Multi-tenant | J23: 330935 | K23: 2024 | N23: 8.3114 | AJ23: 4.0444 | AK23: 4.267 | AM23: 2024 only; total OPX derived (EGI - NOI); limited line-item detail from scanned actuals; large multi-tenant industrial complex
A24: P009 | B24: 407 | C24: R0075212 | D24: 10500 Havana Court | E24: Adams County | F24: CO | G24: Industrial | H24: NNN Single-tenant | K24: 2023 | N24: 332759 | O24: 22784 | P24: 4000 | X24: 12804 | Y24: 12804 | AA24: 6910 | AB24: 1800 | AC24: 8710 | AD24: 2209 | AE24: 1956 | AF24: 4165 | AG24: 8397 | AH24: 127005 | AI24: 60552 | AJ24: 187557 | AK24: 265550 | AM24: [NO SF] NNN; P&L excludes depreciation ($68,209) and mortgage interest ($60,714) from NOI calc; acctg/legal/bank/dues in Other; 2023 actuals
A25: P009 | B25: 407 | C25: R0075212 | D25: 10500 Havana Court | E25: Adams County | F25: CO | G25: Industrial | H25: NNN Single-tenant | K25: 2024 | N25: 359583 | O25: 27489 | P25: 6000 | X25: 9601 | Y25: 9601 | AA25: 3045 | AB25: 1960 | AC25: 5005 | AD25: 3555 | AE25: 1567 | AF25: 5122 | AG25: 10035 | AH25: 69350 | AI25: 101114 | AJ25: 170464 | AK25: 290993 | AM25: [NO SF] NNN; depreciation ($52,109) and mortgage interest ($58,574) excluded from NOI; Other includes acctg, dues, inspections; 2024 actuals
A26: P010 | B26: 210 | C26: R0098225 | D26: Broadway Business Center (7040B Broadway) | E26: Denver | F26: CO | G26: Flex/Industrial | H26: Multi-tenant CAM | J26: 105000 | K26: 2023 | L26: 7.0284 | M26: 4.8451 | N26: 11.8736 | O26: 0.4657 | P26: 0.9934 | X26: 0.6328 | Y26: 0.6328 | Z26: 0.4669 | AA26: 0.2172 | AB26: 0.5585 | AC26: 1.2425 | AD26: 0.5097 | AF26: 0.7223 | AH26: 4.6141 | AI26: 2.1859 | AJ26: 6.8 | AK26: 5.0762 | AM26: CAM recovery structure; mgmt = prop mgmt fee $50,590 + recoverable mgmt $53,721; snow in contract; 2023 actuals; NOI estimated
A27: P010 | B27: 210 | C27: R0098225 | D27: Broadway Business Center (7040B Broadway) | E27: Denver | F27: CO | G27: Flex/Industrial | H27: Multi-tenant CAM | J27: 105000 | K27: 2024 | L27: 8.5979 | M27: 7.4693 | N27: 16.0672 | O27: 0.481 | P27: 1.1752 | X27: 0.7155 | Y27: 0.7155 | Z27: 0.5619 | AA27: 0.1728 | AB27: 0.4984 | AC27: 1.233 | AD27: 0.8304 | AF27: 0.9542 | AH27: 4.7875 | AI27: 5.1839 | AJ27: 9.9714 | AK27: 6.0952 | AM27: 2024 RE Tax inflated by $111,314 prior-yr catchup; normalized tax ~$425k; parking lot $52,328 in snow/contract; NOI estimated
A28: P011 | B28: 210 | C28: R0103767 | D28: 5650 Washington St (Washington Business Park) | E28: Adams County | F28: CO | G28: Industrial/Flex | H28: Multi-tenant | K28: 2022 | N28: 502006 | O28: 16872 | P28: 54025 | X28: 71762 | Y28: 71762 | AA28: 6528 | AC28: 6528 | AD28: 4858 | AE28: 525 | AF28: 5383 | AH28: 209625 | AI28: 64792 | AJ28: 274417 | AK28: 227649 | AM28: [NO SF] Mgmt fee $54,025 (2022 only ? not in later years); R&M = bldg maint + repairs + HVAC + plumbing; water/gas from operating stmt
A29: P011 | B29: 210 | C29: R0103767 | D29: 5650 Washington St (Washington Business Park) | E29: Adams County | F29: CO | G29: Industrial/Flex | H29: Multi-tenant | K29: 2023 | N29: 532468 | O29: 15442 | X29: 83293 | Y29: 83293 | AA29: 6029 | AC29: 6029 | AD29: 6487 | AF29: 6487 | AH29: 141304 | AI29: 63133 | AJ29: 204437 | AK29: 328030 | AM29: [NO SF] No mgmt fee in 2023; R&M higher due to building repairs; gas negligible per statement; 2023 actuals
A30: P011 | B30: 210 | C30: R0103767 | D30: 5650 Washington St (Washington Business Park) | E30: Adams County | F30: CO | G30: Industrial/Flex | H30: Multi-tenant | K30: 2024 | N30: 517234 | O30: 20795 | X30: 32385 | Y30: 32385 | AA30: 4814 | AC30: 4814 | AD30: 5690 | AF30: 5690 | AJ30: 331645 | AK30: 185389 | AM30: [NO SF] RE Tax not separately identified in 2024 column of operating stmt; total OPX from actuals; NOI confirmed
A31: P012 | B31: 344 | C31: R0124385 | D31: Unknown (Tax District 555) | E31: Adams County | F31: CO | G31: Office | H31: Multi-tenant | J31: 20170 | K31: 2023 | N31: 13.6708 | AH31: 5.3592 | AI31: 2.2399 | AJ31: 7.5992 | AK31: 8.3116 | AM31: Limited line-item detail; totals from PROFORMA BASIS FOR OFFER.xlsx actuals section
A32: P012 | B32: 344 | C32: R0124385 | D32: Unknown (Tax District 555) | E32: Adams County | F32: CO | G32: Office | H32: Multi-tenant | J32: 20170 | K32: 2024 | N32: 14.802 | AH32: 6.3208 | AI32: 2.1665 | AJ32: 9.1814 | AK32: 8.4812 | AM32: CapEx $14,000 non-recurring excluded from OPX; limited line-item detail
A33: P013 | B33: 353 | C33: R0169176 | D33: Unknown (new const., opened Oct 2023) | E33: Adams County | F33: CO | G33: Retail/Office | H33: Multi-tenant | I33: 2023 | K33: 2023 | L33: 270793 | M33: 258323 | N33: 524533 | O33: 16865 | P33: 26496 | X33: 50972 | Y33: 50972 | AA33: 7543 | AC33: 7543 | AD33: 4602 | AE33: 51467 | AF33: 56069 | AH33: 157946 | AI33: 125577 | AJ33: 283523 | AK33: 241009 | AM33: [NO SF] 2023 partial year (opened Oct 2023); RE Tax high for new construction; gas $3,877 + elec $47,590 in utilities
A34: P013 | B34: 353 | C34: R0169176 | D34: Unknown (new const., opened Oct 2023) | E34: Adams County | F34: CO | G34: Retail/Office | H34: Multi-tenant | I34: 2023 | K34: 2024 | L34: 260040 | M34: 337015 | N34: 597056 | O34: 12437 | P34: 26717 | X34: 36931 | Y34: 36931 | AA34: 27159 | AC34: 27159 | AD34: 5043 | AE34: 54230 | AF34: 59273 | AH34: 162518 | AI34: 156074 | AJ34: 318592 | AK34: 278464 | AM34: [NO SF] Tax consultant $11,515 added to RE Tax line; HOA/exterior maint $27,159 in landscape; recoveries $336,319 + other $696
A35: P014 | B35: 407 | C35: R0198530 | D35: Amazon DEN7 Distribution Center | E35: Aurora | F35: CO | G35: Industrial/Distribution | H35: Single-tenant NNN | J35: 555840 | K35: 2023 | L35: 5.6192 | N35: 5.6192 | O35: 0.1549 | P35: 0.1124 | AC35: 0.0402 | AF35: 0.002 | AH35: 0.3551 | AI35: 2.9096 | AJ35: 3.2647 | AM35: NNN ? expenses = LL CAM billed to Amazon tenant; RE Tax $1.617M dominates; base rent $3.12M; 2023 CAM reconciliation
A36: P014 | B36: 407 | C36: R0198530 | D36: Amazon DEN7 Distribution Center | E36: Aurora | F36: CO | G36: Industrial/Distribution | H36: Single-tenant NNN | J36: 555840 | K36: 2024 | L36: 5.7597 | N36: 5.7597 | O36: 0.1616 | P36: 0.1152 | AB36: 0.0038 | AC36: 0.0314 | AF36: 0.0036 | AH36: 0.2783 | AI36: 3.8893 | AJ36: 4.1677 | AM36: NNN; RE Tax $2.162M = $3.89/SF reflecting Adams County assessment increase (+34% YOY); 2024 CAM reconciliation
A37: P015 | B37: 407 | C37: R0180894 | D37: 1910 N Gun Club Rd | E37: Aurora | F37: CO | G37: Industrial | H37: Distribution Warehouse Multi-Tenant NNN | I37: 2019 | J37: 163386 | K37: 2023 | L37: 12.829 | N37: 12.829 | O37: 0.2491 | P37: 0.3371 | Y37: 0.0395 | AA37: 0.0888 | AB37: 0.3394 | AF37: 0.2688 | AG37: 0.9762 | AH37: 2.3251 | AI37: 5.6528 | AJ37: 7.9779 | AK37: 4.8512 | AM37: Actual accrual; security $159,500 in Other
A38: P015 | B38: 407 | C38: R0180894 | D38: 1910 N Gun Club Rd | E38: Aurora | F38: CO | G38: Industrial | H38: Distribution Warehouse Multi-Tenant NNN | I38: 2019 | J38: 163386 | K38: 2024 | L38: 13.1836 | N38: 13.1836 | O38: 0.2943 | P38: 0.4581 | Y38: 0.0322 | AA38: 0.0822 | AB38: 0.2856 | AF38: 0.3299 | AG38: 0.8113 | AH38: 2.4145 | AI38: 5.5843 | AJ38: 7.9988 | AK38: 5.1848 | AM38: Actual accrual; security $132,552 in Other
A39: P016 | B39: 584 | C39: R0212546/R0212547 | D39: 2780 N Tower Rd | E39: Aurora | F39: CO | G39: Industrial | H39: Mega Warehouse NNN | I39: 1983 | J39: 384953 | K39: 2024 | AM39: County proforma only; limited line-item detail available
A40: P017 | B40: 210 | C40: R0098098 | D40: 1445 E 68th Ave | E40: Denver | F40: CO | G40: Industrial | H40: Industrial Office Mix | I40: 1972 | J40: 63348 | K40: 2024 | AM40: County proforma 2024; YOC 1972/2006/2023 additions
A41: P018 | B41: 406 | C41: R0103783 | D41: 2031 E 58th Ave | E41: Denver | F41: CO | G41: Industrial | H41: Storage Warehouse / Mod Office NNN | I41: 2004 | J41: 18720 | K41: 2024 | L41: 13.2904 | N41: 16.0225 | O41: 0.2061 | AC41: 0.1296 | AH41: 0.3357 | AI41: 2.3964 | AJ41: 2.7321 | AK41: 13.2904 | AM41: NNN billed charges; EGI = base rent + NNN pass-throughs
A42: P018 | B42: 406 | C42: R0103783 | D42: 2031 E 58th Ave | E42: Denver | F42: CO | G42: Industrial | H42: Storage Warehouse / Mod Office NNN | I42: 2004 | J42: 18720 | K42: 2023 | L42: 13.0298 | N42: 15.7619 | O42: 0.2061 | AC42: 0.1296 | AH42: 0.3357 | AI42: 2.3964 | AJ42: 2.7321 | AK42: 13.0298 | AM42: NNN billed charges; EGI = base rent + NNN pass-throughs
A43: P019 | B43: 407 | C43: R0210402/R0210403 | D43: 17190 E 85th Ave | E43: Commerce City | F43: CO | G43: Industrial | H43: Industrial Warehouse NNN | I43: 2021 | J43: 329940 | K43: 2024 | AM43: Petitioner proforma 2024/25; limited line-item detail
A44: P020 | B44: 584 | C44: R0209679 | D44: 17501 E 84th Ave | E44: Commerce City | F44: CO | G44: Industrial | H44: Mega Warehouse / Distribution Center NNN (Lowe's) | I44: 2021 | J44: 999780 | K44: 2023 | L44: 12.3992 | N44: 12.3992 | O44: 0.1505 | P44: 0.1005 | Y44: 0.0533 | AA44: 0.0508 | AB44: 0.1178 | AG44: 0.0084 | AH44: 1.355 | AI44: 4.9234 | AJ44: 8.2796 | AK44: 4.1196 | AM44: Actual accrual; 2023 NOI inflated ~$2.8M by prior-yr RE tax adj; security in Other
A45: P020 | B45: 584 | C45: R0209679 | D45: 17501 E 84th Ave | E45: Commerce City | F45: CO | G45: Industrial | H45: Mega Warehouse / Distribution Center NNN (Lowe's) | I45: 2021 | J45: 999780 | K45: 2024 | L45: 10.003 | N45: 10.003 | O45: 0.172 | P45: 0.1016 | Y45: 0.1205 | AA45: 0.0378 | AB45: 0.1319 | AG45: 0.0308 | AH45: 0.7976 | AI45: 4.9977 | AJ45: 5.7953 | AK45: 4.2077 | AM45: Actual accrual; security $30,799 in Other
A46: P021 | B46: 210 | C46: R0091931 | D46: 6300 E. 58th Ave | E46: Commerce City | F46: CO | G46: Industrial | H46: Multi-Tenant Industrial/Flex | I46: 1999 | J46: 90000 | K46: 2023 | L46: 10.5459 | N46: 13.7594 | O46: 0.176 | P46: 0.516 | Q46: 0.0441 | S46: 0.3032 | T46: 0.0731 | X46: 0.2579 | Y46: 0.6783 | Z46: 0.0103 | AA46: 0.0531 | AB46: 0.1252 | AC46: 0.1886 | AD46: 0.1574 | AE46: 0.0621 | AF46: 0.2196 | AH46: 1.8054 | AI46: 3.1511 | AJ46: 4.9565 | AK46: 8.8029 | AM46: Actual accrual; parking sweep in Trash; admin fees in Mgmt
A47: P021 | B47: 210 | C47: R0091931 | D47: 6300 E. 58th Ave | E47: Commerce City | F47: CO | G47: Industrial | H47: Multi-Tenant Industrial/Flex | I47: 1999 | J47: 90000 | K47: 2024 | L47: 10.1323 | N47: 14.5242 | O47: 0.1757 | P47: 0.725 | Q47: 0.0069 | S47: 0.3996 | T47: 0.087 | X47: 0.2445 | Y47: 0.738 | Z47: 0.0131 | AA47: 0.0496 | AB47: 0.1661 | AC47: 0.2288 | AD47: 0.1748 | AE47: 0.0637 | AF47: 0.2385 | AH47: 1.7609 | AI47: 3.2332 | AJ47: 4.9941 | AK47: 9.3636 | AM47: Actual accrual; snow $14,953 also listed under ext R&M; security/admin in ext maint
A48: P022 | B48: 210 | C48: R0111559 | D48: 3590 N. Himalaya Rd (Bldg 6) | E48: Aurora | F48: CO | G48: Industrial | H48: Multi-Tenant Industrial/Flex NNN | K48: 2024 | L48: 548918 | N48: 766859 | O48: 23025 | AD48: 7986 | AE48: 33669 | AF48: 41655 | AI48: 129107 | AJ48: 250157 | AK48: 374789 | AM48: [NO SF] 2024 only – 2023 was transitional vacancy year; SF not confirmed; approx figures
A49: P023 | B49: 407 | C49: R0191098 | D49: 19754 E. 35th Dr (Bldg 4) | E49: Aurora | F49: CO | G49: Industrial | H49: Single-Tenant Industrial NNN | J49: 155033 | K49: 2023 | L49: 6.2562 | N49: 6.246 | O49: 0.1319 | P49: 0.1932 | AA49: 0.0257 | AD49: 0.2449 | AE49: 0.0885 | AF49: 0.3334 | AH49: 1.9053 | AI49: 0.5968 | AJ49: 2.5021 | AK49: 3.7439 | AM49: NNN; tenant pays most R&M directly; Quality Custom Distribution lease thru 12/31/2029
A50: P023 | B50: 407 | C50: R0191098 | D50: 19754 E. 35th Dr (Bldg 4) | E50: Aurora | F50: CO | G50: Industrial | H50: Single-Tenant Industrial NNN | J50: 155033 | K50: 2024 | L50: 6.5223 | N50: 6.5223 | O50: 0.183 | P50: 0.1894 | AD50: 0.2365 | AE50: 0.1764 | AF50: 0.4129 | AH50: 1.7082 | AI50: 0.7799 | AJ50: 2.4881 | AK50: 4.0342 | AM50: NNN; tenant pays most R&M directly
A51: P024 | B51: 407 | C51: R0111560 | D51: 20320 E. 36th Dr (Bldg 7) | E51: Aurora | F51: CO | G51: Industrial | H51: Single-Tenant Industrial NNN | J51: 200000 | K51: 2023 | L51: 6.9558 | N51: 6.7858 | O51: 0.02 | AE51: 0.0121 | AF51: 0.0121 | AH51: 1.179 | AI51: 0.0174 | AJ51: 1.1964 | AK51: 5.5895 | AM51: FedEx NNN thru 4/30/2024; tenant pays nearly all expenses; 2024 excluded (lease expiry vacancy)
A52: P025 | B52: 210 | C52: R0191099 | D52: 3559 N. Himalaya Rd (Bldg 5) | E52: Aurora | F52: CO | G52: Industrial | H52: Multi-Tenant Industrial NNN | J52: 159047 | K52: 2023 | N52: 13.4944 | P52: 0.0367 | AB52: 0.0177 | AJ52: 6.3824 | AK52: 7.112 | AM52: Multi-tenant NNN; limited expense detail available; approx figures
A53: P025 | B53: 210 | C53: R0191099 | D53: 3559 N. Himalaya Rd (Bldg 5) | E53: Aurora | F53: CO | G53: Industrial | H53: Multi-Tenant Industrial NNN | J53: 159047 | K53: 2024 | N53: 13.507 | AB53: 0.0177 | AJ53: 7.3989 | AK53: 6.1082 | AM53: Multi-tenant NNN; limited expense detail available; approx figures
A54: P026 | B54: 406 | C54: R0092667 | D54: 4901 Locust St | E54: Commerce City | F54: CO | G54: Industrial | H54: Industrial Warehouse | J54: 29512 | K54: 2024 | N54: 14.2131 | O54: 0.15 | P54: 0.3553 | X54: 0.55 | Y54: 0.55 | AF54: 0.25 | AG54: 0.5 | AH54: 2.0053 | AI54: 3.315 | AJ54: 5.3203 | AK54: 8.8928 | AL54: 0.2 | AM54: Newmark stabilized proforma 6/30/2024; cap rate 7.00%; not actual historical
A55: P022 | B55: 210 | C55: R0111559 | D55: 3590 N. Himalaya Rd (Bldg 6) | E55: Aurora | F55: CO | G55: Industrial | H55: Multi-Tenant Industrial/Flex NNN | I55: 1998 | J55: 123603 | K55: 2021 | O55: 0.0839 | P55: 0.351 | AC55: 0.717 | AF55: 0.2998 | AH55: 1.4518 | AI55: 2.3392 | AJ55: 3.791 | AM55: NNN landlord expenses only; from AXG Whse Expenses PSF.xlsx
A56: P022 | B56: 210 | C56: R0111559 | D56: 3590 N. Himalaya Rd (Bldg 6) | E56: Aurora | F56: CO | G56: Industrial | H56: Multi-Tenant Industrial/Flex NNN | I56: 1998 | J56: 123603 | K56: 2022 | O56: 0.0893 | P56: 0.3221 | AC56: 0.7439 | AF56: 0.3112 | AH56: 1.4664 | AI56: 2.5796 | AJ56: 4.046 | AM56: NNN landlord expenses only; from AXG Whse Expenses PSF.xlsx
A57: P024 | B57: 407 | C57: R0111560 | D57: 20320 E. 36th Dr (Bldg 7) | E57: Aurora | F57: CO | G57: Industrial | H57: Single-Tenant Industrial NNN | I57: 1998 | J57: 199962 | K57: 2019 | O57: 0.0423 | P57: 0.131 | AC57: 1.3087 | AH57: 1.482 | AI57: 2.4741 | AJ57: 3.9561 | AM57: NNN landlord expenses only; from AXG Whse Expenses PSF.xlsx
A58: P024 | B58: 407 | C58: R0111560 | D58: 20320 E. 36th Dr (Bldg 7) | E58: Aurora | F58: CO | G58: Industrial | H58: Single-Tenant Industrial NNN | I58: 1998 | J58: 199962 | K58: 2020 | O58: 0.0484 | P58: 0.1332 | AC58: 0.7242 | AH58: 0.9058 | AI58: 2.0784 | AJ58: 2.9841 | AM58: NNN landlord expenses only; from AXG Whse Expenses PSF.xlsx
A59: P025 | B59: 210 | C59: R0191099 | D59: 3559 N. Himalaya Rd (Bldg 5) | E59: Aurora | F59: CO | G59: Industrial | H59: Multi-Tenant Industrial NNN | I59: 2017 | J59: 159047 | K59: 2021 | O59: 0.0956 | P59: 0.3379 | AC59: 0.3767 | AF59: 0.2913 | AH59: 1.1015 | AI59: 3.4893 | AJ59: 4.5908 | AM59: NNN landlord expenses only; from AXG Whse Expenses PSF.xlsx
A60: P025 | B60: 210 | C60: R0191099 | D60: 3559 N. Himalaya Rd (Bldg 5) | E60: Aurora | F60: CO | G60: Industrial | H60: Multi-Tenant Industrial NNN | I60: 2017 | J60: 159047 | K60: 2022 | O60: 0.1017 | P60: 0.3102 | AC60: 0.3353 | AF60: 0.3232 | AH60: 1.0704 | AI60: 2.9479 | AJ60: 4.0183 | AM60: NNN landlord expenses only; from AXG Whse Expenses PSF.xlsx
A61: P027 | B61: 407 | C61: R0132030 | D61: Majestic Commercenter (R0132030) | E61: Commerce City | F61: CO | G61: Industrial | H61: Warehouse NNN | I61: 2001 | J61: 200094 | K61: 2021 | O61: 0.0715 | P61: 0.2651 | AC61: 0.49 | AF61: 0.3539 | AH61: 1.1805 | AI61: 2.8519 | AJ61: 4.0324 | AM61: NNN landlord expenses only; from AXG Whse Expenses PSF.xlsx (R0132030)
A62: P027 | B62: 407 | C62: R0132030 | D62: Majestic Commercenter (R0132030) | E62: Commerce City | F62: CO | G62: Industrial | H62: Warehouse NNN | I62: 2001 | J62: 200094 | K62: 2022 | O62: 0.0761 | P62: 0.2474 | AC62: 0.49 | AF62: 0.3539 | AH62: 1.1674 | AI62: 2.2575 | AJ62: 3.4249 | AM62: NNN landlord expenses only; from AXG Whse Expenses PSF.xlsx (R0132030)
A63: P028 | B63: 407 | C63: R0084040 | D63: Majestic Commercenter (R0084040) | E63: Commerce City | F63: CO | G63: Industrial | H63: Warehouse NNN | I63: 1997 | J63: 177736 | K63: 2021 | O63: 0.0736 | P63: 0.3114 | AC63: 0.552 | AF63: 0.2892 | AH63: 1.2262 | AI63: 2.7188 | AJ63: 3.945 | AM63: NNN landlord expenses only; from AXG Whse Expenses PSF.xlsx (R0084040)
A64: P028 | B64: 407 | C64: R0084040 | D64: Majestic Commercenter (R0084040) | E64: Commerce City | F64: CO | G64: Industrial | H64: Warehouse NNN | I64: 1997 | J64: 177736 | K64: 2022 | O64: 0.0783 | P64: 0.3114 | AC64: 0.6591 | AF64: 0.3559 | AH64: 1.4047 | AI64: 2.8511 | AJ64: 4.2558 | AM64: NNN landlord expenses only; from AXG Whse Expenses PSF.xlsx (R0084040)
A65: P029 | B65: 407 | C65: R0084041 | D65: Majestic Commercenter (R0084041) | E65: Commerce City | F65: CO | G65: Industrial | H65: Warehouse NNN | I65: 1997 | J65: 200371 | K65: 2021 | O65: 0.0686 | P65: 0.1605 | AC65: 0.5869 | AH65: 0.816 | AI65: 2.4919 | AJ65: 3.3079 | AM65: NNN landlord expenses only; from AXG Whse Expenses PSF.xlsx (R0084041)
A66: P029 | B66: 407 | C66: R0084041 | D66: Majestic Commercenter (R0084041) | E66: Commerce City | F66: CO | G66: Industrial | H66: Warehouse NNN | I66: 1997 | J66: 200371 | K66: 2022 | O66: 0.073 | P66: 0.1496 | AC66: 0.5187 | AH66: 0.7413 | AI66: 2.5893 | AJ66: 3.3306 | AM66: NNN landlord expenses only; from AXG Whse Expenses PSF.xlsx (R0084041)
A67: P030 | B67: 584 | C67: R0217015 | D67: Majestic Commercenter (R0217015) | E67: Commerce City | F67: CO | G67: Industrial | H67: Warehouse NNN | I67: 2021 | J67: 548510 | K67: 2022 | O67: 0.1167 | P67: 0.1062 | AC67: 0.1767 | AF67: 0.038 | AH67: 0.4376 | AI67: 2.271 | AJ67: 2.7087 | AM67: NNN landlord expenses only; from AXG Whse Expenses PSF.xlsx (R0217015)
A68: P031 | B68: 407 | C68: R0111562 | D68: Majestic Commercenter (R0111562) | E68: Commerce City | F68: CO | G68: Industrial | H68: Warehouse NNN | I68: 2000 | J68: 149175 | K68: 2019 | O68: 0.0437 | P68: 0.1522 | AC68: 0.6822 | AH68: 0.8781 | AI68: 1.8902 | AJ68: 2.7683 | AM68: NNN landlord expenses only; from AXG Whse Expenses PSF.xlsx (R0111562)
A69: P031 | B69: 407 | C69: R0111562 | D69: Majestic Commercenter (R0111562) | E69: Commerce City | F69: CO | G69: Industrial | H69: Warehouse NNN | I69: 2000 | J69: 149175 | K69: 2020 | O69: 0.0499 | P69: 0.0264 | AC69: 0.1604 | AF69: 1.107 | AH69: 1.3438 | AI69: 1.897 | AJ69: 3.2408 | AM69: NNN landlord expenses only; from AXG Whse Expenses PSF.xlsx (R0111562)
A70: P032 | B70: 407 | C70: R0118875 | D70: Majestic Commercenter (R0118875) | E70: Commerce City | F70: CO | G70: Industrial | H70: Warehouse NNN | I70: 1999 | J70: 279640 | K70: 2021 | O70: 0.0881 | P70: 0.2248 | AC70: 0.3589 | AH70: 0.6718 | AI70: 2.2918 | AJ70: 2.9636 | AM70: NNN landlord expenses only; from AXG Whse Expenses PSF.xlsx (R0118875)
A71: P032 | B71: 407 | C71: R0118875 | D71: Majestic Commercenter (R0118875) | E71: Commerce City | F71: CO | G71: Industrial | H71: Warehouse NNN | I71: 1999 | J71: 279640 | K71: 2022 | O71: 0.0937 | P71: 0.2268 | AC71: 0.0651 | AH71: 0.3856 | AI71: 2.3497 | AJ71: 2.7353 | AM71: NNN landlord expenses only; from AXG Whse Expenses PSF.xlsx (R0118875)
A72: P033 | B72: 407 | C72: R0132031 | D72: Majestic Commercenter (R0132031) | E72: Commerce City | F72: CO | G72: Industrial | H72: Warehouse NNN | I72: 2002 | J72: 280098 | K72: 2021 | O72: 0.0713 | P72: 0.231 | AC72: 0.2633 | AF72: 0.3067 | AH72: 0.8723 | AI72: 2.2816 | AJ72: 3.1539 | AM72: NNN landlord expenses only; from AXG Whse Expenses PSF.xlsx (R0132031)
A73: P033 | B73: 407 | C73: R0132031 | D73: Majestic Commercenter (R0132031) | E73: Commerce City | F73: CO | G73: Industrial | H73: Warehouse NNN | I73: 2002 | J73: 280098 | K73: 2022 | O73: 0.0759 | P73: 0.2109 | AC73: 0.4318 | AF73: 0.3384 | AH73: 1.057 | AI73: 2.3888 | AJ73: 3.4457 | AM73: NNN landlord expenses only; from AXG Whse Expenses PSF.xlsx (R0132031)
A74: P034 | B74: 407 | C74: R0172865 | D74: Majestic Commercenter (R0172865) | E74: Commerce City | F74: CO | G74: Industrial | H74: Warehouse NNN | I74: 2008 | J74: 215461 | K74: 2021 | O74: 0.0809 | P74: 0.3054 | AC74: 0.4686 | AF74: 0.3395 | AH74: 1.1944 | AI74: 2.8499 | AJ74: 4.0443 | AM74: NNN landlord expenses only; from AXG Whse Expenses PSF.xlsx (R0172865)
A75: P034 | B75: 407 | C75: R0172865 | D75: Majestic Commercenter (R0172865) | E75: Commerce City | F75: CO | G75: Industrial | H75: Warehouse NNN | I75: 2008 | J75: 215461 | K75: 2022 | O75: 0.0852 | P75: 0.2898 | AC75: 0.3409 | AF75: 0.348 | AH75: 1.0639 | AI75: 2.7419 | AJ75: 3.8058 | AM75: NNN landlord expenses only; from AXG Whse Expenses PSF.xlsx (R0172865)
A76: P035 | B76: 407 | C76: R0172867 | D76: Majestic Commercenter (R0172867) | E76: Commerce City | F76: CO | G76: Industrial | H76: Warehouse NNN | I76: 2007 | J76: 215560 | K76: 2021 | O76: 0.0975 | P76: 0.2429 | AC76: 0.2979 | AF76: 0.3114 | AH76: 0.9497 | AI76: 2.4921 | AJ76: 3.4419 | AM76: NNN landlord expenses only; from AXG Whse Expenses PSF.xlsx (R0172867)
A77: P035 | B77: 407 | C77: R0172867 | D77: Majestic Commercenter (R0172867) | E77: Commerce City | F77: CO | G77: Industrial | H77: Warehouse NNN | I77: 2007 | J77: 215560 | K77: 2022 | O77: 0.1037 | P77: 0.2556 | AC77: 0.3121 | AF77: 0.3342 | AH77: 1.0056 | AI77: 2.5896 | AJ77: 3.5952 | AM77: NNN landlord expenses only; from AXG Whse Expenses PSF.xlsx (R0172867)
A78: P036 | B78: 407 | C78: R0172868 | D78: Majestic Commercenter (R0172868) | E78: Commerce City | F78: CO | G78: Industrial | H78: Warehouse NNN | I78: 2007 | J78: 202091 | K78: 2021 | O78: 0.0863 | P78: 0.1541 | AC78: 0.4114 | AH78: 0.6518 | AI78: 2.4692 | AJ78: 3.121 | AM78: NNN landlord expenses only; from AXG Whse Expenses PSF.xlsx (R0172868)
A79: P036 | B79: 407 | C79: R0172868 | D79: Majestic Commercenter (R0172868) | E79: Commerce City | F79: CO | G79: Industrial | H79: Warehouse NNN | I79: 2007 | J79: 202091 | K79: 2022 | O79: 0.0918 | P79: 0.1363 | AC79: 0.3275 | AH79: 0.5556 | AI79: 2.5219 | AJ79: 3.0775 | AM79: NNN landlord expenses only; from AXG Whse Expenses PSF.xlsx (R0172868)
A80: P037 | B80: 407 | C80: R0145680 | D80: Majestic Commercenter (R0145680) | E80: Commerce City | F80: CO | G80: Industrial | H80: Warehouse NNN | I80: 2001 | J80: 150027 | K80: 2021 | O80: 0.0779 | P80: 0.2768 | AC80: 0.3322 | AH80: 0.6868 | AI80: 2.8525 | AJ80: 3.5393 | AM80: NNN landlord expenses only; from AXG Whse Expenses PSF.xlsx (R0145680)
A81: P037 | B81: 407 | C81: R0145680 | D81: Majestic Commercenter (R0145680) | E81: Commerce City | F81: CO | G81: Industrial | H81: Warehouse NNN | I81: 2001 | J81: 150027 | K81: 2022 | O81: 0.0828 | P81: 0.2294 | AC81: 0.3617 | AH81: 0.6739 | AI81: 2.7388 | AJ81: 3.4127 | AM81: NNN landlord expenses only; from AXG Whse Expenses PSF.xlsx (R0145680)
A82: P038 | B82: 584 | C82: R0181787 | D82: Majestic Commercenter (R0181787) | E82: Commerce City | F82: CO | G82: Industrial | H82: Warehouse NNN | I82: 2013 | J82: 500358 | K82: 2021 | O82: 0.0743 | P82: 0.2354 | AC82: 0.3128 | AF82: 0.2341 | AH82: 0.8566 | AI82: 2.2838 | AJ82: 3.1403 | AM82: NNN landlord expenses only; from AXG Whse Expenses PSF.xlsx (R0181787)
A83: P038 | B83: 584 | C83: R0181787 | D83: Majestic Commercenter (R0181787) | E83: Commerce City | F83: CO | G83: Industrial | H83: Warehouse NNN | I83: 2013 | J83: 500358 | K83: 2022 | O83: 0.079 | P83: 0.2014 | AC83: 0.2328 | AF83: 0.2263 | AH83: 0.7396 | AI83: 2.5398 | AJ83: 3.2794 | AM83: NNN landlord expenses only; from AXG Whse Expenses PSF.xlsx (R0181787)
A84: P039 | B84: 584 | C84: R0191101 | D84: Majestic Commercenter (R0191101) | E84: Commerce City | F84: CO | G84: Industrial | H84: Warehouse NNN | I84: 2017 | J84: 522120 | K84: 2021 | O84: 0.0822 | P84: 0.2582 | AC84: 0.2825 | AF84: 0.1793 | AH84: 0.8022 | AI84: 2.1785 | AJ84: 2.9807 | AM84: NNN landlord expenses only; from AXG Whse Expenses PSF.xlsx (R0191101)
A85: P039 | B85: 584 | C85: R0191101 | D85: Majestic Commercenter (R0191101) | E85: Commerce City | F85: CO | G85: Industrial | H85: Warehouse NNN | I85: 2017 | J85: 522120 | K85: 2022 | O85: 0.0874 | P85: 0.2219 | AC85: 0.1719 | AF85: 0.1738 | AH85: 0.655 | AI85: 2.2402 | AJ85: 2.8952 | AM85: NNN landlord expenses only; from AXG Whse Expenses PSF.xlsx (R0191101)
A86: P040 | B86: 407 | C86: R0202874 | D86: 900 E 128th Ave | E86: Henderson | F86: CO | G86: Industrial | H86: Last-Mile Distribution NNN | K86: 2021 | L86: 2633716 | N86: 3256403 | O86: 56624 | Q86: 300 | X86: 29535 | Y86: 30138 | AA86: 54136 | AB86: 127274 | AF86: 18748 | AH86: 731951 | AK86: 2524452 | AM86: [NO SF] Amazon AMZL Site 51812; SF not extracted; RE Tax not broken out in 2021
A87: P040 | B87: 407 | C87: R0202874 | D87: 900 E 128th Ave | E87: Henderson | F87: CO | G87: Industrial | H87: Last-Mile Distribution NNN | K87: 2022 | P87: 69999 | AI87: 1080500 | AJ87: 1527913 | AK87: 2475461 | AM87: [NO SF] Amazon AMZL Site 51812; 2022 dominated by RE Tax $1.08M; asset mgmt fee $70k
A88: P041 | B88: 386 | C88: R0189384 | D88: 1101 Colorado Blvd | E88: Thornton | F88: CO | G88: Self-Storage | H88: Climate-Controlled | J88: 65766 | K88: 2021 | N88: 13.3807 | AJ88: 6.3574 | AK88: 7.0233 | AM88: Actual SS P&L; mgmt=off-site+on-site combined; admin+adv in Other
A89: P041 | B89: 386 | C89: R0189384 | D89: 1101 Colorado Blvd | E89: Thornton | F89: CO | G89: Self-Storage | H89: Climate-Controlled | J89: 65766 | K89: 2022 | N89: 14.0623 | AJ89: 6.9302 | AK89: 7.1322 | AM89: Actual SS P&L; mgmt=off-site+on-site combined; admin+adv in Other
A90: P041 | B90: 386 | C90: R0189384 | D90: 1101 Colorado Blvd | E90: Thornton | F90: CO | G90: Self-Storage | H90: Climate-Controlled | J90: 65766 | K90: 2023 | N90: 14.16 | O90: 0.6306 | P90: 1.5829 | Y90: 0.2367 | AF90: 0.5644 | AH90: 4.479 | AI90: 2.7358 | AJ90: 7.2147 | AK90: 7.1427 | AM90: Actual SS P&L; mgmt=off-site+on-site combined; admin+adv in Other
A91: P042 | B91: 386 | C91: R0126235 | D91: 15024 Laroy Drive | E91: Northglenn | F91: CO | G91: Self-Storage | H91: Climate-Controlled | J91: 79950 | K91: 2021 | N91: 11.9617 | AJ91: 6.0239 | AK91: 6.4381 | AM91: Actual SS P&L; mgmt=off-site+on-site combined
A92: P042 | B92: 386 | C92: R0126235 | D92: 15024 Laroy Drive | E92: Northglenn | F92: CO | G92: Self-Storage | H92: Climate-Controlled | J92: 79950 | K92: 2022 | N92: 12.7321 | AJ92: 5.4064 | AK92: 7.3257 | AM92: Actual SS P&L; mgmt=off-site+on-site combined
A93: P042 | B93: 386 | C93: R0126235 | D93: 15024 Laroy Drive | E93: Northglenn | F93: CO | G93: Self-Storage | H93: Climate-Controlled | J93: 79950 | K93: 2023 | N93: 11.94 | O93: 0.5105 | P93: 1.3574 | Y93: 0.301 | AF93: 0.2587 | AH93: 3.4355 | AI93: 3.061 | AJ93: 6.4964 | AK93: 5.4436 | AM93: Actual SS P&L; mgmt=off-site+on-site combined
A94: P043 | B94: 386 | C94: R0126234 | D94: 715 W 112th Ave | E94: Northglenn | F94: CO | G94: Self-Storage | H94: Drive-Up/Drop-Off | J94: 83756 | K94: 2021 | N94: 9.7278 | AJ94: 5.2127 | AK94: 4.5151 | AM94: Actual SS P&L; mgmt=off-site+on-site combined
A95: P043 | B95: 386 | C95: R0126234 | D95: 715 W 112th Ave | E95: Northglenn | F95: CO | G95: Self-Storage | H95: Drive-Up/Drop-Off | J95: 83756 | K95: 2022 | N95: 11.7102 | AJ95: 5.4426 | AK95: 6.2675 | AM95: Actual SS P&L; mgmt=off-site+on-site combined
A96: P043 | B96: 386 | C96: R0126234 | D96: 715 W 112th Ave | E96: Northglenn | F96: CO | G96: Self-Storage | H96: Drive-Up/Drop-Off | J96: 83756 | K96: 2023 | N96: 12.0821 | O96: 0.5624 | P96: 1.3342 | Y96: 0.1222 | AF96: 0.1904 | AH96: 3.0787 | AI96: 2.42 | AJ96: 5.4986 | AK96: 6.5859 | AM96: Actual SS P&L; mgmt=off-site+on-site combined
A97: P044 | B97: 386 | C97: R0027089/R0178319 | D97: 2290 E 120th Ave | E97: Thornton | F97: CO | G97: Self-Storage | H97: Drive-Up/Drop-Off | J97: 71909 | K97: 2021 | N97: 11.6457 | AJ97: 6.1981 | AK97: 5.4476 | AM97: Actual SS P&L; combined parcels R0027089+R0178319; mgmt=off-site+on-site
A98: P044 | B98: 386 | C98: R0027089/R0178319 | D98: 2290 E 120th Ave | E98: Thornton | F98: CO | G98: Self-Storage | H98: Drive-Up/Drop-Off | J98: 71909 | K98: 2022 | N98: 13.1494 | AJ98: 6.1981 | AK98: 6.4846 | AM98: Actual SS P&L; combined parcels R0027089+R0178319; mgmt=off-site+on-site
A99: P044 | B99: 386 | C99: R0027089/R0178319 | D99: 2290 E 120th Ave | E99: Thornton | F99: CO | G99: Self-Storage | H99: Drive-Up/Drop-Off | J99: 71909 | K99: 2023 | N99: 13.6392 | O99: 0.6036 | P99: 1.9706 | Y99: 0.248 | AF99: 0.298 | AH99: 4.1574 | AI99: 2.5917 | AJ99: 6.7491 | AK99: 6.8462 | AM99: Actual SS P&L; combined parcels R0027089+R0178319; mgmt=off-site+on-site
A100: P045 | B100: 386 | C100: R0043569 | D100: 40131 Quivas St | E100: Thornton | F100: CO | G100: Self-Storage | H100: Drive-Up/Drop-Off | J100: 41900 | K100: 2024 | N100: 17.1375 | O100: 0.4543 | P100: 2.2428 | Y100: 0.2809 | AF100: 0.1293 | AH100: 4.9831 | AI100: 4.213 | AJ100: 9.196 | AK100: 7.9414 | AM100: Actual FY2024 P&L; mgmt=off-site $42,964+on-site $51,011; RE Tax est from matrix
...

Sheet Adams County Resources
A1: Municipality | B1: Category | C1: Resource Name | D1: URL | E1: Notes | F1: Unnamed: 5 | G1: Unnamed: 6
A2: Adams County (Unincorporated) | B2: Property Assessment | C2: Assessor Property Lookup | D2: https://adcogov.org/property-look | E2: Primary parcel/property search tool for all of Adams County
A3: Adams County (Unincorporated) | B3: Property Assessment | C3: Assessor GIS QuickSearch | D3: https://gisapp.adcogov.org/quicksearch/ | E3: Address or parcel-based search with map
A4: Adams County (Unincorporated) | B4: Property Assessment | C4: Assessor Main Page | D4: https://adcogov.org/assessor | E4: Assessor office info and resources
A5: Adams County (Unincorporated) | B5: Property Assessment | C5: NOV / Online Appeals Portal | D5: https://assessor.adcogov.org/ | E5: Notice of Valuation and assessment appeals
A6: Adams County (Unincorporated) | B6: Property Assessment | C6: Public Data Download | D6: https://assessornovs.adcogov.org/adamscountynovs | E6: Weekly-updated bulk assessor data download
A7: Adams County (Unincorporated) | B7: Property Tax / Treasurer | C7: Treasurer Division | D7: https://adamscountyco.gov/our-county/elected-officials/treasurer-public-trustee/treasurer-division/ | E7: Main treasurer page
A8: Adams County (Unincorporated) | B8: Property Tax / Treasurer | C8: Online Tax Payment | D8: https://adcotax.com/treasurer/web/login.jsp | E8: Pay property taxes online
A9: Adams County (Unincorporated) | B9: Property Tax / Treasurer | C9: Property Tax Inquiry | D9: https://adamsil.devnetwedge.com/ | E9: Look up tax balances and payment history
A10: Adams County (Unincorporated) | B10: Property Tax / Treasurer | C10: Taxing Authorities / Mill Levy | D10: https://adamscountyco.gov/our-county/elected-officials/treasurer-public-trustee/treasurer-division/property-tax-information/taxing-authorities/ | E10: Mill levy lookup by taxing district
A11: Adams County (Unincorporated) | B11: Property Tax / Treasurer | C11: DOLA Division of Property Taxation | D11: https://dpt.colorado.gov/locality/adams-county-treasurer | E11: Colorado state-level property tax data for Adams County
A12: Adams County (Unincorporated) | B12: Property Tax / Treasurer | C12: DOLA Mill Levy Public Info (HB24-1302) | D12: https://dlg.colorado.gov/hb24-1302-mill-levy-public-information | E12: Statewide mill levy transparency portal
A13: Adams County (Unincorporated) | B13: Deed / Title Records | C13: Clerk & Recorder Recording Page | D13: https://adcogov.org/recording | E13: Official recording office
... A17: Adams County (Unincorporated) | B17: GIS / Mapping | C17: Advanced GIS Map Viewer | D17: https://gisapp.adcogov.org/Html5Viewer/index.html?viewer=AdvancedExt.Advanced_HTML | E17: Full-featured interactive map
A18: Adams County (Unincorporated) | B18: GIS / Mapping | C18: Open Data Hub (ArcGIS) | D18: https://data-adcogov.opendata.arcgis.com/ | E18: Downloadable datasets including zoning | F18: parcels | G18: flood zones
A19: Adams County (Unincorporated) | B19: GIS / Mapping | C19: GIS Interactive Maps Page | D19: https://adamscountyco.gov/service/gis-interactive-maps/ | E19: Links to all county GIS tools
A20: Adams County (Unincorporated) | B20: Permits | C20: E-Permit Center (Accela) | D20: https://aca-prod.accela.com/ADAMSCO/Default.aspx | E20: Online permit applications and search
A21: Adams County (Unincorporated) | B21: Permits | C21: E-Permit Center Landing | D21: https://epermits.adcogov.org/ | E21: Permit portal landing page
A22: Adams County (Unincorporated) | B22: Permits | C22: Building Safety | D22: https://adcogov.org/building-safety | E22: Building department info
A23: Adams County (Unincorporated) | B23: Code Enforcement | C23: Eye on Adams (Permits + Violations) | D23: https://adamscounty.buildingeye.com/ | E23: Track permits and code enforcement cases
A24: Adams County (Unincorporated) | B24: Code Enforcement | C24: Code Violations Enforcement Search | D24: https://adamscounty.buildingeye.com/enforcement | E24: Violation lookup only
