Workbook

Sheet Schedules & Values
B1: CityView Industrial Park - Schedule Numbers, Square Footage & Petitioner's Requested 2026 Values
B2: Source: Petitioner's Exhibit A (SF) and Exhibit H (requested value allocation)
A4: OCCC | B4: Address | C4: Schedule # | D4: Description | E4: YOC | F4: Land SF | G4: Imp SF | H4: Land Value | I4: $/SF | J4: IMP Value | K4: $/SF | L4: Total Value | M4: $/SF | N4: Requested Land Value | O4: Requested Imp Value | P4: Requested Total Value | Q4: $/SF | R4: Tax Liability | S4: Notes
B5: 5800 Franklin St | C5: R0103784 | D5: Vacant land | F5: 123710 | G5: 0 | H5: 989680 | I5: =H5/F5 | J5: 0 | L5: =H5+J5 | N5: 989680 | O5: 0 | P5: 989680 | R5: 27733.38
B6: 1761 E 58th Ave | C6: R0103785 | D6: Distribution Warehouse | E6: 1986 | F6: 87120 | G6: 32500 | H6: 1393920 | I6: =H6/F6 | J6: 3496391 | K6: =J6/G6 | L6: =J6+H6 | M6: =L6/G6 | N6: 871200 | O6: 1930597 | P6: 2801797 | Q6: =P6/G6 | R6: 137040.32
B7: 1805 E 58th Ave | C7: R0103786 | D7: Distribution Warehouse | E7: 1986 | F7: 87120 | G7: 41060 | H7: 1393920 | I7: =H7/F7 | J7: 4269562 | K7: =J7/G7 | L7: =H7+J7 | M7: =L7/G7 | N7: 871200 | O7: 2668547 | P7: 3539747 | Q7: =P7/G7 | R7: 158706.38
B8: 1771 E 58th Ave | C8: R0103787 | D8: Distribution Warehouse | E8: 1985 | F8: 89734 | G8: 40000 | H8: 1435728 | I8: =H8/F8 | J8: 4583116 | K8: =J8/G8 | L8: =H8+J8 | M8: =L8/G8 | N8: 897336 | O8: 2551029 | P8: 3448365 | Q8: =P8/G8 | R8: 168664.74
B9: 5800 Franklin St | C9: R0103788 | D9: Distribution Warehouse / Office | E9: 1975 | F9: 86806 | G9: 43010 | H9: 1388912 | I9: =H9/F9 | J9: 4543537 | K9: =J9/G9 | L9: =H9+J9 | M9: =L9/G9 | N9: 868064 | O9: 2839791 | P9: 3707855 | Q9: =P9/G9 | R9: 166243.54
B10: 1707 E 58th Ave | C10: R0103789 | D10: Distribution Warehouse | E10: 1973 | F10: 111113 | G10: 30319 | H10: 1777792 | I10: =H10/F10 | J10: 2886210 | K10: =J10/G10 | L10: =H10+J10 | M10: =L10/G10 | N10: 1111128 | O10: 1502646 | P10: 2613775 | Q10: =P10/G10 | R10: 65598.2 | S10: 49.81% exempt (Certified Mapping & Technical Testing Inc., CO State entity); exemption not disputed
B11: 1791 E 58th Ave | C11: R0103790 | D11: Distribution Warehouse | E11: 1984 | F11: 102802 | G11: 33625 | H11: 1233612 | I11: =H11/F11 | J11: 3825979 | K11: =J11/G11 | L11: =H11+J11 | M11: =L11/G11 | N11: 1028016 | O11: 1870766 | P11: 2898782 | Q11: =P11/G11 | R11: 141783.74 | S11: 50.13% exempt per Exhibit H caption
B12: TOTALS/AVG | F12: 688405 | G12: 220514 | H12: =SUM(H5:H11) | I12: =AVERAGE(I5:I11) | J12: =SUM(J5:J11) | K12: =AVERAGE(K6:K11) | L12: =SUM(L5:L11) | M12: =L12/G12 | N12: 6636624 | O12: 13363376 | P12: 20000000 | R12: =SUM(R5:R11)
K21: =2773026/26250
K22: =1770511/16760

Sheet Lease Comps
A5: IND | B5: R0070622 - 460-550 E 76th Ave
B6: Unit | C6: Tenant | D6: Term | E6: Start | F6: End | G6: SF | H6: $/SF
B7: 425-302 CU | C7: Radica | D7: 63 | E7: 45231 | F7: 47118 | G7: 19717 | H7: =182382/G7
B8: 425-504-CU | C8: Oak Tree Enterprise | D8: 34 | E8: 45078 | F8: 46112 | G8: 6592 | H8: =64502/G8 | Q8: 859754
B9: 425-402 | C9: Bella Restoration Services | D9: 50 | E9: 44743 | F9: 46265 | G9: 11352 | H9: =96378/G9
A12: IND | B12: R0084237 - 14501 E 35TH PL
B13: 4770 A | C13: Denver Botanic Gardens | D13: 84 | E13: 45231 | F13: 47787 | G13: 6000 | H13: =69540/G13 | L13: =4125+1670 | M13: =L13*12
B14: 4770 C | C14: Components Distributors | D14: 49 | E14: 45047 | F14: 46538 | G14: 12000 | H14: =144348/G14 | L14: =8500+3529 | M14: =L14*12
B15: 4770 F | C15: Global Mail d/b/a DHL | D15: 13 | E15: 45261 | F15: 45657 | G15: 10000 | H15: =116628/G15 | L15: =6666+3053 | M15: =L15*12
C16: eCommerce
A23: OFF | B23: 5208 Adams Street
B24: Unit | C24: Tenant | D24: Term | E24: Start | F24: End | G24: SF | H24: $/SF | K24: YC
E25: 45344 | G25: 4486 | H25: 25 | I25: NNN | K25: 1975
A27: OFF | B27: 3840 York Street - York Street Yards
B28: Unit | C28: Tenant | D28: Term | E28: Start | F28: End | G28: SF | H28: $/SF | K28: YC
E29: 45161 | G29: 4088 | H29: 25 | I29: NNN | K29: 1942/2021
A31: OFF | B31: 3975 56th Avenue
B32: Unit | C32: Tenant | D32: Term | E32: Start | F32: End | G32: SF | H32: $/SF | K32: YC
E33: 44690 | G33: 2500 | H33: 24.02 | I33: NNN | K33: 1982
A35: OFF | B35: 5475 Peoris Street
B36: Unit | C36: Tenant | D36: Term | E36: Start | F36: End | G36: SF | H36: $/SF | K36: YC
B37: Bldg 4 | E37: 45051 | G37: 1600 | H37: 22.5 | I37: NNN | K37: 1985
A39: OFF | B39: 6535 York Street
B40: Unit | C40: Tenant | D40: Term | E40: Start | F40: End | G40: SF | H40: $/SF | J40: $/SF | K40: YC
C41: JKD Welding Corp | D41: 12 | E41: 45458 | G41: 1250 | H41: 20 | I41: MG + $5 CAM | J41: 25 | K41: 1985
A44: OFF | B44: 9655 E 25th Ave
B45: Unit | C45: Tenant | D45: Term | E45: Start | F45: End | G45: SF | H45: $/SF | K45: YC
D46: 12 | E46: 45162 | G46: 1472 | H46: 20 | I46: NNN | K46: 1984
A48: OFF | B48: 3975 E 56th Ave
B49: Unit | C49: Tenant | D49: Term | E49: Start | F49: End | G49: SF | H49: $/SF | K49: YC
E50: 44595 | G50: 2500 | H50: 24.02 | I50: NNN | K50: 1982
A52: OFF | B52: 3801 Race Street
B53: Unit | C53: Tenant | D53: Term | E53: Start | F53: End | G53: SF | H53: $/SF | K53: YC
E54: 45244 | G54: 2074 | H54: 18 | I54: NNN | K54: 1955
G57: Min | H57: =MIN(H25,H29,H33,H37,H41,H46,H50,H54)
G58: Max | H58: =MAX(H25,H29,H33,H37,H41,H46,H50,H54)
G59: Avg | H59: =AVERAGE(H54,H50,H46,H41,H37,H33,H29,H25)
G60: Med | H60: =MEDIAN(H54,H50,H46,H41,H37,H33,H29,H25)

Sheet Market Rent Roll 2024
A1: CityView Industrial Park - Rent Roll (Rent Roll - Jun 2024)
A2: Source rent roll dated: May 17, 2024 (for June 2024)
A3: Source: Sterling Property Tax Specialists appeal package (Exhibit F), Adams County 2026 NOV protest
A7: Building/Unit Group | B7: Space | C7: SF | D7: Vacant SF | E7: Tenant | F7: Lease Start | G7: Term Expires | H7: Renewal/Option Expires | I7: Total Annual Rent | J7: Base Monthly Rent | K7: Annual Rate PSF | L7: CAM PSF (Annual) | M7: Notes
A8: 5800 | B8: 100 | C8: 500 | E8: CVP Management Office | I8: =C8*K8 | K8: 20 | M8: Management office - no rent
A9: 5800 | B9: 101 | C9: 1048 | E9: MR Solutions | F9: 08/01/23 | G9: 7/31/24 | I9: =C9*K9 | J9: 1222.67 | K9: 20 | L9: 9.5457 | M9: Office only
A10: 5800 | B10: 102 | C10: 960 | E10: R. Baker | F10: 09/01/22 | G10: 6/30/2024 | I10: =C10*K10 | J10: 782.4 | K10: 20 | L10: 9.5457 | M10: Month-to-month lease
A11: 5800 | B11: 104A | C11: 121 | E11: Vacant | I11: =C11*K11 | K11: 20
A12: 5800 | B12: 104B | C12: 121 | E12: Vacant | I12: =C12*K12 | K12: 20
A13: 5800 | B13: 104C | C13: 121 | E13: Vacant | I13: =C13*K13 | K13: 20
A14: 5800 | B14: 104 | C14: 722 | E14: Training Room 103 | I14: =C14*K14 | K14: 20
A15: 5800 | B15: CA | C15: 1435 | E15: Common Area | I15: =C15*K15 | K15: 20
A16: 5800 | B16: A | C16: 196 | E16: Vacant | I16: =C16*K16 | K16: 30
A17: 5800 | B17: B | C17: 121 | E17: Vacant | I17: =C17*K17 | K17: 30
A18: 5800 | B18: C | C18: 196 | E18: WEIL Construction Inc. | F18: 09/01/22 | G18: 08/31/24 | H18: 8/31/23 | I18: =C18*K18 | K18: 30
A19: 5800 | B19: D | C19: 121 | E19: Vacant | I19: =C19*K19 | K19: 30
A20: 5800 | B20: E | C20: 196 | E20: WEIL Construction Inc. | F20: 07/01/23 | G20: 08/31/24 | H20: 8/31/24 | I20: =C20*K20 | K20: 30
A21: 5800 | B21: Copy Room | C21: 107.2 | E21: Vacant | I21: =C21*K21 | K21: 30
A22: 5800 | B22: 106 | C22: 706 | E22: S&R Environmental Consulting, Inc. | F22: 12/01/23 | G22: 11/30/24 | H22: 11/30/26 | I22: =C22*K22 | J22: 628.93 | K22: 25 | L22: 9.5457
A23: 5800 | B23: 201 | C23: 2114.9 | E23: Global IT Innovative Systems | F23: 10/01/23 | G23: 09/30/24 | H23: 9/30/24 | I23: =C23*K23 | J23: 3631.65 | K23: 20 | L23: 4.25
A24: 5800 | B24: 201a | C24: 1385.1 | E24: Global IT Innovative Systems | I24: =C24*K24 | K24: 20
A25: 5800 | B25: 200, 202 | C25: 3108.59 | E25: Global IT Innovative Systems | I25: =C25*K25 | K25: 20
A26: 5800 | B26: CA | C26: 299.4 | E26: Global IT Innovative Systems | I26: =C26*K26 | K26: 30
A27: 5802 | B27: 107 | C27: 2274 | E27: Colorado Construction Cleaning, Inc. | F27: 06/01/23 | G27: 05/31/24 | H27: 5/31/24 | I27: =C27*K27 | J27: 884.97 | K27: 20 | L27: 7.6195 | M27: Contacted for renewal
A28: 5802 | B28: 203 | C28: 380.25 | E28: Global IT Innovative Systems | I28: =C28*K28 | K28: 30 | M28: Input #'s manually
A29: 5802 | B29: 205 | C29: 736 | E29: Global IT Innovative Systems | I29: =C29*K29 | K29: 25 | M29: No cleaning or supplies
A30: 5802 | B30: 204 | C30: 713 | E30: Global IT Innovative Systems | I30: =C30*K30 | K30: 25
A31: 5802 | B31: 206 | C31: 713 | E31: Global IT Innovative Systems | I31: =C31*K31 | K31: 25
A32: 5802 | B32: Storage | C32: 75.6 | E32: Global IT Innovative Systems | I32: =C32*K32 | K32: 30
A33: 5802 | B33: Unit M-105 | C33: 584 | E33: P&H Equipment | F33: 09/01/23 | G33: 08/31/24 | H33: 8/31/26 | I33: =C33*K33 | J33: 327.53 | K33: 25 | L33: 9.5457
A34: 5800/5802 OFFICE TOTALS | C34: =SUM(C8:C33) | D34: 1313.2 | I34: =SUM(I8:I33) | J34: $7,478.14 | K34: =AVERAGE(K8:K33)
A35: 5806 | B35: A-n | C35: 875 | E35: Global IT Innovative Systems | G35: 09/30/24 | H35: 09/30/24 | I35: =K35*C35 | K35: 10
A36: 5806 | B36: A-s | C36: 875 | E36: Global IT Innovative Systems | I36: =K36*C36 | K36: 10
A37: 5806 | B37: B-s | C37: 1221 | E37: Global IT Innovative Systems | F37: 10/01/23 | I37: =K37*C37 | J37: 414.34 | K37: 10 | L37: 4.5088 | M37: Input #'s manually
A38: 5806 | B38: B-n | C38: 350 | E38: Global IT Innovative Systems | F38: 10/01/23 | G38: 09/30/24 | H38: 09/30/24 | I38: =K38*C38 | J38: 484.4 | K38: 10
A39: 5808 | B39: A | C39: 3550 | E39: Miggy & Ernie's | F39: 3/1/2023 | G39: 2/28/2024 | H39: 2/28/2024 | I39: =K39*C39 | J39: 1606.38 | K39: 10 | L39: 7.6195
A40: 1609 | B40: A-B | C40: 3500 | E40: Keiths Paint Shop LLC | F40: 5/1/2024 | G40: 4/30/2025 | H40: 4/30/2028 | I40: =K40*C40 | J40: 1822.92 | K40: 10 | L40: 7.6195
A41: 1609 | B41: C | C41: 1750 | E41: Keiths Paint Shop LLC | F41: 5/1/2024 | G41: 4/30/2025 | H41: 4/30/2028 | I41: =K41*C41 | J41: 911.46 | K41: 10 | L41: 7.6195
A42: 1609 | B42: D-E | C42: 3250 | E42: Keiths Paint Shop LLC | F42: 5/1/2024 | G42: 4/30/2025 | H42: 4-30-28 | I42: =K42*C42 | J42: 1692.71 | K42: 10 | L42: 7.6195
A43: 1609 | B43: F | C43: 1564 | E43: Keiths Paint Shop LLC | F43: 5/1/2024 | G43: 4/30/2025 | I43: =K43*C43 | J43: 814.58 | K43: 10 | L43: 7.6195
A44: 1609 | B44: G | C44: 1750 | E44: Adessa | F44: 7/1/2023 | G44: 6/30/2024 | H44: 6/30/2025 | I44: =K44*C44 | J44: 901.25 | K44: 10 | L44: 7.6195
A45: 1609 | B45: H-I | C45: 3500 | E45: Keiths Paint Shop LLC | F45: 5/1/2024 | G45: 4/30/2025 | H45: 4-.30-28 | I45: =K45*C45 | J45: 1822.92 | K45: 10 | L45: 7.6195
A46: 1707-09 | B46: A07-B09 | C46: 15000 | E46: Certified Mapping and Technical Testing Inc. | F46: 07/01/24 | G46: 6/30/2024 | H46: 6/30/25 | I46: =K46*C46 | J46: 5025 | K46: 10 | L46: 3.6829 | M46: NO TAXES; partially exempt entity (see Schedule R0103789, 49.81% exempt)
A47: 1721-23 | B47: A21 | C47: 7500 | E47: Good Bread | F47: 6/1/2024 | G47: 5/31/2025 | H47: 5/31/2028 | I47: =K47*C47 | K47: 10 | L47: 7.6195 | M47: Combined w/ B23 rent shown on B23 row
A48: 1721-23 | B48: B23 | C48: 2728.17 | E48: Good Bread | F48: 06/01/24 | G48: 05/31/25 | H48: 5/31/28 | I48: =K48*C48 | J48: 1873.34 | K48: 10 | L48: 7.6195
A49: 1721-23 | B49: C23 w/h freeze | C49: 277.98 | E49: Good Bread Freezer | F49: 06/01/24 | G49: 05/31/25 | H49: 5/31/28 | I49: =K49*C49 | J49: 190.88 | K49: 10 | L49: 7.6195
A50: 1721-23 | B50: C23 w/h | C50: 4557.12 | E50: Good Bread | F50: 06/01/24 | G50: 05/31/25 | H50: 5/31/28 | I50: =K50*C50 | J50: 3129.22 | K50: 10 | L50: 7.6195
A51: 1751 | B51: A | C51: 4866.3 | E51: Coda Coffee Company | F51: 9/1/2023 | G51: 8/31/2024 | H51: 8/31/2024 | I51: =K51*C51 | J51: 3852.49 | K51: 10 | L51: 7.62
A52: 1751 | B52: B-2 | C52: 1921.48 | E52: Coda Coffee Company | F52: 9/1/2023 | G52: 8/31/2024 | H52: 8/31/2024 | I52: =K52*C52 | J52: 1521.17 | K52: 10 | L52: 7.62
A53: 1751 | B53: B-1 | C53: 1132.83 | E53: Coda Coffee Company | F53: 9/1/2023 | G53: 8/31/2024 | H53: 8/31/2024 | I53: =K53*C53 | J53: 896.82 | K53: 10 | L53: 7.62
A54: 1751 | B54: B-3 | C54: 3450 | E54: Coda Coffee Company | F54: 9/1/2023 | G54: 8/31/2024 | H54: 8/31/2024 | I54: =K54*C54 | J54: 2731.25 | K54: 10 | L54: 7.62
A55: 1751 | B55: D east | C55: 855.88 | E55: Coda Coffee Company | F55: 9/1/2023 | G55: 8/31/2024 | H55: 8/31/2024 | I55: =K55*C55 | J55: 677.57 | K55: 10 | L55: 7.62
A56: 1751 | B56: D 2nd floor | C56: 650.92 | E56: Unoccupied (2nd floor small storage) | F56: 09/01/21 | I56: =K56*C56 | K56: 10
A57: 1751 | B57: D west | C57: 993.08 | E57: Coda Coffee Company | F57: 9/1/2023 | G57: 8/31/2024 | H57: 8/31/2024 | I57: =K57*C57 | J57: 786.19 | K57: 10 | L57: 7.62
A58: 1751 | B58: E | C58: 5000 | E58: Reliant Dry Ice | F58: 11/1/2023 | G58: 10/31/2024 | H58: 10/31/2025 | I58: =K58*C58 | J58: 2583.33 | K58: 10 | L58: 7.6195
A59: 1791 | B59: A | C59: 5157 | E59: ReEnergize | F59: 06/01/24 | G59: 05/31/25 | H59: 5/31/25 | I59: =K59*C59 | J59: 2733.21 | K59: 10 | L59: 7.6195
A60: 1791 | B60: B | C60: 4000 | E60: Coda Coffee Company | F60: 09/01/23 | G60: 8/31/2024 | H60: 8/31/24 | I60: =K60*C60 | J60: 3166.67 | K60: 10 | L60: 7.6195
A61: 1791 | B61: C & D | C61: 4000 | E61: Allcomm Data Supplies Inc. | F61: 09/01/22 | G61: 08/31/24 | H61: 8/31/26 | I61: =K61*C61 | J61: 1800 | K61: 10 | L61: 7.6195
A62: 1791 | B62: E | C62: 2000 | E62: RossComm LLC | F62: 05/01/24 | G62: 04/30/25 | H62: 4/30/25 | I62: =K62*C62 | J62: 1125 | K62: 10 | L62: 7.6195
A63: 1791 | B63: F | C63: 2000 | E63: R&O Heating Inc. | F63: 08/01/23 | G63: 07/31/24 | H63: 7/31/26 | I63: =K63*C63 | J63: 1166.67 | K63: 10 | L63: 7.6195
A64: 1791 | B64: G | C64: 2000 | E64: R&O Heating Inc. | F64: 08/01/23 | G64: 07/31/24 | H64: 7/31/26 | I64: =K64*C64 | J64: 1166.67 | K64: 10 | L64: 7.6195
A65: 1791 | B65: H | C65: 2000 | E65: R&O Heating Inc. | F65: 08/01/23 | G65: 07/31/24 | H65: 7/31/26 | I65: =K65*C65 | J65: 1166.67 | K65: 10 | L65: 7.6195
A66: 1791 | B66: M | C66: 2000 | E66: Harlan Bakeries Co LLC | F66: 02/01/23 (roll cont. 1-18-17) | G66: 01/31/25 | H66: 1/31/25 | I66: =K66*C66 | J66: 1040 | K66: 10 | L66: 7.6195 | M66: Envigo/Vanguard listed as prior tenant 06/01/23-05/31/25, term to 5/13/26
A67: 1791 | B67: N | C67: 2000 | E67: Mr. Dino's Baths | G67: 05/31/24 | H67: 05/31/24 | I67: =K67*C67 | K67: 10
A68: 1771 | B68: A/A-1 | C68: 3760 | E68: Colorado Comfort Air | F68: 7/1/2023 | G68: 6/30/2024 | H68: 6/30/2028 | I68: =K68*C68 | J68: 1942.67 | K68: 10 | L68: 7.6195
A69: 1771 | B69: B | C69: 3987.76 | E69: CODA Coffee | F69: 02/15/24 | G69: 8/31/2024 | H69: 8/31/24 | I69: =K69*C69 | J69: 1993.88 | K69: 10 | L69: 5.92
A70: 1771 | B70: C | C70: 2562.24 | E70: REDCO Tire | F70: 07/01/23 | G70: 06/30/24 | H70: 6/30/28 | I70: =K70*C70 | J70: 1281.12 | K70: 10 | L70: 7.6195
A71: 1771 | B71: D | C71: 4585.15 | E71: Coda Coffee | F71: 9/1/2023 | G71: 8/31/24 | H71: 08/31/24 | I71: =K71*C71 | J71: 3629.91 | K71: 10 | L71: 7.6195
A72: 1771 | B72: E & F | C72: 5000 | E72: Happel & Associates Inc. | F72: 9/1/2023 | G72: 8/31/24 | H72: 08/31/25 | I72: =K72*C72 | J72: 2704.17 | K72: 10 | L72: 7.6195
A73: 1761 | B73: A | C73: 2625 | E73: Harlan Bakeries | F73: 09/01/23 | G73: 08/31/24 | H73: 8/31/25 | I73: =K73*C73 | J73: 1060.94 | K73: 10 | L73: 7.6195
A74: 1761 | B74: A-5 | C74: 3750 | E74: Good Bread Inc. | F74: 06/01/24 | G74: 05/31/25 | H74: 5/31/28 | I74: =K74*C74 | J74: 1594 | K74: 10 | L74: 7.6195
A75: 1761 | B75: A3 | C75: 1250 | E75: Santa Fe Mechanical | F75: 09/01/23 | G75: 08/31/24 | H75: 8/31/25 | I75: =K75*C75 | J75: 751.04 | K75: 10 | L75: 7.6195
A76: 1761 | B76: A4 | C76: 5000 | E76: Santa Fe Mechanical | F76: 09/01/23 | G76: 08/31/24 | H76: 8/31/25 | I76: =K76*C76 | J76: 3004.17 | K76: 10 | L76: 7.6195
A77: 1761 (cont.) | B77: A1 | C77: 6675 | E77: Whatnot Ventures LLC | F77: 06/01/24 | G77: 05/31/25 | H77: 5/1/26 | I77: =K77*C77 | J77: 2742.31 | K77: 10 | L77: 7.6195
A78: 1761 (cont.) | B78: A2 | C78: 3200 | E78: Inland Island Brewing | F78: 10/01/22 | G78: 09/30/24 | H78: 9/30/27 | I78: =K78*C78 | J78: 1210.67 | K78: 10 | L78: 7.6195
A79: 1761 (cont.) | B79: B | C79: 2765 | E79: Inland Island Brewing | F79: 10/01/22 | G79: 09/30/24 | H79: 9/30/27 | I79: =K79*C79 | J79: 1046.09 | K79: 10 | L79: 7.6195
... A82: 1805 | B82: A,B | C82: 3000 | E82: Savory Retail Group, LLC | F82: 04/01/24 | G82: 03/31/25 | H82: 03/31/30 | I82: =K82*C82 | J82: 1337.5 | K82: 10 | L82: 7.6195
A83: 1805 | B83: C | C83: 3000 | E83: Savory | F83: 04/01/24 | G83: 03/31/25 | H83: 03/31/30 | I83: =K83*C83 | J83: 1337.5 | K83: 10 | L83: 7.6195 | M83: 180-day notice from tenant to continue
A84: 1805 | B84: D | C84: 2000 | E84: Savory | F84: 04/01/24 | G84: 03/31/25 | H84: 03/31/30 | I84: =K84*C84 | J84: 891.67 | K84: 10 | L84: 7.6195 | M84: 180-day notice from tenant to continue
A85: 1805 | B85: E,F,G | C85: 6000 | E85: Savory | F85: 04/01/24 | G85: 03/31/25 | H85: 03/31/30 | I85: =K85*C85 | J85: 2675 | K85: 10 | L85: 7.6195 | M85: 180-day notice from tenant to continue
A86: 1805 | B86: H | C86: 2000 | E86: M.R. Solutions, Inc. | F86: 08/01/23 | G86: 07/31/24 | H86: 7/31/02 [sic] | I86: =K86*C86 | J86: 1416.67 | K86: 10 | L86: 7.6195
A87: 1805 | B87: I | C87: 2000 | E87: M.R. Solutions, Inc. | F87: 08/01/23 | G87: 07/31/24 | H87: 7/31/24 | I87: =K87*C87 | J87: 1416.67 | K87: 10 | L87: 7.6195
A88: 1805 | B88: J-s | C88: 2172 | E88: ReEnergize | F88: 06/01/23 | G88: 05/31/24 | H88: 5/31/24 | I88: =K88*C88 | J88: 1035.32 | K88: 10 | L88: 7.6195
A89: 1805 | B89: J (Ne) | C89: 1475 | E89: P&H Equipment | F89: 09/01/23 | G89: 08/31/24 | H89: 8/31/2026 | I89: =K89*C89 | J89: 798.96 | K89: 10 | L89: 7.6195
A90: 1805 | B90: J (Nw) | C90: 440 | E90: ReEnergize | F90: 06/01/23 | G90: 05/31/24 | H90: 5/31/24 | I90: =K90*C90 | J90: 209.74 | K90: 10 | L90: 7.6195
A91: 1805 | B91: K | C91: 1325 | E91: ReEnergize | F91: 06/01/23 | G91: 05/31/24 | H91: 5/31/24 | I91: =K91*C91 | J91: 631.58 | K91: 10 | L91: 7.6195
A92: 1805 | B92: K office | C92: 680 | E92: ReEnergize | F92: 06/01/23 | G92: 05/31/24 | H92: 5/31/24 | I92: =K92*C92 | J92: 324.13 | K92: 10 | L92: 7.6195
A93: 1805 | B93: L | C93: 2005 | E93: ReEnergize | F93: 06/01/23 | G93: 05/31/24 | H93: 5/31/24 | I93: =K93*C93 | J93: 955.72 | K93: 10 | L93: 7.6195
A94: 1805 | B94: M | C94: 3005 | E94: Savory Spice | F94: 6/1/2024 | G94: 5/31/2025 | H94: 3/31/27 / 3/31/30 | I94: =K94*C94 | J94: 3503.2 | K94: 10 | L94: 7.6195 | M94: Rent shown w/ $1,595.15 add'l figure in source
A95: 1805 | B95: N | C95: 3000 | E95: Harlan | F95: 09/01/23 | G95: 08/31/24 | I95: =K95*C95 | J95: 375 | K95: 10 | L95: 7.6195 | M95: Month-to-month, roll continues (Hal Harlan 1-18-17)
A96: 1805 | B96: O1, O2, O3 | C96: 9000 | E96: Coda Coffee | F96: 09/01/23 | G96: 08/31/24 | H96: 8/31/24 | I96: =K96*C96 | J96: 7125 | K96: 10 | L96: 7.6195
A97: WAREHOUSE TOTALS | C97: =SUM(C35:C96) | D97: 650.92 | I97: =SUM(I35:I96) | J97: $107,996.75 | K97: =AVERAGE(K35:K96) | M97: Warehouse totals per rent roll
A98: BUILDING TOTAL (Office+Wse) | C98: =C97+C34 | D98: 1964.12 | I98: =I97+I34 | J98: $115,474.89 | M98: Building totals per rent roll
A99: OUTSIDE/STORAGE | B99: Franklin - 5898 Franklin (10,000 SF) | C99: 10000 | E99: Keith Werkheiser | F99: 12/01/23 | G99: mo to mo | H99: mo to mo | I99: =(12*1225) | M99: Lease document for this parcel
A100: OUTSIDE/STORAGE | B100: Franklin - 5898 Franklin (6,375 SF) | C100: 6375 | E100: Keith Werkheiser | F100: 05/01/23 | G100: 04/30/25 | H100: 4/30/28 | I100: =(12*1275)
A101: OUTSIDE/STORAGE | B101: Franklin (500 SF) | C101: 500 | E101: Colorado Construction Cleaning | F101: 03/01/22 | G101: mo to mo | I101: 50
A102: OUTSIDE/STORAGE | B102: 1900 E. 58th (1,000 SF) | C102: 1000 | E102: P&H Equipment
A103: OUTSIDE/STORAGE | B103: Mapleton (1,000 SF) | C103: 1000 | E103: P&H Equipment
A104: OUTSIDE/STORAGE | B104: Hillside B - 5952 Franklin (17,447.77 SF) | C104: 17447.77 | E104: Lobos Structures, LLC. | F104: 07/01/23 | G104: 06/30/24 | H104: 6/30/24 | I104: 363.49
A105: OUTSIDE/STORAGE | B105: Hillside B - 5952 Franklin (17,447.77 SF) #2 | C105: 17447.77 | E105: Lobos Structures, LLC. | F105: 07/01/23 | G105: 06/30/24 | H105: 6/30/24 | I105: 363.49
...

Sheet Market Pro Forma
H1: ='Market Rent Roll 2024'!B127 | J1: comps
C2: 2023 Actual | D2: $/SF | E2: 2024 Actual | G2: ACO Projection | H2: $/SF | J2: 1803 E 58th Ave (nextdoor) | K2: 2 | L2: 3
B3: PGI
B4: Industrial Office | C4: 121582.27 | D4: =C4/H1 | E4: 115289.07 | F4: =E4/H1 | G4: ='Market Rent Roll 2024'!I125 | H4: =G4/H1
B5: Warehouse | C5: 1213722.6 | D5: =C5/H1 | E5: 1296540.4 | F5: =E5/H1 | G5: ='Market Rent Roll 2024'!I126 | H5: =G5/H1
B6: ='Market Rent Roll 2024'!A128 | C6: =(60343.3-48000) | D6: =C6/H1 | E6: =(82884.19-48000) | F6: =E6/H1
B7: Other | C7: =(96439.27-59039) | D7: =C7/H1 | E7: =(59677.83-23677.83) | F7: =E7/H1
B9: Total PGI | C9: =SUM(C4:C7) | D9: =C9/H1 | E9: =E4+E5+E6+E7 | F9: =E9/H1 | G9: =SUM(G4:G7) | H9: =G9/H1 | J9: =379611/25000
B10: Expense Reimbursements | C10: 1181430 | D10: =C10/H1 | E10: 1446433.2 | F10: =E10/H1 | G10: =G24
B11: PGI | C11: =C9+C10 | D11: =C11/H1 | E11: =E9+E10 | F11: =E11/H1
A13: 0.05 | B13: Less Vacancy & Collection Loss @ 5% | G13: =G11*A13
B15: EGI | C15: =C11-C13 | G15: =G11-G13
B17: Reimburseable Expenses
B18: RE Taxes | C18: 528000 | D18: =C18/H1 | E18: 774996 | G18: ='Schedules & Values'!R12 | H18: =G18/H1 | J18: =80613/25000
B19: Insurance | C19: 60720 | D19: =C19/H1 | J19: =8380/25000
B20: Mgmt | C20: 133294 | D20: =C20/H1
B21: Repairs & Maintenance | C21: =188734+67548.08+14677.25+14881 | D21: =C21/H1 | J21: =7597/25000
B22: Utilities | C22: =44485.83+28513.94+12000 | D22: =C22/H1
B23: Payroll/Services | C23: =105227.25+143964 | D23: =C23/H1
B24: Total Reimburseable Expenses | C24: =C18+C19+C20+C21+C22+C23 | D24: =C24/H1 | G24: =G18+G19+G20+G21
B26: Non-Reimbursable Expenses
B27: Landlord Costs | C27: 106201.72 | D27: =C27/H1 | J27: =5245/25000
B28: Replacement Reserves | C28: 0
B29: Total Non-Reimburseable Expenses | C29: =C27+C28 | D29: =C29/H1 | G29: =G27+G28
B31: Less: Total Operating Expenses | C31: =C29+C24 | D31: =C31/H1 | G31: =G29+G24
B33: Stabilized NOI | C33: =C15-C31 | D33: =C33/H1 | G33: =G15-G31
B35: Cap Rate | C35: 0.065 | G35: 0.07
B37: Value | C37: =C33/C35 | D37: =C37/H1 | G37: =G33/G35
I40: 528000
I41: 60720
I42: 44485
I43: 28513
I44: 188734
I45: 67548
I46: 14677
I47: 105227
I48: 14881
I49: 12000
I50: 143964
I51: 133294
I52: 800
I53: =SUM(I40:I52)

Sheet Rent Roll - Jun 2024
A1: CityView Industrial Park - Rent Roll (Rent Roll - Jun 2024)
A2: Source rent roll dated: May 17, 2024 (for June 2024)
A3: Source: Sterling Property Tax Specialists appeal package (Exhibit F), Adams County 2026 NOV protest
A5: Building/Unit Group | B5: Space | C5: Leased SF | D5: Vacant SF | E5: Tenant | F5: Lease Start | G5: Term Expires | H5: Renewal/Option Expires | I5: Total Monthly Rent | J5: Base Monthly Rent | K5: Annual Rate PSF | L5: CAM PSF (Annual) | N5: Notes
A6: 5800 | B6: 100 | C6: 500 | E6: CVP Management Office | M6: =K6+L6 | N6: Management office - no rent
A7: 5800 | B7: 101 | C7: 1048 | E7: MR Solutions | F7: 08/01/23 | G7: 7/31/24 | I7: 2056.32 | J7: 1222.67 | K7: 14 | L7: 9.5457 | M7: =K7+L7 | N7: Office only
A8: 5800 | B8: 102 | C8: 960 | E8: R. Baker | F8: 09/01/22 | G8: 6/30/2024 | I8: 1546.06 | J8: 782.4 | K8: 9.78 | L8: 9.5457 | M8: =K8+L8 | N8: Month-to-month lease
A9: 5800 | B9: 104A | D9: 121 | E9: Vacant | M9: =K9+L9
A10: 5800 | B10: 104B | D10: 121 | E10: Vacant | M10: =K10+L10
A11: 5800 | B11: 104C | D11: 121 | E11: Vacant | M11: =K11+L11
A12: 5800 | B12: 104 | C12: 722 | E12: Training Room 103 | M12: =K12+L12
A13: 5800 | B13: 103 | M13: =K13+L13
A14: 5800 | B14: CA | C14: 1435 | E14: Common Area | M14: =K14+L14
A15: 5800 | B15: A | C15: 196 | E15: Vacant | M15: =K15+L15
A16: 5800 | B16: B | C16: 121 | E16: Vacant | M16: =K16+L16
A17: 5800 | B17: C | C17: 196 | E17: WEIL Construction Inc. | F17: 09/01/22 | G17: 08/31/24 | H17: 8/31/23 | I17: 535.57 | M17: =K17+L17
A18: 5800 | B18: D | C18: 121 | E18: Vacant | M18: =K18+L18
A19: 5800 | B19: E | C19: 196 | E19: WEIL Construction Inc. | F19: 07/01/23 | G19: 08/31/24 | H19: 8/31/24 | I19: 515.15 | M19: =K19+L19
A20: 5800 | B20: Copy Room | C20: 107.2 | E20: Vacant | M20: =K20+L20
A21: 5800 | B21: 106 | C21: 706 | E21: S&R Environmental Consulting, Inc. | F21: 12/01/23 | G21: 11/30/24 | H21: 11/30/26 | I21: 1190.53 | J21: 628.93 | K21: 10.69 | L21: 9.5457 | M21: =K21+L21
A22: 5800 | B22: 201 | C22: 2114.9 | E22: Global IT Innovative Systems | F22: 10/01/23 | G22: 09/30/24 | H22: 9/30/24 | I22: 8007.46 | J22: 3631.65 | K22: 4.31 | L22: 4.25 | M22: =K22+L22
A23: 5800 | B23: 201a | C23: 1385.1 | E23: Global IT Innovative Systems | M23: =K23+L23
A24: 5800 | B24: 200, 202 | C24: 3108.59 | E24: Global IT Innovative Systems | M24: =K24+L24
A25: 5800 | B25: CA | C25: 299.4 | E25: Global IT Innovative Systems | M25: =K25+L25
A26: 5802 | B26: 107 | C26: 2274 | E26: Colorado Construction Cleaning, Inc. | F26: 06/01/23 | G26: 05/31/24 | H26: 5/31/24 | I26: 2328.86 | J26: 884.97 | K26: 4.67 | L26: 7.6195 | M26: =K26+L26 | N26: Contacted for renewal
A27: 5802 | B27: 203 | C27: 380.25 | E27: Global IT Innovative Systems | M27: =K27+L27 | N27: Input #'s manually
A28: 5802 | B28: 205 | C28: 736 | E28: Global IT Innovative Systems | M28: =K28+L28 | N28: No cleaning or supplies
A29: 5802 | B29: 204 | C29: 713 | E29: Global IT Innovative Systems | M29: =K29+L29
A30: 5802 | B30: 206 | C30: 713 | E30: Global IT Innovative Systems | M30: =K30+L30
A31: 5802 | B31: Storage | C31: 75.6 | E31: Global IT Innovative Systems | M31: =K31+L31
A32: 5802 | B32: Unit M-105 | C32: 584 | E32: P&H Equipment | F32: 09/01/23 | G32: 08/31/24 | H32: 8/31/26 | I32: 792.08 | J32: 327.53 | K32: 6.73 | L32: 9.5457 | M32: =K32+L32
A33: 5800/5802 | C33: 17741.84 | D33: 1313.2 | I33: $16,972.04 | J33: $7,478.14 | K33: $4.18 blended | N33: Office totals per rent roll
A34: 5806 | B34: A-n | C34: 875 | E34: Global IT Innovative Systems | G34: 09/30/24 | H34: 09/30/24
A35: 5806 | B35: A-s | C35: 875 | E35: Global IT Innovative Systems
A36: 5806 | B36: B-s | C36: 1221 | E36: Global IT Innovative Systems | F36: 10/01/23 | I36: 1202.19 | J36: 414.34 | K36: 4.414 | L36: 4.5088 | N36: Input #'s manually
A37: 5806 | B37: B-n | C37: 350 | E37: Global IT Innovative Systems | F37: 10/01/23 | G37: 09/30/24 | H37: 09/30/24 | I37: 484.4 | J37: 484.4
A38: 5808 | B38: A | C38: 3550 | E38: Miggy & Ernie's | F38: 3/1/2023 | G38: 2/28/2024 | H38: 2/28/2024 | I38: 3860.48 | J38: 1606.38 | K38: 5.43 | L38: 7.6195
A39: 1609 | B39: A-B | C39: 3500 | E39: Keiths Paint Shop LLC | F39: 5/1/2024 | G39: 4/30/2025 | H39: 4/30/2028 | I39: 4045.27 | J39: 1822.92 | K39: 6.25 | L39: 7.6195
A40: 1609 | B40: C | C40: 1750 | E40: Keiths Paint Shop LLC | F40: 5/1/2024 | G40: 4/30/2025 | H40: 4/30/2028 | I40: 2022.64 | J40: 911.46 | K40: 6.25 | L40: 7.6195
A41: 1609 | B41: D-E | C41: 3250 | E41: Keiths Paint Shop LLC | F41: 5/1/2024 | G41: 4/30/2025 | H41: 4-30-28 | I41: 3756.32 | J41: 1692.71 | K41: 6.25 | L41: 7.6195
A42: 1609 | B42: F | C42: 1564 | E42: Keiths Paint Shop LLC | F42: 5/1/2024 | G42: 4/30/2025 | I42: 1807.66 | J42: 814.58 | K42: 6.25 | L42: 7.6195
A43: 1609 | B43: G | C43: 1750 | E43: Adessa | F43: 7/1/2023 | G43: 6/30/2024 | H43: 6/30/2025 | I43: 2012.43 | J43: 901.25 | K43: 6.18 | L43: 7.6195
A44: 1609 | B44: H-I | C44: 3500 | E44: Keiths Paint Shop LLC | F44: 5/1/2024 | G44: 4/30/2025 | H44: 4-.30-28 | I44: 4045.27 | J44: 1822.92 | K44: 6.25 | L44: 7.6195
A45: 1707-09 | B45: A07-B09 | C45: 15000 | E45: Certified Mapping and Technical Testing Inc. | F45: 07/01/24 | G45: 6/30/2024 | H45: 6/30/25 | I45: 9628.63 | J45: 5025 | K45: 4.02 | L45: 3.6829 | N45: NO TAXES; partially exempt entity (see Schedule R0103789, 49.81% exempt)
A46: 1721-23 | B46: A21 | C46: 7500 | E46: Good Bread | F46: 6/1/2024 | G46: 5/31/2025 | H46: 5/31/2028 | K46: 8.24 | L46: 7.6195 | N46: Combined w/ B23 rent shown on B23 row
A47: 1721-23 | B47: B23 | C47: 2728.17 | E47: Good Bread | F47: 06/01/24 | G47: 05/31/25 | H47: 5/31/28 | I47: 3605.62 | J47: 1873.34 | K47: 8.24 | L47: 7.6195
A48: 1721-23 | B48: C23 w/h freeze | C48: 277.98 | E48: Good Bread Freezer | F48: 06/01/24 | G48: 05/31/25 | H48: 5/31/28 | I48: 367.39 | J48: 190.88 | K48: 8.24 | L48: 7.6195
A49: 1721-23 | B49: C23 w/h | C49: 4557.12 | E49: Good Bread | F49: 06/01/24 | G49: 05/31/25 | H49: 5/31/28 | I49: 6022.8 | J49: 3129.22 | K49: 8.24 | L49: 7.6195
A50: 1751 | B50: A | C50: 4866.3 | E50: Coda Coffee Company | F50: 9/1/2023 | G50: 8/31/2024 | H50: 8/31/2024 | I50: 7027.39 | J50: 3852.49 | K50: 9.5 | L50: 7.62
A51: 1751 | B51: B-2 | C51: 1921.48 | E51: Coda Coffee Company | F51: 9/1/2023 | G51: 8/31/2024 | H51: 8/31/2024 | I51: 2741.23 | J51: 1521.17 | K51: 9.5 | L51: 7.62
A52: 1751 | B52: B-1 | C52: 1132.83 | E52: Coda Coffee Company | F52: 9/1/2023 | G52: 8/31/2024 | H52: 8/31/2024 | I52: 1616.12 | J52: 896.82 | K52: 9.5 | L52: 7.62
A53: 1751 | B53: B-3 | C53: 3450 | E53: Coda Coffee Company | F53: 9/1/2023 | G53: 8/31/2024 | H53: 8/31/2024 | I53: 4921.86 | J53: 2731.25 | K53: 9.5 | L53: 7.62
A54: 1751 | B54: D east | C54: 855.88 | E54: Coda Coffee Company | F54: 9/1/2023 | G54: 8/31/2024 | H54: 8/31/2024 | I54: 1221.02 | J54: 677.57 | K54: 9.5 | L54: 7.62
A55: 1751 | B55: D 2nd floor | C55: 650.92 | E55: Unoccupied (2nd floor small storage) | F55: 09/01/21
A56: 1751 | B56: D west | C56: 993.08 | E56: Coda Coffee Company | F56: 9/1/2023 | G56: 8/31/2024 | H56: 8/31/2024 | I56: 1416.75 | J56: 786.19 | K56: 9.5 | L56: 7.62
A57: 1751 | B57: E | C57: 5000 | E57: Reliant Dry Ice | F57: 11/1/2023 | G57: 10/31/2024 | H57: 10/31/2025 | I57: 5758.13 | J57: 2583.33 | K57: 6.2 | L57: 7.6195
A58: 1791 | B58: A | C58: 5157 | E58: ReEnergize | F58: 06/01/24 | G58: 05/31/25 | H58: 5/31/25 | I58: 6007.69 | J58: 2733.21 | K58: 6.36 | L58: 7.6195
A59: 1791 | B59: B | C59: 4000 | E59: Coda Coffee Company | F59: 09/01/23 | G59: 8/31/2024 | H59: 8/31/24 | I59: 5706.5 | J59: 3166.67 | K59: 9.5 | L59: 7.6195
A60: 1791 | B60: C & D | C60: 4000 | E60: Allcomm Data Supplies Inc. | F60: 09/01/22 | G60: 08/31/24 | H60: 8/31/26 | I60: 4339.83 | J60: 1800 | K60: 5.4 | L60: 7.6195
A61: 1791 | B61: E | C61: 2000 | E61: RossComm LLC | F61: 05/01/24 | G61: 04/30/25 | H61: 4/30/25 | I61: 2394.92 | J61: 1125 | K61: 6.75 | L61: 7.6195
A62: 1791 | B62: F | C62: 2000 | E62: R&O Heating Inc. | F62: 08/01/23 | G62: 07/31/24 | H62: 7/31/26 | I62: 2481.58 | J62: 1166.67 | K62: 7 | L62: 7.6195
A63: 1791 | B63: G | C63: 2000 | E63: R&O Heating Inc. | F63: 08/01/23 | G63: 07/31/24 | H63: 7/31/26 | I63: 2436.58 | J63: 1166.67 | K63: 7 | L63: 7.6195
A64: 1791 | B64: H | C64: 2000 | E64: R&O Heating Inc. | F64: 08/01/23 | G64: 07/31/24 | H64: 7/31/26 | I64: 2436.58 | J64: 1166.67 | K64: 7 | L64: 7.6195
A65: 1791 | B65: M | C65: 2000 | E65: Harlan Bakeries Co LLC | F65: 02/01/23 (roll cont. 1-18-17) | G65: 01/31/25 | H65: 1/31/25 | I65: 2309.92 | J65: 1040 | K65: 6.24 | L65: 7.6195 | N65: Envigo/Vanguard listed as prior tenant 06/01/23-05/31/25, term to 5/13/26
A66: 1791 | B66: N | C66: 2000 | E66: Mr. Dino's Baths | G66: 05/31/24 | H66: 05/31/24
A67: 1771 | B67: A/A-1 | C67: 3760 | E67: Colorado Comfort Air | F67: 7/1/2023 | G67: 6/30/2024 | H67: 6/30/2028 | I67: 4330.11 | J67: 1942.67 | K67: 6.2 | L67: 7.6195
A68: 1771 | B68: B | C68: 3987.76 | E68: CODA Coffee | F68: 02/15/24 | G68: 8/31/2024 | H68: 8/31/24 | I68: 3961.17 | J68: 1993.88 | K68: 6 | L68: 5.92
A69: 1771 | B69: C | C69: 2562.24 | E69: REDCO Tire | F69: 07/01/23 | G69: 06/30/24 | H69: 6/30/28 | I69: 2908.04 | J69: 1281.12 | K69: 6 | L69: 7.6195
A70: 1771 | B70: D | C70: 4585.15 | E70: Coda Coffee | F70: 9/1/2023 | G70: 8/31/24 | H70: 08/31/24 | I70: 6541.29 | J70: 3629.91 | K70: 9.5 | L70: 7.6195
A71: 1771 | B71: E & F | C71: 5000 | E71: Happel & Associates Inc. | F71: 9/1/2023 | G71: 8/31/24 | H71: 08/31/25 | I71: 5878.96 | J71: 2704.17 | K71: 6.49 | L71: 7.6195
A72: 1761 | B72: A | C72: 2625 | E72: Harlan Bakeries | F72: 09/01/23 | G72: 08/31/24 | H72: 8/31/25 | I72: 2727.7 | J72: 1060.94 | K72: 4.85 | L72: 7.6195
A73: 1761 | B73: A-5 | C73: 3750 | E73: Good Bread Inc. | F73: 06/01/24 | G73: 05/31/25 | H73: 5/31/28 | I73: 3975.09 | J73: 1594 | K73: 5.1008 | L73: 7.6195
A74: 1761 | B74: A3 | C74: 1250 | E74: Santa Fe Mechanical | F74: 09/01/23 | G74: 08/31/24 | H74: 8/31/25 | I74: 1544.74 | J74: 751.04 | K74: 7.21 | L74: 7.6195
A75: 1761 | B75: A4 | C75: 5000 | E75: Santa Fe Mechanical | F75: 09/01/23 | G75: 08/31/24 | H75: 8/31/25 | I75: 6178.96 | J75: 3004.17 | K75: 7.21 | L75: 7.6195
A76: 1761 (cont.) | B76: A1 | C76: 6675 | E76: Whatnot Ventures LLC | F76: 06/01/24 | G76: 05/31/25 | H76: 5/1/26 | I76: 6980.66 | J76: 2742.31 | K76: 4.93 | L76: 7.6195
A77: 1761 (cont.) | B77: A2 | C77: 3200 | E77: Inland Island Brewing | F77: 10/01/22 | G77: 09/30/24 | H77: 9/30/27 | I77: 3242.53 | J77: 1210.67 | K77: 4.54 | L77: 7.6195
A78: 1761 (cont.) | B78: B | C78: 2765 | E78: Inland Island Brewing | F78: 10/01/22 | G78: 09/30/24 | H78: 9/30/27 | I78: 2801.75 | J78: 1046.09 | K78: 4.54 | L78: 7.6195
... A81: 1805 | B81: A,B | C81: 3000 | E81: Savory Retail Group, LLC | F81: 04/01/24 | G81: 03/31/25 | H81: 03/31/30 | I81: 3915.54 | J81: 1337.5 | K81: 5.35 | L81: 7.6195
A82: 1805 | B82: C | C82: 3000 | E82: Savory | F82: 04/01/24 | G82: 03/31/25 | H82: 03/31/30 | I82: 3242.38 | J82: 1337.5 | K82: 5.35 | L82: 7.6195 | N82: 180-day notice from tenant to continue
A83: 1805 | B83: D | C83: 2000 | E83: Savory | F83: 04/01/24 | G83: 03/31/25 | H83: 03/31/30 | I83: 2161.58 | J83: 891.67 | K83: 5.35 | L83: 7.6195 | N83: 180-day notice from tenant to continue
A84: 1805 | B84: E,F,G | C84: 6000 | E84: Savory | F84: 04/01/24 | G84: 03/31/25 | H84: 03/31/30 | I84: 6484.75 | J84: 2675 | K84: 5.35 | L84: 7.6195 | N84: 180-day notice from tenant to continue
A85: 1805 | B85: H | C85: 2000 | E85: M.R. Solutions, Inc. | F85: 08/01/23 | G85: 07/31/24 | H85: 7/31/02 [sic] | I85: 2686.58 | J85: 1416.67 | K85: 8.5 | L85: 7.6195
A86: 1805 | B86: I | C86: 2000 | E86: M.R. Solutions, Inc. | F86: 08/01/23 | G86: 07/31/24 | H86: 7/31/24 | I86: 2686.58 | J86: 1416.67 | K86: 8.5 | L86: 7.6195
A87: 1805 | B87: J-s | C87: 2172 | E87: ReEnergize | F87: 06/01/23 | G87: 05/31/24 | H87: 5/31/24 | I87: 2509.45 | J87: 1035.32 | K87: 5.72 | L87: 7.6195
A88: 1805 | B88: J (Ne) | C88: 1475 | E88: P&H Equipment | F88: 09/01/23 | G88: 08/31/24 | H88: 8/31/2026 | I88: 1735.52 | J88: 798.96 | K88: 6.5 | L88: 7.6195
A89: 1805 | B89: J (Nw) | C89: 440 | E89: ReEnergize | F89: 06/01/23 | G89: 05/31/24 | H89: 5/31/24 | I89: 489.13 | J89: 209.74 | K89: 5.72 | L89: 7.6195
A90: 1805 | B90: K | C90: 1325 | E90: ReEnergize | F90: 06/01/23 | G90: 05/31/24 | H90: 5/31/24 | I90: 1472.9 | J90: 631.58 | K90: 5.72 | L90: 7.6195
A91: 1805 | B91: K office | C91: 680 | E91: ReEnergize | F91: 06/01/23 | G91: 05/31/24 | H91: 5/31/24 | I91: 755.91 | J91: 324.13 | K91: 5.72 | L91: 7.6195
A92: 1805 | B92: L | C92: 2005 | E92: ReEnergize | F92: 06/01/23 | G92: 05/31/24 | H92: 5/31/24 | I92: 2228.81 | J92: 955.72 | K92: 5.72 | L92: 7.6195
A93: 1805 | B93: M | C93: 3005 | E93: Savory Spice | F93: 6/1/2024 | G93: 5/31/2025 | H93: 3/31/27 / 3/31/30 | I93: 11048 | J93: 3503.2 | K93: 6.37 | L93: 7.6195 | N93: Rent shown w/ $1,595.15 add'l figure in source
A94: 1805 | B94: N | C94: 3000 | E94: Harlan | F94: 09/01/23 | G94: 08/31/24 | I94: 2279.88 | J94: 375 | K94: 1.5 | L94: 7.6195 | N94: Month-to-month, roll continues (Hal Harlan 1-18-17)
A95: 1805 | B95: O1, O2, O3 | C95: 9000 | E95: Coda Coffee | F95: 09/01/23 | G95: 08/31/24 | H95: 8/31/24 | I95: 12839.63 | J95: 7125 | K95: 9.5 | L95: 7.6195
A96: WAREHOUSE TOTALS | C96: 197501.99 | D96: 650.92 | I96: $228,439.08 | J96: $107,996.75 | K96: $6.45 blended | N96: Warehouse totals per rent roll
A97: BUILDING TOTAL (Office+Wse) | C97: 215243.83 | D97: 1964.12 | I97: $245,411.12 | J97: $115,474.89 | N97: Building totals per rent roll
A98: OUTSIDE/STORAGE | B98: Franklin - 5898 Franklin (10,000 SF) | C98: 10000 | E98: Keith Werkheiser | F98: 12/01/23 | G98: mo to mo | H98: mo to mo | I98: 1225 | N98: Lease document for this parcel
A99: OUTSIDE/STORAGE | B99: Franklin - 5898 Franklin (6,375 SF) | C99: 6375 | E99: Keith Werkheiser | F99: 05/01/23 | G99: 04/30/25 | H99: 4/30/28 | I99: 1275
A100: OUTSIDE/STORAGE | B100: Franklin (500 SF) | C100: 500 | E100: Colorado Construction Cleaning | F100: 03/01/22 | G100: mo to mo | I100: 50
A101: OUTSIDE/STORAGE | B101: 1900 E. 58th (1,000 SF) | C101: 1000 | E101: P&H Equipment
A102: OUTSIDE/STORAGE | B102: Mapleton (1,000 SF) | C102: 1000 | E102: P&H Equipment
A103: OUTSIDE/STORAGE | B103: Hillside B - 5952 Franklin (17,447.77 SF) | C103: 17447.77 | E103: Lobos Structures, LLC. | F103: 07/01/23 | G103: 06/30/24 | H103: 6/30/24 | I103: 363.49
...

Sheet WALT Summary
A1: CityView Industrial Park - Rent Roll Summary & WALT
A2: WALT = Weighted Average Lease Term remaining to contractual expiry. Occupied suites only (vacant space & common area excluded).
A3: Analysis (valuation) date: | B3: 45473 | C3: CO appraisal date for 2025-26 reassessment (rent roll 6/30/2024).
K4: WALT by Tenant
A5: Tenant | B5: Bldg / Suite | C5: Type | D5: Leased SF | E5: Base $/SF | F5: Base Annual Rent | G5: Lease Expiry | H5: Remaining Term (yrs) | I5: key | K5: Tenant | L5: Leased SF | M5: Base Annual Rent | N5: WALT (yrs)
A6: MR Solutions | B6: 5800 / 101 | C6: Office | D6: 1048 | E6: 14 | F6: =E6*D6 -> 14672 | G6: 45504 | H6: =MAX(0,(G6-$B$3)/365.25) -> 0.084873 | I6: M.R. Solutions | K6: Coda Coffee | L6: =SUMIF($I$6:$I$82,K6,$D$6:$D$82) -> 41257 | M6: =SUMIF($I$6:$I$82,K6,$F$6:$F$82) -> 377983.5 | N6: =SUMPRODUCT(($I$6:$I$82=K6)*$D$6:$D$82*$H$6:$H$82)/L6 -> 0.182617
A7: R. Baker | B7: 5800 / 102 | C7: Office | D7: 960 | E7: 9.78 | F7: =E7*D7 -> 9388.8 | G7: 45473 | H7: =MAX(0,(G7-$B$3)/365.25) -> 0 | I7: R. Baker | K7: Good Bread | L7: =SUMIF($I$6:$I$82,K7,$D$6:$D$82) -> 18813 | M7: =SUMIF($I$6:$I$82,K7,$F$6:$F$82) -> 143247.12 | N7: =SUMPRODUCT(($I$6:$I$82=K7)*$D$6:$D$82*$H$6:$H$82)/L7 -> 0.91718
A8: S&R Environmental Consulting, Inc. | B8: 5800 / 106 | C8: Office | D8: 706 | E8: 10.69 | F8: =E8*D8 -> 7547.14 | G8: 45626 | H8: =MAX(0,(G8-$B$3)/365.25) -> 0.418891 | I8: S&R Environmental Consulting, Inc. | K8: Certified Mapping and Technical Testing Inc. | L8: =SUMIF($I$6:$I$82,K8,$D$6:$D$82) -> 15000 | M8: =SUMIF($I$6:$I$82,K8,$F$6:$F$82) -> 60300 | N8: =SUMPRODUCT(($I$6:$I$82=K8)*$D$6:$D$82*$H$6:$H$82)/L8 -> 0
A9: Global IT Innovative Systems | B9: 5800 / 200, 202 | C9: Office | D9: 3109 | F9: =E9*D9 -> 0 | G9: 45565 | H9: =MAX(0,(G9-$B$3)/365.25) -> 0.251882 | I9: Global IT Innovative Systems | K9: Savory Retail Group | L9: =SUMIF($I$6:$I$82,K9,$D$6:$D$82) -> 14000 | M9: =SUMIF($I$6:$I$82,K9,$F$6:$F$82) -> 74900 | N9: =SUMPRODUCT(($I$6:$I$82=K9)*$D$6:$D$82*$H$6:$H$82)/L9 -> 0.750171
A10: Global IT Innovative Systems | B10: 5800 / 201 | C10: Office | D10: 2115 | E10: 4.31 | F10: =E10*D10 -> 9115.65 | G10: 45565 | H10: =MAX(0,(G10-$B$3)/365.25) -> 0.251882 | I10: Global IT Innovative Systems | K10: Keith's Paint Shop | L10: =SUMIF($I$6:$I$82,K10,$D$6:$D$82) -> 13564 | M10: =SUMIF($I$6:$I$82,K10,$F$6:$F$82) -> 84775 | N10: =SUMPRODUCT(($I$6:$I$82=K10)*$D$6:$D$82*$H$6:$H$82)/L10 -> 0.832307
A11: Global IT Innovative Systems | B11: 5800 / 201a | C11: Office | D11: 1385 | F11: =E11*D11 -> 0 | G11: 45565 | H11: =MAX(0,(G11-$B$3)/365.25) -> 0.251882 | I11: Global IT Innovative Systems | K11: Global IT Innovative Systems | L11: =SUMIF($I$6:$I$82,K11,$D$6:$D$82) -> 12847 | M11: =SUMIF($I$6:$I$82,K11,$F$6:$F$82) -> 20318.644 | N11: =SUMPRODUCT(($I$6:$I$82=K11)*$D$6:$D$82*$H$6:$H$82)/L11 -> 0.251882
A12: WEIL Construction Inc. | B12: 5800 / C | C12: Office | D12: 196 | F12: =E12*D12 -> 0 | G12: 45535 | H12: =MAX(0,(G12-$B$3)/365.25) -> 0.169747 | I12: WEIL Construction | K12: ReEnergize | L12: =SUMIF($I$6:$I$82,K12,$D$6:$D$82) -> 11779 | M12: =SUMIF($I$6:$I$82,K12,$F$6:$F$82) -> 70676.36 | N12: =SUMPRODUCT(($I$6:$I$82=K12)*$D$6:$D$82*$H$6:$H$82)/L12 -> 0.401553
A13: Global IT Innovative Systems | B13: 5800 / CA | C13: Office | D13: 299 | F13: =E13*D13 -> 0 | G13: 45565 | H13: =MAX(0,(G13-$B$3)/365.25) -> 0.251882 | I13: Global IT Innovative Systems | K13: Harlan Bakeries | L13: =SUMIF($I$6:$I$82,K13,$D$6:$D$82) -> 7625 | M13: =SUMIF($I$6:$I$82,K13,$F$6:$F$82) -> 29711.25 | N13: =SUMPRODUCT(($I$6:$I$82=K13)*$D$6:$D$82*$H$6:$H$82)/L13 -> 0.27962
A14: WEIL Construction Inc. | B14: 5800 / E | C14: Office | D14: 196 | F14: =E14*D14 -> 0 | G14: 45535 | H14: =MAX(0,(G14-$B$3)/365.25) -> 0.169747 | I14: WEIL Construction | K14: Inland Island Brewing | L14: =SUMIF($I$6:$I$82,K14,$D$6:$D$82) -> 7115 | M14: =SUMIF($I$6:$I$82,K14,$F$6:$F$82) -> 34268.6 | N14: =SUMPRODUCT(($I$6:$I$82=K14)*$D$6:$D$82*$H$6:$H$82)/L14 -> 0.251882
A15: Colorado Construction Cleaning, Inc. | B15: 5802 / 107 | C15: Office | D15: 2274 | E15: 4.67 | F15: =E15*D15 -> 10619.58 | G15: 45443 | H15: =MAX(0,(G15-$B$3)/365.25) -> 0 | I15: Colorado Construction Cleaning, Inc. | K15: Whatnot Ventures LLC | L15: =SUMIF($I$6:$I$82,K15,$D$6:$D$82) -> 6675 | M15: =SUMIF($I$6:$I$82,K15,$F$6:$F$82) -> 32907.75 | N15: =SUMPRODUCT(($I$6:$I$82=K15)*$D$6:$D$82*$H$6:$H$82)/L15 -> 0.91718
A16: Global IT Innovative Systems | B16: 5802 / 203 | C16: Office | D16: 380 | F16: =E16*D16 -> 0 | G16: 45565 | H16: =MAX(0,(G16-$B$3)/365.25) -> 0.251882 | I16: Global IT Innovative Systems | K16: Santa Fe Mechanical | L16: =SUMIF($I$6:$I$82,K16,$D$6:$D$82) -> 6250 | M16: =SUMIF($I$6:$I$82,K16,$F$6:$F$82) -> 45062.5 | N16: =SUMPRODUCT(($I$6:$I$82=K16)*$D$6:$D$82*$H$6:$H$82)/L16 -> 0.169747
A17: Global IT Innovative Systems | B17: 5802 / 204 | C17: Office | D17: 713 | F17: =E17*D17 -> 0 | G17: 45565 | H17: =MAX(0,(G17-$B$3)/365.25) -> 0.251882 | I17: Global IT Innovative Systems | K17: R&O Heating | L17: =SUMIF($I$6:$I$82,K17,$D$6:$D$82) -> 6000 | M17: =SUMIF($I$6:$I$82,K17,$F$6:$F$82) -> 42000 | N17: =SUMPRODUCT(($I$6:$I$82=K17)*$D$6:$D$82*$H$6:$H$82)/L17 -> 0.084873
A18: Global IT Innovative Systems | B18: 5802 / 205 | C18: Office | D18: 736 | F18: =E18*D18 -> 0 | G18: 45565 | H18: =MAX(0,(G18-$B$3)/365.25) -> 0.251882 | I18: Global IT Innovative Systems | K18: M.R. Solutions | L18: =SUMIF($I$6:$I$82,K18,$D$6:$D$82) -> 5048 | M18: =SUMIF($I$6:$I$82,K18,$F$6:$F$82) -> 48672 | N18: =SUMPRODUCT(($I$6:$I$82=K18)*$D$6:$D$82*$H$6:$H$82)/L18 -> 0.084873
A19: Global IT Innovative Systems | B19: 5802 / 206 | C19: Office | D19: 713 | F19: =E19*D19 -> 0 | G19: 45565 | H19: =MAX(0,(G19-$B$3)/365.25) -> 0.251882 | I19: Global IT Innovative Systems | K19: Happel & Associates Inc. | L19: =SUMIF($I$6:$I$82,K19,$D$6:$D$82) -> 5000 | M19: =SUMIF($I$6:$I$82,K19,$F$6:$F$82) -> 32450 | N19: =SUMPRODUCT(($I$6:$I$82=K19)*$D$6:$D$82*$H$6:$H$82)/L19 -> 0.169747
A20: Global IT Innovative Systems | B20: 5802 / Storage | C20: Office | D20: 76 | F20: =E20*D20 -> 0 | G20: 45565 | H20: =MAX(0,(G20-$B$3)/365.25) -> 0.251882 | I20: Global IT Innovative Systems | K20: Reliant Dry Ice | L20: =SUMIF($I$6:$I$82,K20,$D$6:$D$82) -> 5000 | M20: =SUMIF($I$6:$I$82,K20,$F$6:$F$82) -> 31000 | N20: =SUMPRODUCT(($I$6:$I$82=K20)*$D$6:$D$82*$H$6:$H$82)/L20 -> 0.336756
A21: P&H Equipment | B21: 5802 / Unit M-105 | C21: Office | D21: 584 | E21: 6.73 | F21: =E21*D21 -> 3930.32 | G21: 45535 | H21: =MAX(0,(G21-$B$3)/365.25) -> 0.169747 | I21: P&H Equipment | K21: Allcomm Data Supplies Inc. | L21: =SUMIF($I$6:$I$82,K21,$D$6:$D$82) -> 4000 | M21: =SUMIF($I$6:$I$82,K21,$F$6:$F$82) -> 21600 | N21: =SUMPRODUCT(($I$6:$I$82=K21)*$D$6:$D$82*$H$6:$H$82)/L21 -> 0.169747
A22: Keiths Paint Shop LLC | B22: 1609 / A-B | C22: Warehouse | D22: 3500 | E22: 6.25 | F22: =E22*D22 -> 21875 | G22: 45777 | H22: =MAX(0,(G22-$B$3)/365.25) -> 0.832307 | I22: Keith's Paint Shop | K22: Colorado Comfort Air | L22: =SUMIF($I$6:$I$82,K22,$D$6:$D$82) -> 3760 | M22: =SUMIF($I$6:$I$82,K22,$F$6:$F$82) -> 23312 | N22: =SUMPRODUCT(($I$6:$I$82=K22)*$D$6:$D$82*$H$6:$H$82)/L22 -> 0
A23: Keiths Paint Shop LLC | B23: 1609 / C | C23: Warehouse | D23: 1750 | E23: 6.25 | F23: =E23*D23 -> 10937.5 | G23: 45777 | H23: =MAX(0,(G23-$B$3)/365.25) -> 0.832307 | I23: Keith's Paint Shop | K23: Miggy & Ernie's | L23: =SUMIF($I$6:$I$82,K23,$D$6:$D$82) -> 3550 | M23: =SUMIF($I$6:$I$82,K23,$F$6:$F$82) -> 19276.5 | N23: =SUMPRODUCT(($I$6:$I$82=K23)*$D$6:$D$82*$H$6:$H$82)/L23 -> 0
A24: Keiths Paint Shop LLC | B24: 1609 / D-E | C24: Warehouse | D24: 3250 | E24: 6.25 | F24: =E24*D24 -> 20312.5 | G24: 45777 | H24: =MAX(0,(G24-$B$3)/365.25) -> 0.832307 | I24: Keith's Paint Shop | K24: Savory Spice | L24: =SUMIF($I$6:$I$82,K24,$D$6:$D$82) -> 3005 | M24: =SUMIF($I$6:$I$82,K24,$F$6:$F$82) -> 19141.85 | N24: =SUMPRODUCT(($I$6:$I$82=K24)*$D$6:$D$82*$H$6:$H$82)/L24 -> 0.91718
A25: Keiths Paint Shop LLC | B25: 1609 / F | C25: Warehouse | D25: 1564 | E25: 6.25 | F25: =E25*D25 -> 9775 | G25: 45777 | H25: =MAX(0,(G25-$B$3)/365.25) -> 0.832307 | I25: Keith's Paint Shop | K25: REDCO Tire | L25: =SUMIF($I$6:$I$82,K25,$D$6:$D$82) -> 2562 | M25: =SUMIF($I$6:$I$82,K25,$F$6:$F$82) -> 15372 | N25: =SUMPRODUCT(($I$6:$I$82=K25)*$D$6:$D$82*$H$6:$H$82)/L25 -> 0
A26: Adessa | B26: 1609 / G | C26: Warehouse | D26: 1750 | E26: 6.18 | F26: =E26*D26 -> 10815 | G26: 45473 | H26: =MAX(0,(G26-$B$3)/365.25) -> 0 | I26: Adessa | K26: Colorado Construction Cleaning, Inc. | L26: =SUMIF($I$6:$I$82,K26,$D$6:$D$82) -> 2274 | M26: =SUMIF($I$6:$I$82,K26,$F$6:$F$82) -> 10619.58 | N26: =SUMPRODUCT(($I$6:$I$82=K26)*$D$6:$D$82*$H$6:$H$82)/L26 -> 0
A27: Keiths Paint Shop LLC | B27: 1609 / H-I | C27: Warehouse | D27: 3500 | E27: 6.25 | F27: =E27*D27 -> 21875 | G27: 45777 | H27: =MAX(0,(G27-$B$3)/365.25) -> 0.832307 | I27: Keith's Paint Shop | K27: P&H Equipment | L27: =SUMIF($I$6:$I$82,K27,$D$6:$D$82) -> 2059 | M27: =SUMIF($I$6:$I$82,K27,$F$6:$F$82) -> 13517.82 | N27: =SUMPRODUCT(($I$6:$I$82=K27)*$D$6:$D$82*$H$6:$H$82)/L27 -> 0.169747
A28: Certified Mapping and Technical Testing Inc. | B28: 1707-09 / A07-B09 | C28: Warehouse | D28: 15000 | E28: 4.02 | F28: =E28*D28 -> 60300 | G28: 45473 | H28: =MAX(0,(G28-$B$3)/365.25) -> 0 | I28: Certified Mapping and Technical Testing Inc. | K28: Mr. Dino's Baths | L28: =SUMIF($I$6:$I$82,K28,$D$6:$D$82) -> 2000 | M28: =SUMIF($I$6:$I$82,K28,$F$6:$F$82) -> 13500 | N28: =SUMPRODUCT(($I$6:$I$82=K28)*$D$6:$D$82*$H$6:$H$82)/L28 -> 0.832307
A29: Good Bread | B29: 1721-23 / A21 | C29: Warehouse | D29: 7500 | E29: 8.24 | F29: =E29*D29 -> 61800 | G29: 45808 | H29: =MAX(0,(G29-$B$3)/365.25) -> 0.91718 | I29: Good Bread | K29: RossComm LLC | L29: =SUMIF($I$6:$I$82,K29,$D$6:$D$82) -> 2000 | M29: =SUMIF($I$6:$I$82,K29,$F$6:$F$82) -> 0 | N29: =SUMPRODUCT(($I$6:$I$82=K29)*$D$6:$D$82*$H$6:$H$82)/L29 -> 0
A30: Good Bread | B30: 1721-23 / B23 | C30: Warehouse | D30: 2728 | E30: 8.24 | F30: =E30*D30 -> 22478.72 | G30: 45808 | H30: =MAX(0,(G30-$B$3)/365.25) -> 0.91718 | I30: Good Bread | K30: Adessa | L30: =SUMIF($I$6:$I$82,K30,$D$6:$D$82) -> 1750 | M30: =SUMIF($I$6:$I$82,K30,$F$6:$F$82) -> 10815 | N30: =SUMPRODUCT(($I$6:$I$82=K30)*$D$6:$D$82*$H$6:$H$82)/L30 -> 0
A31: Good Bread | B31: 1721-23 / C23 w/h | C31: Warehouse | D31: 4557 | E31: 8.24 | F31: =E31*D31 -> 37549.68 | G31: 45808 | H31: =MAX(0,(G31-$B$3)/365.25) -> 0.91718 | I31: Good Bread | K31: R. Baker | L31: =SUMIF($I$6:$I$82,K31,$D$6:$D$82) -> 960 | M31: =SUMIF($I$6:$I$82,K31,$F$6:$F$82) -> 9388.8 | N31: =SUMPRODUCT(($I$6:$I$82=K31)*$D$6:$D$82*$H$6:$H$82)/L31 -> 0
A32: Good Bread Freezer | B32: 1721-23 / C23 w/h freeze | C32: Warehouse | D32: 278 | E32: 8.24 | F32: =E32*D32 -> 2290.72 | G32: 45808 | H32: =MAX(0,(G32-$B$3)/365.25) -> 0.91718 | I32: Good Bread | K32: S&R Environmental Consulting, Inc. | L32: =SUMIF($I$6:$I$82,K32,$D$6:$D$82) -> 706 | M32: =SUMIF($I$6:$I$82,K32,$F$6:$F$82) -> 7547.14 | N32: =SUMPRODUCT(($I$6:$I$82=K32)*$D$6:$D$82*$H$6:$H$82)/L32 -> 0.418891
A33: Coda Coffee Company | B33: 1751 / A | C33: Warehouse | D33: 4866 | E33: 9.5 | F33: =E33*D33 -> 46227 | G33: 45535 | H33: =MAX(0,(G33-$B$3)/365.25) -> 0.169747 | I33: Coda Coffee | K33: WEIL Construction | L33: =SUMIF($I$6:$I$82,K33,$D$6:$D$82) -> 392 | M33: =SUMIF($I$6:$I$82,K33,$F$6:$F$82) -> 0 | N33: =SUMPRODUCT(($I$6:$I$82=K33)*$D$6:$D$82*$H$6:$H$82)/L33 -> 0.169747
A34: Coda Coffee Company | B34: 1751 / B-1 | C34: Warehouse | D34: 1133 | E34: 9.5 | F34: =E34*D34 -> 10763.5 | G34: 45535 | H34: =MAX(0,(G34-$B$3)/365.25) -> 0.169747 | I34: Coda Coffee | K34: TOTAL / WALT | L34: =SUM(L6:L33) -> 204991 | M34: =SUM(M6:M33) -> 1292363.4 | N34: =SUMPRODUCT(L6:L33,N6:N33)/L34 -> 0.365557
A35: Coda Coffee Company | B35: 1751 / B-2 | C35: Warehouse | D35: 1921 | E35: 9.5 | F35: =E35*D35 -> 18249.5 | G35: 45535 | H35: =MAX(0,(G35-$B$3)/365.25) -> 0.169747 | I35: Coda Coffee
A36: Coda Coffee Company | B36: 1751 / B-3 | C36: Warehouse | D36: 3450 | E36: 9.5 | F36: =E36*D36 -> 32775 | G36: 45535 | H36: =MAX(0,(G36-$B$3)/365.25) -> 0.169747 | I36: Coda Coffee
A37: Coda Coffee Company | B37: 1751 / D east | C37: Warehouse | D37: 856 | E37: 9.5 | F37: =E37*D37 -> 8132 | G37: 45535 | H37: =MAX(0,(G37-$B$3)/365.25) -> 0.169747 | I37: Coda Coffee
A38: Coda Coffee Company | B38: 1751 / D west | C38: Warehouse | D38: 993 | E38: 9.5 | F38: =E38*D38 -> 9433.5 | G38: 45535 | H38: =MAX(0,(G38-$B$3)/365.25) -> 0.169747 | I38: Coda Coffee
A39: Reliant Dry Ice | B39: 1751 / E | C39: Warehouse | D39: 5000 | E39: 6.2 | F39: =E39*D39 -> 31000 | G39: 45596 | H39: =MAX(0,(G39-$B$3)/365.25) -> 0.336756 | I39: Reliant Dry Ice
A40: Harlan Bakeries | B40: 1761 / A | C40: Warehouse | D40: 2625 | E40: 4.85 | F40: =E40*D40 -> 12731.25 | G40: 45535 | H40: =MAX(0,(G40-$B$3)/365.25) -> 0.169747 | I40: Harlan Bakeries
A41: Good Bread Inc. | B41: 1761 / A-5 | C41: Warehouse | D41: 3750 | E41: 5.1008 | F41: =E41*D41 -> 19128 | G41: 45808 | H41: =MAX(0,(G41-$B$3)/365.25) -> 0.91718 | I41: Good Bread
A42: Santa Fe Mechanical | B42: 1761 / A3 | C42: Warehouse | D42: 1250 | E42: 7.21 | F42: =E42*D42 -> 9012.5 | G42: 45535 | H42: =MAX(0,(G42-$B$3)/365.25) -> 0.169747 | I42: Santa Fe Mechanical
A43: Santa Fe Mechanical | B43: 1761 / A4 | C43: Warehouse | D43: 5000 | E43: 7.21 | F43: =E43*D43 -> 36050 | G43: 45535 | H43: =MAX(0,(G43-$B$3)/365.25) -> 0.169747 | I43: Santa Fe Mechanical
A44: Whatnot Ventures LLC | B44: 1761 (cont.) / A1 | C44: Warehouse | D44: 6675 | E44: 4.93 | F44: =E44*D44 -> 32907.75 | G44: 45808 | H44: =MAX(0,(G44-$B$3)/365.25) -> 0.91718 | I44: Whatnot Ventures LLC
A45: Inland Island Brewing | B45: 1761 (cont.) / A2 | C45: Warehouse | D45: 3200 | E45: 4.54 | F45: =E45*D45 -> 14528 | G45: 45565 | H45: =MAX(0,(G45-$B$3)/365.25) -> 0.251882 | I45: Inland Island Brewing
A46: Inland Island Brewing | B46: 1761 (cont.) / B | C46: Warehouse | D46: 2765 | E46: 4.54 | F46: =E46*D46 -> 12553.1 | G46: 45565 | H46: =MAX(0,(G46-$B$3)/365.25) -> 0.251882 | I46: Inland Island Brewing
... A61: Harlan Bakeries Co LLC | B61: 1791 / M | C61: Warehouse | D61: 2000 | E61: 6.24 | F61: =E61*D61 -> 12480 | G61: 45688 | H61: =MAX(0,(G61-$B$3)/365.25) -> 0.588638 | I61: Harlan Bakeries
A62: Mr. Dino's Baths | B62: 1791 / N | C62: Warehouse | D62: 2000 | F62: =E62*D62 -> 0 | G62: 45443 | H62: =MAX(0,(G62-$B$3)/365.25) -> 0 | I62: Mr. Dino's Baths
A63: Savory Retail Group, LLC | B63: 1805 / A,B | C63: Warehouse | D63: 3000 | E63: 5.35 | F63: =E63*D63 -> 16050 | G63: 45747 | H63: =MAX(0,(G63-$B$3)/365.25) -> 0.750171 | I63: Savory Retail Group
A64: Savory | B64: 1805 / C | C64: Warehouse | D64: 3000 | E64: 5.35 | F64: =E64*D64 -> 16050 | G64: 45747 | H64: =MAX(0,(G64-$B$3)/365.25) -> 0.750171 | I64: Savory Retail Group
A65: Savory | B65: 1805 / D | C65: Warehouse | D65: 2000 | E65: 5.35 | F65: =E65*D65 -> 10700 | G65: 45747 | H65: =MAX(0,(G65-$B$3)/365.25) -> 0.750171 | I65: Savory Retail Group
A66: Savory | B66: 1805 / E,F,G | C66: Warehouse | D66: 6000 | E66: 5.35 | F66: =E66*D66 -> 32100 | G66: 45747 | H66: =MAX(0,(G66-$B$3)/365.25) -> 0.750171 | I66: Savory Retail Group
A67: M.R. Solutions, Inc. | B67: 1805 / H | C67: Warehouse | D67: 2000 | E67: 8.5 | F67: =E67*D67 -> 17000 | G67: 45504 | H67: =MAX(0,(G67-$B$3)/365.25) -> 0.084873 | I67: M.R. Solutions
A68: M.R. Solutions, Inc. | B68: 1805 / I | C68: Warehouse | D68: 2000 | E68: 8.5 | F68: =E68*D68 -> 17000 | G68: 45504 | H68: =MAX(0,(G68-$B$3)/365.25) -> 0.084873 | I68: M.R. Solutions
A69: P&H Equipment | B69: 1805 / J (Ne) | C69: Warehouse | D69: 1475 | E69: 6.5 | F69: =E69*D69 -> 9587.5 | G69: 45535 | H69: =MAX(0,(G69-$B$3)/365.25) -> 0.169747 | I69: P&H Equipment
A70: ReEnergize | B70: 1805 / J (Nw) | C70: Warehouse | D70: 440 | E70: 5.72 | F70: =E70*D70 -> 2516.8 | G70: 45443 | H70: =MAX(0,(G70-$B$3)/365.25) -> 0 | I70: ReEnergize
A71: ReEnergize | B71: 1805 / J-s | C71: Warehouse | D71: 2172 | E71: 5.72 | F71: =E71*D71 -> 12423.84 | G71: 45443 | H71: =MAX(0,(G71-$B$3)/365.25) -> 0 | I71: ReEnergize
A72: ReEnergize | B72: 1805 / K | C72: Warehouse | D72: 1325 | E72: 5.72 | F72: =E72*D72 -> 7579 | G72: 45443 | H72: =MAX(0,(G72-$B$3)/365.25) -> 0 | I72: ReEnergize
A73: ReEnergize | B73: 1805 / K office | C73: Warehouse | D73: 680 | E73: 5.72 | F73: =E73*D73 -> 3889.6 | G73: 45443 | H73: =MAX(0,(G73-$B$3)/365.25) -> 0 | I73: ReEnergize
A74: ReEnergize | B74: 1805 / L | C74: Warehouse | D74: 2005 | E74: 5.72 | F74: =E74*D74 -> 11468.6 | G74: 45443 | H74: =MAX(0,(G74-$B$3)/365.25) -> 0 | I74: ReEnergize
... A77: Coda Coffee | B77: 1805 / O1, O2, O3 | C77: Warehouse | D77: 9000 | E77: 9.5 | F77: =E77*D77 -> 85500 | G77: 45535 | H77: =MAX(0,(G77-$B$3)/365.25) -> 0.169747 | I77: Coda Coffee
A78: Global IT Innovative Systems | B78: 5806 / A-n | C78: Warehouse | D78: 875 | F78: =E78*D78 -> 0 | G78: 45565 | H78: =MAX(0,(G78-$B$3)/365.25) -> 0.251882 | I78: Global IT Innovative Systems
A79: Global IT Innovative Systems | B79: 5806 / A-s | C79: Warehouse | D79: 875 | F79: =E79*D79 -> 0 | G79: 45565 | H79: =MAX(0,(G79-$B$3)/365.25) -> 0.251882 | I79: Global IT Innovative Systems
A80: Global IT Innovative Systems | B80: 5806 / B-n | C80: Warehouse | D80: 350 | E80: 16.61 | F80: =E80*D80 -> 5813.5 | G80: 45565 | H80: =MAX(0,(G80-$B$3)/365.25) -> 0.251882 | I80: Global IT Innovative Systems
A81: Global IT Innovative Systems | B81: 5806 / B-s | C81: Warehouse | D81: 1221 | E81: 4.414 | F81: =E81*D81 -> 5389.494 | G81: 45565 | H81: =MAX(0,(G81-$B$3)/365.25) -> 0.251882 | I81: Global IT Innovative Systems
A82: Miggy & Ernie's | B82: 5808 / A | C82: Warehouse | D82: 3550 | E82: 5.43 | F82: =E82*D82 -> 19276.5 | G82: 45350 | H82: =MAX(0,(G82-$B$3)/365.25) -> 0 | I82: Miggy & Ernie's
A84: TOTAL / WALT (all occupied) | D84: =SUM(D6:D82) -> 204991 | F84: =SUM(F6:F82) -> 1292363.4 | H84: =SUMPRODUCT(D6:D82,H6:H82)/D84 -> 0.365557
A86: WALT (years):
A87: SF-weighted (all) | B87: =SUMPRODUCT(D6:D82,H6:H82)/SUM(D6:D82) -> 0.365557
A88: Rent-weighted (all) | B88: =SUMPRODUCT(F6:F82,H6:H82)/SUM(F6:F82) -> 0.372054
A89: SF-weighted - Office | B89: =SUMPRODUCT((C6:C82="Office")*D6:D82*H6:H82)/SUMIF(C6:C82,"Office",D6:D82) -> 0.190432
A90: SF-weighted - Warehouse | B90: =SUMPRODUCT((C6:C82="Warehouse")*D6:D82*H6:H82)/SUMIF(C6:C82,"Warehouse",D6:D82) -> 0.379872
A92: Holdover/expired leases (expiry <= analysis date) contribute 0 to remaining term. Short WALT reflects predominantly 1-year terms rolling to market.

Sheet Rent Roll - Dec 2023
A1: CityView Industrial Park - Rent Roll (Rent Roll - Dec 2023)
A2: Source rent roll dated: November 22, 2023 (for December 2023)
A3: Source: Sterling Property Tax Specialists appeal package (Exhibit F), Adams County 2026 NOV protest
A5: Building/Unit Group | B5: Space | C5: Leased SF | D5: Vacant SF | E5: Tenant | F5: Lease Start | G5: Term Expires | H5: Renewal/Option Expires | I5: Total Monthly Rent | J5: Base Monthly Rent | K5: Annual Rate PSF | L5: CAM PSF (Annual) | M5: Notes
A6: 5800 | B6: 100 | C6: 500 | E6: CVP Management Office | M6: Management office - no rent
A7: 5800 | B7: 101 | C7: 1048 | E7: MR Solutions | F7: 08/01/23 | G7: 7/31/24 | I7: 1981.77 | J7: 1222.67 | K7: 14 | L7: 8.692 | M7: Office only
A8: 5800 | B8: 102 | C8: 960 | E8: R. Baker | F8: 09/01/22 | G8: 12/30/23 | H8: 12/30/23 | I8: 1477.76 | J8: 782.4 | K8: 9.78 | L8: 8.692 | M8: Month-to-month lease
A9: 5800 | B9: 104A | D9: 121 | E9: Vacant
A10: 5800 | B10: 104B | D10: 121 | E10: Vacant
A11: 5800 | B11: 104C | D11: 121 | E11: Vacant
A12: 5800 | B12: 104 | C12: 722 | E12: Training Room 103
A13: 5800 | B13: CA | C13: 1435 | E13: Common Area
A14: 5800 | B14: A | C14: 196 | E14: STAT Medical Resources, LLC | F14: 12/01/22 | G14: 11/30/23 | H14: 11/30/23 | I14: 560
A15: 5800 | B15: B | C15: 121 | E15: Vacant
A16: 5800 | B16: C | C16: 196 | E16: WEIL Construction Inc. | F16: 09/01/22 | G16: 08/31/24 | H16: 8/31/23 | I16: 535.57
A17: 5800 | B17: D | C17: 121 | E17: Vacant
A18: 5800 | B18: E | C18: 196 | E18: WEIL Construction Inc. | F18: 07/01/23 | G18: 07/01/23 | H18: 8/31/24 | I18: 515.15
A19: 5800 | B19: Copy Room | C19: 107.2 | E19: Vacant
A20: 5800 | B20: 106 | C20: 706 | E20: S&R Environmental Consulting, Inc. | F20: 12/01/22 | G20: 11/30/23 | H20: 11/30/23 | I20: 1116.19 | J20: 604.81 | K20: 10.28 | L20: 8.692 | M20: Contacted for renewal
A21: 5800 | B21: 201 | C21: 2114.9 | E21: Global IT Innovative Systems | F21: 10/01/23 | G21: 09/30/24 | H21: 9/30/24 | I21: 7220.21 | J21: 3631.65 | K21: 4.31 | L21: 4.25
A22: 5800 | B22: 201a | C22: 1385.1 | E22: Global IT Innovative Systems
A23: 5800 | B23: 200, 202 | C23: 3108.59 | E23: Global IT Innovative Systems
A24: 5800 | B24: CA | C24: 299.4 | E24: Global IT Innovative Systems
A25: 5802 | B25: 107 | C25: 2274 | E25: Colorado Construction Cleaning, Inc. | F25: 06/01/23 | G25: 05/31/24 | H25: 5/31/24 | I25: 1986.96 | J25: 884.97 | K25: 4.67 | L25: 5.8153
A26: 5802 | B26: 203 | C26: 380.25 | E26: Global IT Innovative Systems | M26: Input #'s manually
A27: 5802 | B27: 205 | C27: 736 | E27: Global IT Innovative Systems | M27: No cleaning or supplies
A28: 5802 | B28: 204 | C28: 713 | E28: Global IT Innovative Systems
A29: 5802 | B29: 206 | C29: 713 | E29: Global IT Innovative Systems
A30: 5802 | B30: Storage | C30: 75.6 | E30: Global IT Innovative Systems
A31: 5802 | B31: Unit M-105 | C31: 584 | E31: P&H Equipment | F31: 09/01/23 | G31: 08/31/24 | H31: 8/31/26 | I31: 750.54 | J31: 327.53 | K31: 6.73 | L31: 8.692
A32: 5800/5802 OFFICE TOTALS | C32: 17741.84 | D32: 1313.2 | I32: $16,144.15 | J32: $7,454.02 | K32: $4.15 blended | M32: Office totals per rent roll
A33: 5806 | B33: A-n | C33: 875 | E33: Global IT Innovative Systems | G33: 09/30/24 | H33: 09/30/24
A34: 5806 | B34: A-s | C34: 875 | E34: Global IT Innovative Systems
A35: 5806 | B35: B-s | C35: 1221 | E35: Global IT Innovative Systems | F35: 10/01/23 | I35: 1202.19 | J35: 414.34 | K35: 4.414 | L35: 4.5088 | M35: Input #'s manually
A36: 5806 | B36: B-n | C36: 350 | E36: Global IT Innovative Systems | F36: 10/01/23 | G36: 09/30/24 | H36: 09/30/24 | I36: 484.4 | J36: 484.4
A37: 5808 | B37: A | C37: 3550 | E37: Miggy & Ernie's Demo | G37: 2/28/2024 | H37: 2/28/24 | I37: 3326.73 | J37: 1606.38 | K37: 5.43 | L37: 5.82 | M37: First Right of Refusal: Keiths Paint Shop LLC 2/28/24; lease value noted $44,986.00
A38: 1609 | B38: A-B | C38: 3500 | E38: Keiths Paint Shop LLC | F38: 5/1/2023 | G38: 4/30/2024 | H38: 4/30/2028 | I38: 3446.13 | J38: 1750 | K38: 6 | L38: 5.82
A39: 1609 | B39: C | C39: 1750 | E39: Keiths Paint Shop LLC | F39: 5/1/2023 | G39: 4/30/2024 | H39: 4/30/2028 | I39: 1723.06 | J39: 875 | K39: 6 | L39: 5.82
A40: 1609 | B40: D-E | C40: 3250 | E40: REDCO TIRE | F40: 08/01/22 | G40: 07/31/23 | H40: 7/31/25 | I40: 2984.26 | J40: 1409.28 | K40: 5.2035 | L40: 5.8153 | M40: First Right of Refusal: Keiths Paint Shop LLC
A41: 1609 | B41: F | C41: 1564 | E41: REDCO TIRE | F41: 08/01/22 | G41: 07/31/23 | H41: 7/31/25 | I41: 1436.12 | J41: 678.19 | K41: 5.2035 | L41: 5.8153 | M41: First Right of Refusal: Keiths Paint Shop LLC
A42: 1609 | B42: G | C42: 1751 | E42: Adessa | F42: 07/01/22 | G42: 06/30/23 | H42: 6/30/25 | I42: 1723.06 | J42: 875 | K42: 6 | L42: 5.8153 | M42: First Right of Refusal: Keiths Paint Shop LLC
A43: 1609 | B43: H-I | C43: 3500 | E43: Keiths Paint Shop LLC | F43: 5/1/2023 | G43: 4/30/2024 | H43: 4/30/2028 | I43: 3446.13 | J43: 1750 | K43: 6 | L43: 5.82
A44: 1707-09 | B44: A07-B09 | C44: 15000 | E44: Certified Mapping and Technical Testing Inc. | F44: 07/01/22 | G44: 06/30/2023 | H44: 6/30/25 | I44: 8791.63 | J44: 4875 | K44: 3.9 | L44: 3.1333 | M44: NO TAXES; partially exempt entity
A45: 1721-23 | B45: A21 | C45: 7500 | E45: Good Bread | F45: 06/01/23 | G45: 05/31/24 | H45: 5/31/28 | I45: 8940.81 | J45: 4856.25 | K45: 8 | L45: 5.8153 | M45: Note: $7,106.32 upgrades credited Aug 2012; total upgrades $14,212.63 + 2 bathrooms $5,800 = $20,012.63
A46: 1721-23 | B46: B23 | C46: 2728.17 | E46: Good Bread | F46: 06/01/23 | G46: 05/31/24 | H46: 5/31/28 | I46: 3140.87 | J46: 1818.78 | K46: 8 | L46: 5.8153
A47: 1721-23 | B47: C23 w/h freeze | C47: 277.98 | E47: Good Bread Freezer | F47: 06/01/23 | G47: 05/31/24 | H47: 5/31/28 | I47: 320.03 | J47: 185.32 | K47: 8 | L47: 5.8153
A48: 1721-23 | B48: C23 w/h | C48: 4557.12 | E48: Good Bread | F48: 06/01/23 | G48: 05/31/24 | H48: 5/31/28 | I48: 5246.5 | J48: 3038.08 | K48: 8 | L48: 5.8153
A49: 1751 | B49: A | C49: 4866.3 | E49: Coda Coffee Company | F49: 09/01/22 | G49: 08/31/23 | H49: 8/31/24 | I49: 6295.74 | J49: 3852.49 | K49: 9.5 | L49: 5.82
A50: 1751 | B50: B-2 | C50: 1921.48 | E50: Coda Coffee Company | F50: 09/01/22 | G50: 08/31/23 | H50: 8/31/24 | I50: 2452.34 | J50: 1521.17 | K50: 9.5 | L50: 5.82
A51: 1751 | B51: B-1 | C51: 1132.83 | E51: Coda Coffee Company | F51: 09/01/22 | G51: 08/31/23 | H51: 8/31/24 | I51: 1445.8 | J51: 896.82 | K51: 9.5 | L51: 5.82
A52: 1751 | B52: B-3 | C52: 3450 | E52: Coda Coffee Company | F52: 09/01/22 | G52: 08/31/23 | H52: 8/31/24 | I52: 4403.15 | J52: 2731.25 | K52: 9.5 | L52: 5.82
A53: 1751 | B53: D east | C53: 855.88 | E53: Coda Coffee Company | F53: 09/01/22 | G53: 08/31/23 | H53: 08/31/24 | I53: 1092.34 | J53: 677.57 | K53: 9.5 | L53: 5.82
A54: 1751 | B54: D 2nd floor | C54: 650.92 | E54: Unoccupied (2nd floor small storage) | F54: 09/01/21
A55: 1751 | B55: D west | C55: 993.08 | E55: Coda Coffee Company | F55: 9/1/2023 | G55: 8/31/2024 | H55: 08/31/24 | I55: 1267.44 | J55: 786.19 | K55: 9.5 | L55: 5.82
A56: 1751 | B56: E | C56: 5000 | E56: Reliant Dry Ice | F56: 11/1/2023 | G56: 10/31/2024 | H56: 10/31/25 | I56: 5006.38 | J56: 2583.33 | K56: 6.2 | L56: 5.8153
A57: 1791 | B57: A | C57: 5157 | E57: ReEnergize | F57: 06/01/23 | G57: 05/31/24 | H57: 5/31/25 | I57: 5112.01 | J57: 2612.88 | K57: 6.08 | L57: 5.8153
A58: 1791 | B58: B | C58: 4000 | E58: Coda Coffee Company | F58: 09/01/23 | G58: 08/31/24 | H58: 8/31/24 | I58: 5105.1 | J58: 3166.67 | K58: 9.5 | L58: 5.8153
A59: 1791 | B59: C & D | C59: 4000 | E59: Allcomm Data Supplies Inc. | F59: 09/01/22 | G59: 08/31/24 | H59: 8/31/26 | I59: 3738.43 | J59: 1800 | K59: 5.4 | L59: 5.8153
A60: 1791 | B60: E | C60: 2000 | E60: RossComm LLC | F60: 05/01/23 | G60: 04/30/24 | H60: 4/30/25 | I60: 2052.55 | J60: 1083.33 | K60: 6.5 | L60: 5.8153
A61: 1791 | B61: F | C61: 2000 | E61: R&O Heating Inc. | F61: 08/01/23 | G61: 07/31/24 | H61: 7/31/26 | I61: 2180.88 | J61: 1166.67 | K61: 7 | L61: 5.8153
A62: 1791 | B62: G | C62: 2000 | E62: R&O Heating Inc. | F62: 08/01/23 | G62: 07/31/24 | H62: 7/31/26 | I62: 2135.88 | J62: 1166.67 | K62: 7 | L62: 5.8153
A63: 1791 | B63: H | C63: 2000 | E63: R&O Heating Inc. | F63: 08/01/23 | G63: 07/31/24 | H63: 7/31/26 | I63: 2135.88 | J63: 1166.67 | K63: 7 | L63: 5.8153
A64: 1791 | B64: I & J | C64: 4000 | E64: Envigo/Vanguard | F64: 06/01/23 | G64: 05/31/24 | H64: 5/31/26 | I64: 3851.77 | J64: 1913.33 | K64: 5.74 | L64: 5.8153
A65: 1791 | B65: K & L | C65: 4000 | E65: Envigo/Vanguard | F65: 06/01/23 | G65: 05/31/24 | H65: 5/13/26 | I65: 3851.77 | J65: 1913.33 | K65: 5.74 | L65: 5.8153
A66: 1791 | B66: M | C66: 2000 | E66: Harlan Bakeries Co LLC | F66: 02/01/23 (roll cont. 1-18-17) | G66: 01/31/24 | H66: 1/31/24 | I66: 1969.22 | J66: 1000 | K66: 6 | L66: 5.8153
... A80: 1761 (cont.) | B80: B add on | C80: 1150 | E80: Inland Island Brewing | F80: 10/01/23 | G80: 09/30/24 | H80: 9/30/27 | I80: 1156.26 | J80: 598.96 | K80: 6.25 | L80: 5.8153
A81: 1761 (cont.) | B81: C&D | C81: 6465 | E81: Coda Coffee | F81: 10/01/23 | G81: 09/30/24 | H81: 3/31/25 | I81: 8251.12 | J81: 5118.13 | K81: 9.5 | L81: 5.8153 | M81: Increase in September
A82: 1805 | B82: A,B | C82: 3000 | E82: Savory Retail Group, LLC | F82: 04/01/23 | G82: 03/31/24 | H82: 03/31/30 | I82: 3426.99 | J82: 1300 | K82: 5.2 | L82: 5.8153
A83: 1805 | B83: C | C83: 3000 | E83: Savory | F83: 04/01/23 | G83: 03/31/24 | H83: 03/31/30 | I83: 2753.83 | J83: 1300 | K83: 5.2 | L83: 5.8153 | M83: 180-day notice from tenant to continue
A84: 1805 | B84: D | C84: 2000 | E84: Savory | F84: 04/01/23 | G84: 03/31/24 | H84: 03/31/30 | I84: 1835.88 | J84: 866.67 | K84: 5.2 | L84: 5.8153 | M84: 180-day notice from tenant to continue
A85: 1805 | B85: E,F,G | C85: 6000 | E85: Savory | F85: 04/01/23 | G85: 03/31/24 | H85: 03/31/30 | I85: 5507.65 | J85: 2600 | K85: 5.2 | L85: 5.8153 | M85: 180-day notice from tenant to continue
A86: 1805 | B86: H | C86: 2000 | E86: M.R. Solutions, Inc. | F86: 08/01/23 | G86: 07/31/24 | H86: 7/31/24 | I86: 2385.88 | J86: 1416.67 | K86: 8.5 | L86: 5.8153
A87: 1805 | B87: I | C87: 2000 | E87: M.R. Solutions, Inc. | F87: 08/01/23 | G87: 07/31/24 | H87: 7/31/24 | I87: 2385.88 | J87: 1416.67 | K87: 8.5 | L87: 5.8153
A88: 1805 | B88: J-s | C88: 2172 | E88: ReEnergize | F88: 06/01/23 | G88: 05/31/24 | H88: 5/31/24 | I88: 2182.89 | J88: 1035.32 | K88: 5.72 | L88: 5.8153
A89: 1805 | B89: J (Ne) | C89: 1475 | E89: P&H Equipment | F89: 09/01/23 | G89: 08/31/24 | H89: 8/31/2026 | I89: 1513.76 | J89: 798.96 | K89: 6.5 | L89: 5.8153
A90: 1805 | B90: J (Nw) | C90: 440 | E90: ReEnergize | F90: 06/01/23 | G90: 05/31/24 | H90: 5/31/24 | I90: 422.97 | J90: 209.74 | K90: 5.72 | L90: 5.8153
A91: 1805 | B91: K | C91: 1325 | E91: ReEnergize | F91: 06/01/23 | G91: 05/31/24 | H91: 5/31/24 | I91: 1273.69 | J91: 631.58 | K91: 5.72 | L91: 5.8153
A92: 1805 | B92: K office | C92: 680 | E92: ReEnergize | F92: 06/01/23 | G92: 05/31/24 | H92: 5/31/24 | I92: 653.67 | J92: 324.13 | K92: 5.72 | L92: 5.8153
A93: 1805 | B93: L | C93: 2005 | E93: ReEnergize | F93: 06/01/23 | G93: 05/31/24 | H93: 5/31/24 | I93: 1927.36 | J93: 955.72 | K93: 5.72 | L93: 5.8153
A94: 1805 | B94: M | C94: 3005 | E94: Savory Spice | F94: 06/01/23 | G94: 05/31/24 | H94: 3/31/25 / 3/31/30 | I94: 3003.82 | J94: 1547.58 | K94: 6.18 | L94: 5.8153
A95: 1805 | B95: N | C95: 3000 | E95: Harlan | F95: 09/01/23 | G95: 08/31/24 | I95: 1828.83 | J95: 375 | K95: 1.5 | L95: 5.8153 | M95: Month-to-month, continue roll (Hal Harlan 1-18-17)
A96: 1805 | B96: O1, O2, O3 | C96: 9000 | E96: Coda Coffee | F96: 09/01/23 | G96: 08/31/24 | H96: 8/31/24 | I96: 11486.48 | J96: 7125 | K96: 9.5 | L96: 5.8153
A97: WAREHOUSE TOTALS | C97: 197501.99 | D97: 650.92 | I97: $199,599.70 | J97: $106,144.46 | K97: $6.34 blended | M97: Warehouse totals per rent roll
A98: BUILDING TOTAL (Office+Wse) | C98: 215243.83 | D98: 1964.12 | I98: $215,743.84 | J98: $113,598.48 | M98: Building totals per rent roll
A99: OUTSIDE/STORAGE | B99: Franklin - 5898 Franklin (10,000 SF) | C99: 10000 | E99: Keith Werkheiser | F99: 12/01/23 | G99: mo to mo | H99: mo to mo | I99: 1225
A100: OUTSIDE/STORAGE | B100: Franklin - 5898 Franklin (6,375 SF) | C100: 6375 | E100: Keith Werkheiser | F100: 05/01/23 | G100: 04/30/24 | H100: 4/30/28 | I100: 1275
A101: OUTSIDE/STORAGE | B101: Franklin (500 SF) | C101: 500 | E101: Colorado Construction Cleaning | F101: 03/01/22 | G101: mo to mo
A102: OUTSIDE/STORAGE | B102: 1900 E. 58th (1,000 SF) | C102: 1000 | E102: P&H Equipment
A103: OUTSIDE/STORAGE | B103: Mapleton (1,000 SF) | C103: 1000 | E103: P&H Equipment
A104: OUTSIDE/STORAGE | B104: Hillside B - 5952 Franklin (17,447.77 SF) | C104: 17447.77 | E104: Lobos Structures, LLC. | F104: 07/01/23 | G104: 06/30/24 | H104: 6/30/24 | I104: 363.49
A105: OUTSIDE/STORAGE | B105: Hillside B - 5952 Franklin (17,447.77 SF) #2 | C105: 17447.77 | E105: Lobos Structures, LLC. | F105: 07/01/23 | G105: 06/30/24 | H105: 6/30/24 | I105: 363.49
A106: OUTSIDE/STORAGE | B106: Yard A (5,730 SF) | C106: 5730 | E106: Happel & Associates | F106: 09/01/23 | G106: 08/31/24 | H106: 8/31/25 | I106: 210.1
A107: OUTSIDE/STORAGE | B107: Yard C (17,000 SF) | C107: 17000 | E107: Harlan | F107: 05/31/24 | G107: 5/31/24 | I107: 395.44
A108: OUTSIDE/STORAGE | B108: Yard C (5,000 SF) | C108: 5000 | E108: P&H Equipment | F108: 09/01/23 | G108: 08/31/24 | I108: 104.16 | M108: All of P&H under one yard, D
A109: OUTSIDE/STORAGE | B109: Yard D (17,825 SF) | C109: 17825 | E109: P & H Equipment (clean dirt) | F109: 09/01/23 | G109: 08/31/24 | H109: 8/31/26 | I109: 2499.86
A110: OUTSIDE/STORAGE | B110: Yard E (14,500 SF) | C110: 14500 | E110: P & H Equipment (4 trucks) | F110: 09/01/23 | G110: 08/31/24 | H110: 8/31/26
A111: OUTSIDE/STORAGE | B111: Yard F (29,338 SF) | C111: 29338 | E111: P&H Equipment | F111: 09/01/23 | G111: 08/31/24 | H111: 8/31/26
A112: OUTSIDE/STORAGE | B112: Yard G (6,375 SF) | D112: 6375 | E112: Vacant
A113: OUTSIDE/STORAGE TOTALS | C113: 59500.54 | D113: 0 | I113: $3,437.08 | M113: Outside/storage totals per rent roll
A114: PROJECT TOTALS | C114: 274744.37 | D114: 1964.12 | I114: $219,180.92 | J114: $113,598.48 | M114: Project (bldg+outside) totals per rent roll
...

Sheet Rent Roll - Jun 2023
A1: CityView Industrial Park - Rent Roll (Rent Roll - Jun 2023)
A2: Source rent roll dated: May 19, 2023 (for June 2023)
A3: Source: Sterling Property Tax Specialists appeal package (Exhibit F), Adams County 2026 NOV protest
A5: Building/Unit Group | B5: Space | C5: Leased SF | D5: Vacant SF | E5: Tenant | F5: Lease Start | G5: Term Expires | H5: Renewal/Option Expires | I5: Total Monthly Rent | J5: Base Monthly Rent | K5: Annual Rate PSF | L5: CAM PSF (Annual) | M5: Notes
A6: 5800 | B6: 100 | C6: 500 | E6: CVP Management Office | M6: Management office - no rent
A7: 5800 | B7: 101 | C7: 1048 | E7: MR Solutions | F7: 08/01/22 | G7: 7/31/23 | H7: 7/31/23 | I7: 1785.27 | J7: 1026.17 | K7: 11.75 | L7: 8.692 | M7: Office only
A8: 5800 | B8: 102 | C8: 960 | E8: R. Baker | F8: 09/01/22 | G8: 06/30/23 | H8: 6/30/23 | I8: 1477.76 | J8: 782.4 | K8: 9.78 | L8: 8.692 | M8: Month-to-month lease
A9: 5800 | B9: 104A | D9: 121 | E9: Vacant
A10: 5800 | B10: 104B | D10: 121 | E10: Vacant
A11: 5800 | B11: 104C | D11: 121 | E11: Vacant
A12: 5800 | B12: 104 | C12: 722 | E12: Training Room 103
A13: 5800 | B13: CA | C13: 1327.88 | E13: Common Area
A14: 5800 | B14: A | C14: 196 | E14: STAT Medical Resources, LLC | F14: 12/01/22 | G14: 11/30/23 | H14: 11/30/23 | I14: 560
A15: 5800 | B15: B | C15: 121 | E15: Copper River Infrastructure | F15: 12/01/22 | G15: 11/30/23 | H15: 11/30/23 | I15: 252.08
A16: 5800 | B16: C | C16: 196 | E16: WEIL Construction Inc. | F16: 09/01/22 | G16: 08/31/23 | H16: 8/31/23 | I16: 515
A17: 5800 | B17: D | C17: 121 | E17: Vacant
A18: 5800 | B18: E | D18: 196 | E18: Vacant
A19: 5800 | B19: Copy Room | C19: 107.2 | E19: Vacant
A20: 5800 | B20: 106 | C20: 706 | E20: S&R Environmental Consulting, Inc. | F20: 12/01/22 | G20: 11/30/23 | H20: 11/30/23 | I20: 1116.19 | J20: 604.81 | K20: 10.28 | L20: 8.692
A21: 5800 | B21: 201 | C21: 2114.9 | E21: Global IT Innovative Systems | F21: 10/01/22 | G21: 09/30/23 | H21: 9/30/23 | I21: 7009.95 | J21: 3525.89 | K21: 4.31 | L21: 4.25
A22: 5800 | B22: 201a | C22: 1385.1 | E22: Global IT Innovative Systems
A23: 5800 | B23: 200, 202 | C23: 3108.59 | E23: Global IT Innovative Systems
A24: 5800 | B24: CA | C24: 299.4 | E24: Global IT Innovative Systems
A25: 5802 | B25: 107 | C25: 2274 | E25: Colorado Construction Cleaning, Inc. | F25: 06/01/23 | G25: 05/31/24 | H25: 5/31/24 | I25: 1986.96 | J25: 884.97 | K25: 4.67 | L25: 5.8153
A26: 5802 | B26: 203 | C26: 380.25 | E26: Global IT Innovative Systems | M26: Input #'s manually
A27: 5802 | B27: 205 | C27: 736 | E27: Global IT Innovative Systems | M27: No cleaning or supplies
A28: 5802 | B28: 204 | C28: 713 | E28: Global IT Innovative Systems
A29: 5802 | B29: 206 | C29: 713 | E29: Global IT Innovative Systems
A30: 5802 | B30: Storage | C30: 75.6 | E30: Global IT Innovative Systems
A31: 5802 | B31: Unit M-105 | C31: 584 | E31: Vacant
A32: 5800/5802 OFFICE TOTALS | C32: 16854.72 | D32: 2093.2 | I32: $14,703.21 | J32: $6,824.23 | K32: $3.40 blended | M32: Office totals per rent roll
A33: 5806 | B33: A-n | C33: 875 | E33: Global IT Innovative Systems | G33: 09/30/23 | H33: 09/30/23
A34: 5806 | B34: A-s | C34: 875 | E34: Global IT Innovative Systems
A35: 5806 | B35: B-s | C35: 1221 | E35: Global IT Innovative Systems | F35: 10/01/22 | I35: 1166.72 | J35: 402.28 | K35: 4.414 | L35: 4.5088 | M35: Input #'s manually
A36: 5806 | B36: B-n | C36: 350 | E36: Global IT Innovative Systems | F36: 10/01/22 | G36: 09/30/23 | H36: 09/30/23 | I36: 470.37 | J36: 470.37
A37: 5808 | B37: A | C37: 3550 | E37: Miggy & Ernie's Demo | F37: 03/01/23 | G37: 02/28/24 | H37: 2/28/24 | I37: 3326.73 | J37: 1606.38 | K37: 5.43 | L37: 5.8153 | M37: First Right of Refusal: Keiths Paint Shop LLC
A38: 1609 | B38: A-B | C38: 3500 | E38: Keiths Paint Shop LLC | F38: 05/01/23 | G38: 04/30/24 | H38: 4/30/28 | I38: 3446.13 | J38: 1750 | K38: 6 | L38: 5.8153 | M38: Post new statement amount 5-1-23
A39: 1609 | B39: C | C39: 1750 | E39: Keiths Paint Shop LLC | F39: 05/01/23 | G39: 04/30/24 | H39: 4/30/28 | I39: 1723.06 | J39: 875 | K39: 6 | L39: 5.8153 | M39: Post new statement amount 5-1-23
A40: 1609 | B40: D-E | C40: 3250 | E40: REDCO TIRE | F40: 08/01/22 | G40: 07/31/23 | H40: 7/31/25 | I40: 2984.26 | J40: 1409.28 | K40: 5.2035 | L40: 5.8153 | M40: First Right of Refusal: Keiths Paint Shop LLC
A41: 1609 | B41: F | C41: 1564 | E41: REDCO TIRE | F41: 08/01/22 | G41: 07/31/23 | H41: 7/31/25 | I41: 1436.12 | J41: 678.19 | K41: 5.2035 | L41: 5.8153 | M41: First Right of Refusal: Keiths Paint Shop LLC
A42: 1609 | B42: G | C42: 1751 | E42: Adessa | F42: 07/01/22 | G42: 06/30/23 | H42: 6/30/25 | I42: 1723.06 | J42: 875 | K42: 6 | L42: 5.8153 | M42: First Right of Refusal: Keiths Paint Shop LLC
A43: 1609 | B43: H-I | C43: 3500 | E43: Keiths Paint Shop LLC | F43: 05/01/23 | G43: 04/30/24 | H43: 4/30/28 | I43: 3446.13 | J43: 1750 | K43: 6 | L43: 5.8153 | M43: Post new statement amount 5-1-23
A44: 1707-09 | B44: A07-B09 | C44: 15000 | E44: Certified Mapping and Technical Testing Inc. | F44: 07/01/22 | G44: 06/30/23 | H44: 6/30/25 | I44: 8791.63 | J44: 4875 | K44: 3.9 | L44: 3.1333 | M44: NO TAXES; partially exempt entity
A45: 1721-23 | B45: A21 | C45: 7500 | E45: Good Bread | F45: 06/01/23 | G45: 05/31/24 | H45: 5/31/28 | I45: 8940.81 | J45: 4856.25 | K45: 8 | L45: 5.8153 | M45: Credited $7,106.32 for upgrades Aug 2012; total upgrades $14,212.63 + 2 bathrooms $5,800 = $20,012.63
A46: 1721-23 | B46: B23 | C46: 2728.17 | E46: Good Bread | F46: 06/01/23 | G46: 05/31/24 | H46: 5/31/28 | I46: 3140.87 | J46: 1818.78 | K46: 8 | L46: 5.8153
A47: 1721-23 | B47: C23 w/h freeze | C47: 277.98 | E47: Good Bread Freezer | F47: 06/01/23 | G47: 05/31/24 | H47: 5/31/28 | I47: 320.03 | J47: 185.32 | K47: 8 | L47: 5.8153
A48: 1721-23 | B48: C23 w/h | C48: 4557.12 | E48: Good Bread | F48: 06/01/23 | G48: 05/31/24 | H48: 5/31/28 | I48: 5246.5 | J48: 3038.08 | K48: 8 | L48: 5.8153
A49: 1751 | B49: A | C49: 4866.3 | E49: Coda Coffee Company | F49: 09/01/22 | G49: 08/31/23 | H49: 8/31/24 | I49: 5890.21 | J49: 3446.96 | K49: 8.5 | L49: 5.8153
A50: 1751 | B50: B-2 | C50: 1921.48 | E50: Coda Coffee Company | F50: 09/01/22 | G50: 08/31/23 | H50: 8/31/24 | I50: 2292.21 | J50: 1361.05 | K50: 8.5 | L50: 5.8153
A51: 1751 | B51: B-1 | C51: 1132.83 | E51: Coda Coffee Company | F51: 09/01/22 | G51: 08/31/23 | H51: 8/31/24 | I51: 1351.4 | J51: 802.42 | K51: 8.5 | L51: 5.8153
A52: 1751 | B52: B-3 | C52: 3450 | E52: Coda Coffee Company | F52: 09/01/22 | G52: 08/31/23 | H52: 8/31/24 | I52: 4115.65 | J52: 2443.75 | K52: 8.5 | L52: 5.8153
A53: 1751 | B53: D east | C53: 855.88 | E53: Coda Coffee Company | F53: 09/01/22 | G53: 08/31/23 | H53: 08/31/24 | I53: 1021.01 | J53: 606.25 | K53: 8.5 | L53: 5.8153
A54: 1751 | B54: D 2nd floor | E54: Unoccupied (2nd floor small storage) | F54: 09/01/21
A55: 1751 | B55: D west | C55: 993.08 | E55: Coda Coffee Company | F55: 09/01/22 | G55: 08/31/23 | H55: 08/31/24 | I55: 1184.69 | J55: 703.43 | K55: 8.5 | L55: 5.8153
A56: 1751 | B56: E | C56: 5000 | E56: Reliant Dry Ice | F56: 11/01/22 | G56: 10/31/23 | H56: 10/31/25 | I56: 4923.04 | J56: 2500 | K56: 6 | L56: 5.8153
A57: 1791 | B57: A | C57: 5157 | E57: ReEnergize | F57: 06/01/23 | G57: 05/31/24 | H57: 5/31/25 | I57: 5112.01 | J57: 2612.88 | K57: 6.08 | L57: 5.8153
A58: 1791 | B58: B | C58: 4000 | E58: Coda Coffee Company | F58: 09/01/22 | G58: 08/31/23 | H58: 8/31/24 | I58: 4771.77 | J58: 2833.33 | K58: 8.5 | L58: 5.8153
A59: 1791 | B59: C & D | C59: 4000 | E59: Allcomm Data Supplies Inc. | F59: 09/01/22 | G59: 08/31/23 | H59: 8/31/26 | I59: 3655.1 | J59: 1716.67 | K59: 5.15 | L59: 5.8153
A60: 1791 | B60: E | C60: 2000 | E60: RossComm LLC | F60: 05/01/22 | G60: 04/30/23 | H60: 4/30/23 | I60: 1814.22 | J60: 845 | K60: 5.07 | L60: 5.8153 | M60: First Right of Refusal: All Comm Data; contacted for renewal
A61: 1791 | B61: F | C61: 2000 | E61: R&O Heating Inc. | F61: 08/01/22 | G61: 07/31/23 | H61: 7/31/23 | I61: 1872.55 | J61: 858.33 | K61: 5.15 | L61: 5.8153
A62: 1791 | B62: G | C62: 2000 | E62: R&O Heating Inc. | F62: 08/01/22 | G62: 07/31/23 | H62: 7/31/23 | I62: 1827.55 | J62: 858.33 | K62: 5.15 | L62: 5.8153
A63: 1791 | B63: H | C63: 2000 | E63: R&O Heating Inc. | F63: 08/01/22 | G63: 07/31/23 | H63: 7/31/23 | I63: 1827.55 | J63: 858.33 | K63: 5.15 | L63: 5.8153
A64: 1791 | B64: I & J | C64: 4000 | E64: Envigo/Vanguard | F64: 06/01/23 | G64: 05/31/24 | H64: 5/31/26 | I64: 3851.77 | J64: 1913.33 | K64: 5.74 | L64: 5.8153
A65: 1791 | B65: K & L | C65: 4000 | E65: Envigo/Vanguard | F65: 06/01/23 | G65: 05/31/24 | H65: 5/13/26 | I65: 3851.77 | J65: 1913.33 | K65: 5.74 | L65: 5.8153
A66: 1791 | B66: M | C66: 2000 | E66: Harlan Bakeries Co LLC | F66: 02/01/23 (roll cont. 1-18-17) | G66: 01/31/24 | H66: 1/31/24 | I66: 1969.22 | J66: 1000 | K66: 6 | L66: 5.8153
A67: 1791 | B67: N | C67: 2000 | E67: Mr. Dino's Baths | F67: 06/01/23 | G67: 5/31/24 | H67: 05/31/24 | I67: 1789.22 | J67: 820 | K67: 4.92 | L67: 5.8153
A68: 1771 | B68: A/A-1 | C68: 3760 | E68: Colorado Comfort Air | F68: 07/01/22 | G68: 06/30/23 | H68: 6/30/23 | I68: 3275.99 | J68: 1453.87 | K68: 4.64 | L68: 5.8153 | M68: Contacted for renewal; doing 5-year renewal
A69: 1771 | B69: B | C69: 3987.76 | E69: Keyser Ventures LLC | F69: 05/01/23 | G69: 04/30/24 | H69: 4/30/27 | I69: 3718.92 | J69: 1711.41 | K69: 5.15 | L69: 5.8153
A70: 1771 | B70: C | C70: 2562.24 | E70: Soapoint Graphics | F70: 12/01/21 | G70: 11/30/22 | H70: 11/30/22 | I70: 1942.3 | J70: 625.61 | K70: 2.93 | L70: 5.8153 | M70: Moving mid-June
A71: 1771 | B71: D | C71: 4585 | E71: Coda Coffee | F71: 9/1/2022 | G71: 8/31/23 | H71: 08/31/24 | I71: 5469.82 | J71: 3247.81 | K71: 8.5 | L71: 5.8153
A72: 1771 | B72: E & F | C72: 5000 | E72: Happel & Associates Inc. | F72: 9/1/2022 | G72: 8/31/23 | H72: 8/31/25 | I72: 4923.04 | J72: 2500 | K72: 6 | L72: 5.8153
A73: 1761 | B73: A | C73: 2625 | E73: Harlan Bakeries | F73: 09/01/22 | G73: 08/31/23 | H73: 8/31/25 | I73: 2302.41 | J73: 1030.31 | K73: 4.71 | L73: 5.8153
A74: 1761 | B74: A-5 | C74: 3750 | E74: Good Bread Inc. | F74: 06/01/23 | G74: 05/31/24 | I74: 3364.84 | J74: 1547.56 | K74: 4.9522 | L74: 5.8153
A75: 1761 | B75: A3 | C75: 1250 | E75: Santa Fe Mechanical | F75: 09/01/22 | G75: 08/31/23 | H75: 8/31/25 | I75: 1334.93 | J75: 729.17 | K75: 7 | L75: 5.8153
A76: 1761 | B76: A4 | C76: 5000 | E76: Santa Fe Mechanical | F76: 09/01/22 | G76: 08/31/23 | H76: 8/31/25 | I76: 5339.71 | J76: 2916.67 | K76: 7 | L76: 5.8153
A77: 1761 (cont.) | B77: A1 | C77: 6675 | E77: Whatnot Ventures LLC | F77: 06/01/23 | G77: 05/31/24 | H77: 5/31/26 | I77: 5899.2 | J77: 2664.44 | K77: 4.79 | L77: 5.8153
A78: 1761 (cont.) | B78: A2 | C78: 3200 | E78: Inland Island Brewing | F78: 10/01/22 | G78: 09/30/23 | H78: 9/30/2027 | I78: 2726.75 | J78: 1176 | K78: 4.41 | L78: 5.8153
A79: 1761 (cont.) | B79: B | C79: 2765 | E79: Inland Island Brewing | F79: 10/01/22 | G79: 09/30/23 | H79: 9/30/27 | I79: 2356.08 | J79: 1046.09 | K79: 4.41 | L79: 5.8153
A80: 1761 (cont.) | B80: B add on | C80: 1150 | E80: Inland Island Brewing | F80: 10/01/22 | G80: 09/30/23 | H80: 9/30/27 | I80: 1132.3 | J80: 575 | K80: 6 | L80: 5.8153
A81: 1761 (cont.) | B81: C&D | C81: 6465 | E81: Coda Coffee | F81: 10/01/22 | G81: 09/30/23 | H81: 3/31/25 | I81: 7712.37 | J81: 4579.38 | K81: 8.5 | L81: 5.8153
A82: 1805 | B82: A,B | C82: 3000 | E82: Savory Retail Group, LLC | F82: 04/01/23 | G82: 03/31/24 | H82: 03/31/30 | I82: 3426.99 | J82: 1300 | K82: 5.2 | L82: 5.8153
A83: 1805 | B83: D | C83: 2000 | E83: Savory Retail Group, LLC | F83: 04/01/23 | G83: 03/31/24 | H83: 03/31/30 | I83: 1835.88 | J83: 866.67 | K83: 5.2 | L83: 5.8153
A84: 1805 | B84: E,F,G | C84: 6000 | E84: Savory Retail Group, LLC | F84: 04/01/23 | G84: 03/31/24 | H84: 03/31/30 | I84: 5507.65 | J84: 2600 | K84: 5.2 | L84: 5.8153
A85: 1805 | B85: H | C85: 2000 | E85: M.R. Solutions, Inc. | F85: 08/01/22 | G85: 07/31/23 | H85: 7/31/23 | I85: 1969.22 | J85: 1000 | K85: 6 | L85: 5.8153
A86: 1805 | B86: I | C86: 2000 | E86: M.R. Solutions, Inc. | F86: 08/01/22 | G86: 07/31/23 | I86: 1969.22 | J86: 1000 | K86: 6 | L86: 5.8153
A87: 1805 | B87: J-s | C87: 2172 | E87: ReEnergize | F87: 06/01/23 | G87: 05/31/24 | H87: 5/31/24 | I87: 2182.89 | J87: 1035.32 | K87: 5.72 | L87: 5.8153
A88: 1805 | B88: J (Ne) | C88: 1475 | E88: P&H Equipment | F88: 02/01/21 | G88: 01/31/23 | H88: 1/31/23 | I88: 1421.57 | J88: 706.77 | K88: 5.75 | L88: 5.8153 | M88: Not renewing, on mo-to-mo until caught up 1/31/2023
A89: 1805 | B89: J (Nw) | C89: 440 | E89: ReEnergize | F89: 06/01/23 | G89: 05/31/24 | H89: 5/31/24 | I89: 422.97 | J89: 209.74 | K89: 5.72 | L89: 5.8153
A90: 1805 | B90: K | C90: 1325 | E90: ReEnergize | F90: 06/01/23 | G90: 05/31/24 | H90: 5/31/24 | I90: 1273.69 | J90: 631.58 | K90: 5.72 | L90: 5.8153
A91: 1805 | B91: K office | C91: 680 | E91: ReEnergize | F91: 06/01/23 | G91: 05/31/24 | H91: 5/31/24 | I91: 653.67 | J91: 324.13 | K91: 5.72 | L91: 5.8153
A92: 1805 | B92: L | C92: 2005 | E92: ReEnergize | F92: 06/01/23 | G92: 05/31/23 | H92: 5/31/24 | I92: 1927.36 | J92: 955.72 | K92: 5.72 | L92: 5.8153
A93: 1805 | B93: M | C93: 3005 | E93: Mountain Strong LTD | F93: 06/01/23 | G93: 05/31/24 | H93: 5/31/25 | I93: 3003.82 | J93: 1547.58 | K93: 6.18 | L93: 5.8153
A94: 1805 | B94: N | C94: 3000 | E94: Harlan | F94: 09/01/22 | G94: 08/31/23 | I94: 1811.33 | J94: 357.5 | K94: 1.43 | L94: 5.8153
A95: 1805 | B95: O1, O2, O3 | C95: 9000 | E95: Coda Coffee | F95: 09/01/22 | G95: 08/31/23 | H95: 8/1/24 | I95: 10736.48 | J95: 6375 | K95: 8.5 | L95: 5.8153
A96: WAREHOUSE TOTALS | C96: 197502.84 | D96: 0 | I96: $192,173.54 | J96: $98,666.71 | K96: $5.84 blended | M96: Warehouse totals per rent roll
A97: BUILDING TOTAL (Office+Wse) | C97: 214357.56 | D97: 2093.2 | I97: $206,876.74 | J97: $105,490.94 | M97: Building totals per rent roll
A98: OUTSIDE/STORAGE | B98: Franklin Hillside A (10,000 SF) | C98: 10000 | E98: Sams Hauling | F98: 07/01/02 | G98: mo to mo | H98: mo to mo | I98: 200
A99: OUTSIDE/STORAGE | B99: Franklin - 5898 Franklin (6,375 SF) | C99: 6375 | E99: Keith Werkheiser | F99: 05/01/23 | G99: 04/30/24 | H99: 4/30/28 | I99: 1275
A100: OUTSIDE/STORAGE | B100: Franklin (500 SF) | C100: 500 | E100: Colorado Construction Cleaning | F100: 03/01/22 | G100: mo to mo
A101: OUTSIDE/STORAGE | B101: 1900 E. 58th (1,000 SF) | C101: 1000 | E101: P&H Equipment
...

Sheet Base Period Leases (Exh E)
A1: CityView Industrial Park - Base Period Lease Summary (Petitioner's Exhibit E)
A2: Base period = trailing period used in Petitioner's appeal analysis (see Appeal_Docs.pdf)
A4: NEW LEASES DURING BASE PERIOD
A5: Unit | B5: Tenant | C5: Unit SF | D5: Lease Date | E5: Termination Date | F5: Rent Rate PSF | G5: Basis
A6: 1771 | B6: REDCO | C6: 2562 | D6: 7/1/2023 | E6: 6/30/2028 | F6: 6 | G6: NNN
A7: 1609 | B7: Werkheiser | C7: 4814 | D7: 7/1/2023 | E7: 4/30/2028 | F7: 6 | G7: NNN
A8: 5802-105 | B8: P&H Equipment | C8: 584 | D8: 9/1/2023 | E8: 8/31/2026 | F8: 6.73 | G8: NNN
A9: 1805 | B9: Savory | C9: 3005 | D9: 10/15/2023 | E9: 3/31/1930 [sic, likely 3/31/2030] | F9: 6.18 | G9: NNN
A10: Weighted Average Rate PSF (New Leases) | F10: 6.09
A13: RENEWALS DURING BASE PERIOD
A14: Unit | B14: Tenant | C14: Unit SF | D14: Lease Date | E14: Termination Date | F14: Rent Rate PSF
A15: 5800-106 | B15: S&R Environmental | C15: 706 | D15: 12/1/2023 | E15: 11/30/2026 | F15: 10.69
A16: 1805 | B16: ReEnergize | C16: 6622 | D16: 6/1/2024 | E16: 5/31/2027 | F16: 5.89
A17: 5808 | B17: Miggy and Ernie | C17: 3550 | D17: 3/1/2024 | E17: 2/28/2027 | F17: 6
A18: 1771 | B18: Happel | C18: 5000 | D18: 9/1/2022 | E18: 8/31/2025 | F18: 6
A19: 1771 | B19: Colorado Comfort | C19: 3760 | D19: 7/1/2023 | E19: 6/30/2028 | F19: 6.2
A20: Basement | B20: Weil Construction | C20: 150 | D20: 9/1/2023 | E20: 8/31/2024 | F20: 5.25
A21: 1791 | B21: RossComm | C21: 2000 | D21: 5/1/2023 | E21: 4/30/2025 | F21: 6.5
A22: 1805 | B22: MR Solutions | C22: 4000 | D22: 8/1/2023 | E22: 7/31/2024 | F22: 8.5
A23: 5800-101 | B23: MR Solutions | C23: 1049 | D23: 8/1/2023 | E23: 7/31/2024 | F23: 14
A24: 1791 | B24: R&O Heating | C24: 6000 | D24: 8/1/2023 | E24: 7/31/2026 | F24: 7
A25: 1805 | B25: P&H Equipment | C25: 1475 | D25: 9/1/2023 | E25: 8/31/2026 | F25: 6.5
A26: 5800-5802 | B26: Global IT | C26: 12847 | D26: 10/1/2023 | E26: 9/30/2024 | F26: 4.11
A27: 1805 | B27: Savory | C27: 14000 | D27: 4/1/2023 | E27: 3/31/2027 | F27: 5.2
A28: Weighted Average Rate PSF (Renewals) | F28: 5.9
A31: OFFICE RENEWAL DURING BASE PERIOD (Gross basis)
A32: Unit | B32: Tenant | C32: Unit SF | D32: Lease Date | E32: Termination Date | F32: Rent Rate PSF
A33: 5800-103C | B33: Weil Construction (office) | C33: 196 | D33: 9/1/2023 | E33: 8/31/2024 | F33: 31.53 | G33: FSG

Sheet Inc-Exp Stmt 2024 (Exh C-1)
A1: CityView Industrial Park - Income & Expense Statement, Twelve Months Ending Dec 31, 2024
A2: Source: Petitioner's Exhibit C
A4: Section | B4: Line Item | C4: Dec Actual | D4: Dec Budget | E4: Dec Variance $ | F4: Dec Variance % | G4: YTD Actual | H4: YTD Budget | I4: YTD Variance $ | J4: YTD Variance %
A5: INCOME | B5: Office Rent | C5: 10335.85 | D5: 9929 | E5: 406.85 | F5: 4.10% | G5: 115289.07 | H5: 112690 | I5: 2599.07 | J5: 2.31%
A6: INCOME | B6: Warehouse Rent | C6: 110312.38 | D6: 109508 | E6: 804.38 | F6: 0.73% | G6: 1296540.4 | H6: 1284295 | I6: 12245.38 | J6: 0.95%
A7: INCOME | B7: Outside Storage | C7: 7006.01 | D7: 7308 | E7: -301.99 | F7: -4.13% | G7: 82884.19 | H7: 85800 | I7: -2915.81 | J7: -3.40%
A8: INCOME | B8: CAM/Taxes/Insurance Reimb | C8: 124214.12 | D8: 120242 | E8: 3972.12 | F8: 3.30% | G8: 1446433.2 | H8: 1443088 | I8: 3345.16 | J8: 0.23%
A9: INCOME | B9: PY CAM Adjustment | C9: 3280.16 | D9: -7241 | E9: 10521.16 | F9: -145.30% | G9: 32357.56 | H9: -72410 | I9: 104767.56 | J9: -144.69%
A10: INCOME | B10: Other Income | C10: 5619.82 | D10: 1184 | E10: 4435.82 | F10: 374.65% | G10: 59677.83 | H10: 13616 | I10: 46061.83 | J10: 338.29%
A11: INCOME | B11: TOTAL INCOME | C11: 260768.34 | D11: 240930 | E11: 19838.34 | F11: 8.23% | G11: 3033182.2 | H11: 2867079 | I11: 166103.19 | J11: 5.79%
A12: COMMON AREA | B12: Gas & Electric | C12: 2867.95 | D12: 2353 | E12: 514.95 | F12: 21.88% | G12: 44693.63 | H12: 47085 | I12: -2391.37 | J12: -5.08%
A13: COMMON AREA | B13: Water & Sewer | C13: 1709.11 | D13: 1857 | E13: -147.89 | F13: -7.96% | G13: 25447.6 | H13: 32487 | I13: -7039.4 | J13: -21.67%
A14: COMMON AREA | B14: Repairs & Maintenance | C14: 9826.41 | D14: 4463 | E14: 5363.41 | F14: 120.17% | G14: 191599.47 | H14: 154748 | I14: 36851.47 | J14: 23.81%
A15: COMMON AREA | B15: Snow Removal | C15: 9768.98 | D15: 3735 | E15: 6033.98 | F15: 161.55% | G15: 44318.56 | H15: 60811 | I15: -16492.44 | J15: -27.12%
A16: COMMON AREA | B16: Landscape Maintenance | C16: 2483.67 | D16: 1380 | E16: 1103.67 | F16: 79.98% | G16: 21718.56 | H16: 25860 | I16: -4141.44 | J16: -16.01%
... A45: TOTAL | B45: NET CASH FLOW (DEFICIT) | C45: 47058.66 | D45: 93618.46 | E45: -46559.8 | F45: -49.73% | G45: 1128200.3 | H45: 937095.06 | I45: 191105.22 | J45: 20.39%

Sheet Inc-Exp Stmt 2023 (Exh C-2)
A1: CityView Industrial Park - Income & Expense Statement, Twelve Months Ending Dec 31, 2023
A2: Source: Petitioner's Exhibit C
A4: Section | B4: Line Item | C4: Dec Actual | D4: Dec Budget | E4: Dec Variance $ | F4: Dec Variance % | G4: YTD Actual | H4: YTD Budget | I4: YTD Variance $ | J4: YTD Variance %
A5: INCOME | B5: Office Rent | C5: 10059.49 | D5: 9136 | E5: 923.49 | F5: 10.11% | G5: 121582.27 | H5: 99426 | I5: 22156.27 | J5: 22.28%
A6: INCOME | B6: Warehouse Rent | C6: 106130.23 | D6: 102385 | E6: 3745.23 | F6: 3.66% | G6: 1213722.6 | H6: 1186203 | I6: 27519.56 | J6: 2.32%
A7: INCOME | B7: Outside Storage | C7: 5676.63 | D7: 5349 | E7: 327.63 | F7: 6.13% | G7: 60343.3 | H7: 61721 | I7: -1377.7 | J7: -2.23%
A8: INCOME | B8: CAM/Taxes/Insurance Reimb | C8: 99058.27 | D8: 99854 | E8: -795.73 | F8: -0.80% | G8: 1181430.5 | H8: 1198248 | I8: -16817.52 | J8: -1.40%
A9: INCOME | B9: Other Income | C9: 21087.77 | D9: -3206 | E9: 24293.77 | F9: -757.76% | G9: 96439.27 | H9: -30284 | I9: 126723.27 | J9: -418.45%
A10: INCOME | B10: TOTAL INCOME | C10: 242012.39 | D10: 213518 | E10: 28494.39 | F10: 13.35% | G10: 2673517.9 | H10: 2515314 | I10: 158203.88 | J10: 6.29%
A11: COMMON AREA | B11: Gas & Electric | C11: 4037.7 | D11: 2337 | E11: 1700.7 | F11: 72.77% | G11: 44485.83 | H11: 45553 | I11: -1067.17 | J11: -2.34%
A12: COMMON AREA | B12: Water & Sewer | C12: 1925.23 | D12: 1801 | E12: 124.23 | F12: 6.90% | G12: 28513.94 | H12: 33046 | I12: -4532.06 | J12: -13.71%
A13: COMMON AREA | B13: Repairs & Maintenance | C13: 13865.03 | D13: 4214 | E13: 9651.03 | F13: 229.02% | G13: 188734.64 | H13: 125359 | I13: 63375.64 | J13: 50.56%
A14: COMMON AREA | B14: Snow Removal | C14: 13918.75 | D14: 3735 | E14: 10183.75 | F14: 272.66% | G14: 67548.08 | H14: 60811 | I14: 6737.08 | J14: 11.08%
A15: COMMON AREA | B15: Landscape Maintenance | C15: 592 | D15: 496 | E15: 96 | F15: 19.35% | G15: 14677.25 | H15: 26366 | I15: -11688.75 | J15: -44.33%
A16: COMMON AREA | B16: Services | C16: 12735.97 | D16: 7301 | E16: 5434.97 | F16: 74.44% | G16: 105227.25 | H16: 86230 | I16: 18997.25 | J16: 22.03%
... A42: TOTAL | B42: NET CASH FLOW (DEFICIT) | C42: 40952.51 | D42: 94888.46 | E42: -53935.95 | F42: -56.84% | G42: 1024381.1 | H42: 973473.52 | I42: 50907.55 | J42: 5.23%

Sheet Actual Income Analysis (Exh D)
A1: CityView Industrial Park - Petitioner's Analysis of Actual Income & Expense (Exhibit D)
A2: NLA per rent roll 6-30-2024: 217,208 SF
A4: Line Item | B4: 2023 | C4: 2024
A5: NLA | B5: 217208 | C5: 217208
A6: Office Income | B6: 121582.27 | C6: 115289.07
A7: Warehouse Income | B7: 1213722.6 | C7: 1296540.4
A8: Outside Storage | B8: 60343.3 | C8: 82884.19
A9: CAM/Taxes/Insurance Reimb | B9: 1181430.5 | C9: 1446433.2
A10: Other Income | B10: 96439.27 | C10: 59677.83
A11: Gross Income | B11: 2673517.9 | C11: 3033182.2
A12: Adj - PY CAM adj (from 2024 stmt) | B12: 32357.56
A13: Adj - Outside Storage (adjacent parcel, excluded) | B13: -48000 | C13: -48000
A14: Adj - Other Income excl. | B14: -59039.27 | C14: -23677.83
A15: Total Adjustments to Income | B15: -74681.71 | C15: -104035.39
A16: Income after Adjustments | B16: 2598836.2 | C16: 2929146.8
A17: All Expenses | B17: 1449048.4 | C17: 1727787.4
A18: Adj - Public Service Land Lease | B18: -1800 | C18: 0
A19: Adj - Property Tax | B19: -528000 | C19: -774996
A20: Total Adjustment to Expenses | B20: -529800 | C20: -793515.21
A21: Total Expenses after Adjustments | B21: 919248.39 | C21: 934272.22
A22: NOI | B22: 1679587.8 | C22: 1994874.6
A23: Cap Rate | B23: 0.0725 | C23: 0.0725
A24: ETR | B24: 0.029 | C24: 0.029
... A28: PSF | B28: 76.18 | C28: 90.48
A29: PY CAM adjustment | C29: 32357.56
A30: Adj - PY CAM adjustment | C30: -32357.56
A31: Adj - 58th Ave Construction Project | C31: -18519.21

Sheet Proforma Analysis (Exh G)
A1: CityView Industrial Park - Petitioner's Proforma Income Analysis (Exhibit G) | D1: Market Rent Proforma (Exhibit G methodology, at market rent)
A3: NLA | B3: 217208 | D3: NLA | E3: =B3 | G3: Market Rent Inputs (blue = adjust)
A4: Office Income (17,742 SF @ $25.00 PSF NNN) | B4: 443550 | D4: Office Income (Office SF x market rent) | E4: =H4*H6 -> 399195 | G4: Office SF | H4: 17742
A5: Warehouse Income (199,466 SF @ $6.00 PSF NNN) | B5: 1196796 | D5: Warehouse Income (Warehouse SF x market rent) | E5: =H5*H7 -> 2194126 | G5: Warehouse SF | H5: 199466
A6: Outside Storage | B6: 35000 | D6: Outside Storage | E6: =B6 -> 35000 | G6: Office Market Rent ($/SF NNN) | H6: 22.5
A7: Other Income (late charges) | B7: 30000 | D7: Other Income (late charges) | E7: =B7 -> 30000 | G7: Warehouse Market Rent ($/SF NNN) | H7: 11
A8: Income - all sources | B8: 1705346 | D8: Income - all sources | E8: =SUM(E4:E7) -> 2658321
A9: Vacancy & Collection Allowance (5%) | B9: -85267 | D9: Vacancy & Collection Allowance | E9: =-H9*E8 -> -132916.05 | G9: Vacancy & Collection % | H9: 0.05
A10: Effective Gross Income | B10: 1620079 | D10: Effective Gross Income | E10: =E8+E9 -> 2525405 | G10: Expense Ratio % | H10: 0.05
A11: Expense Ratio (5%) | B11: -85267 | D11: Expense Ratio | E11: =-H10*E8 -> -132916.05 | G11: Reserves % | H11: 0.03
A12: Reserves for Replacements (3%) | B12: -51160 | D12: Reserves for Replacements | E12: =-H11*E8 -> -79749.63
A13: Total Expense Deductions | B13: -136428 | D13: Total Expense Deductions | E13: =E11+E12 -> -212665.68 | G13: Office rent: comps $18-25 NNN (avg $22.32, med $23.26).
A14: NOI | B14: 1483651 | D14: NOI | E14: =E10+E13 -> 2312739.3 | G14: Warehouse rent: industrial comps $8.49-$12.03 NNN.
A15: Cap Rate | B15: 0.0725 | D15: Cap Rate | E15: =B15 -> 0.0725 | G15: Vac/Exp/Reserve % & cap rate = identical to Petitioner Exh G.
A16: Indicated Value | B16: 20464152 | D16: Indicated Value | E16: =E14/E15 -> 31899852
A17: Rounded Value | B17: 20464200 | D17: Rounded Value | E17: =ROUND(E16,-2) -> 31899900
A18: PSF | B18: 94.21 | D18: PSF | E18: =E16/B3 -> 146.86315
D20: Value uplift vs Petitioner (as filed) | E20: =E16-B16 -> 11435700
D21: Petitioner as-filed indicated value = cell B16.
D24: Sensitivity: Indicated Value by Market Rent
D25: WH \ Office $/SF | E25: 20 | F25: 22.5 | G25: 25
D26: 10 | E26: =($H$4*E$25+$H$5*$D26+$B$6+$B$7)*(1-$H$9-$H$10-$H$11)/$B$15 -> 28974000 | F26: =($H$4*F$25+$H$5*$D26+$B$6+$B$7)*(1-$H$9-$H$10-$H$11)/$B$15 -> 29506260 | G26: =($H$4*G$25+$H$5*$D26+$B$6+$B$7)*(1-$H$9-$H$10-$H$11)/$B$15 -> 30038520
D27: 11 | E27: =($H$4*E$25+$H$5*$D27+$B$6+$B$7)*(1-$H$9-$H$10-$H$11)/$B$15 -> 31367592 | F27: =($H$4*F$25+$H$5*$D27+$B$6+$B$7)*(1-$H$9-$H$10-$H$11)/$B$15 -> 31899852 | G27: =($H$4*G$25+$H$5*$D27+$B$6+$B$7)*(1-$H$9-$H$10-$H$11)/$B$15 -> 32432112
D28: 12 | E28: =($H$4*E$25+$H$5*$D28+$B$6+$B$7)*(1-$H$9-$H$10-$H$11)/$B$15 -> 33761184 | F28: =($H$4*F$25+$H$5*$D28+$B$6+$B$7)*(1-$H$9-$H$10-$H$11)/$B$15 -> 34293444 | G28: =($H$4*G$25+$H$5*$D28+$B$6+$B$7)*(1-$H$9-$H$10-$H$11)/$B$15 -> 34825704
D30: Each cell = full indicated value using Exhibit G methodology (12.0x effective gross multiplier).

Sheet Cap Rate Survey (Exh B)
A1: Lowery Real Estate Investment Survey - 2024 Winter/Spring Colorado (Industrial/Warehouse)
A2: Full survey (all CO & TX property types) attached in source PDF as Petitioner's Exhibit B
A4: Property Type | B4: Industrial/Warehouse
A5: Stabilized Cap Rate Min | B5: 0.06
A6: Stabilized Cap Rate Max | B6: 0.0771
A7: Stabilized Cap Rate Avg | B7: 0.0662
A8: Terminal Cap Rate Min | B8: 0.065
A9: Terminal Cap Rate Max | B9: 0.07
A10: Terminal Cap Rate Avg | B10: 0.0675
A11: Discount/Yield (IRR) Min | B11: 0.07
A12: Discount/Yield (IRR) Max | B12: 0.09
A13: Discount/Yield (IRR) Avg | B13: 0.0806
A14: Source | B14: Lowery Real Estate Investment Survey (LPA), 2024 Winter/Spring - Colorado
A16: Denver Winter/Spring 2024 Range (all property types) | B16: 6% to 12.5%
A17: Denver Winter/Spring 2024 Average (all property types) | B17: 7.72%
